Workbook
Name AGEPROG: 'AÇÕES E PROGRAMAS'!$A$2:$A$4
Name ARMBHPROG: 'AÇÕES E PROGRAMAS'!$B$2:$B$3
Name ARMVAPROG: 'AÇÕES E PROGRAMAS'!$C$2:$C$4
Name ARSAEPROG: 'AÇÕES E PROGRAMAS'!$E$2:$E$3
Name ARTEMIGPROG: 'AÇÕES E PROGRAMAS'!$DJ$2
Name CBMMGPROG: 'AÇÕES E PROGRAMAS'!$S$2:$S$5
Name CGEPROG: 'AÇÕES E PROGRAMAS'!$Q$2:$Q$6
Name DERPROG: 'AÇÕES E PROGRAMAS'!$U$2:$U$4
Name EAGE: AGRUPAMENTO!$C$115:$C$210
Name EGMG: AGRUPAMENTO!$C$2:$C$114
Name ELEMENTO: AGRUPAMENTO!$K$2:$K$267
Name EMATERPROG: 'AÇÕES E PROGRAMAS'!$X$2:$X$6
Name EMCPROG: 'AÇÕES E PROGRAMAS'!$Z$2:$Z$4
Name EOGE: AGRUPAMENTO!$C$211:$C$256
Name EPAMIGPROG: 'AÇÕES E PROGRAMAS'!$Y$2:$Y$4
Name EPMMG: AGRUPAMENTO!$C$575:$C$751
Name ESEAPA: AGRUPAMENTO!$C$475:$C$574
Name ESEDE: AGRUPAMENTO!$C$383:$C$474
Name ESEE: AGRUPAMENTO!$C$752:$C$948
Name ESEF: AGRUPAMENTO!$C$257:$C$382
Name ESPMGPROG: 'AÇÕES E PROGRAMAS'!$AB$2:$AB$3
Name FAOPPROG: 'AÇÕES E PROGRAMAS'!$AF$2:$AF$6
Name FAPEMIGPROG: 'AÇÕES E PROGRAMAS'!$AE$2:$AE$4
Name FCSPROG: 'AÇÕES E PROGRAMAS'!$AD$2:$AD$6
Name FDMPROG: 'AÇÕES E PROGRAMAS'!$AT$2
Name FEAMPROG: 'AÇÕES E PROGRAMAS'!$AI$2:$AI$4
Name FEASPROG: 'AÇÕES E PROGRAMAS'!$BE$2:$BE$3
Name FESPROG: 'AÇÕES E PROGRAMAS'!$BN$2:$BN$11
Name FGPPROG: 'AÇÕES E PROGRAMAS'!$AV$2
Name FHAPROG: 'AÇÕES E PROGRAMAS'!$AK$2:$AK$8
Name FHEMIGPROG: 'AÇÕES E PROGRAMAS'!$AL$2:$AL$3
Name FHIDROPROG: 'AÇÕES E PROGRAMAS'!$AZ$2:$AZ$6
Name FJPPROG: 'AÇÕES E PROGRAMAS'!$AM$2:$AM$6
Name FONTEARMBH: 'FONTE 1.0'!$A$2:$A$3
Name FONTEARMVA: 'FONTE 1.0'!$B$2:$B$3
Name FONTEARSAE: 'FONTE 1.0'!$C$2:$C$3
Name FONTEDER: 'FONTE 1.0'!$D$2:$D$10
Name FONTEFAOP: 'FONTE 1.0'!$F$2:$F$4
Name FONTEFCS: 'FONTE 1.0'!$G$2:$G$3
Name FONTEFDM: 'FONTE 1.0'!$R$2:$R$3
Name FONTEFEAM: 'FONTE 1.0'!$H$2:$H$5
Name FONTEFEAS: 'FONTE 1.0'!$S$2:$S$4
Name FONTEFJP: 'FONTE 1.0'!$I$2:$I$4
Name FONTEFUNTRANS: 'FONTE 1.0'!$E$2
Name FONTEIDENE: 'FONTE 1.0'!$J$2:$J$3
Name FONTEIEF: 'FONTE 1.0'!$K$2:$K$8
Name FONTEIEPHA: 'FONTE 1.0'!$L$2:$L$4
Name FONTEIGAM: 'FONTE 1.0'!$M$2:$M$6
Name FONTEIMA: 'FONTE 1.0'!$N$2:$N$4
Name FONTEJUCEMG: 'FONTE 1.0'!$O$2
Name FONTELEMG: 'FONTE 1.0'!$P$2
Name FONTESEDESE: 'FONTE 1.0'!$Q$2:$Q$7
Name FPPPROG: 'AÇÕES E PROGRAMAS'!$AY$2
Name FUCAMPROG: 'AÇÕES E PROGRAMAS'!$AH$2:$AH$4
Name FUNAPECPROG: 'AÇÕES E PROGRAMAS'!$AQ$2:$AQ$3
Name FUNEDPROG: 'AÇÕES E PROGRAMAS'!$AJ$2:$AJ$6
Name FUNTRANSPROG: 'AÇÕES E PROGRAMAS'!$BH$2:$BH$3
Name GMGPROG: 'AÇÕES E PROGRAMAS'!$BU$2:$BU$9
Name HEMOMINASPROG: 'AÇÕES E PROGRAMAS'!$AC$2:$AC$3
Name IDENEPROG: 'AÇÕES E PROGRAMAS'!$BW$2:$BW$4

Sheet INDICE
D7: ORÇAMENTO BASE ZERO (OBZ) 2026
B11: MATERIAL DE APOIO | D11: BASE OBZ | F11: MATERIAL DE APOIO
B12: CLASSIFICADOR ORÇAMENTÁRIO | F12: CONCEITOS METODOLÓGICOS IMPORTANTES
B13: DECRETO DIÁRIAS | D13: BASE OBZ - EXEMPLO

Sheet BASE OBZ - EXEMPLO
F1: INDICE | H1: PROJETO ORÇAMENTO BASE-ZERO
A2: UNIDADE ORÇAMENTÁRIA | B2: N2 | C2: SUB SIGLA | D2: N3 | E2: PROGRAMAUO | F2: PROGRAMA | G2: prog cod | H2: AÇÃO | I2: ELEMENTO | J2: ELEMENTO_ITEM | K2: Agrupamento | L2: GRUPO | M2: FONTEUO | N2: FONTE | O2: DESCRIÇÃO DO ITEM | P2: NOVO? | Q2: PREMISSA VOLUME | R2: VOLUME | S2: PREMISSA DE PREÇO | T2: PREÇO UNITÁRIO | U2: FREQUÊNCIA PAGAMENTO | V2: VALOR TOTAL ITEM | W2: CLASSIFICAÇÃO CENÁRIO | X2: DESCRIÇÃO DO CENÁRIO | Y2: RISCO DE NÃO FAZER | Z2: BENEFICIO AO FAZER | AA2: PRIORIDADE N3 | AB2: PRIORIDADE N2 | AC2: PRIORIDADE N1 | AD2: PRIORIDADE N2 | AE2: PRIORIDADE N1
A3: FAOP | B3: Subsecretaria de Promoção Cultural | D3: Superintendência de artes | E3: =CONCATENATE(A3,"PROG") -> FAOPPROG | F3: 060 - FORMACAO CULTURAL | G3: =CONCATENATE("P",(LEFT(F3,3)),A3) -> P060FAOP | H3: 1029 - ATIVIDADES DE ENSINO, FORMACAO E QUALIFICACAO PROFISSIONAL E TECNICA EM CULTURA E PATRIMONIO | I3: 1401 - DIÁRIAS CIVIL | J3: =CONCATENATE("ELEM",LEFT(#REF!,2)) -> #REF! | K3: Diárias e viagens | L3: 3 - Outras Despesas de Custeio | M3: =VLOOKUP(L3,#REF!,2,FALSE) -> #REF! | N3: 10 | O3: DIÁRIA PARA ATENDER HOSPEDAGEM DE PROFESSOR CONVIDADO PARA LECIONAR | P3: NÃO | Q3: NÚMERO DE DIÁRIAS UTILIZADAS (2) X NUMERO DE SERVIDORES FAVORECIDOS (1) | R3: 2 | S3: VALOR DA DIÁRIA DE ACORDO COM DECRETO 47.045/2016 (FAIXA 1 - MUNICÍPIO ESPECIAL) | T3: 294 | U3: 1 | V3: =R3*T3*U3 -> 588 | W3: LIMIAR | X3: REALIZAÇÃO DE CURSO COM APENAS UM PROFESSOR CONVIDADO | Y3: CURSO PRECISA DE PELO MENOS UM PROFESSOR PARA SER REALIZADO | Z3: NÃO É POSSÍVEL REALIZAR CURSO SEM PROFESSOR | AA3: CURSO PRECISA DE PELO MENOS UM PROFESSOR PARA SER REALIZADO | AB3: NÃO É POSSÍVEL REALIZAR CURSO SEM PROFESSOR
A4: FAOP | B4: Subsecretaria de Promoção Cultural | D4: Superintendência de artes | E4: =CONCATENATE(A4,"PROG") -> FAOPPROG | F4: 060 - FORMACAO CULTURAL | G4: =CONCATENATE("P",(LEFT(F4,3)),A4) -> P060FAOP | H4: 1029 - ATIVIDADES DE ENSINO, FORMACAO E QUALIFICACAO PROFISSIONAL E TECNICA EM CULTURA E PATRIMONIO | I4: 3301 - PASSAGENS - PESSOA FÍSICA | J4: =CONCATENATE("ELEM",LEFT(#REF!,2)) -> #REF! | K4: Diárias e viagens | L4: 3 - Outras Despesas de Custeio | M4: Diárias e viagens | N4: 10 | O4: PASSAGEM DE IDA E VOLTA PARA ATENDER DESLOCAMENTO DE PROFESSOR CONVIDADO PARA LECIONAR | P4: NÃO | Q4: 1 PASSAGEM DE IDA E VOLTA DE CONTAGEM PARA BH | R4: 1 | S4: VALOR DA PASSAGEM IDA E VOLTA | T4: 20 | U4: 1 | V4: =R4*T4*U4 -> 20 | W4: LIMIAR | X4: REALIZAÇÃO DE CURSO COM APENAS UM PROFESSOR CONVIDADO | Y4: CURSO PRECISA DE PELO MENOS UM PROFESSOR PARA SER REALIZADO | Z4: NÃO É POSSÍVEL REALIZAR CURSO SEM PROFESSOR | AA4: CURSO PRECISA DE PELO MENOS UM PROFESSOR PARA SER REALIZADO | AB4: NÃO É POSSÍVEL REALIZAR CURSO SEM PROFESSOR
A5: FAOP | B5: Subsecretaria de Promoção Cultural | D5: Superintendência de artes | E5: =CONCATENATE(A5,"PROG") -> FAOPPROG | F5: 060 - FORMACAO CULTURAL | G5: =CONCATENATE("P",(LEFT(F5,3)),A5) -> P060FAOP | H5: 1029 - ATIVIDADES DE ENSINO, FORMACAO E QUALIFICACAO PROFISSIONAL E TECNICA EM CULTURA E PATRIMONIO | I5: 1401 - DIÁRIAS CIVIL | J5: =CONCATENATE("ELEM",LEFT(#REF!,2)) -> #REF! | K5: Diárias e viagens | L5: 3 - Outras Despesas de Custeio | M5: Diárias e viagens | N5: 10 | O5: DIÁRIA PARA ATENDER HOSPEDAGEM DE PROFESSOR EXTRA CONVIDADO PARA LECIONAR | P5: SIM | Q5: NÚMERO DE DIÁRIAS UTILIZADAS (2) X NUMERO DE SERVIDORES FAVORECIDOS (1) | R5: 2 | S5: VALOR DA DIÁRIA DE ACORDO COM DECRETO 47.045/2016 (FAIXA 1 - MUNICÍPIO ESPECIAL) | T5: 294 | U5: 1 | V5: =R5*T5*U5 -> 588 | W5: LIMIAR | X5: CURSO MINISTRADO COM UM PROFESSOR EXTRA CONVIDADO | Y5: CURSO MENOS INTERESSANTE, MENOR CARGA HORÁRIO E POSSÍVEL MENOR ADESÃO DO PÚBLICO | Z5: CURSO COM MAIOR QUALIDADE E ADESÃO DO PÚBLICO | AA5: CURSO MENOS INTERESSANTE, MENOR CARGA HORÁRIO E POSSÍVEL MENOR ADESÃO DO PÚBLICO | AB5: CURSO COM MAIOR QUALIDADE E ADESÃO DO PÚBLICO
A6: FAOP | B6: Subsecretaria de Promoção Cultural | D6: Superintendência de artes | E6: =CONCATENATE(A6,"PROG") -> FAOPPROG | F6: 060 - FORMACAO CULTURAL | G6: =CONCATENATE("P",(LEFT(F6,3)),A6) -> P060FAOP | H6: 1029 - ATIVIDADES DE ENSINO, FORMACAO E QUALIFICACAO PROFISSIONAL E TECNICA EM CULTURA E PATRIMONIO | I6: 3301 - PASSAGENS - PESSOA FÍSICA | J6: =CONCATENATE("ELEM",LEFT(#REF!,2)) -> #REF! | K6: Diárias e viagens | L6: 3 - Outras Despesas de Custeio | M6: Diárias e viagens | N6: 10 | O6: PASSAGEM DE IDA E VOLTA PARA ATENDER DESLOCAMENTO DE PROFESSOR EXTRA CONVIDADO PARA LECIONAR | P6: SIM | Q6: 1 PASSAGEM DE IDA E VOLTA DE CONTAGEM PARA BH | R6: 1 | S6: VALOR DA PASSAGEM IDA E VOLTA | T6: 20 | U6: 1 | V6: =R6*T6*U6 -> 20 | W6: LIMIAR | X6: CURSO MINISTRADO COM UM PROFESSOR EXTRA CONVIDADO | Y6: CURSO MENOS INTERESSANTE, MENOR CARGA HORÁRIO E POSSÍVEL MENOR ADESÃO DO PÚBLICO | Z6: CURSO COM MAIOR QUALIDADE E ADESÃO DO PÚBLICO | AA6: CURSO MENOS INTERESSANTE, MENOR CARGA HORÁRIO E POSSÍVEL MENOR ADESÃO DO PÚBLICO | AB6: CURSO COM MAIOR QUALIDADE E ADESÃO DO PÚBLICO
A7: FAOP | B7: Subsecretaria de Promoção Cultural | D7: Superintendência de artes | E7: =CONCATENATE(A7,"PROG") -> FAOPPROG | F7: 060 - FORMACAO CULTURAL | G7: =CONCATENATE("P",(LEFT(F7,3)),A7) -> P060FAOP | H7: 1029 - ATIVIDADES DE ENSINO, FORMACAO E QUALIFICACAO PROFISSIONAL E TECNICA EM CULTURA E PATRIMONIO | I7: 3952 - CONTRATAÇÃO DE ESTAGIÁRIOS | J7: =CONCATENATE("ELEM",LEFT(#REF!,2)) -> #REF! | K7: Estagiários | L7: 3 - Outras Despesas de Custeio | M7: Estagiários | N7: 60 | O7: ESTAGIÁRIO CARGA HORÁRIA 30 HORAS SEMANAIS | P7: SIM | Q7: NÚMERO DE ESTAGIÁRIOS | R7: 2 | S7: VALOR DA BOLSA ESTAGIÁRIO + VALE TRANSPORTE | T7: 900 | U7: 12 | V7: =R7*T7*U7 -> 21600 | W7: INCREMENTAL | X7: EXPANSÃO DOS CURSOS PARA A MODALIDADE EAD | Y7: MAIOR DEMORA PARA A REALIZAÇÃO DOS PROCESSOS DE TESTE DA PLATAFORMA; CURSO MAIS DESORGANIZADO E ACÚMULO DE TAREFAS AOS SERVIDORES | Z7: PROCESSOS MAIS ÁGEIS; CURSO MAIS ORGANIZADO E SERVIDORES MENOS SOBRECARREGADOS | AA7: MAIOR DEMORA PARA A REALIZAÇÃO DOS PROCESSOS DE TESTE DA PLATAFORMA; CURSO MAIS DESORGANIZADO E ACÚMULO DE TAREFAS AOS SERVIDORES | AB7: PROCESSOS MAIS ÁGEIS; CURSO MAIS ORGANIZADO E SERVIDORES MENOS SOBRECARREGADOS | AC7: 3 | AD7: 3
A8: FAOP | B8: Subsecretaria de Promoção Cultural | D8: Superintendência de artes | E8: =CONCATENATE(A8,"PROG") -> FAOPPROG | F8: 060 - FORMACAO CULTURAL | G8: =CONCATENATE("P",(LEFT(F8,3)),A8) -> P060FAOP | H8: 1029 - ATIVIDADES DE ENSINO, FORMACAO E QUALIFICACAO PROFISSIONAL E TECNICA EM CULTURA E PATRIMONIO | I8: 3005 - MATERIAL PARA ESCRITÓRIO | J8: =CONCATENATE("ELEM",LEFT(#REF!,2)) -> #REF! | K8: Aquisição de material de consumo | L8: 3 - Outras Despesas de Custeio | M8: Aquisição de material de consumo | N8: 10 | O8: PACOTE DE FOLHA A4 BRANCA COM 100 UNIDADES | P8: NÃO | Q8: MÉDIA DE CONSUMO PARA UM CURSO DE 2 DIAS | R8: 1 | S8: CONSULTA DO VALOR DO ITEM NO SIAD | T8: 25 | U8: 1 | V8: =R8*T8*U8 -> 25 | W8: LIMIAR | X8: REALIZAÇÃO DE CURSO COM APENAS UM PROFESSOR CONVIDADO | Y8: ALUNOS PRECISAM DE FOLHA PARA REALIZAR AS ATIVIDADES AVALIATIVAS | Z8: NÃO É POSSÍVEL REALIZAR AS ATIVIDADES SEM QUE OS ALUNOS TENHAM ONDE ESCREVER AS RESPOSTAS | AA8: ALUNOS PRECISAM DE FOLHA PARA REALIZAR AS ATIVIDADES AVALIATIVAS | AB8: NÃO É POSSÍVEL REALIZAR AS ATIVIDADES SEM QUE OS ALUNOS TENHAM ONDE ESCREVER AS RESPOSTAS
A9: FAOP | B9: Subsecretaria de Promoção Cultural | D9: Superintendência de artes | E9: =CONCATENATE(A9,"PROG") -> FAOPPROG | F9: 060 - FORMACAO CULTURAL | G9: =CONCATENATE("P",(LEFT(F9,3)),A9) -> P060FAOP | H9: 1029 - ATIVIDADES DE ENSINO, FORMACAO E QUALIFICACAO PROFISSIONAL E TECNICA EM CULTURA E PATRIMONIO | I9: 3005 - MATERIAL PARA ESCRITÓRIO | J9: =CONCATENATE("ELEM",LEFT(#REF!,2)) -> #REF! | K9: Aquisição de material de consumo | L9: 3 - Outras Despesas de Custeio | M9: Aquisição de material de consumo | N9: 60 | O9: KIT DE MATERIAL PARA CURSO (CANETA ESFEROGRÁFICA AZUL, LÁPIS, BORRACHA) | P9: NÃO | Q9: 1 KIT POR PESSOA X MÉDIA DE INSCRIÇÕES NO CURSO (100) | R9: 100 | S9: CONSULTA DO VALOR DOS ITENS QUE COMPÕES O KIT NO SIAD | T9: 8 | U9: 1 | V9: =R9*T9*U9 -> 800 | W9: INCREMENTAL | X9: FORNECIMENTO DE ITENS DE SUPORTE AO PARTICIPANTE DOS CURSOS | Y9: MENOR ADESÃO AO CURSO DEVIDO AO PÚBLICO ALVO NÃO POSSUIR CONDIÇÕES FINANCEIRAS DE ADQUIRIR OS MATERIAIS DO KIT | Z9: MAIOR ADESÃO DO PÚBLICO ALVO E MELHOR DESEMPENHO DOS ALUNOS | AA9: MENOR ADESÃO AO CURSO DEVIDO AO PÚBLICO ALVO NÃO POSSUIR CONDIÇÕES FINANCEIRAS DE ADQUIRIR OS MATERIAIS DO KIT | AB9: MAIOR ADESÃO DO PÚBLICO ALVO E MELHOR DESEMPENHO DOS ALUNOS | AC9: 1 | AD9: 2
A10: FAOP | B10: Subsecretaria de Promoção Cultural | D10: Superintendência de artes | E10: =CONCATENATE(A10,"PROG") -> FAOPPROG | F10: 060 - FORMACAO CULTURAL | G10: =CONCATENATE("P",(LEFT(F10,3)),A10) -> P060FAOP | H10: 1029 - ATIVIDADES DE ENSINO, FORMACAO E QUALIFICACAO PROFISSIONAL E TECNICA EM CULTURA E PATRIMONIO | I10: 3903 - FORNECIMENTO DE ALIMENTAÇÃO | J10: =CONCATENATE("ELEM",LEFT(#REF!,2)) -> #REF! | K10: Alimentação | L10: 3 - Outras Despesas de Custeio | M10: Alimentação | N10: 60 | O10: FORNECIMENTO DE COFFEE BREAK PARA O CURSO | P10: SIM | Q10: CONTRATO FIRMADO | R10: 1 | S10: VALOR HISTÓRICO DOS CONTRADOS FIRMADOS | T10: 500 | U10: 1 | V10: =R10*T10*U10 -> 500 | W10: INCREMENTAL | X10: FORNECIMENTO DE ITENS DE SUPORTE AO PARTICIPANTE DOS CURSOS | Y10: POSSIBILIDADE DO PÚBLICO ALVO NÃO ADERIR AO CURSO POR QUESTÕES FINANCEIRAS QUE IMPOSSIBILITEM A AQUISIÇÃO DE LANCHE DURANTE O DIA; MAIOR TEMPO DE INTERVALO DURANTE O CURSO E MENOR ADESÃO DO PÚBLICO AO CURSO | Z10: CURSO MAIS ATRATIVO, GERANDO MAIOR ADESÃO DO PÚBLICO ALVO | AA10: POSSIBILIDADE DO PÚBLICO ALVO NÃO ADERIR AO CURSO POR QUESTÕES FINANCEIRAS QUE IMPOSSIBILITEM A AQUISIÇÃO DE LANCHE DURANTE O DIA; MAIOR TEMPO DE INTERVALO DURANTE O CURSO E MENOR ADESÃO DO PÚBLICO AO CURSO | AB10: CURSO MAIS ATRATIVO, GERANDO MAIOR ADESÃO DO PÚBLICO ALVO | AC10: 1 | AD10: 2
A11: FAOP | B11: Subsecretaria de Promoção Cultural | D11: Superintendência de artes | E11: =CONCATENATE(A11,"PROG") -> FAOPPROG | F11: 060 - FORMACAO CULTURAL | G11: =CONCATENATE("P",(LEFT(F11,3)),A11) -> P060FAOP | H11: 1029 - ATIVIDADES DE ENSINO, FORMACAO E QUALIFICACAO PROFISSIONAL E TECNICA EM CULTURA E PATRIMONIO | I11: 4007 - AQUISIÇÃO DE SOFTWARE DESENVOLVIDOS PELA PRODEMGE | J11: =CONCATENATE("ELEM",LEFT(#REF!,2)) -> #REF! | K11: PRODEMGE | L11: 4 - Investimento | M11: PRODEMGE | N11: 10 | O11: DESENVOLVIMENTO DE PLATAFORMA MOODLE PARA CURSO EAD | P11: SIM | Q11: CONTRATO FIRMADO | R11: 1 | S11: TABELA DE SERVIÇOS PRODEMGE | T11: 5000 | U11: 1 | V11: =R11*T11*U11 -> 5000 | W11: INCREMENTAL | X11: EXPANSÃO DOS CURSOS PARA A MODALIDADE EAD | Y11: MENOR PÚBLICO DEVIDO À OFERTA DE CURSOS SOMENTE NA MODALIDADE PRESENCIAL | Z11: ATINGIR MAIOR PÚBLICO | AA11: MENOR PÚBLICO DEVIDO À OFERTA DE CURSOS SOMENTE NA MODALIDADE PRESENCIAL | AB11: ATINGIR MAIOR PÚBLICO | AC11: 3 | AD11: 3
A12: FAOP | B12: Subsecretaria de Promoção Cultural | D12: Superintendência de artes | E12: =CONCATENATE(A12,"PROG") -> FAOPPROG | F12: 056 - FOMENTO, DEMOCRATIZACAO E ACESSO A CULTURA E AO TURISMO | G12: =CONCATENATE("P",(LEFT(F12,3)),A12) -> P056FAOP | H12: 1027 - ACOES DE DIFUSAO DAS ARTES E DO PATRIMONIO CULTURAL | I12: 3702 - LOCAÇÃO DE SERVIÇOS DE APOIO ADMINISTRATIVO | J12: =CONCATENATE("ELEM",LEFT(#REF!,2)) -> #REF! | K12: Demais terceirizados | L12: 3 - Outras Despesas de Custeio | M12: Demais terceirizados | N12: 10 | O12: POSTO DE TRABALHO DE SEGURANÇA 24H | P12: NÃO | Q12: CONTRATATO FIRMADO COM A EMPRESA "SECURITY" | R12: 1 | S12: VALOR MENSAL DO CONTRATO | T12: 2000 | U12: 12 | V12: =R12*T12*U12 -> 24000 | W12: LIMIAR | X12: SEGURANÇA MÍNIMA NECESSÁRIA PARA ATENDER A GUARDA DO MUSEU DURANTE 12H | Y12: AUSÊNCIA DE SEGURANÇA DO MUSEU, DEIXANDO O PRÉDIO COMPLETAMENTE VULNERÁVEL | Z12: REDUÇÃO DO RISCO DE DEPREDAÇÃO DO MUSEU | AA12: AUSÊNCIA DE SEGURANÇA DO MUSEU, DEIXANDO O PRÉDIO COMPLETAMENTE VULNERÁVEL | AB12: REDUÇÃO DO RISCO DE DEPREDAÇÃO DO MUSEU
A13: FAOP | B13: Subsecretaria de Promoção Cultural | D13: Superintendência de artes | E13: =CONCATENATE(A13,"PROG") -> FAOPPROG | F13: 056 - FOMENTO, DEMOCRATIZACAO E ACESSO A CULTURA E AO TURISMO | G13: =CONCATENATE("P",(LEFT(F13,3)),A13) -> P056FAOP | H13: 1027 - ACOES DE DIFUSAO DAS ARTES E DO PATRIMONIO CULTURAL | I13: 3702 - LOCAÇÃO DE SERVIÇOS DE APOIO ADMINISTRATIVO | J13: =CONCATENATE("ELEM",LEFT(#REF!,2)) -> #REF! | K13: Demais terceirizados | L13: 3 - Outras Despesas de Custeio | M13: Demais terceirizados | N13: 60 | O13: ADITIVO PARA SEGURANÇA 24 HORAS (ADICIONAL DE 1 SEGURANÇA) | P13: SIM | Q13: ADITIVO CONTRATUAL COM A EMPRESA "SECURITY" | R13: 1 | S13: VALOR MENSAL DO ADITIVO (NÚMERO DE POSTOS DE TRABALHO X VALOR DO POSTO) | T13: 2000 | U13: 12 | V13: =R13*T13*U13 -> 24000 | W13: LIMIAR | X13: AUMENTO DA SEGURANÇA DO MUSEU, VIABILIZANDO GUARDA NOS PERÍODOS DIURNO E NOTURNO | Y13: MAIOR RISCO DE DEPREDAÇÃO, VISTO QUE SÓ HÁ SEGURANÇA NO LOCAL DURANTE UM PERÍODO DO DIA | Z13: MAIOR SEGURANÇA NO PRÉDIO DA FUNDAÇÃO COM VIGILÂNCIA 24 HORAS | AA13: MAIOR RISCO DE DEPREDAÇÃO, VISTO QUE SÓ HÁ SEGURANÇA NO LOCAL DURANTE UM PERÍODO DO DIA | AB13: MAIOR SEGURANÇA NO PRÉDIO DA FUNDAÇÃO COM VIGILÂNCIA 24 HORAS
A14: FAOP | B14: Subsecretaria de Promoção Cultural | D14: Superintendência de artes | E14: =CONCATENATE(A14,"PROG") -> FAOPPROG | F14: 056 - FOMENTO, DEMOCRATIZACAO E ACESSO A CULTURA E AO TURISMO | G14: =CONCATENATE("P",(LEFT(F14,3)),A14) -> P056FAOP | H14: 1027 - ACOES DE DIFUSAO DAS ARTES E DO PATRIMONIO CULTURAL | I14: 3703 - LOCAÇÃO DE SERVIÇOS DE CONSERVAÇÃO E LIMPEZA REALIZADOS PELA MGS | J14: =CONCATENATE("ELEM",LEFT(#REF!,2)) -> #REF! | K14: Terceirizados - MGS | L14: 3 - Outras Despesas de Custeio | M14: Terceirizados - MGS | N14: 10 | O14: POSTO DE TRABALHO DE MANUTENÇÃO E LIMPEZA | P14: NÃO | Q14: NÚMERO DE POSTOS DE TRABALHO PARA MANUTENÇÃO DO MUSEU | R14: 3 | S14: VALOR MENSAL DO POSTO DE TRABALHO CONFORME CONTRATO | T14: 1500 | U14: 12 | V14: =R14*T14*U14 -> 54000 | W14: LIMIAR | X14: LIMPEZA EFETUADA DE TRÊS EM TRÊS HORAS NOS SALÕES DO MUSEU | Y14: SALÃO DO MUSEU PODE COM ACÚMULO DE SUJEIRA, GERANDO MÁ IMPRESSÃO AOS FREQUENTADORES E DINIMUINDO A VISITAÇÃO | Z14: MUSEU MINIMAMENTE LIMPO | AA14: SALÃO DO MUSEU PODE COM ACÚMULO DE SUJEIRA, GERANDO MÁ IMPRESSÃO AOS FREQUENTADORES E DINIMUINDO A VISITAÇÃO | AB14: MUSEU MINIMAMENTE LIMPO
A15: FAOP | B15: Subsecretaria de Promoção Cultural | D15: Superintendência de artes | E15: =CONCATENATE(A15,"PROG") -> FAOPPROG | F15: 056 - FOMENTO, DEMOCRATIZACAO E ACESSO A CULTURA E AO TURISMO | G15: =CONCATENATE("P",(LEFT(F15,3)),A15) -> P056FAOP | H15: 1027 - ACOES DE DIFUSAO DAS ARTES E DO PATRIMONIO CULTURAL | I15: 3703 - LOCAÇÃO DE SERVIÇOS DE CONSERVAÇÃO E LIMPEZA REALIZADOS PELA MGS | J15: =CONCATENATE("ELEM",LEFT(#REF!,2)) -> #REF! | K15: Terceirizados - MGS | L15: 3 - Outras Despesas de Custeio | M15: Terceirizados - MGS | N15: 60 | O15: POSTO DE TRABALHO DE MANUTENÇÃO E LIMPEZA | P15: SIM | Q15: NÚMERO DE POSTOS DE TRABALHO PARA MANUTENÇÃO DO MUSEU | R15: 2 | S15: VALOR MENSAL DO POSTO DE TRABALHO CONFORME CONTRATO | T15: 1500 | U15: 12 | V15: =R15*T15*U15 -> 36000 | W15: INCREMENTAL | X15: LIMPEZA EFETUADA DE HORA EM HORA NOS SALÕES DO MUSEU | Y15: SALÃO DO MUSEU PODE FICAR SUJO ENTRE UMA E OUTRA VISITA, GERANDO INSATISFAÇÃO DOS FREQUENTADORES | Z15: MUSEU MAIS LIMPO, USUÁRIOS SATISFEITOS E MAIOR VISITAÇÃO | AA15: SALÃO DO MUSEU PODE FICAR SUJO ENTRE UMA E OUTRA VISITA, GERANDO INSATISFAÇÃO DOS FREQUENTADORES | AB15: MUSEU MAIS LIMPO, USUÁRIOS SATISFEITOS E MAIOR VISITAÇÃO | AC15: 2 | AD15: 1
E16: =CONCATENATE(A16,"PROG") -> PROG | G16: =CONCATENATE("P",(LEFT(F16,3)),A16) -> P | J16: =CONCATENATE("ELEM",LEFT(I16,2)) -> ELEM | M16: #N/A
E17: =CONCATENATE(A17,"PROG") -> PROG | G17: =CONCATENATE("P",(LEFT(F17,3)),A17) -> P | J17: =CONCATENATE("ELEM",LEFT(I17,2)) -> ELEM | M17: #N/A
E18: =CONCATENATE(A18,"PROG") -> PROG | G18: =CONCATENATE("P",(LEFT(F18,3)),A18) -> P | J18: =CONCATENATE("ELEM",LEFT(I18,2)) -> ELEM | M18: #N/A
E19: =CONCATENATE(A19,"PROG") -> PROG | G19: =CONCATENATE("P",(LEFT(F19,3)),A19) -> P | J19: =CONCATENATE("ELEM",LEFT(I19,2)) -> ELEM | M19: #N/A
E20: =CONCATENATE(A20,"PROG") -> PROG | G20: =CONCATENATE("P",(LEFT(F20,3)),A20) -> P | J20: =CONCATENATE("ELEM",LEFT(I20,2)) -> ELEM | M20: #N/A
E21: =CONCATENATE(A21,"PROG") -> PROG | G21: =CONCATENATE("P",(LEFT(F21,3)),A21) -> P | J21: =CONCATENATE("ELEM",LEFT(I21,2)) -> ELEM | M21: #N/A
E22: =CONCATENATE(A22,"PROG") -> PROG | G22: =CONCATENATE("P",(LEFT(F22,3)),A22) -> P | J22: =CONCATENATE("ELEM",LEFT(I22,2)) -> ELEM | M22: #N/A
E23: =CONCATENATE(A23,"PROG") -> PROG | G23: =CONCATENATE("P",(LEFT(F23,3)),A23) -> P | J23: =CONCATENATE("ELEM",LEFT(I23,2)) -> ELEM | M23: #N/A
E24: =CONCATENATE(A24,"PROG") -> PROG | G24: =CONCATENATE("P",(LEFT(F24,3)),A24) -> P | J24: =CONCATENATE("ELEM",LEFT(I24,2)) -> ELEM | M24: #N/A
E25: =CONCATENATE(A25,"PROG") -> PROG | G25: =CONCATENATE("P",(LEFT(F25,3)),A25) -> P | J25: =CONCATENATE("ELEM",LEFT(I25,2)) -> ELEM | M25: #N/A
E26: =CONCATENATE(A26,"PROG") -> PROG | G26: =CONCATENATE("P",(LEFT(F26,3)),A26) -> P | J26: =CONCATENATE("ELEM",LEFT(I26,2)) -> ELEM | M26: #N/A
E27: =CONCATENATE(A27,"PROG") -> PROG | G27: =CONCATENATE("P",(LEFT(F27,3)),A27) -> P | J27: =CONCATENATE("ELEM",LEFT(I27,2)) -> ELEM | M27: #N/A
... E501: =CONCATENATE(A501,"PROG") -> PROG | G501: =CONCATENATE("P",(LEFT(F501,3)),A501) -> P | J501: =CONCATENATE("ELEM",LEFT(I501,2)) -> ELEM | M501: #N/A

Sheet EXEMPLO PREENCHIMENTO OBZ
A1: UNIDADE ORÇAMENTÁRIA (NÍVEL 1) | B1: SUBSECRETARIA (NÍVEL 2) | C1: SUB SIGLA | D1: SUPERINTENDENCIA (NÍVEL 3) | E1: PROGRAMAUO | F1: PROGRAMA | G1: prog cod | H1: AÇÃO | I1: ENTREGA | J1: ELEMENTO | K1: elem cod | L1: ELEMENTO_ITEM | M1: GRUPO | N1: FONTEUO | O1: FONTE (OPCIONAL) | P1: ITEM DE MATERIAL (OPCIONAL) | Q1: NOVO? | R1: PREMISSA VOLUME | S1: VOLUME | T1: PREMISSA DE PREÇO | U1: PREÇO UNITÁRIO | V1: FREQUÊNCIA PAGAMENTO | W1: VALOR TOTAL ITEM | X1: CLASSIFICAÇÃO CENÁRIO | Y1: DESCRIÇÃO DO CENÁRIO - pacotes de despesa / gera valor agregado | Z1: RISCO DE NÃO FAZER | AA1: BENEFICIO AO FAZER | AB1: PRIORIDADE N3 | AC1: PRIORIDADE N2 | AD1: PRIORIDADE N1
A2: FAOP | E2: =CONCATENATE(A2,"PROG") -> FAOPPROG | F2: 060 - FORMACAO CULTURAL | G2: =CONCATENATE("P",(LEFT(F2,3)),A2) -> P060FAOP | H2: 1029 - ATIVIDADES DE ENSINO, FORMACAO E QUALIFICACAO PROFISSIONAL E TECNICA EM CULTURA E PATRIMONIO | I2: CURSO DE CAPACITAÇÃO | J2: 30 - MATERIAL DE CONSUMO | K2: =CONCATENATE("ELEM",LEFT(J2,2)) -> ELEM30 | L2: 3012 - MEDICAMENTOS | M2: 3 - Outras Despesas de Custeio | N2: =CONCATENATE("FONTE",A2) -> FONTEFAOP | O2: 45 | Q2: NÃO | R2: NÚMERO DE DIÁRIAS UTILIZADAS (2) X NUMERO DE SERVIDORES FAVORECIDOS (1) | S2: 2 | T2: VALOR DA DIÁRIA | U2: 200 | V2: 1 | W2: =S2*U2*V2 -> 400 | X2: LIMIAR | Y2: curso com um professor | Z2: curso precisa de pelo menos um professor | AA2: não tem como ter curso sem professor
A3: FAOP | E3: =CONCATENATE(A3,"PROG") -> FAOPPROG | F3: 060 - FORMACAO CULTURAL | G3: =CONCATENATE("P",(LEFT(F3,3)),A3) -> P060FAOP | H3: 1029 - ATIVIDADES DE ENSINO, FORMACAO E QUALIFICACAO PROFISSIONAL E TECNICA EM CULTURA E PATRIMONIO | I3: CURSO DE CAPACITAÇÃO | J3: 33 - PASSAGENS E DESPESAS COM LOCOMOÇÃO | K3: =CONCATENATE("ELEM",LEFT(J3,2)) -> ELEM33 | L3: 3301 - PASSAGENS - PESSOA FÍSICA | M3: 3 - Outras Despesas de Custeio | N3: =CONCATENATE("FONTE",A3) -> FONTEFAOP | O3: 45 | Q3: NÃO | R3: 1 PASSAGEM DE IDA E VOLTA DE OURO PRETO PARA BH | S3: 1 | T3: VALOR DA PASSAGEM IDA E VOLTA | U3: 45 | V3: 1 | W3: =S3*U3*V3 -> 45 | X3: LIMIAR | Y3: curso com um professor | Z3: curso precisa de pelo menos um professor | AA3: não tem como ter curso sem professor
A4: FAOP | E4: =CONCATENATE(A4,"PROG") -> FAOPPROG | F4: 060 - FORMACAO CULTURAL | G4: =CONCATENATE("P",(LEFT(F4,3)),A4) -> P060FAOP | H4: 1029 - ATIVIDADES DE ENSINO, FORMACAO E QUALIFICACAO PROFISSIONAL E TECNICA EM CULTURA E PATRIMONIO | I4: CURSO DE CAPACITAÇÃO | J4: 14 - DIÁRIAS - CIVIL | K4: =CONCATENATE("ELEM",LEFT(J4,2)) -> ELEM14 | L4: 1401 - DIÁRIAS CIVIL | M4: 3 - Outras Despesas de Custeio | N4: =CONCATENATE("FONTE",A4) -> FONTEFAOP | O4: 45 | Q4: NÃO | R4: NÚMERO DE DIÁRIAS UTILIZADAS (2) X NUMERO DE SERVIDORES FAVORECIDOS (1) | S4: 2 | T4: VALOR DA DIÁRIA | U4: 200 | V4: 1 | W4: =S4*U4*V4 -> 400 | X4: INCREMENTAL | Y4: curso com professor convidado | Z4: CURSO MENOS INTERESSANTE, MENOR CARGA HORÁRIO E POSSÍVEL MENOS ADESÃO DO PÚBLICO | AA4: 1 | AB4: 1
A5: FAOP | E5: =CONCATENATE(A5,"PROG") -> FAOPPROG | F5: 060 - FORMACAO CULTURAL | G5: =CONCATENATE("P",(LEFT(F5,3)),A5) -> P060FAOP | H5: 1029 - ATIVIDADES DE ENSINO, FORMACAO E QUALIFICACAO PROFISSIONAL E TECNICA EM CULTURA E PATRIMONIO | I5: CURSO DE CAPACITAÇÃO EM RESTAURAÇÃO | J5: 33 - PASSAGENS E DESPESAS COM LOCOMOÇÃO | K5: =CONCATENATE("ELEM",LEFT(J5,2)) -> ELEM33 | L5: 3301 - PASSAGENS - PESSOA FÍSICA | M5: 3 - Outras Despesas de Custeio | N5: =CONCATENATE("FONTE",A5) -> FONTEFAOP | O5: 45 | Q5: NÃO | R5: 1 PASSAGEM DE IDA E VOLTA DE OURO PRETO PARA BH | S5: 1 | T5: VALOR DA PASSAGEM IDA E VOLTA | U5: 45 | V5: 1 | W5: =S5*U5*V5 -> 45 | X5: INCREMENTAL | Y5: curso com professor convidado | Z5: CURSO MENOS INTERESSANTE, MENOR CARGA HORÁRIO E POSSÍVEL MENOS ADESÃO DO PÚBLICO | AA5: CURSO COM MAIOR QUALIDADE E ADESÃO DO PÚBLICO | AB5: 1
A6: FAOP | E6: =CONCATENATE(A6,"PROG") -> FAOPPROG | F6: 060 - FORMACAO CULTURAL | G6: =CONCATENATE("P",(LEFT(F6,3)),A6) -> P060FAOP | H6: 1029 - ATIVIDADES DE ENSINO, FORMACAO E QUALIFICACAO PROFISSIONAL E TECNICA EM CULTURA E PATRIMONIO | I6: CURSO DE CAPACITAÇÃO EM RESTAURAÇÃO | J6: 30 - MATERIAL DE CONSUMO | K6: =CONCATENATE("ELEM",LEFT(J6,2)) -> ELEM30 | L6: 3004 - MATERIAL GRÁFICO E IMPRESSOS | M6: 3 - Outras Despesas de Custeio | N6: =CONCATENATE("FONTE",A6) -> FONTEFAOP | O6: 45 | P6: IMPRESSÃO DE FLYER PARA DIVULGAÇÃO (TAMANHO MEIO OFÍCIO) | Q6: NÃO | R6: QUANTITATIVO DE FLYERS NECESSÁRIOS PARA DIVULGAÇÃO DO EVENTO | S6: 300 | T6: PESQUISA DE PREÇO NA INTERNET | U6: 0.3 | V6: 1 | W6: =S6*U6*V6 -> 90 | X6: INCREMENTAL | Y6: curso com um professor | Z6: POUCAS INSCRIÇÕES NO CURSO DEVIDO A FALTA DE DIVULGAÇÃO - TER QUE DIVULGAR SOMENTE PELA INTERNET | AA6: MAIS PESSOAS CONHECENDO O CURSO E MAIORES CHANCES DE INSCRIÇÕES | AB6: 1
A7: FAOP | E7: =CONCATENATE(A7,"PROG") -> FAOPPROG | F7: 060 - FORMACAO CULTURAL | G7: =CONCATENATE("P",(LEFT(F7,3)),A7) -> P060FAOP | H7: 1029 - ATIVIDADES DE ENSINO, FORMACAO E QUALIFICACAO PROFISSIONAL E TECNICA EM CULTURA E PATRIMONIO | I7: CURSO DE CAPACITAÇÃO EM RESTAURAÇÃO | J7: 30 - MATERIAL DE CONSUMO | K7: =CONCATENATE("ELEM",LEFT(J7,2)) -> ELEM30 | L7: 3004 - MATERIAL GRÁFICO E IMPRESSOS | M7: 3 - Outras Despesas de Custeio | N7: =CONCATENATE("FONTE",A7) -> FONTEFAOP | O7: 45 | P7: IMPRESSÃO DE FLYER PARA DIVULGAÇÃO (TAMANHO MEIO OFÍCIO) | Q7: SIM | R7: QUANTITATIVO DE FLYERS NECESSÁRIOS PARA DIVULGAÇÃO DO EVENTO | S7: 200 | T7: PESQUISA DE PREÇO NA INTERNET | U7: 0.3 | V7: 1 | W7: =S7*U7*V7 -> 60 | X7: INCREMENTAL | Y7: curso com um professor e professor convidado | Z7: POUCAS INSCRIÇÕES NO CURSO DEVIDO A FALTA DE DIVULGAÇÃO | AA7: MAIS PESSOAS CONHECENDO O CURSO E MAIORES CHANCES DE INSCRIÇÕES | AB7: 2
A8: FAOP | E8: =CONCATENATE(A8,"PROG") -> FAOPPROG | F8: 060 - FORMACAO CULTURAL | G8: =CONCATENATE("P",(LEFT(F8,3)),A8) -> P060FAOP | H8: 1029 - ATIVIDADES DE ENSINO, FORMACAO E QUALIFICACAO PROFISSIONAL E TECNICA EM CULTURA E PATRIMONIO | I8: CURSO DE CAPACITAÇÃO EM RESTAURAÇÃO | J8: 30 - MATERIAL DE CONSUMO | K8: =CONCATENATE("ELEM",LEFT(J8,2)) -> ELEM30 | L8: 3005 - MATERIAL PARA ESCRITÓRIO | M8: 3 - Outras Despesas de Custeio | N8: =CONCATENATE("FONTE",A8) -> FONTEFAOP | O8: 45 | P8: PACOTE DEFOLHA A4 BRANCA COM 100 UNIDADES | Q8: NÃO | R8: MÉDIA DE CONSUMO PARA UM CURSO DE 2 DIAS | S8: 1 | T8: CONSULTA DO VALOR DO ITEM NO SIAD | U8: 25 | V8: 1 | W8: =S8*U8*V8 -> 25 | X8: LIMIAR | Y8: curso com um professor e professor convidado
A9: FAOP | E9: =CONCATENATE(A9,"PROG") -> FAOPPROG | F9: 060 - FORMACAO CULTURAL | G9: =CONCATENATE("P",(LEFT(F9,3)),A9) -> P060FAOP | H9: 1029 - ATIVIDADES DE ENSINO, FORMACAO E QUALIFICACAO PROFISSIONAL E TECNICA EM CULTURA E PATRIMONIO | I9: CURSO DE CAPACITAÇÃO EM RESTAURAÇÃO | J9: 30 - MATERIAL DE CONSUMO | K9: =CONCATENATE("ELEM",LEFT(J9,2)) -> ELEM30 | L9: 3005 - MATERIAL PARA ESCRITÓRIO | M9: 3 - Outras Despesas de Custeio | N9: =CONCATENATE("FONTE",A9) -> FONTEFAOP | O9: 45 | P9: PACOTE DEFOLHA A4 BRANCA COM 100 UNIDADES | Q9: NÃO | R9: MÉDIA DE CONSUMO PARA UM CURSO DE 2 DIAS | S9: 1 | T9: CONSULTA DO VALOR DO ITEM NO SIAD | U9: 25 | V9: 1 | W9: =S9*U9*V9 -> 25 | X9: LIMIAR | Y9: curso com um professor
X10: INCREMENTAL | Y10: curso com coffe break
X11: INCREMENTAL | Y11: curso com coffe break
A12: FAOP | E12: =CONCATENATE(A12,"PROG") -> FAOPPROG | F12: 060 - FORMACAO CULTURAL | G12: =CONCATENATE("P",(LEFT(F12,3)),A12) -> P060FAOP | H12: 1029 - ATIVIDADES DE ENSINO, FORMACAO E QUALIFICACAO PROFISSIONAL E TECNICA EM CULTURA E PATRIMONIO | I12: MANUTENÇÃO DO ESPAÇO DE REALIZAÇÃO DOS CURSOS | J12: 37 - LOCAÇÃO DE MÃO-DE-OBRA | K12: =CONCATENATE("ELEM",LEFT(J12,2)) -> ELEM37 | L12: 3703 - LOCAÇÃO DE SERVIÇOS DE CONSERVAÇÃO E LIMPEZA REALIZADOS PELA MGS | M12: 3 - Outras Despesas de Custeio | N12: =CONCATENATE("FONTE",A12) -> FONTEFAOP | Q12: NÃO | R12: NÚMERO DE VIGIAS NECESSÁRIOS PARA SEGURANÇA MEIO TURNO | S12: 2 | T12: VALOR MENSAL DO POSTO DE TRABALHO CONFORME CONTRATO | U12: 2000 | V12: 12 | W12: =S12*U12*V12 -> 48000 | X12: LIMIAR
A13: FAOP | E13: =CONCATENATE(A13,"PROG") -> FAOPPROG | F13: 060 - FORMACAO CULTURAL | G13: =CONCATENATE("P",(LEFT(F13,3)),A13) -> P060FAOP | H13: 1029 - ATIVIDADES DE ENSINO, FORMACAO E QUALIFICACAO PROFISSIONAL E TECNICA EM CULTURA E PATRIMONIO | I13: MANUTENÇÃO DO ESPAÇO DE REALIZAÇÃO DOS CURSOS | J13: 37 - LOCAÇÃO DE MÃO-DE-OBRA | K13: =CONCATENATE("ELEM",LEFT(J13,2)) -> ELEM37 | L13: 3703 - LOCAÇÃO DE SERVIÇOS DE CONSERVAÇÃO E LIMPEZA REALIZADOS PELA MGS | M13: 3 - Outras Despesas de Custeio | N13: =CONCATENATE("FONTE",A13) -> FONTEFAOP | Q13: SIM | R13: NÚMERO DE VIGIAS NECESSÁRIOS PARA SEGURANÇA 24 HORAS | S13: 2 | T13: VALOR MENSAL DO POSTO DE TRABALHO CONFORME CONTRATO | U13: 2000 | V13: 12 | W13: =S13*U13*V13 -> 48000 | X13: INCREMENTAL
A14: FAOP | E14: =CONCATENATE(A14,"PROG") -> FAOPPROG | F14: 060 - FORMACAO CULTURAL | G14: =CONCATENATE("P",(LEFT(F14,3)),A14) -> P060FAOP | H14: 1029 - ATIVIDADES DE ENSINO, FORMACAO E QUALIFICACAO PROFISSIONAL E TECNICA EM CULTURA E PATRIMONIO | I14: MANUTENÇÃO DO ESPAÇO DE REALIZAÇÃO DOS CURSOS | J14: 37 - LOCAÇÃO DE MÃO-DE-OBRA | K14: =CONCATENATE("ELEM",LEFT(J14,2)) -> ELEM37 | L14: 3703 - LOCAÇÃO DE SERVIÇOS DE CONSERVAÇÃO E LIMPEZA REALIZADOS PELA MGS | M14: 3 - Outras Despesas de Custeio | N14: =CONCATENATE("FONTE",A14) -> FONTEFAOP | Q14: NÃO | R14: NÚMERO DE FAXINEIRAS PARA MANUTENÇÃO DO ESPAÇO DOS CURSOS | S14: 1 | T14: VALOR MENSAL DO POSTO DE TRABALHO CONFORME CONTRATO | U14: 1500 | V14: 12 | W14: =S14*U14*V14 -> 18000 | X14: LIMIAR | Y14: segurança 24 horas | AB14: 1
A15: FAOP | E15: =CONCATENATE(A15,"PROG") -> FAOPPROG | F15: 060 - FORMACAO CULTURAL | G15: =CONCATENATE("P",(LEFT(F15,3)),A15) -> P060FAOP | H15: 1029 - ATIVIDADES DE ENSINO, FORMACAO E QUALIFICACAO PROFISSIONAL E TECNICA EM CULTURA E PATRIMONIO | I15: MANUTENÇÃO DO ESPAÇO DE REALIZAÇÃO DOS CURSOS | J15: 39 - OUTROS SERVIÇOS DE TERCEIROS - PESSOA JURÍDICA | K15: =CONCATENATE("ELEM",LEFT(J15,2)) -> ELEM39 | L15: 3912 - TARIFA DE ENERGIA ELÉTRICA | M15: 3 - Outras Despesas de Custeio | N15: =CONCATENATE("FONTE",A15) -> FONTEFAOP | Q15: NÃO | R15: fazer o rateio | S15: 1 | T15: VALOR MENSAL DO POSTO DE TRABALHO CONFORME CONTRATO | U15: 1500 | V15: 12 | W15: =S15*U15*V15 -> 18000 | X15: LIMIAR
J16: 39 - OUTROS SERVIÇOS DE TERCEIROS - PESSOA JURÍDICA
A18: DER | E18: =CONCATENATE(A18,"PROG") -> DERPROG | F18: 081 - INFRAESTRUTURA RODOVIARIA | G18: =CONCATENATE("P",(LEFT(F18,3)),A18) -> P081DER | H18: 2039 - RECUPERACAO E MANUTENCAO DA MALHA VIARIA | I18: RECAPEAMENTO DE VIAS | J18: 51 - OBRAS E INSTALAÇÕES | K18: =CONCATENATE("ELEM",LEFT(J18,2)) -> ELEM51 | L18: 5107 - EXECUÇÃO DE OBRAS POR CONTRATO DE BENS NÃO PATRIMONIÁVEIS | M18: 4 - Investimento | N18: =CONCATENATE("FONTE",A18) -> FONTEDER | Q18: NÃO | R18: KM DE RODOVIA A SEREM PAVIMENTADOS | S18: 500 | T18: VALOR MÉDIO POR KM PAVIMENTADO | U18: 50000 | V18: 1 | W18: =S18*U18*V18 -> 25000000
A19: DER | E19: =CONCATENATE(A19,"PROG") -> DERPROG | F19: 081 - INFRAESTRUTURA RODOVIARIA | G19: =CONCATENATE("P",(LEFT(F19,3)),A19) -> P081DER | H19: 2039 - RECUPERACAO E MANUTENCAO DA MALHA VIARIA | I19: RECAPEAMENTO DE VIAS | J19: 35 - SERVIÇOS DE CONSULTORIA | K19: =CONCATENATE("ELEM",LEFT(J19,2)) -> ELEM35 | L19: 3502 - SERVIÇOS DE CONSULTORIA ? PESSOA JURÍDICA | M19: 3 - Outras Despesas de Custeio | N19: =CONCATENATE("FONTE",A19) -> FONTEDER | P19: CONTRATAÇÃO DE CONSULTORIA PARA REALIZAÇÃO DE PROJETO DE ENGENHARIA | Q19: SIM | R19: CONTRATO FIRMADO | S19: 1 | T19: VALOR MÉDIO DE MERCADO | U19: 25000 | V19: 1 | W19: =S19*U19*V19 -> 25000
E20: =CONCATENATE(A20,"PROG") -> PROG | G20: =CONCATENATE("P",(LEFT(F20,3)),A20) -> P | K20: =CONCATENATE("ELEM",LEFT(J20,2)) -> ELEM | N20: =CONCATENATE("FONTE",A20) -> FONTE | W20: =S20*U20*V20 -> 0
E21: =CONCATENATE(A21,"PROG") -> PROG | G21: =CONCATENATE("P",(LEFT(F21,3)),A21) -> P | K21: =CONCATENATE("ELEM",LEFT(J21,2)) -> ELEM | N21: =CONCATENATE("FONTE",A21) -> FONTE | W21: =S21*U21*V21 -> 0
E22: =CONCATENATE(A22,"PROG") -> PROG | G22: =CONCATENATE("P",(LEFT(F22,3)),A22) -> P | K22: =CONCATENATE("ELEM",LEFT(J22,2)) -> ELEM | N22: =CONCATENATE("FONTE",A22) -> FONTE | W22: =S22*U22*V22 -> 0
E23: =CONCATENATE(A23,"PROG") -> PROG | G23: =CONCATENATE("P",(LEFT(F23,3)),A23) -> P | K23: =CONCATENATE("ELEM",LEFT(J23,2)) -> ELEM | N23: =CONCATENATE("FONTE",A23) -> FONTE | W23: =S23*U23*V23 -> 0
E24: =CONCATENATE(A24,"PROG") -> PROG | G24: =CONCATENATE("P",(LEFT(F24,3)),A24) -> P | K24: =CONCATENATE("ELEM",LEFT(J24,2)) -> ELEM | N24: =CONCATENATE("FONTE",A24) -> FONTE | W24: =S24*U24*V24 -> 0
E25: =CONCATENATE(A25,"PROG") -> PROG | G25: =CONCATENATE("P",(LEFT(F25,3)),A25) -> P | K25: =CONCATENATE("ELEM",LEFT(J25,2)) -> ELEM | N25: =CONCATENATE("FONTE",A25) -> FONTE | W25: =S25*U25*V25 -> 0
E26: =CONCATENATE(A26,"PROG") -> PROG | G26: =CONCATENATE("P",(LEFT(F26,3)),A26) -> P | K26: =CONCATENATE("ELEM",LEFT(J26,2)) -> ELEM | N26: =CONCATENATE("FONTE",A26) -> FONTE | W26: =S26*U26*V26 -> 0
E27: =CONCATENATE(A27,"PROG") -> PROG | G27: =CONCATENATE("P",(LEFT(F27,3)),A27) -> P | K27: =CONCATENATE("ELEM",LEFT(J27,2)) -> ELEM | N27: =CONCATENATE("FONTE",A27) -> FONTE | W27: =S27*U27*V27 -> 0
E28: =CONCATENATE(A28,"PROG") -> PROG | G28: =CONCATENATE("P",(LEFT(F28,3)),A28) -> P | K28: =CONCATENATE("ELEM",LEFT(J28,2)) -> ELEM | N28: =CONCATENATE("FONTE",A28) -> FONTE | W28: =S28*U28*V28 -> 0
E29: =CONCATENATE(A29,"PROG") -> PROG | G29: =CONCATENATE("P",(LEFT(F29,3)),A29) -> P | K29: =CONCATENATE("ELEM",LEFT(J29,2)) -> ELEM | N29: =CONCATENATE("FONTE",A29) -> FONTE | W29: =S29*U29*V29 -> 0
E30: =CONCATENATE(A30,"PROG") -> PROG | G30: =CONCATENATE("P",(LEFT(F30,3)),A30) -> P | K30: =CONCATENATE("ELEM",LEFT(J30,2)) -> ELEM | N30: =CONCATENATE("FONTE",A30) -> FONTE | W30: =S30*U30*V30 -> 0
E31: =CONCATENATE(A31,"PROG") -> PROG | G31: =CONCATENATE("P",(LEFT(F31,3)),A31) -> P | K31: =CONCATENATE("ELEM",LEFT(J31,2)) -> ELEM | N31: =CONCATENATE("FONTE",A31) -> FONTE | W31: =S31*U31*V31 -> 0
... E215: =CONCATENATE(A215,"PROG") -> PROG | G215: =CONCATENATE("P",(LEFT(F215,3)),A215) -> P | K215: =CONCATENATE("ELEM",LEFT(J215,2)) -> ELEM | N215: =CONCATENATE("FONTE",A215) -> FONTE | W215: =S215*U215*V215 -> 0

Sheet PONTOS IMPORTANTES
H1: INDICE
B2: PONTOS IMPORTANTES NA ELABORAÇÃO DO OBZ
B4: Cenário Limiar: nível de serviço mínimo aceitável para garantir a execução de entregas (políticas públicas) essenciais às condições de sobrevivência do órgão | E4: Cenário Incremental: despesas que geram nível de serviço e de qualidade superiores, realizadas para melhorar os resultados ou diminuir riscos. (Por exemplo: cenários intermediários e ótimo).
B6: O OBZ terá como foco a margem discricionária do orçamento de cada órgão: despesas de custeio e capital sobre as quais a unidade tem liberdade de alocação. As Planilhas OBZ não conterão, portanto: Despesas com pessoal (Grupo 1) e auxílios (IPU 7); Fontes de recursos vinculadas a instrumentos jurídicos (exemplos: convênios e contrapartidas, fontes federais, recursos da Vale, etc.); Emendas parlamentares e de CPP (IPUs 8 e 4); Despesas com precatórios (IPU 9); Despesas de Recursos Recebidos para Contrapartida (IPU 3 e 6) e Despesas de Exercícios Anteriores (DEA - Elemento de despesa 92)
B8: PONTOS DE ATENÇÃO – PREENCHIMENTO DA PLANILHA
B10: Preencher riscos de não fazer e benefícios de fazer para: Cenários Limiar e Incremental | E10: Não existe prioridade entre cenários limiares de diferentes níveis N3. Todo cenário limiar será prioridade 0 (zero).
B12: Se atentar ao número de cenários por ação, com intuito de viabilizar análise gerencial: o nível N1 analisará toda a planilha, portanto é necessário que a forma de construção dos cenários permita uma visão consolidada dos dados, e apresente um valor significante em relação ao orçamento do órgão.

Sheet ELEMENTO
A1: 13 - OBRIGAÇÕES PATRONAIS | B1: 14 - DIÁRIAS - CIVIL | C1: 15 - DIÁRIAS - MILITAR | D1: 16 - OUTRAS DESPESAS VARIÁVEIS - PESSOAL CIVIL | E1: 17 - OUTRAS DESPESAS VARIÁVEIS - PESSOAL MILITAR | F1: 18 - AUXÍLIO FINANCEIRO A ESTUDANTES | G1: 19 - AUXÍLIO-FARDAMENTO | H1: 20 - AUXÍLIO FINANCEIRO A PESQUISADORES | I1: 30 - MATERIAL DE CONSUMO | J1: 31 - PREMIAÇÕES CULTURAIS, ARTÍSTICAS, CIENTÍFICAS, DESPORTIVAS E OUTRAS. | K1: 32 - MATERIAL, BEM OU SERVIÇO PARA DISTRIBUIÇÃO GRATUITA | L1: 33 - PASSAGENS E DESPESAS COM LOCOMOÇÃO | M1: 34 - OUTRAS DESPESAS DE PESSOAL DECORRENTES DE CONTRATOS DE TERCEIRIZAÇÃO | N1: 35 - SERVIÇOS DE CONSULTORIA | O1: 36 - OUTROS SERVIÇOS DE TERCEIROS - PESSOA FÍSICA | P1: 37 - LOCAÇÃO DE MÃO-DE-OBRA | Q1: 38 - ARRENDAMENTO MERCANTIL | R1: 39 - OUTROS SERVIÇOS DE TERCEIROS - PESSOA JURÍDICA | S1: 40 - SERVIÇOS DE TECNOLOGIA DA INFORMAÇÃO E COMUNICAÇÃO - PESSOA JURÍDICA | T1: 41 - CONTRIBUIÇÕES | U1: 42 - AUXÍLIOS | V1: 43 - SUBVENÇÕES SOCIAIS | W1: 45 - SUBVENÇÕES ECONÔMICAS | X1: 47 - OBRIGAÇÕES TRIBUTÁRIAS E CONTRIBUTIVAS | Y1: 48 - OUTROS AUXÍLIOS FINANCEIROS A PESSOAS FÍSICAS | Z1: 51 - OBRAS E INSTALAÇÕES | AA1: 52 - EQUIPAMENTOS E MATERIAL PERMANENTE | AB1: 61 - AQUISIÇÃO DE IMÓVEIS | AC1: 62 - AQUISIÇÃO DE PRODUTOS PARA REVENDA | AD1: 63 - AQUISIÇÃO DE TÍTULOS DE CRÉDITO | AE1: 64 - AQUISIÇÃO DE TÍTULOS REPRESENTATIVOS DE CAPITAL JÁ INTEGRALIZADO | AF1: 65 - CONSTITUIÇÃO OU AUMENTO DE CAPITAL DE EMPRESAS | AG1: 66 - CONCESSÃO DE EMPRÉSTIMOS E FINANCIAMENTOS | AH1: 67 - DEPÓSITOS COMPULSÓRIOS | AI1: 93 - INDENIZAÇÕES E RESTITUIÇÕES | AJ1: 94 - INDENIZAÇÕES E RESTITUIÇÕES TRABALHISTAS | AK1: 95 - INDENIZAÇÃO PELA EXECUÇÃO DE TRABALHOS DE CAMPO
A2: 1304 - INSS | B2: 1401 - DIÁRIAS CIVIL | C2: 1501 - DIÁRIAS MILITAR | D2: 1601 - SERVIÇO EXTRAORDINÁRIO | E2: 1701 - OUTRAS DESPESAS VARIÁVEIS ? PESSOAL MILITAR | F2: 1801 - AUXÍLIO FINANCEIRO A ESTUDANTES | G2: 1901 - AUXÍLIO-FARDAMENTO | H2: 2001 - AUXÍLIO FINANCEIRO A PESQUISADORES | I2: 3001 - ARTIGOS PARA CONFECÇÃO E VESTUÁRIO | J2: 3101 - PRÊMIOS, DIPLOMAS, CONDECORAÇÕES E MEDALHAS | K2: 3201 - MATERIAL DE DISTRIBUIÇÃO GRATUITA | L2: 3301 - PASSAGENS - PESSOA FÍSICA | M2: 3401 - OUTRAS DESPESAS DE PESSOAL DECORRENTES DE CONTRATOS DE TERCEIRIZAÇÃO | N2: 3501 - SERVIÇOS DE CONSULTORIA ? PESSOA FÍSICA | O2: 3601 - ESTAGIÁRIOS | P2: 3701 - LOCAÇÃO DE SERVIÇOS DE CONSERVAÇÃO E LIMPEZA | Q2: 3801 - ARRENDAMENTO MERCANTIL | R2: 3901 - VALE-TRANSPORTE | S2: 4002 - SERVIÇOS DE TECNOLOGIA DA INFORMAÇÃO | T2: 4101 - CONTRIBUIÇÕES | U2: 4201 - AUXÍLIOS | V2: 4301 - SUBVENÇÕES SOCIAIS | W2: 4501 - SUBVENÇÕES ECONÔMICAS | X2: 4702 - IMPOSTO DE RENDA - IR | Y2: 4801 - OUTROS AUXÍLIOS FINANCEIROS A PESSOAS FÍSICAS | Z2: 5101 - ESTUDOS E PROJETOS DE BENS PATRIMONIÁVEIS | AA2: 5201 - AERONAVES E COMPONENTES ESTRUTURAIS | AB2: 6101 - TERRENOS | AC2: 6201 - AQUISIÇÃO DE PRODUTOS PARA REVENDA | AD2: 6301 - AQUISIÇÃO DE TÍTULOS DE CRÉDITO | AE2: 6401 - AQUISIÇÃO DE TÍTULOS REPRESENTATIVOS DE CAPITAL JÁ INTEGRALIZADO | AF2: 6501 - CONSTITUIÇÃO OU AUMENTO DE CAPITAL DE EMPRESAS | AG2: 6601 - CONCESSÃO DE EMPRÉSTIMOS E FINANCIAMENTOS | AH2: 6701 - DEPÓSITOS COMPULSÓRIOS | AI2: 9301 - AJUDA DE CUSTO | AJ2: 9401 - INDENIZAÇÕES E RESTITUIÇÕES TRABALHISTAS | AK2: 9501 - INDENIZAÇÃO PELA EXECUÇÃO DE TRABALHOS DE CAMPO
A3: 1305 - OBRIGAÇÃO PATRONAL - PESSOAL ATIVO - PREVIDÊNCIA | D3: 1602 - SUBSTITUIÇÃO EM CARGOS EM COMISSÃO | G3: 1902 - ADIANTAMENTO ? FARDAMENTO | I3: 3002 - ARTIGOS PARA ESPORTE | J3: 3102 - PRÊMIOS LOTÉRICOS | K3: 3202 - MATERIAL DE ASSISTÊNCIA HUMANITÁRIA | L3: 3302 - DESPESAS COM TRANSPORTE URBANO, PEDÁGIO E ESTACIONAMENTO - PESSOA FÍSICA | M3: 3402 - AGENTES PENITENCIÁRIOS | N3: 3502 - SERVIÇOS DE CONSULTORIA ? PESSOA JURÍDICA | O3: 3602 - MÉDICOS RESIDENTES | P3: 3702 - LOCAÇÃO DE SERVIÇOS DE APOIO ADMINISTRATIVO | R3: 3902 - VALE-REFEIÇÃO | S3: 4003 - SERVIÇOS DE INFORMÁTICA EXECUTADOS PELA PRODEMGE | T3: 4102 - TRANSFERÊNCIAS AO FUNDHAB | X3: 4703 - IMPOSTO PREDIAL TERRITORIAL URBANO - IPTU | Y3: 4802 - AUXILIO FINANCEIRO ? PROGRAMA POUPANÇA JOVEM | Z3: 5102 - EXECUÇÃO DIRETA DE OBRAS DE BENS PATRIMONIÁVEIS | AA3: 5202 - ANIMAIS DE TRABALHO, PRODUÇÃO E / OU REPRODUÇÃO | AB3: 6102 - SALAS E ESCRITÓRIOS | AF3: 6502 - CONSTITUIÇÃO OU AUMENTO DE CAPITAL DE EMPRESAS ? CAPITAL INTEGRALIZADO | AG3: 6602 - EMPRÉSTIMOS E FINANCIAMENTOS ? FUNDOS DE DESENVOLVIMENTO | AI3: 9302 - AJUDA DE CUSTO ESPECIAL | AJ3: 9330 - REEMBOLSO DE DESPESA REALIZADA E CONTRATOS OU CONVÊNIOS FIRMADOS EM REGIME DE PARCERIA
A4: 1306 - OBRIGAÇÃO PATRONAL - PESSOAL INATIVO - PREVIDÊNCIA | D4: 1603 - AULAS FACULTATIVAS | G4: 1903 - AUXILIO FARDAMENTO PAGO A PESSOAL CONTRATADO | I4: 303 - UTENSÍLIOS PARA COPA, REFEITÓRIO E COZINHA | J4: 3103 - COMISSÕES LOTÉRICAS | L4: 3303 - FRETAMENTO E LOCAÇÃO - PESSOA FÍSICA | M4: 3403 - OBRIGAÇÃO PATRONAL – INSS | N4: 3503 - SERVIÇOS DE CONSULTORIA ? ORGANISMO INTERNACIONAL | O4: 3603 - SALÁRIOS DE INTERNOS | P4: 3703 - LOCAÇÃO DE SERVIÇOS DE CONSERVAÇÃO E LIMPEZA REALIZADOS PELA MGS | R4: 3903 - FORNECIMENTO DE ALIMENTAÇÃO | S4: 4004 - SERVIÇO DE TELECOMUNICAÇÃO | T4: 4103 - CONTRIBUIÇÕES AO IPLEMG | X4: 4704 - IMPOSTO SOBRE OPERAÇÕES FINANCEIRAS - IOF | Y4: 4803 - AUXÍLIO PARA PROFISSIONAIS DE PROGRAMAS DE CAPACITAÇÃO E FORMAÇÃO | Z4: 5103 - EXECUÇÃO DE OBRAS POR CONTRATO DE BENS PATRIMONIÁVEIS | AA4: 5203 - ARMAMENTO E EQUIPAMENTO DE USO POLICIAL | AB4: 6103 - FAZENDAS | AG4: 6603 - CONCESSÃO DE FINANCIAMENTOS HABITACIONAIS | AI4: 9303 - PERDAS DECORRENTES DE APLICAÇÕES FINANCEIRAS
A5: 1308 - OBRIGAÇÃO PATRONAL - PENSIONISTAS - PREVIDÊNCIA | D5: 1604 - GRATIFICAÇÃO POR ENCARGOS EXTRAORDINÁRIOS | I5: 3004 - MATERIAL GRÁFICO E IMPRESSOS | J5: 3104 - PREMIAÇÕES | L5: 3304 - PASSAGENS - PESSOA JURÍDICA | M5: 3404 - OBRIGAÇÃO PATRONAL – ASSISTÊNCIA À SAÚDE | O5: 3604 - DIÁRIAS A COLABORADORES EVENTUAIS | P5: 3704 - LOCAÇÃO DE SERVIÇOS DE APOIO ADMINISTRATIVO REALIZADOS PELA MGS | R5: 3904 - CONFECÇÃO EM GERAL | S5: 4005 - REDE IP MULTISSERVIÇOS | T5: 4104 - CONTRIBUIÇÕES DO FUNDO ESTADUAL DE SAUDE - FES - LC 141/2012 | X5: 4705 - IMPOSTO SOBRE A PROPRIEDADE DE VEÍCULOS AUTOMOTORES - IPVA | Z5: 5104 - INSTALAÇÕES PARA OBRAS EM ANDAMENTO | AA5: 5204 - MÁQUINAS, APARELHOS, UTENSÍLIOS E EQUIPAMENTOS DE USO INDUSTRIAL | AB5: 6104 - EDIFÍCIOS | AI5: 9304 - DESPESAS REFERENTES A RESSARCIMENTO PREVISTO NO PROGRAMA PRIMEIRO EMPREGO DO ESTADO DE MINA GERAIS
A6: 1309 - OBRIGAÇÃO PATRONAL - PRECATÓRIOS - PREVIDÊNCIA | D6: 1605 - FÉRIAS-PRÊMIO | I6: 3005 - MATERIAL PARA ESCRITÓRIO | L6: 3305 - SERVIÇOS DE TRANSPORTES DE PASSAGEIROS, FRETAMENTO E LOCAÇÃO - PESSOA JURÍDICA | M6: 3405 - SALÁRIO-FAMÍLIA | O6: 3606 - FORNECIMENTO DE ALIMENTAÇÃO | P6: 3705 - DESPESAS COM O PAGAMENTO DE ENCARGOS TRABALHISTAS À MGS | R6: 3905 - TRANSPORTE E ACONDICIONAMENTO DE ANIMAIS | S6: 4006 - AQUISIÇÃO DE SOFTWARE | T6: 4105 - CONTRIBUIÇÕES À FUNDAÇÃO DE PREVIDÊNCIA COMPLEMENTAR DO ESTADO DE MINAS GERAIS -PREVCOM?MG | X6: 4706 - CONTRIBUIÇÃO PARA A FORMAÇÃO DO PASEP/PIS | Z6: 5106 - ESTUDOS E PROJETOS DE BENS NÃO PATRIMONIÁVEIS | AA6: 5205 - EMBARCAÇÕES, PONTÕES, DIQUES, FLUTUANTES E COMPONENTES ESTRUTURAIS | AB6: 6105 - IMÓVEIS PARA FINS DE TRANSFERÊNCIA A TERCEIROS | AI6: 9305 - DESPESAS DECORRENTES DE CONTRATOS DE CONCESSÃO OU PERMISSÃO
A7: 1310 - OBRIGAÇÃO PATRONAL - OUTRAS SENTENÇAS JUDICIAIS - PREVIDÊNCIA | D7: 1606 - JORNADA COMPLEMENTAR DE TRABALHO | I7: 3006 - MATERIAL DE DESENHO | O7: 3607 - CONFECÇÃO EM GERAL | P7: 3706 - LOCAÇÃO DE SERVIÇOS DE SAÚDE | R7: 3906 - TRANSPORTE E ACONDICIONAMENTO DE MATERIAIS E EQUIPAMENTOS | S7: 4007 - AQUISIÇÃO DE SOFTWARE DESENVOLVIDOS PELA PRODEMGE | T7: 4106 - TRANSFERÊNCIAS PARA FINANCIAMENTO DO TRANSPORTE ESCOLAR | X7: 4707 - TAXA DE LIMPEZA PÚBLICA E COLETA DE RESÍDUOS | Z7: 5107 - EXECUÇÃO DE OBRAS POR CONTRATO DE BENS NÃO PATRIMONIÁVEIS | AA7: 5206 - EQUIPAMENTOS DE COMUNICAÇÃO E TELEFONIA | AB7: 6106 - IMÓVEIS NECESSÁRIOS À REALIZAÇÃO DE OBRAS DE BENS PATRIMONIAVEIS | AI7: 9306 - RESTITUIÇÃO DE RECURSOS DE CONVÊNIO E DE CONTRAPARTIDA
A8: 1314 - OBRIGAÇÃO PATRONAL - ENCARGOS POR PAGAMENTO EM ATRASO | I8: 3007 - MATERIAL DE ENSINO | O8: 3608 - MÉDICOS | P8: 3707 - DESPESAS COM O PAGAMENTO DE OBRIGAÇÕES TRABALHISTAS | R8: 3909 - PUBLICIDADE | T8: 4107 - TRANSFERÊNCIAS ENTRE FUNDOS ESTADUAIS | X8: 4708 - TAXA DE ILUMINAÇÃO PÚBLICA | Z8: 5109 - EXECUÇÃO DIRETA DE OBRAS DE BENS NÃO PATRIMONIÁVEIS | AA8: 5207 - EQUIPAMENTOS DE INFORMÁTICA | AB8: 6107 - IMÓVEIS NECESSÁRIOS À REALIZAÇÃO DE OBRAS DE BENS NÃO-PATRIMONIAVEIS | AI8: 9307 - RESSARCIMENTO REFERENTE A PESSOAL REQUISITADO DA ADMINISTRAÇÃO ESTADUAL
A9: 1315 - OBRIGAÇÃO PATRONAL - PRÊMIO DE PRODUTIVIDADE | I9: 3008 - PRODUTOS ALIMENTÍCIOS | O9: 3609 - DENTISTAS | R9: 3910 - PRÊMIOS DE SEGUROS | T9: 4108 - TRANSFERÊNCIAS ESPECIAIS A MUNICÍPIOS | X9: 4709 - TAXAS AMBIENTAIS | Z9: 5110 - MATERIAL PARA OBRAS - BENS PATRIMONIÁVEIS | AA9: 5208 - EQUIPAMENTOS DE SOM, VÍDEO, FOTOGRÁFICO E CINEMATOGRÁFICO | AB9: 6108 - CASAS | AI9: 9308 - DESPESAS DE CARÁTER INDENIZATÓRIO RELATIVAS AO MANDADO PARLAMENTAR
A10: 1317 - INSS – DEMAIS DESPESAS | I10: 3009 - FORRAGENS E OUTROS ALIMENTOS PARA ANIMAIS | O10: 3610 - EVENTUAL DE GABINETE | R10: 3911 - ASSINATURAS DE JORNAIS, REVISTAS E PERIÓDICOS | X10: 4710 - PASEP - ADESÃO AO PARCELAMENTO DECORRENTE DE LEI ESPECÍFICA | Z10: 5111 - CONTRUÇÃO DE UNIDADES HABITACIONAIS | AA10: 5209 - EQUIPAMENTOS HOSPITALARES, ODONTOLÓGICOS E DE LABORATÓRIO | AI10: 9309 - PREMIO DE PRODUTIVIDADE
A11: 1318 - OBRIGAÇÃO PATRONAL PESSOAL INATIVO – ENTIDADES CONVENIADAS – ASSISTÊNCIA À SAÚDE | I11: 3010 - MATERIAL MÉDICO E HOSPITALAR | O11: 3611 - LOCAÇÃO DE BENS IMÓVEIS | R11: 3912 - TARIFA DE ENERGIA ELÉTRICA | X11: 4799 - OUTROS - OBRIGAÇÕES TRIBUTÁRIAS E CONTRIBUTIVAS | Z11: 5112 - MATERIAL PARA OBRAS - BENS NÃO PATRIMONIÁVEIS | AA11: 5210 - FERRAMENTAS, EQUIPAMENTOS E INSTRUMENTOS PARA OFICINA, MEDIÇÃO E INSPEÇÃO | AI11: 9310 - RESTITUIÇÃO DE RECEITA - EXERCÍCIO ANTERIOR
A12: 1319 - OBRIGAÇÃO PATRONAL PESSOAL MILITAR INATIVO LC 125/2012 – PREVIDÊNCIA | I12: 3011 - MATERIAL ODONTOLÓGICO | O12: 3612 - DESPESAS MIÚDAS DE PRONTO PAGAMENTO | R12: 3913 - TARIFA DE ÁGUA E ESGOTO | Z12: 5113 - INSTALAÇÕES PARA INCORPORAÇÃO A BENS IMÓVEIS | AA12: 5211 - INSTRUMENTOS DE LABORATÓRIO, MÉDICOS E ODONTOLÓGICOS | AI12: 9311 - COMPENSAÇÃO FINANCEIRA DOS REGIMES DE PREVIDÊNCIA
A13: 1320 - OBRIGAÇÃO PATRONAL PESSOAL MILITAR ATIVO LC 125/2012 - PREVIDÊNCIA | I13: 3012 - MEDICAMENTOS | O13: 3613 - PESSOAL DE ENFERMAGEM | R13: 3914 - SERVIÇO DE TELEFONIA | Z13: 5114 - EXECUÇÃO DE OBRAS POR EMPRESAS CONTROLADAS | AA13: 5212 - MÁQUINAS, APARELHOS, UTENSÍLIOS E EQUIPAMENTOS DE USO ADMINISTRATIVO | AI13: 9312 - INDENIZAÇÃO POR UTILIZAÇÃO DE BENS DE TERCEIROS
A14: 1321 - OBRIGAÇÃO PATRONAL - PESSOAL ATIVO - ASSISTÊNCIA À SAÚDE | I14: 3013 - MATERIAIS DE LABORATÓRIO E PRODUTOS QUÍMICOS EM GERAL | O14: 3614 - MONITORES, FISCAIS E EXAMINADORES | R14: 3915 - SERVIÇO POSTAL-TELEGRÁFICO | AA14: 5213 - MATERIAL ESPORTIVO E RECREATIVO | AI14: 9313 - REEMBOLSO DE DESPESAS MÉDICO-HOSPITALARES
A15: 1322 - OBRIGAÇÃO PATRONAL - PESSOAL INATIVO - ASSISTÊNCIA À SAÚDE | I15: 3014 - MATERIAL RADIOLÓGICO | O15: 3615 - ENCARGOS FINANCEIROS | R15: 3916 - LOCAÇÃO DE TV POR ASSINATURA | AA15: 5214 - MOBILIÁRIO | AI15: 9314 - INDENIZAÇÕES DETERMINADAS POR DECISÕES JUDICIAIS
A16: 1324 - OBRIGAÇÃO PATRONAL - PENSIONISTAS - ASSISTÊNCIA À SAÚDE | I16: 3015 - MATERIAL FOTOGRÁFICO, CINEMATOGRÁFICO E DE COMUNICAÇÃO | O16: 3616 - REPARO E MANUTENÇÃO DE VEÍCULOS | R16: 3917 - LOCAÇÃO DE VEÍCULOS | AA16: 5215 - OBJETOS DE ARTE E ANTIGÜIDADES | AI16: 9315 - INDENIZAÇÃO DECORRENTE DE RESCISÃO UNILATERAL
A17: 1325 - OBRIGAÇÃO PATRONAL - ADESÃO AO PARCELAMENTO DECORRENTE DE LEI ESPECÍFICA - PREVIDÊNCIA | I17: 3016 - MATERIAL DE INFORMÁTICA | O17: 3617 - REPAROS DE EQUIPAMENTOS, INSTALAÇÕES E MATERIAL PERMANENTE | R17: 3918 - REPAROS DE VEÍCULOS | AA17: 5216 - TRATORES, SIMILARES E IMPLEMENTOS | AI17: 9316 - INDENIZAÇÕES DETERMINADAS POR LEI ESPECÍFICA
A18: 1326 - OBRIGAÇÃO PATRONAL SUPLEMENTAR – PESSOAL ATIVO | I18: 3017 - ARTIGOS PARA LIMPEZA E HIGIENE | O18: 3618 - REPAROS DE BENS IMÓVEIS | R18: 3919 - LOCAÇÃO DE MÁQUINAS E EQUIPAMENTOS | AA18: 5217 - VEÍCULOS | AI18: 9317 - INDENIZAÇÃO DECORRENTE DO EXERCÍCIO DO CARGO DE CONSELHEIRO-PRESIDENTE E PROCURADOR-GERAL JUNTO AO TRIBUNAL DE CONTAS
I19: 3018 - MATÉRIAS-PRIMAS E PRODUTOS PARA MANIPULAÇÃO E INDÚSTRIAS DE TRANSFORMAÇÃO | O19: 3619 - CONFERÊNCIAS E EXPOSIÇÕES | R19: 3920 - LOCAÇÃO DE BENS IMÓVEIS | AA19: 5218 - COLEÇÕES E MATERIAIS BIBLIOGRÁFICOS | AI19: 9318 - DESPESAS COM AUXILIO MORADIA DE CARÁTER INDENIZATÓRIO RELATIVAS AO MANDADO PARLAMENTAR
I20: 3019 - MATERIAL PARA MANUTENÇÃO E REPAROS DE IMÓVEIS DE PROPRIEDADE DA ADMINISTRAÇÃO PÚBLICA | O20: 3620 - JETONS A CONSELHEIROS | R20: 3921 - INSTALAÇÃO, REPARAÇÃO, ADAPTAÇÃO E CONSERVAÇÃO DE EQUIPAMENTO E MATERIAL PERMANENTE | AA20: 5219 - INSTRUMENTOS MUSICAIS E ARTÍSTICOS | AI20: 9319 - INDENIZAÇÕES DECORRENTES DA UTILIZAÇÃO DE LEITOS DE INSTITUIÇÕES DE SAÚDE PRIVADAS
I21: 3020 - MATERIAL ELÉTRICO E ELETRÔNICO | O21: 3621 - ADVOGADOS DATIVOS | R21: 3922 - REPAROS DE BENS IMÓVEIS | AA21: 5220 - EQUIPAMENTOS DE SEGURANÇA ELETRÔNICA | AI21: 9323 - INDENIZAÇÃO DECORRENTE DE AUXÍLIO-SAÚDE
I22: 3021 - MATERIAL PARA MANUTENÇÃO E REPAROS DE BENS DE DOMÍNIO PÚBLICO OU DE TERCEIROS | O22: 3622 - TAXA DE CONDOMÍNIO | R22: 3923 - RECEPÇÕES, HOSPEDAGENS, HOMENAGENS E FESTIVIDADES | AA22: 5221 - MATERIAL DIDÁTICO | AI22: 9324 - AUXÍLIO-MORADIA DE CARÁTER INDENIZATÓRIO DEVIDO A MAGISTRADO
I23: 3022 - FERRAMENTAS, FERRAGENS E UTENSÍLIOS | O23: 3623 - GRATIFICAÇÃO POR ENCARGO DE CURSO OU CONCURSO | R23: 3924 - CURSOS, EXPOSIÇÕES, CONGRESSOS E CONFERÊNCIAS | AA23: 5222 - ESTRUTURAS E COMPONENTES | AI23: 9325 - AUXÍLIO-MORADIA DE CARÁTER INDENIZATÓRIO DEVIDO PELO TCE
I24: 3023 - MATERIAL PARA MANUTENÇÃO DE VEÍCULOS AUTOMOTORES | O24: 3624 - SERVIÇOS TÉCNICOS JUDICIAIS ? HONORÁRIOS PERICIAIS ? JUSTIÇA GRATUITA | R24: 3925 - ENCARGOS JUDICIAIS | AA24: 5223 - MÁQUINAS E EQUIPAMENTOS GRÁFICOS | AI24: 9326 - RESTITUICAO REFERENTE A TAXA DE INSCRIÇÃO, MATERIAL E SIMILARES
I25: 3024 - PEÇAS E ACESSÓRIOS PARA EQUIPAMENTOS E OUTROS MATERIAIS PERMANENTES | O25: 3625 - CONTRATAÇÃO PARA PRESTAÇÃO DE SERVIÇO POR CREDENCIADOS | R25: 3926 - ENCARGOS FINANCEIROS | AA25: 5224 - MÁQUINAS, INSTALAÇÕES E UTENSÍLIOS DE ESCRITÓRIO | AI25: 9327 - INDENIZAÇÃO DE TRANSPORTE DEVIDA AO OFICIAL DE JUSTIÇA E OFICIAL DE CARTÓRIO
I26: 3025 - MATERIAL DE SEGURANÇA, APETRECHOS OPERACIONAIS E POLICIAIS | O26: 3626 - SERVIÇOS DE ABASTECIMENTO E DISTRIBUIÇÃO DE ÁGUA | R26: 3928 - SERVIÇOS DE SAÚDE EXECUTADOS COM RECURSOS DO SUS | AA26: 5225 - APARELHOS E UTENSÍLIOS DOMÉSTICOS | AI26: 9328 - PENSÃO ACIDENTÁRIA
I27: 3026 - COMBUSTÍVEIS E LUBRIFICANTES PARA VEÍCULOS AUTOMOTORES | O27: 3627 - JUÍZES LEIGOS | R27: 3929 - SERVIÇOS MÉDICOS, ODONTOLÓGICOS E LABORATORIAIS | AA27: 5226 - EQUIPAMENTOS DE PROTEÇÃO, SEGURANÇA E SOCORRO | AI27: 9329 - DESPESA REFERENTE A RESSARCIMENTO SOBRE A REMUNERAÇÃO DOS PRESOS EM TRABALHO
I28: 3027 - COMBUSTÍVEIS E LUBRIFICANTES PARA EQUIPAMENTOS E OUTROS MATERIAIS PERMANENTES | O28: 3628 - SERVICOS TECNICOS JUDICIAIS - HONORARIOS PERICIAIS | R28: 3930 - MULTAS DE TRÂNSITO | AA28: 5299 - OUTROS MATERIAIS PERMANENTES | AI28: 9399 - OUTRAS INDENIZAÇÕES E RESTITUIÇÕES
I29: 3028 - ANIMAIS DESTINADOS A ESTUDOS, À PREPARAÇÃO DE PRODUTOS E AO ABATE | O29: 3629 - DIREITOS AUTORAIS | R29: 3931 - LOCAÇÃO DE SERVIÇOS GRÁFICOS
I30: 3029 - - SEMENTES, MUDAS DE PLANTAS E INSUMOS | O30: 3630 - SERVIÇOS MÉDICOS PRESTADOS POR CONTRATO | R30: 3933 - TAXA DE ADMINISTRAÇÃO
I31: 3030 - MATERIAIS PARA ACONDICIONAMENTO E EMBALAGEM | O31: 3631 - SERVIÇOS DE TREINAMENTO, CAPACITAÇÃO E APERFEIÇOAMENTO DE PESSOAL | R31: 3934 - SEGURO DE AERONAVES
I32: 3031 - LIVROS TÉCNICOS | O32: 3699 - OUTRAS DESPESAS PAGAS A PESSOAS FÍSICAS | R32: 3935 - REPARO E MANUTENÇÃO DE AERONAVES
I33: 3032 - MATERIAL CÍVICO E EDUCATIVO | R33: 3937 - TAXA DE CONDOMÍNIO
I34: 3033 - COMBUSTÍVEIS E LUBRIFICANTES PARA AERONAVES | R34: 3938 - SERVIÇOS DE IMPRESSÃO E ENCADERNAÇÃO
I35: 3034 - PEÇAS E ACESSÓRIOS PARA AERONAVES | R35: 3939 - SERVIÇOS DE PUBLICAÇÃO E DIVULGAÇÃO
I36: 3036 - MATERIAL BIBLIOGRÁFICO PARA BIBLIOTECAS PÚBLICAS | R36: 3941 - ANUIDADES, CERTIFICADOS E REGISTROS
I37: 3037 - MEDICAMENTOS ? DECISÃO JUDICIAL | R37: 3942 - SERVIÇOS GRÁFICOS DE SEGURANÇA
I38: 3038 - LEITE ? PROGRAMA LEITE PELA VIDA | R38: 3943 - SERVIÇOS DE ADMINISTRAÇÃO E GERENCIAMENTO DE FROTA DE VEÍCULOS
I39: 3039 - MATERIAL DE CONFECÇÃO EM GERAL | R39: 3944 - SERVIÇO DE SEGURANÇA FAZENDÁRIA
I40: 3040 - MATERIAL DE CAMA, MESA E BANHO | R40: 3946 - TERMO DE PARCERIA COM ORGANIZAÇÃO DA SOCIEDADE CIVIL DE INTERESSE PÚBLICO - OSCIP
I41: 3041 - MATERIAL DE PROTEÇÃO E SEGURANÇA | R41: 3947 - TAXA DE ADMINISTRAÇÃO DE CRÉDITO DE FINANCIAMENTOS HABITACIONAIS
I42: 3099 - OUTROS MATERIAIS | R42: 3948 - CURSOS DE FORMAÇÃO, CAPACITAÇÃO E PÓS-GRADUAÇÃO PARA SERVIDORES
R43: 3949 - CURSOS DE FORMAÇÃO E CAPACITAÇÃO PARA O CIDADÃO
R44: 3950 - SERVIÇOS DE AGENCIAMENTO DE VIAGENS
R45: 3951 - SERVIÇO DE GERENCIAMENTO, SUPERVISÃO E FISCALIZAÇÃO DE OBRAS
R46: 3952 - CONTRATAÇÃO DE ESTAGIÁRIOS
R47: 3953 - CURSOS DE FORMAÇÃO E CAPACITAÇÃO PROMOVIDOS PELO ESTADO
R48: 3954 - CONTRATO DE PARCERIA PÚBLICO-PRIVADA
R49: 3955 - EVENTOS DE COMUNICAÇÃO INSTITUCIONAL
R50: 3956 - SERVIÇOS DE PESQUISAS
R51: 3957 - COMISSÃO PELA CONSTRUÇÃO DE UNIDADES HABITACIONAIS
R52: 3958 - CONTRATAÇÃO DE PROJETOS EM PESQUISA DE CIÊNCIA, INOVAÇÃO E TECNOLOGIA
R53: 3959 - SERVIÇOS SANITÁRIOS E TRATAMENTO DE RESÍDUOS
R54: 3960 - SERVIÇOS DE ATENDIMENTO AO CIDADÃO
... R90: 3999 - OUTROS SERVIÇOS-PESSOA JURÍDICA

Sheet DECRETO DIÁRIAS
G1: INDICE
B3: DECRETO 47045, DE 14/09/2016 DISPÕE SOBRE VIAGEM A SERVIÇO E CONCESSÃO DE DIÁRIA NO ÂMBITO DA ADMINISTRAÇÃO PÚBLICA DIRETA, AUTÁRQUICA E FUNDACIONAL DO PODER EXECUTIVO E DÁ OUTRAS PROVIDÊNCIAS.
B5: Tabela de Valores – Viagens Nacionais | F5: Tabela de Valores – Viagens ao Exterior
B6: DESTINO | C6: FAIXA I (R$) | D6: FAIXA II (R$) | F6: SERVIDORES | G6: LOCALIDADE/VALOR (U$)
B7: Capitais, inclusive Belo Horizonte | C7: 470 | D7: 665 | G7: América do Sul e América Central | H7: Demais Localidades no exterior
B8: Municípios especiais e municípios de outros Estados que não sejam capitais | C8: 362 | D8: 608 | F8: Governador do Estado; Vice-Governador do Estado | G8: 400 | H8: 550
B9: Demais municípios | C9: 258 | D9: 354 | F9: Secretário-Geral, Secretário de Estado, Secretário Adjunto de Estado | G9: 350 | H9: 450
B10: Faixa I: Servidor que exerça cargo efetivo que exija até o nível médio ou superior de escolaridade, servidor investido em cargo de provimento em comissão, servidor que exerça função pública que exija até o nível médio ou superior de escolaridade, e os membros de conselhos estaduais. | F10: Demais autoridades – Subsecretário, dirigente máximo de órgão autônomo, fundação e autarquia e seus respectivos Vices e servidor investido em cargo de provimento em comissão do Grupo de Direção e Assessoramento que esteja no nível DAD-8 a DAD-12 ou DAI-26 a DAI-40 e exerça atividades inerentes à chefia de Gabinete do Vice-Governador ou de Secretaria de Estado ou de entidades ou às assessorias especiais do Governador. | G10: 300 | H10: 400
B14: Faixa II: Secretário-Geral, Secretário de Estado, Secretário Adjunto, Subsecretário, dirigente máximo de órgão autônomo, fundação e autarquia e seus respectivos vices, Comandante de Aeronave, Comandante de Avião, Comandante de Avião a jato, Piloto de Helicóptero, Primeiro Oficial de Aeronave e servidor investido em cargo de provimento em comissão do Grupo de Direção e Assessoramento que esteja no nível DAD-8 a DAD-12 ou DAI-25 a DAI-40 e exerça atividades inerentes à chefia de gabinete do Vice-Governador, de Secretaria de Estado ou de entidades ou às assessorias especiais do Governador.
B15: Relação dos Municípios Especiais: Araxá, Caxambú, Contagem, Ipatinga, Juiz de Fora, Ouro Preto, Patos de Minas, Tiradentes, Uberlândia. | F15: Demais servidores | G15: 300 | H15: 300
B18: Link para o Decreto: | C18: https://www.almg.gov.br/consulte/legislacao/completa/completa.html?num=47045&ano=2016&tipo=DEC

Sheet BASE OBZ
F1: INDICE | H1: PROJETO ORÇAMENTO BASE-ZERO
A2: UNIDADE ORÇAMENTÁRIA | B2: N2 | C2: SUB SIGLA | D2: N3 | E2: PROGRAMAUO | F2: PROGRAMA | G2: prog cod | H2: AÇÃO | I2: ELEMENTO | J2: ELEMENTO_ITEM | K2: Agrupamento | L2: GRUPO | M2: FONTEUO | N2: FONTE | O2: DESCRIÇÃO DO ITEM | P2: NOVO? | Q2: PREMISSA VOLUME | R2: VOLUME | S2: PREMISSA DE PREÇO | T2: PREÇO UNITÁRIO | U2: FREQUÊNCIA PAGAMENTO | V2: VALOR TOTAL ITEM | W2: CLASSIFICAÇÃO CENÁRIO | X2: DESCRIÇÃO DO CENÁRIO | Y2: RISCO DE NÃO FAZER | Z2: BENEFICIO AO FAZER | AA2: PRIORIDADE N3 | AB2: PRIORIDADE N2 | AC2: PRIORIDADE N1 | AD2: PARECER DCMEFO | AE2: DELIBERAÇÃO COFIN
A3: SEE | B3: Subsecretaria de Gestão de Recursos Humanos | D3: Subsecretaria de Gestão de Recursos Humanos | F3: 169 - GESTÃO DO SISTEMA ESTADUAL DE EDUCAÇÃO | H3: 2128 - GESTÃO DO ÓRGÃO CENTRAL | I3: ELEMENTO | J3: 3924 - CURSOS, EXPOSICOES, CONGRESSOS E CONFERENCIAS | K3: =VLOOKUP(CONCATENATE(A3,LEFT(J3,4)),AGRUPAMENTO!$D$2:$E$6784,2,FALSE) -> Cursos de formação e capacitações | L3: 3 - Outras Despesas de Custeio | N3: 10 | O3: Verba necessária para funcionamento mínimo da Subsecretaria, Superintendência e Diretorias. | P3: NÃO | Q3: Valor estimado para 10 inscrições | R3: 10 | S3: Valor estimado para 10 inscrições | T3: 1000 | U3: 1 | V3: =R3*T3*U3 -> 10000 | W3: LIMIAR | X3: Aquisição de inscrições para participação em congressos e seminários. | Y3: Deixar de atender demandas da Secretaria | Z3: Possibilitar a participação em congressos e seminários de interesse da Secretaria. | AA3: 0 | AB3: 0 | AC3: 0 | AD3: 1 | AE3: 1
A4: SEE | B4: Subsecretaria de Gestão de Recursos Humanos | D4: Subsecretaria de Gestão de Recursos Humanos | F4: 169 - GESTÃO DO SISTEMA ESTADUAL DE EDUCAÇÃO | H4: 2128 - Gestão do Órgão Central | I4: ELEMENTO | J4: 1401 - DIARIAS - CIVIL | K4: =VLOOKUP(CONCATENATE(A4,LEFT(J4,4)),AGRUPAMENTO!$D$2:$E$6784,2,FALSE) -> Diárias e viagens | L4: 3 - Outras Despesas de Custeio | N4: 10 | O4: Diárias para atender demandas da SG. | P4: NÃO | Q4: Conforme demanda. | R4: 200 | S4: Decreto de diárias | T4: 500 | U4: 1 | V4: =R4*T4*U4 -> 100000 | W4: LIMIAR | X4: Viagens à serviço | Y4: Deixar de atender demandas da Secretaria | Z4: Permitir o atendimento às demandas da Secretaria, e garantir estrutura mínima de atuação. | AA4: 0 | AB4: 0 | AC4: 0 | AD4: 1 | AE4: 1
A5: SEE | B5: Subsecretaria de Gestão de Recursos Humanos | D5: Subsecretaria de Gestão de Recursos Humanos | F5: 169 - GESTÃO DO SISTEMA ESTADUAL DE EDUCAÇÃO | H5: 2128 - Gestão do Órgão Central | I5: ELEMENTO | J5: 3301 - PASSAGENS - PESSOA FISICA | K5: =VLOOKUP(CONCATENATE(A5,LEFT(J5,4)),AGRUPAMENTO!$D$2:$E$6784,2,FALSE) -> Diárias e viagens | L5: 3 - Outras Despesas de Custeio | N5: 10 | O5: Despesas com passagens rodoviárias | P5: NÃO | Q5: Conforme demanda. | R5: 150 | S5: Passagens ida e volta | T5: 300 | U5: 1 | V5: =R5*T5*U5 -> 45000 | W5: LIMIAR | X5: Atendimento de demandas de projetos da SEE | Y5: Deixar de atender demandas da Secretaria | Z5: Permitir o atendimento às demandas da Secretaria | AA5: 0 | AB5: 0 | AC5: 0 | AD5: 1 | AE5: 1
A6: SEE | B6: Subsecretaria de Gestão de Recursos Humanos | D6: Subsecretaria de Gestão de Recursos Humanos | F6: 169 - GESTÃO DO SISTEMA ESTADUAL DE EDUCAÇÃO | H6: 2128 - Gestão do Órgão Central | I6: ELEMENTO | J6: 1401 - DIARIAS - CIVIL | K6: =VLOOKUP(CONCATENATE(A6,LEFT(J6,4)),AGRUPAMENTO!$D$2:$E$6784,2,FALSE) -> Diárias e viagens | L6: 3 - Outras Despesas de Custeio | N6: 10 | O6: Encontro gerencial DIPEs | P6: NÃO | Q6: Valor previsto para 2 pessoas, 2 vezes ano | R6: 1 | S6: Decreto de diárias | T6: 149000 | U6: 2 | V6: =R6*T6*U6 -> 298000 | W6: LIMIAR | X6: Promover o alinhamento das ações e diretrizes da SEE/SG, para o exercício de 20256 | Y6: Deixar de atender demandas da Secretaria | Z6: Permitir o atendimento às demandas da Secretaria | AA6: 0 | AB6: 0 | AC6: 0 | AD6: 1 | AE6: 1
A7: SEE | B7: Subsecretaria de Gestão de Recursos Humanos | D7: Subsecretaria de Gestão de Recursos Humanos | F7: 169 - GESTÃO DO SISTEMA ESTADUAL DE EDUCAÇÃO | H7: 2128 - Gestão do Órgão Central | I7: ELEMENTO | J7: 3302 - DESPESAS COM TRANSPORTE URBANO, PEDAGIO E ESTACIONAMETO PESSOA FISICA | K7: =VLOOKUP(CONCATENATE(A7,LEFT(J7,4)),AGRUPAMENTO!$D$2:$E$6784,2,FALSE) -> Diárias e viagens | L7: 3 - Outras Despesas de Custeio | N7: 10 | O7: Encontro gerencial DIPEs | P7: NÃO | Q7: Valor estimado | R7: 1 | S7: Valor médio de despesas com táxi, estacionamento e pedágio | T7: 75680 | U7: 2 | V7: =R7*T7*U7 -> 151360 | W7: LIMIAR | X7: Promover o alinhamento das ações e diretrizes da SEE/SG, para o exercício de 20256 | Y7: Deixar de atender demandas da Secretaria | Z7: Permitir o atendimento às demandas da Secretaria | AA7: 0 | AB7: 0 | AC7: 0 | AD7: 1 | AE7: 1
A8: SEE | B8: Subsecretaria de Gestão de Recursos Humanos | D8: Subsecretaria de Gestão de Recursos Humanos | F8: 169 - GESTÃO DO SISTEMA ESTADUAL DE EDUCAÇÃO | H8: 2128 - Gestão do Órgão Central | I8: ELEMENTO | J8: 1401 - DIARIAS - CIVIL | K8: =VLOOKUP(CONCATENATE(A8,LEFT(J8,4)),AGRUPAMENTO!$D$2:$E$6784,2,FALSE) -> Diárias e viagens | L8: 3 - Outras Despesas de Custeio | N8: 10 | O8: Diárias para participar de capacitação/treinamento, na SEE | P8: NÃO | Q8: Vr previsto para 3 pessoas, 3 vezes no ano | R8: 1 | S8: Decreto de diárias | T8: 224400 | U8: 3 | V8: =R8*T8*U8 -> 673200 | W8: LIMIAR | X8: Viagens à serviço | Y8: Deixar de atender demandas da Secretaria | Z8: Permitir o atendimento às demandas da Secretaria | AA8: 0 | AB8: 0 | AC8: 0 | AD8: 1 | AE8: 1
A9: SEE | B9: Subsecretaria de Gestão de Recursos Humanos | D9: Subsecretaria de Gestão de Recursos Humanos | F9: 169 - GESTÃO DO SISTEMA ESTADUAL DE EDUCAÇÃO | H9: 2128 - Gestão do Órgão Central | I9: ELEMENTO | J9: 3301 - PASSAGENS - PESSOA FISICA | K9: =VLOOKUP(CONCATENATE(A9,LEFT(J9,4)),AGRUPAMENTO!$D$2:$E$6784,2,FALSE) -> Diárias e viagens | L9: 3 - Outras Despesas de Custeio | N9: 10 | O9: Despesas com transportes/deslocamentos, na SEE | P9: NÃO | Q9: Vr previsto para 3 pessoas, 3 vezes no ano | R9: 1 | S9: Verba para transporte | T9: 113520 | U9: 3 | V9: =R9*T9*U9 -> 340560 | W9: LIMIAR | X9: Atendimento de demandas de projetos da SEE | Y9: Deixar de atender demandas da Secretaria | Z9: Permitir o atendimento às demandas da Secretaria | AA9: 0 | AB9: 0 | AC9: 0 | AD9: 1 | AE9: 1
A10: SEE | B10: Subsecretaria de Gestão de Recursos Humanos | D10: Subsecretaria de Gestão de Recursos Humanos | F10: 169 - GESTÃO DO SISTEMA ESTADUAL DE EDUCAÇÃO | H10: 2128 - Gestão do Órgão Central | I10: ELEMENTO | J10: 1401 - DIARIAS - CIVIL | K10: =VLOOKUP(CONCATENATE(A10,LEFT(J10,4)),AGRUPAMENTO!$D$2:$E$6784,2,FALSE) -> Diárias e viagens | L10: 3 - Outras Despesas de Custeio | N10: 10 | O10: Diárias para participar de capacitação/treinamento | P10: NÃO | Q10: Vr previsto para 3 pessoas, 5 vezes no ano | R10: 1 | S10: Decreto de diárias | T10: 158400 | U10: 5 | V10: =R10*T10*U10 -> 792000 | W10: LIMIAR | X10: Viagens à serviço | Y10: Deixar de atender demandas da Secretaria | Z10: Permitir o atendimento às demandas da Secretaria | AA10: 0 | AB10: 0 | AC10: 0 | AD10: 1 | AE10: 1
A11: SEE | B11: Subsecretaria de Gestão de Recursos Humanos | D11: Subsecretaria de Gestão de Recursos Humanos | F11: 169 - GESTÃO DO SISTEMA ESTADUAL DE EDUCAÇÃO | H11: 2128 - Gestão do Órgão Central | I11: ELEMENTO | J11: 3301 - PASSAGENS - PESSOA FISICA | K11: =VLOOKUP(CONCATENATE(A11,LEFT(J11,4)),AGRUPAMENTO!$D$2:$E$6784,2,FALSE) -> Diárias e viagens | L11: 3 - Outras Despesas de Custeio | N11: 10 | O11: Despesas com transportes/deslocamentos, nas SREs | P11: NÃO | Q11: Vr previsto para 3 pessoas, 5 vezes no ano | R11: 1 | S11: Verba para transporte | T11: 92400 | U11: 5 | V11: =R11*T11*U11 -> 462000 | W11: LIMIAR | X11: Atendimento de demandas de projetos da SEE | Y11: Deixar de atender demandas da Secretaria | Z11: Permitir o atendimento às demandas da Secretaria | AA11: 0 | AB11: 0 | AC11: 0 | AD11: 1 | AE11: 1
A12: SEE | B12: Subsecretaria de Gestão de Recursos Humanos | D12: Subsecretaria de Gestão de Recursos Humanos | F12: 169 - GESTÃO DO SISTEMA ESTADUAL DE EDUCAÇÃO | H12: 2128 - Gestão do Órgão Central | I12: ELEMENTO | J12: 1401 - DIARIAS - CIVIL | K12: =VLOOKUP(CONCATENATE(A12,LEFT(J12,4)),AGRUPAMENTO!$D$2:$E$6784,2,FALSE) -> Diárias e viagens | L12: 3 - Outras Despesas de Custeio | N12: 10 | O12: Força-tarefa para redução do passivo de processos de pagamentos, nas SREs | P12: NÃO | Q12: Diárias (servidores da SRE vindo a BH) | R12: 1 | S12: Decreto de diárias | T12: 5000 | U12: 5 | V12: =R12*T12*U12 -> 25000 | W12: LIMIAR | X12: Viagens à serviço | Y12: Deixar de atender demandas da Secretaria | Z12: Permitir o atendimento às demandas da Secretaria | AA12: 0 | AB12: 0 | AC12: 0 | AD12: 1 | AE12: 1
A13: SEE | B13: Subsecretaria de Gestão de Recursos Humanos | D13: Subsecretaria de Gestão de Recursos Humanos | F13: 169 - GESTÃO DO SISTEMA ESTADUAL DE EDUCAÇÃO | H13: 2128 - Gestão do Órgão Central | I13: ELEMENTO | J13: 1401 - DIARIAS - CIVIL | K13: =VLOOKUP(CONCATENATE(A13,LEFT(J13,4)),AGRUPAMENTO!$D$2:$E$6784,2,FALSE) -> Diárias e viagens | L13: 3 - Outras Despesas de Custeio | N13: 10 | O13: Diárias para participar de capacitação/treinamento, dos gestores setoriais da Avaliação de desempenho | P13: NÃO | Q13: Vr previsto para 1 pessoas da SRE. | R13: 1 | S13: Verba para diárias dos cursitas do mestrado e doutorado, conforme cronograma dos encontratos presenciais de cada instituição. | T13: 63000 | U13: 1 | V13: =R13*T13*U13 -> 63000 | W13: LIMIAR | X13: Viagens à serviço | Y13: Deixar de atender demandas da Secretaria | Z13: Permitir o atendimento às demandas da Secretaria | AA13: 0 | AB13: 0 | AC13: 0 | AD13: 1 | AE13: 1
A14: SEE | B14: Subsecretaria de Gestão de Recursos Humanos | D14: Subsecretaria de Gestão de Recursos Humanos | F14: 169 - GESTÃO DO SISTEMA ESTADUAL DE EDUCAÇÃO | H14: 2128 - Gestão do Órgão Central | I14: ELEMENTO | J14: 3301 - PASSAGENS - PESSOA FISICA | K14: =VLOOKUP(CONCATENATE(A14,LEFT(J14,4)),AGRUPAMENTO!$D$2:$E$6784,2,FALSE) -> Diárias e viagens | L14: 3 - Outras Despesas de Custeio | N14: 10 | O14: Despesas com transportes/deslocamentos, dos gestores setorias da AD. | P14: NÃO | Q14: Vr previsto para 1 pessoas da SRE. | R14: 1 | S14: Verba para transporte (passagem e táxi) dos cursitas, conforme cronograma dos encontratos presenciais de cada instituição. | T14: 27000 | U14: 1 | V14: =R14*T14*U14 -> 27000 | W14: LIMIAR | X14: Atendimento de demandas de projetos da SEE | Y14: Deixar de atender demandas da Secretaria | Z14: Permitir o atendimento às demandas da Secretaria | AA14: 0 | AB14: 0 | AC14: 0 | AD14: 1 | AE14: 1
... A55: SEE | B55: Gabinete | D55: Assessoria de Comunicação Social/ASCOM | F55: 169 - GESTÃO DO SISTEMA ESTADUAL DE EDUCAÇÃO | H55: 2128 - Gestão do Órgão Central | I55: ELEMENTO | J55: 3974 - SERVICO DE REALIZACAO DE CONCURSO PUBLICO E PROCESSO SIMPLIFICADO | K55: =VLOOKUP(CONCATENATE(A55,LEFT(J55,4)),AGRUPAMENTO!$D$2:$E$6784,2,FALSE) -> Concurso público | L55: 3 - Outras Despesas de Custeio | N55: 10 | O55: TDCO SECOM para campanha informativa sobre o processo de cadastramento/matrícula escolar na rede pública de ensino para o ano de 2026 e para campanha de Divulgação Do Trilhas De Futuro 2026, programa que Oferece cursos técnicos profissionais gratuitos em Minas Gerais. | P55: SIM | Q55: TDCO SECOM | R55: 1 | S55: Campanhas de divulgação | T55: 15000000 | U55: 1 | V55: =R55*T55*U55 -> 15000000 | W55: LIMIAR | X55: Campanha informativa sobre o processo de cadastramento/matrícula escolar na rede pública de ensino para o ano de 2026. | Y55: Aumento da evasão escolar e baixo número de adesão nos programas e ações institucionais da educação. | Z55: Alta adesão aos programas e ações institucionais da educação com consequente diminuição da evasão escolar e aumento da profissionalização de jovens da educação básica. | AA55: 0 | AB55: 0 | AC55: 0 | AD55: 1 | AE55: 1
A56: SEE | B56: Gabinete | D56: Assessoria de Ensino Superior - ASU | F56: 169 - GESTÃO DO SISTEMA ESTADUAL DE EDUCAÇÃO | H56: 2128 - Gestão do Órgão Central | I56: ELEMENTO | J56: 3952 - CONTRATAÇÃO DE ESTAGIÁRIOS | K56: =VLOOKUP(CONCATENATE(A56,LEFT(J56,4)),AGRUPAMENTO!$D$2:$E$6784,2,FALSE) -> Estagiários | L56: 3 - Outras Despesas de Custeio | N56: 10 | O56: PAGAMENTO DE TAXA ADMINISTRATIVA REFERENTE A SERVIÇOS DE GESTÃO ADMINISTRATIVA DE ESTÁGIO | P56: NÃO | Q56: 12 | R56: 1 | S56: TAXA ADM. MENSAL | T56: 6297.35 | U56: 12 | V56: =R56*T56*U56 -> 75568.2 | W56: LIMIAR | X56: REALIZAR SERVIÇOS DE GESTÃO ADMINISTRATIVA DE ESTÁGIO PRESTADOS PELA AGENCIA DE INTEGRAÇÃO ESTÁGIOS | Y56: SERVIÇOS DE ESTÁGIO SERÃO INTERROMPIDOS EM TODA A SEE | Z56: ESTAGIÁRIOS CONTRATADOS AGREGANDO AINDA MAIS QUALIDADE NOS TRABALHOS DESENVOLVIDOS PELA SEE | AA56: 0 | AB56: 0 | AC56: 0 | AD56: 1 | AE56: 1
A57: SEE | B57: Gabinete | D57: Gabinete | F57: 169 - GESTÃO DO SISTEMA ESTADUAL DE EDUCAÇÃO | H57: 2128 - Gestão do Órgão Central | I57: ELEMENTO | J57: 1401 - DIARIAS - CIVIL | K57: =VLOOKUP(CONCATENATE(A57,LEFT(J57,4)),AGRUPAMENTO!$D$2:$E$6784,2,FALSE) -> Diárias e viagens | L57: 3 - Outras Despesas de Custeio | N57: 10 | O57: Diárias para atender demandas do gabinete e assesorias | P57: NÃO | Q57: Conforme demanda. | R57: 500 | S57: Decreto de diárias | T57: 2044.5 | U57: 1 | V57: =R57*T57*U57 -> 1022250 | W57: LIMIAR | X57: Viagens à serviço para demandas diversas do gabinete. | Y57: Não atendimento de viagem para participação presencial em reuniões, encontros , congressos , etc. | Z57: Atendimento em viagens com custeio de despesas de servidores para efetiva participação presencial em reuniões , encontro, congressos , etc. | AA57: 0 | AB57: 0 | AC57: 0 | AD57: 1 | AE57: 1
A58: SEE | B58: Gabinete | D58: Gabinete | F58: 169 - GESTÃO DO SISTEMA ESTADUAL DE EDUCAÇÃO | H58: 2128 - Gestão do Órgão Central | I58: ELEMENTO | J58: 3302 - DESPESAS COM TRANSPORTE URBANO, PEDAGIO E ESTACIONAMETO PESSOA FISICA | K58: =VLOOKUP(CONCATENATE(A58,LEFT(J58,4)),AGRUPAMENTO!$D$2:$E$6784,2,FALSE) -> Diárias e viagens | L58: 3 - Outras Despesas de Custeio | N58: 10 | O58: Despesas com transporte urbano em viagens | P58: NÃO | Q58: Conforme demanda. | R58: 250 | S58: Valor médio de despesas com estacionamento, pedágio e taxi | T58: 200 | U58: 1 | V58: =R58*T58*U58 -> 50000 | W58: LIMIAR | X58: Atendimento a servidores com valores para cobrir despesas com adiantamento em viagem . | Y58: Não atendimento do deslocamento dos servidores em viagem com recurso para o custeio com deslocamento em viagem . | Z58: Atendimento as servidores em viagem | AA58: 0 | AB58: 0 | AC58: 0 | AD58: 1 | AE58: 1
A59: SEE | B59: Gabinete | D59: Gabinete | F59: 169 - GESTÃO DO SISTEMA ESTADUAL DE EDUCAÇÃO | H59: 2128 - Gestão do Órgão Central | I59: ELEMENTO | J59: 3301 - PASSAGENS - PESSOA FISICA | K59: =VLOOKUP(CONCATENATE(A59,LEFT(J59,4)),AGRUPAMENTO!$D$2:$E$6784,2,FALSE) -> Diárias e viagens | L59: 3 - Outras Despesas de Custeio | N59: 10 | O59: Despesas com passagens rodoviárias | P59: NÃO | Q59: Conforme demanda. | R59: 250 | S59: Passagens ida e volta | T59: 400 | U59: 1 | V59: =R59*T59*U59 -> 100000 | W59: LIMIAR | X59: Atendimento a servidores com valores para cobrir despesas com adiantamento em viagem . | Y59: Não atendimento do deslocamento dos servidores em viagem com recurso para o custeio com deslocamento em viagem . | Z59: Atendimento as servidores em viagem | AA59: 0 | AB59: 0 | AC59: 0 | AD59: 1 | AE59: 1
A60: SEE | B60: Gabinete | D60: Assessoria de Ensino Superior - ASU | F60: 169 - GESTÃO DO SISTEMA ESTADUAL DE EDUCAÇÃO | H60: 2128 - Gestão do Órgão Central | I60: ELEMENTO | J60: 3625 - CONTRATAÇÃO PARA PRESTAÇÃO DE SERVIÇO POR CREDENCIADOS | K60: =VLOOKUP(CONCATENATE(A60,LEFT(J60,4)),AGRUPAMENTO!$D$2:$E$6784,2,FALSE) -> Demais despesas de custeio | L60: 3 - Outras Despesas de Custeio | N60: 10 | O60: PAGAMENTO DE AVALIADORES NOS PROCESSOS REGULATÓRIOS DAS INSTITUIÇÕES DE ENSINO SUPERIOR QUE FORMAM O SISTEMA ESTADUAL DE EDUCAÇÃO DE MINAS GERAIS E SEUS RESPECTIVOS CURSOS | P60: NÃO | Q60: COMISSÃO DE AVALIAÇÃO COMPOSTA POR 2 AVALIADORES, E AVALIAÇÃO REALIZADA COM 2 DIAS | R60: 4 | S60: VALOR POR UM DIA DE AVALIAÇÃO PARA CADA UM DOS AVALIADORES | T60: 1550 | U60: 30 | V60: =R60*T60*U60 -> 186000 | W60: LIMIAR | X60: REALIZAR PROCESSO REGULATÓRIO COMPOSTO POR COMISSÃO COM 2 (DOIS) OU 3 (TRÊS) AVALIADORES E 2 (DOIS) OU 3 (TRÊS) DIAS DE AVALIAÇÃO | Y60: AFETA O FUNCIONAMENTO DA INSTITUIÇÃO DE ENSINO SUPERIOR. CURSOS FICAM SEM COLAÇÃO DE GRAU E EMISSÃO DE DIPLOMA | Z60: REGULARIZAR FUNCIONAMENTO DA INSTITUIÇÃO E DO CURSO E MANTER A QUALIDADE DE ENSINO SUPERIOR NO ESTADO | AA60: 0 | AB60: 0 | AC60: 0 | AD60: 1 | AE60: 1
A61: SEE | B61: Gabinete | D61: Gabinete | F61: 169 - GESTÃO DO SISTEMA ESTADUAL DE EDUCAÇÃO | H61: 2128 - Gestão do Órgão Central | I61: ELEMENTO | J61: 3004 - MATERIAL GRÁFICO E IMPRESSOS | K61: =VLOOKUP(CONCATENATE(A61,LEFT(J61,4)),AGRUPAMENTO!$D$2:$E$6784,2,FALSE) -> Material de consumo | L61: 3 - Outras Despesas de Custeio | N61: 10 | O61: Despesas com Material Gráfico e Impresso | P61: NÃO | Q61: CONFORME DEMANDA. | R61: 12 | S61: Média | T61: 10000 | U61: 1 | V61: =R61*T61*U61 -> 120000 | W61: LIMIAR | X61: Atender demandas de material gráfico. | Y61: Não atendimento da demanda . | Z61: Atendimento a demanda de setores da SEE/MG. | AA61: 0 | AB61: 0 | AC61: 0 | AD61: 1 | AE61: 1
A62: SEE | B62: Gabinete | D62: Gabinete | F62: 169 - GESTÃO DO SISTEMA ESTADUAL DE EDUCAÇÃO | H62: 2128 - Gestão do Órgão Central | I62: ELEMENTO | J62: 3610 - EVENTUAL DE GABINETE | K62: =VLOOKUP(CONCATENATE(A62,LEFT(J62,4)),AGRUPAMENTO!$D$2:$E$6784,2,FALSE) -> Demais despesas de custeio | L62: 3 - Outras Despesas de Custeio | N62: 10 | O62: Eventual de Gabinete | P62: NÃO | Q62: 12 | R62: 12 | S62: VALOR CONFORME LEGISLAÇÃO VIGENTE . | T62: 1000 | U62: 1 | V62: =R62*T62*U62 -> 12000 | W62: LIMIAR | X62: Para cobrir despesas dos Gabinetes. | Y62: Não atendimento da execução de despesas de Eventual de Gabinete. | Z62: Atendimento da execução de despesas de Eventual de Gabinete. | AA62: 0 | AB62: 0 | AC62: 0 | AD62: 1 | AE62: 1
A63: SEE | B63: Gabinete | D63: Gabinete | F63: 169 - GESTÃO DO SISTEMA ESTADUAL DE EDUCAÇÃO | H63: 2128 - Gestão do Órgão Central | I63: ELEMENTO | J63: 3612 - DESPESAS MIÚDAS DE PRONTO PAGAMENTO | K63: =VLOOKUP(CONCATENATE(A63,LEFT(J63,4)),AGRUPAMENTO!$D$2:$E$6784,2,FALSE) -> Demais despesas de custeio | L63: 3 - Outras Despesas de Custeio | N63: 10 | O63: Despesas Miúdas de Pronto Pagamento | P63: NÃO | Q63: 12 | R63: 12 | S63: VALOR CONFORME LEGISLAÇÃO VIGENTE . | T63: 400 | U63: 1 | V63: =R63*T63*U63 -> 4800 | W63: LIMIAR | X63: Para cobrir despesas de caráter inadiável, classificadas como material de consumo e/ou consumo . | Y63: Não atendimento da execução de despesas de pequeno vulto e de necessidade imediata, desde que devidamente justificada. | Z63: Atendimento da execução de despesas da execução de despesas de Eventual de Gabinete. | AA63: 0 | AB63: 0 | AC63: 0 | AD63: 1 | AE63: 1
A64: SEE | B64: Gabinete | D64: Gabinete | F64: 169 - GESTÃO DO SISTEMA ESTADUAL DE EDUCAÇÃO | H64: 2128 - Gestão do Órgão Central | I64: ELEMENTO | J64: 3924 - CURSOS, EXPOSIÇÕES, CONGRESSOS E CONFERÊNCIAS | K64: =VLOOKUP(CONCATENATE(A64,LEFT(J64,4)),AGRUPAMENTO!$D$2:$E$6784,2,FALSE) -> Cursos de formação e capacitações | L64: 3 - Outras Despesas de Custeio | N64: 10 | O64: Cursos, exposições,congressos e conferências. | P64: NÃO | Q64: Eventos | R64: 1 | S64: Média | T64: 5000 | U64: 10 | V64: =R64*T64*U64 -> 50000 | W64: LIMIAR | X64: Atendimento de demandas de projetos da SEE | Y64: Descontibuidade de ações | Z64: Continuidade de ações | AA64: 0 | AB64: 0 | AC64: 0 | AD64: 1 | AE64: 1
A65: SEE | B65: Gabinete | D65: Gabinete | F65: 169 - GESTÃO DO SISTEMA ESTADUAL DE EDUCAÇÃO | H65: 2128 - Gestão do Órgão Central | I65: ELEMENTO | J65: 3948 - CURSOS DE FORMAÇÃO, CAPACITAÇÃO E PÓS-GRADUAÇÃO PARA SERVIDORES | K65: =VLOOKUP(CONCATENATE(A65,LEFT(J65,4)),AGRUPAMENTO!$D$2:$E$6784,2,FALSE) -> Cursos de formação e capacitações | L65: 3 - Outras Despesas de Custeio | N65: 10 | O65: Curso de formação, capacitação e pós graduação para servidores. | P65: NÃO | Q65: Cursos | R65: 1 | S65: Média | T65: 5000 | U65: 10 | V65: =R65*T65*U65 -> 50000 | W65: LIMIAR | X65: Atendimento de demandas de projetos da SEE | Y65: Descontibuidade de ações | Z65: Continuidade de ações | AA65: 0 | AB65: 0 | AC65: 0 | AD65: 1 | AE65: 1
A66: SEE | B66: Gabinete | D66: Gabinete | F66: 169 - GESTÃO DO SISTEMA ESTADUAL DE EDUCAÇÃO | H66: 2128 - Gestão do Órgão Central | I66: ELEMENTO | J66: 3941 - ANUIDADES, CERTIFICADOS E REGISTROS | K66: =VLOOKUP(CONCATENATE(A66,LEFT(J66,4)),AGRUPAMENTO!$D$2:$E$6784,2,FALSE) -> Demais despesas de custeio | L66: 3 - Outras Despesas de Custeio | N66: 10 | O66: Anuidades | P66: NÃO | Q66: 1 | R66: 1 | S66: CONFORME RESOLUÇÃO QUE DISPÕE SOBRE O VALOR DA CONTRIBUIÇÃO DE REPRESENTAÇÃO INSTITUCIONAL QUE alude o ART. 51, INCISO I, DO ESTATUTO SOCIAL DO CONSED. | T66: 395000 | U66: 1 | V66: =R66*T66*U66 -> 395000 | W66: LIMIAR | X66: Para atendimento a SEE/MG, exercendo funções de caráter normativo, consultivo, deliberativo e de assessoramento ao Secretário de Estado da Educação. | Y66: Inadiplência. | Z66: Participação efetiva e colaborativa junto ao CONSED . | AA66: 0 | AB66: 0 | AC66: 0 | AD66: 1 | AE66: 1
A67: SEE | B67: Gabinete | D67: Gabinete | F67: 169 - GESTÃO DO SISTEMA ESTADUAL DE EDUCAÇÃO | H67: 2128 - Gestão do Órgão Central | I67: ELEMENTO | J67: 1401 - DIARIAS - CIVIL | K67: =VLOOKUP(CONCATENATE(A67,LEFT(J67,4)),AGRUPAMENTO!$D$2:$E$6784,2,FALSE) -> Diárias e viagens | L67: 3 - Outras Despesas de Custeio | N67: 10 | O67: Diárias para atender evento MOVEMENTE. | P67: NÃO | Q67: Conforme demanda. | R67: 4000 | S67: Decreto de diárias | T67: 2044.5 | U67: 1 | V67: =R67*T67*U67 -> 8178000 | W67: LIMIAR | X67: Evento MOVEMENTE - Encontro de gestores escolares | Y67: Evento não realizado | Z67: Evento realizado e ações alinhadas para o exercício | AA67: 0 | AB67: 0 | AC67: 0 | AD67: 1 | AE67: 1
A68: SEE | B68: Gabinete | D68: Gabinete | F68: 169 - GESTÃO DO SISTEMA ESTADUAL DE EDUCAÇÃO | H68: 2128 - Gestão do Órgão Central | I68: ELEMENTO | J68: 3302 - DESPESAS COM TRANSPORTE URBANO, PEDAGIO E ESTACIONAMETO PESSOA FISICA | K68: =VLOOKUP(CONCATENATE(A68,LEFT(J68,4)),AGRUPAMENTO!$D$2:$E$6784,2,FALSE) -> Diárias e viagens | L68: 3 - Outras Despesas de Custeio | N68: 10 | O68: Despesas com transporte MOVEMENTE | P68: NÃO | Q68: Conforme demanda. | R68: 4000 | S68: Valor médio de despesas com estacionamento, pedágio e taxi | T68: 200 | U68: 1 | V68: =R68*T68*U68 -> 800000 | W68: LIMIAR | X68: Evento MOVEMENTE - Encontro de gestores escolares | Y68: Evento não realizado | Z68: Evento realizado e ações alinhadas para o exercício | AA68: 0 | AB68: 0 | AC68: 0 | AD68: 1 | AE68: 1
A69: SEE | B69: Gabinete | D69: Gabinete | F69: 169 - GESTÃO DO SISTEMA ESTADUAL DE EDUCAÇÃO | H69: 2128 - Gestão do Órgão Central | I69: ELEMENTO | J69: 3301 - PASSAGENS - PESSOA FISICA | K69: =VLOOKUP(CONCATENATE(A69,LEFT(J69,4)),AGRUPAMENTO!$D$2:$E$6784,2,FALSE) -> Diárias e viagens | L69: 3 - Outras Despesas de Custeio | N69: 10 | O69: Despesas com passagens MOVEMENTE | P69: NÃO | Q69: Conforme demanda. | R69: 4000 | S69: Passagens ida e volta | T69: 400 | U69: 1 | V69: =R69*T69*U69 -> 1600000 | W69: LIMIAR | X69: Evento MOVEMENTE - Encontro de gestores escolares | Y69: Evento não realizado | Z69: Evento realizado e ações alinhadas para o exercício | AA69: 0 | AB69: 0 | AC69: 0 | AD69: 1 | AE69: 1
A70: SEE | B70: Gabinete | D70: Assessoria Jurídica | F70: 169 - GESTÃO DO SISTEMA ESTADUAL DE EDUCAÇÃO | H70: 2128 - Gestão do Órgão Central | I70: ELEMENTO | J70: 3948 - CURSOS DE FORMAÇÃO, CAPACITAÇÃO E PÓS-GRADUAÇÃO PARA SERVIDORES | K70: =VLOOKUP(CONCATENATE(A70,LEFT(J70,4)),AGRUPAMENTO!$D$2:$E$6784,2,FALSE) -> Cursos de formação e capacitações | L70: 3 - Outras Despesas de Custeio | N70: 10 | O70: Cursos, exposições,congressos e conferências. | P70: NÃO | Q70: Cursos | R70: 40 | S70: Média | T70: 2500 | U70: 28 | V70: =R70*T70*U70 -> 2800000 | W70: LIMIAR | X70: Atendimento de demandas de projetos da SEE | Y70: Descontibuidade de ações | Z70: Atualização do conhecimento dos servidores nas diversas áreas de atuação na Assessoria Jurídica | AA70: 0 | AB70: 0 | AC70: 0 | AD70: 1 | AE70: 1
A71: SEE | B71: Gabinete | D71: Assessoria Jurídica | F71: 169 - GESTÃO DO SISTEMA ESTADUAL DE EDUCAÇÃO | H71: 2128 - Gestão do Órgão Central | I71: ELEMENTO | J71: 3031 - LIVROS TÉCNICOS | K71: =VLOOKUP(CONCATENATE(A71,LEFT(J71,4)),AGRUPAMENTO!$D$2:$E$6784,2,FALSE) -> Material de consumo | L71: 3 - Outras Despesas de Custeio | N71: 10 | O71: Livros - doutrina jurídica | P71: NÃO | Q71: Livros | R71: 40 | S71: Média | T71: 9 | U71: 250 | V71: =R71*T71*U71 -> 90000 | W71: LIMIAR | X71: Demandas por material literário | Y71: Desatualização quanto ao normativo jurídico | Z71: Atualização do conhecimento dos servidores nas diversas áreas de atuação na Assessoria Jurídica | AA71: 0 | AB71: 0 | AC71: 0 | AD71: 1 | AE71: 1
A72: SEE | B72: Gabinete | D72: Assessoria de Inovação | F72: 169 - GESTÃO DO SISTEMA ESTADUAL DE EDUCAÇÃO | H72: 2128 - Gestão do Órgão Central | I72: ELEMENTO | J72: 4002 - SERVIÇOS DE TECNOLOGIA DA INFORMAÇÃO | K72: =VLOOKUP(CONCATENATE(A72,LEFT(J72,4)),AGRUPAMENTO!$D$2:$E$6784,2,FALSE) -> Serviços de TIC | L72: 3 - Outras Despesas de Custeio | N72: 10 | O72: Contratação de Creditos azure e licenças Microsoft | P72: SIM | Q72: Contrato a ser firmado em 2025 | R72: 1 | S72: VALOR ANUAL DO CONTRATO | T72: 1878274.7 | U72: 1 | V72: =R72*T72*U72 -> 1878274.7 | W72: LIMIAR | X72: servico microsoft creditos azure, subscricao de licenca de software project plan 5 edu, power automate edu sub per user edu, power automate flow edu sub min 5 licenses edu, power automate attended rpa usl edu sub per user edu, power automate unattended rpa ao edu sub per bot edu, power bi pro por usuario edu, visual studio pro sub msdn edu, sql server enterprise academic core, assurance | Y72: Paralisação da engenharia de dados automatizada. | Z72: A aquisição de subscrição de licenças e serviços técnicos especializados é essencial para a manutenção e o desenvolvimento de soluções tecnológicas - em especial sistemas, painéis/dashboads e automações - de responsabilidade desta Assessoria de Inovação. | AA72: 0 | AB72: 0 | AC72: 0 | AD72: 1 | AE72: 1
A73: SEE | B73: Gabinete | D73: Assessoria de Inovação | F73: 169 - GESTÃO DO SISTEMA ESTADUAL DE EDUCAÇÃO | H73: 2128 - Gestão do Órgão Central | I73: ELEMENTO | J73: 4006 - AQUISICAO DE SOFTWARE | K73: =VLOOKUP(CONCATENATE(A73,LEFT(J73,4)),AGRUPAMENTO!$D$2:$E$6784,2,FALSE) -> Aquisições de itens de TIC | L73: 4 - Investimento | N73: 10 | O73: servicos tecnicos especializados no desenvolvimento, implementacao e sustentacao de solucoes das plataformas microsoft | P73: SIM | Q73: Contrato a ser firmado em 2025 | R73: 1 | S73: VALOR MENSAL DO CONTRATO | T73: 68170 | U73: 12 | V73: =R73*T73*U73 -> 818040 | W73: LIMIAR | X73: Serviço de Desenvolvimento, Manutenção e Sustentação dos Sistemas de Informação | Y73: Paralisação da engenharia de dados automatizada. | Z73: A aquisição de subscrição de licenças e serviços técnicos especializados é essencial para a manutenção e o desenvolvimento de soluções tecnológicas - em especial sistemas, painéis/dashboads e automações - de responsabilidade desta Assessoria de Inovação. | AA73: 0 | AB73: 0 | AC73: 0 | AD73: 1 | AE73: 1
A74: SEE | B74: Gabinete | D74: Assessoria de Inovação | F74: 169 - GESTÃO DO SISTEMA ESTADUAL DE EDUCAÇÃO | H74: 2128 - Gestão do Órgão Central | I74: ELEMENTO | J74: 4002 - SERVIÇOS DE TECNOLOGIA DA INFORMAÇÃO | K74: =VLOOKUP(CONCATENATE(A74,LEFT(J74,4)),AGRUPAMENTO!$D$2:$E$6784,2,FALSE) -> Serviços de TIC | L74: 3 - Outras Despesas de Custeio | N74: 10 | O74: Contratação de Plataformas | P74: SIM | Q74: Contrato a ser firmado em 2025 | R74: 1 | S74: VALOR ANUAL DO CONTRATO | T74: 25836 | U74: 1 | V74: =R74*T74*U74 -> 25836 | W74: LIMIAR | X74: Licença de FlutterFlow, DreamFlow, Notion Plus, WeWeb, Supabase cloud, N8N cloud e Lovable | Y74: Perde-se a possibilidade de construir apps sem conhecimento avançado de programação. Redução de agilidade e menor produtividade por falta de automatização. | Z74: As plataformas permitem o desenvolvimento de aplicativos e dashboards, além da utilização de recursos de automação. | AA74: 0 | AB74: 0 | AC74: 0 | AD74: 1 | AE74: 1
A75: SEE | B75: Gabinete | D75: Assessoria de Inovação | F75: 169 - GESTÃO DO SISTEMA ESTADUAL DE EDUCAÇÃO | H75: 2128 - Gestão do Órgão Central | I75: ELEMENTO | J75: 4002 - SERVIÇOS DE TECNOLOGIA DA INFORMAÇÃO | K75: =VLOOKUP(CONCATENATE(A75,LEFT(J75,4)),AGRUPAMENTO!$D$2:$E$6784,2,FALSE) -> Serviços de TIC | L75: 3 - Outras Despesas de Custeio | N75: 10 | O75: Contratação de serviços de nuvem | P75: SIM | Q75: Contrato a ser firmado em 2025 | R75: 1 | S75: VALOR MENSAL DO CONTRATO | T75: 400141.84 | U75: 12 | V75: =R75*T75*U75 -> 4801702.1 | W75: LIMIAR | X75: Infraestrutura como Servico (IAAS), Plataforma como Servico (PAAS), Software como Serviço - (SAAS) e Servico Especializado em Tecnologia da Informacao e Comunicacao - TIC | Y75: Maior risco de falhas e indisponibilidade sem infraestrutura profissional, atrasos no desenvolvimento de software por infraestrutura limitada, menor produtividade por falta de ferramentas modernas e integradas . | Z75: Reduz custos com servidores físicos, permite escalar recursos conforme a demanda, acelera o desenvolvimento de aplicações e permite o uso imediato de softwares prontos. | AA75: 0 | AB75: 0 | AC75: 0 | AD75: 1 | AE75: 1
A76: SEE | B76: Gabinete | D76: Assessoria de Inovação | F76: 169 - GESTÃO DO SISTEMA ESTADUAL DE EDUCAÇÃO | H76: 2128 - Gestão do Órgão Central | I76: ELEMENTO | J76: 4002 - SERVIÇOS DE TECNOLOGIA DA INFORMAÇÃO | K76: =VLOOKUP(CONCATENATE(A76,LEFT(J76,4)),AGRUPAMENTO!$D$2:$E$6784,2,FALSE) -> Serviços de TIC | L76: 3 - Outras Despesas de Custeio | N76: 10 | O76: Certificação de servidor Web | P76: SIM | Q76: Contrato a ser firmado em 2025 | R76: 1 | S76: VALOR ANUAL DO CONTRATO | T76: 2000 | U76: 1 | V76: =R76*T76*U76 -> 2000 | W76: LIMIAR | X76: Certificação digital para acesso ao B-Cadastro | Y76: Impossibilitará o acesso a plataforma B-Cadastro e consulta a dados como CPF e CNPJ. | Z76: Viabilizará o uso seguro e eficiente da plataforma B-cadastro, ferramenta estratégica para a modernização da gestão pública. | AA76: 0 | AB76: 0 | AC76: 0 | AD76: 1 | AE76: 1
A77: SEE | B77: Gabinete | D77: Assessoria de Inovação | F77: 169 - GESTÃO DO SISTEMA ESTADUAL DE EDUCAÇÃO | H77: 2128 - Gestão do Órgão Central | I77: ELEMENTO | J77: 4002 - SERVIÇOS DE TECNOLOGIA DA INFORMAÇÃO | K77: =VLOOKUP(CONCATENATE(A77,LEFT(J77,4)),AGRUPAMENTO!$D$2:$E$6784,2,FALSE) -> Serviços de TIC | L77: 3 - Outras Despesas de Custeio | N77: 10 | O77: Licença Scriptcase | P77: NÃO | Q77: Contrato Firmado | R77: 1 | S77: VALOR ANUAL DO CONTRATO | T77: 30000 | U77: 1 | V77: =R77*T77*U77 -> 30000 | W77: LIMIAR | X77: Utilização da solução Scriptcase | Y77: Perda de suporte e da licença do scriptcase | Z77: Desenvolvimento e Manutenção de sistemas utilizando a ferramenta scriptcase trazendo agilidade nas entregas | AA77: 0 | AB77: 0 | AC77: 0 | AD77: 1 | AE77: 1
A78: SEE | B78: Gabinete | D78: Assessoria de Inovação | F78: 169 - GESTÃO DO SISTEMA ESTADUAL DE EDUCAÇÃO | H78: 2128 - Gestão do Órgão Central | I78: ELEMENTO | J78: 4002 - SERVIÇOS DE TECNOLOGIA DA INFORMAÇÃO | K78: =VLOOKUP(CONCATENATE(A78,LEFT(J78,4)),AGRUPAMENTO!$D$2:$E$6784,2,FALSE) -> Serviços de TIC | L78: 3 - Outras Despesas de Custeio | N78: 10 | O78: Serviços técnicos especializados em pesquisa e aconselhamento imparcial em Tecnologia da Informação | P78: NÃO | Q78: Contrato Firmado | R78: 1 | S78: VALOR MENSAL DO CONTRATO | T78: 231900 | U78: 12 | V78: =R78*T78*U78 -> 2782800 | W78: LIMIAR | X78: Serviços técnicos especializados em pesquisa e aconselhamento imparcial em Tecnologia da Informação | Y78: Paralisação na prestação dos serviços de pesquisa e aconselhamento nas iniciativas de transformação gerencial e digital da SEE | Z78: Utilização de melhores práticas, aconselhamento executivo, pesquisas e ferramentas que permitam apoiar as iniciativas de transformação gerencial e digital da SEE | AA78: 0 | AB78: 0 | AC78: 0 | AD78: 1 | AE78: 1
... A316: SEE | B316: Subsecretaria de Desenvolvimento da Educação Básica | D316: Superintendência de Políticas Pedagógicas | F316: 167 - Apoio Pedagógico Para o Desenvolvimento da Educação Básica | H316: 1033 - Modalidades e Temáticas Especiais | I316: ELEMENTO | J316: 3301 - PASSAGENS - PESSOA FISICA | K316: =VLOOKUP(CONCATENATE(A316,LEFT(J316,4)),AGRUPAMENTO!$D$2:$E$6784,2,FALSE) -> Diárias e viagens | L316: 3 - Outras Despesas de Custeio | N316: 10 | O316: Monitoramento da Equipe Central com passagem para 3 servidores para formação PCD, ERER. | P316: NÃO | Q316: Monitoramento | R316: 10 | S316: Legislação vigente | T316: 300 | U316: 1 | V316: =R316*T316*U316 -> 3000 | W316: LIMIAR | X316: Atendimento de demandas de projetos da SEE | Y316: Deixar de atender demandas da Secretaria | Z316: Permitir o atendimento às demandas da Secretaria | AA316: 0 | AB316: 0 | AC316: 0 | AD316: 1 | AE316: 1

Sheet ORGANOGRAMA
A1: AGE | B1: ARMBH | C1: ARMVA | D1: ARSAE | E1: ARTEMIG | F1: CBMMG | G1: CGE | H1: DER | I1: EMATER | J1: EMC | K1: EPAMIG | L1: ESPMG | M1: FAOP | N1: FAPEMIG | O1: FCS | P1: FDM | Q1: FEAM | R1: FEAS | S1: FES | T1: FGP | U1: FHA | V1: FHEMIG | W1: FHIDRO | X1: FJP | Y1: FPP | Z1: FUCAM | AA1: FUNAPEC | AB1: FUNED | AC1: FUNTRANS | AD1: GMG | AE1: HEMOMINAS | AF1: IDENE | AG1: IEF | AH1: IEPHA | AI1: IGAM | AJ1: IMA | AK1: IPSEMG | AL1: IPSM | AM1: JUCEMG | AN1: LEMG | AO1: OGE | AP1: PCMG | AQ1: PMMG | AR1: SCC | AS1: SEAPA | AT1: SEC.GERAL | AU1: SECOM | AV1: SECULT | AW1: SEDE | AX1: SEDESE | AY1: SEE | AZ1: SEF | BA1: SEGOV | BB1: SEINFRA | BC1: SEJUSP | BD1: SEMAD | BE1: SEPLAG | BF1: TVMINAS | BG1: UEMG | BH1: UNIMONTES | BI1: UTRAMIG
A2: SUB DE ADMINISTRAÇÃO | B2: dsadasdas | C2: DSADAA
A3: dsadasj | B3: dksadsa | C3: FFDSSA
A4: kfdsafas | B4: kdsasa

Sheet CENÁRIO
A1: Cenário | C1: Novo
A2: LIMIAR | C2: SIM
A3: INCREMENTAL | C3: NÃO
C4: SIM
A7: GRUPO DE DESPESA
A8: 3 - Outras Despesas de Custeio
A9: 4 - Investimento
A10: 5 - Inversões Financeiras

Sheet VALIDACAO
A2: PROGRAMAUO | B2: prog cod | C2: Elemento
A3: =CONCATENATE('BASE OBZ'!A3,"PROG") -> SEEPROG | B3: =CONCATENATE("P",(LEFT('BASE OBZ'!F3,3)),'BASE OBZ'!A3) -> P169SEE | C3: Elemento
A4: =CONCATENATE('BASE OBZ'!A4,"PROG") -> SEEPROG | B4: =CONCATENATE("P",(LEFT('BASE OBZ'!F4,3)),'BASE OBZ'!A4) -> P169SEE | C4: Elemento
A5: =CONCATENATE('BASE OBZ'!A5,"PROG") -> SEEPROG | B5: =CONCATENATE("P",(LEFT('BASE OBZ'!F5,3)),'BASE OBZ'!A5) -> P169SEE | C5: Elemento
A6: =CONCATENATE('BASE OBZ'!A6,"PROG") -> SEEPROG | B6: =CONCATENATE("P",(LEFT('BASE OBZ'!F6,3)),'BASE OBZ'!A6) -> P169SEE | C6: Elemento
A7: =CONCATENATE('BASE OBZ'!A7,"PROG") -> SEEPROG | B7: =CONCATENATE("P",(LEFT('BASE OBZ'!F7,3)),'BASE OBZ'!A7) -> P169SEE | C7: Elemento
A8: =CONCATENATE('BASE OBZ'!A8,"PROG") -> SEEPROG | B8: =CONCATENATE("P",(LEFT('BASE OBZ'!F8,3)),'BASE OBZ'!A8) -> P169SEE | C8: Elemento
A9: =CONCATENATE('BASE OBZ'!A9,"PROG") -> SEEPROG | B9: =CONCATENATE("P",(LEFT('BASE OBZ'!F9,3)),'BASE OBZ'!A9) -> P169SEE | C9: Elemento
A10: =CONCATENATE('BASE OBZ'!A10,"PROG") -> SEEPROG | B10: =CONCATENATE("P",(LEFT('BASE OBZ'!F10,3)),'BASE OBZ'!A10) -> P169SEE | C10: Elemento
A11: =CONCATENATE('BASE OBZ'!A11,"PROG") -> SEEPROG | B11: =CONCATENATE("P",(LEFT('BASE OBZ'!F11,3)),'BASE OBZ'!A11) -> P169SEE | C11: Elemento
A12: =CONCATENATE('BASE OBZ'!A12,"PROG") -> SEEPROG | B12: =CONCATENATE("P",(LEFT('BASE OBZ'!F12,3)),'BASE OBZ'!A12) -> P169SEE | C12: Elemento
A13: =CONCATENATE('BASE OBZ'!A13,"PROG") -> SEEPROG | B13: =CONCATENATE("P",(LEFT('BASE OBZ'!F13,3)),'BASE OBZ'!A13) -> P169SEE | C13: Elemento
A14: =CONCATENATE('BASE OBZ'!A14,"PROG") -> SEEPROG | B14: =CONCATENATE("P",(LEFT('BASE OBZ'!F14,3)),'BASE OBZ'!A14) -> P169SEE | C14: Elemento
A15: =CONCATENATE('BASE OBZ'!A15,"PROG") -> SEEPROG | B15: =CONCATENATE("P",(LEFT('BASE OBZ'!F15,3)),'BASE OBZ'!A15) -> P169SEE | C15: Elemento
A16: =CONCATENATE('BASE OBZ'!#REF!,"PROG") -> #REF! | B16: =CONCATENATE("P",(LEFT('BASE OBZ'!#REF!,3)),'BASE OBZ'!#REF!) -> #REF! | C16: Elemento
A17: =CONCATENATE('BASE OBZ'!#REF!,"PROG") -> #REF! | B17: =CONCATENATE("P",(LEFT('BASE OBZ'!#REF!,3)),'BASE OBZ'!#REF!) -> #REF! | C17: Elemento
A18: =CONCATENATE('BASE OBZ'!A16,"PROG") -> SEEPROG | B18: =CONCATENATE("P",(LEFT('BASE OBZ'!F16,3)),'BASE OBZ'!A16) -> P162SEE | C18: Elemento
A19: =CONCATENATE('BASE OBZ'!A17,"PROG") -> SEEPROG | B19: =CONCATENATE("P",(LEFT('BASE OBZ'!F17,3)),'BASE OBZ'!A17) -> P162SEE | C19: Elemento
A20: =CONCATENATE('BASE OBZ'!A18,"PROG") -> SEEPROG | B20: =CONCATENATE("P",(LEFT('BASE OBZ'!F18,3)),'BASE OBZ'!A18) -> P162SEE | C20: Elemento
A21: =CONCATENATE('BASE OBZ'!A19,"PROG") -> SEEPROG | B21: =CONCATENATE("P",(LEFT('BASE OBZ'!F19,3)),'BASE OBZ'!A19) -> P162SEE | C21: Elemento
A22: =CONCATENATE('BASE OBZ'!A20,"PROG") -> SEEPROG | B22: =CONCATENATE("P",(LEFT('BASE OBZ'!F20,3)),'BASE OBZ'!A20) -> P162SEE | C22: Elemento
A23: =CONCATENATE('BASE OBZ'!A21,"PROG") -> SEEPROG | B23: =CONCATENATE("P",(LEFT('BASE OBZ'!F21,3)),'BASE OBZ'!A21) -> P162SEE | C23: Elemento
A24: =CONCATENATE('BASE OBZ'!A22,"PROG") -> SEEPROG | B24: =CONCATENATE("P",(LEFT('BASE OBZ'!F22,3)),'BASE OBZ'!A22) -> P162SEE | C24: Elemento
A25: =CONCATENATE('BASE OBZ'!A23,"PROG") -> SEEPROG | B25: =CONCATENATE("P",(LEFT('BASE OBZ'!F23,3)),'BASE OBZ'!A23) -> P162SEE | C25: Elemento
A26: =CONCATENATE('BASE OBZ'!A24,"PROG") -> SEEPROG | B26: =CONCATENATE("P",(LEFT('BASE OBZ'!F24,3)),'BASE OBZ'!A24) -> P162SEE | C26: Elemento
A27: =CONCATENATE('BASE OBZ'!A25,"PROG") -> SEEPROG | B27: =CONCATENATE("P",(LEFT('BASE OBZ'!F25,3)),'BASE OBZ'!A25) -> P162SEE | C27: Elemento
A28: =CONCATENATE('BASE OBZ'!A26,"PROG") -> SEEPROG | B28: =CONCATENATE("P",(LEFT('BASE OBZ'!F26,3)),'BASE OBZ'!A26) -> P162SEE | C28: Elemento
A29: =CONCATENATE('BASE OBZ'!A27,"PROG") -> SEEPROG | B29: =CONCATENATE("P",(LEFT('BASE OBZ'!F27,3)),'BASE OBZ'!A27) -> P162SEE | C29: Elemento
... A261: =CONCATENATE('BASE OBZ'!A259,"PROG") -> SEEPROG | B261: =CONCATENATE("P",(LEFT('BASE OBZ'!F259,3)),'BASE OBZ'!A259) -> P167SEE | C261: Elemento
A262: =CONCATENATE('BASE OBZ'!A261,"PROG") -> SEEPROG | B262: =CONCATENATE("P",(LEFT('BASE OBZ'!F261,3)),'BASE OBZ'!A261) -> P167SEE | C262: Elemento
A263: =CONCATENATE('BASE OBZ'!A262,"PROG") -> SEEPROG | B263: =CONCATENATE("P",(LEFT('BASE OBZ'!F262,3)),'BASE OBZ'!A262) -> P165SEE | C263: Elemento
A264: =CONCATENATE('BASE OBZ'!#REF!,"PROG") -> #REF! | B264: =CONCATENATE("P",(LEFT('BASE OBZ'!#REF!,3)),'BASE OBZ'!#REF!) -> #REF! | C264: Elemento
A265: =CONCATENATE('BASE OBZ'!A263,"PROG") -> SEEPROG | B265: =CONCATENATE("P",(LEFT('BASE OBZ'!F263,3)),'BASE OBZ'!A263) -> P165SEE | C265: Elemento
A266: =CONCATENATE('BASE OBZ'!A264,"PROG") -> SEEPROG | B266: =CONCATENATE("P",(LEFT('BASE OBZ'!F264,3)),'BASE OBZ'!A264) -> P165SEE | C266: Elemento
A267: =CONCATENATE('BASE OBZ'!A265,"PROG") -> SEEPROG | B267: =CONCATENATE("P",(LEFT('BASE OBZ'!F265,3)),'BASE OBZ'!A265) -> P165SEE | C267: Elemento
A268: =CONCATENATE('BASE OBZ'!A266,"PROG") -> SEEPROG | B268: =CONCATENATE("P",(LEFT('BASE OBZ'!F266,3)),'BASE OBZ'!A266) -> P165SEE | C268: Elemento
A269: =CONCATENATE('BASE OBZ'!A267,"PROG") -> SEEPROG | B269: =CONCATENATE("P",(LEFT('BASE OBZ'!F267,3)),'BASE OBZ'!A267) -> P165SEE | C269: Elemento
A270: =CONCATENATE('BASE OBZ'!A268,"PROG") -> SEEPROG | B270: =CONCATENATE("P",(LEFT('BASE OBZ'!F268,3)),'BASE OBZ'!A268) -> P167SEE | C270: Elemento
A271: =CONCATENATE('BASE OBZ'!A269,"PROG") -> SEEPROG | B271: =CONCATENATE("P",(LEFT('BASE OBZ'!F269,3)),'BASE OBZ'!A269) -> P167SEE | C271: Elemento
A272: =CONCATENATE('BASE OBZ'!A270,"PROG") -> SEEPROG | B272: =CONCATENATE("P",(LEFT('BASE OBZ'!F270,3)),'BASE OBZ'!A270) -> P165SEE | C272: Elemento
A273: =CONCATENATE('BASE OBZ'!#REF!,"PROG") -> #REF! | B273: =CONCATENATE("P",(LEFT('BASE OBZ'!#REF!,3)),'BASE OBZ'!#REF!) -> #REF! | C273: Elemento
A274: =CONCATENATE('BASE OBZ'!A272,"PROG") -> SEEPROG | B274: =CONCATENATE("P",(LEFT('BASE OBZ'!F272,3)),'BASE OBZ'!A272) -> P167SEE | C274: Elemento
A275: =CONCATENATE('BASE OBZ'!#REF!,"PROG") -> #REF! | B275: =CONCATENATE("P",(LEFT('BASE OBZ'!#REF!,3)),'BASE OBZ'!#REF!) -> #REF! | C275: Elemento
A276: =CONCATENATE('BASE OBZ'!A273,"PROG") -> SEEPROG | B276: =CONCATENATE("P",(LEFT('BASE OBZ'!F273,3)),'BASE OBZ'!A273) -> P005SEE | C276: Elemento
A277: =CONCATENATE('BASE OBZ'!A274,"PROG") -> SEEPROG | B277: =CONCATENATE("P",(LEFT('BASE OBZ'!F274,3)),'BASE OBZ'!A274) -> P005SEE | C277: Elemento
A278: =CONCATENATE('BASE OBZ'!#REF!,"PROG") -> #REF! | B278: =CONCATENATE("P",(LEFT('BASE OBZ'!#REF!,3)),'BASE OBZ'!#REF!) -> #REF! | C278: Elemento
A279: =CONCATENATE('BASE OBZ'!A275,"PROG") -> SEEPROG | B279: =CONCATENATE("P",(LEFT('BASE OBZ'!F275,3)),'BASE OBZ'!A275) -> P167SEE | C279: Elemento
A280: =CONCATENATE('BASE OBZ'!A276,"PROG") -> SEEPROG | B280: =CONCATENATE("P",(LEFT('BASE OBZ'!F276,3)),'BASE OBZ'!A276) -> P167SEE | C280: Elemento
A281: =CONCATENATE('BASE OBZ'!A277,"PROG") -> SEEPROG | B281: =CONCATENATE("P",(LEFT('BASE OBZ'!F277,3)),'BASE OBZ'!A277) -> P167SEE | C281: Elemento
A282: =CONCATENATE('BASE OBZ'!A278,"PROG") -> SEEPROG | B282: =CONCATENATE("P",(LEFT('BASE OBZ'!F278,3)),'BASE OBZ'!A278) -> P167SEE | C282: Elemento
A283: =CONCATENATE('BASE OBZ'!A279,"PROG") -> SEEPROG | B283: =CONCATENATE("P",(LEFT('BASE OBZ'!F279,3)),'BASE OBZ'!A279) -> P167SEE | C283: Elemento
A284: =CONCATENATE('BASE OBZ'!A280,"PROG") -> SEEPROG | B284: =CONCATENATE("P",(LEFT('BASE OBZ'!F280,3)),'BASE OBZ'!A280) -> P167SEE | C284: Elemento
A285: =CONCATENATE('BASE OBZ'!A281,"PROG") -> SEEPROG | B285: =CONCATENATE("P",(LEFT('BASE OBZ'!F281,3)),'BASE OBZ'!A281) -> P167SEE | C285: Elemento
A286: =CONCATENATE('BASE OBZ'!A282,"PROG") -> SEEPROG | B286: =CONCATENATE("P",(LEFT('BASE OBZ'!F282,3)),'BASE OBZ'!A282) -> P167SEE | C286: Elemento
A287: =CONCATENATE('BASE OBZ'!A283,"PROG") -> SEEPROG | B287: =CONCATENATE("P",(LEFT('BASE OBZ'!F283,3)),'BASE OBZ'!A283) -> P167SEE | C287: Elemento
A288: =CONCATENATE('BASE OBZ'!A284,"PROG") -> SEEPROG | B288: =CONCATENATE("P",(LEFT('BASE OBZ'!F284,3)),'BASE OBZ'!A284) -> P167SEE | C288: Elemento
A289: =CONCATENATE('BASE OBZ'!A285,"PROG") -> SEEPROG | B289: =CONCATENATE("P",(LEFT('BASE OBZ'!F285,3)),'BASE OBZ'!A285) -> P167SEE | C289: Elemento
A290: =CONCATENATE('BASE OBZ'!A286,"PROG") -> SEEPROG | B290: =CONCATENATE("P",(LEFT('BASE OBZ'!F286,3)),'BASE OBZ'!A286) -> P167SEE | C290: Elemento
... A307: =CONCATENATE('BASE OBZ'!A303,"PROG") -> SEEPROG | B307: =CONCATENATE("P",(LEFT('BASE OBZ'!F303,3)),'BASE OBZ'!A303) -> P167SEE | C307: Elemento
A308: =CONCATENATE('BASE OBZ'!#REF!,"PROG") -> #REF! | B308: =CONCATENATE("P",(LEFT('BASE OBZ'!#REF!,3)),'BASE OBZ'!#REF!) -> #REF! | C308: Elemento
A309: =CONCATENATE('BASE OBZ'!#REF!,"PROG") -> #REF! | B309: =CONCATENATE("P",(LEFT('BASE OBZ'!#REF!,3)),'BASE OBZ'!#REF!) -> #REF! | C309: Elemento
A310: =CONCATENATE('BASE OBZ'!A304,"PROG") -> SEEPROG | B310: =CONCATENATE("P",(LEFT('BASE OBZ'!F304,3)),'BASE OBZ'!A304) -> P167SEE | C310: Elemento
A311: =CONCATENATE('BASE OBZ'!#REF!,"PROG") -> #REF! | B311: =CONCATENATE("P",(LEFT('BASE OBZ'!#REF!,3)),'BASE OBZ'!#REF!) -> #REF! | C311: Elemento
A312: =CONCATENATE('BASE OBZ'!A305,"PROG") -> SEEPROG | B312: =CONCATENATE("P",(LEFT('BASE OBZ'!F305,3)),'BASE OBZ'!A305) -> P167SEE | C312: Elemento
A313: =CONCATENATE('BASE OBZ'!#REF!,"PROG") -> #REF! | B313: =CONCATENATE("P",(LEFT('BASE OBZ'!#REF!,3)),'BASE OBZ'!#REF!) -> #REF! | C313: Elemento
A314: =CONCATENATE('BASE OBZ'!#REF!,"PROG") -> #REF! | B314: =CONCATENATE("P",(LEFT('BASE OBZ'!#REF!,3)),'BASE OBZ'!#REF!) -> #REF! | C314: Elemento
A315: =CONCATENATE('BASE OBZ'!A306,"PROG") -> SEEPROG | B315: =CONCATENATE("P",(LEFT('BASE OBZ'!F306,3)),'BASE OBZ'!A306) -> P167SEE | C315: Elemento
A316: =CONCATENATE('BASE OBZ'!A307,"PROG") -> SEEPROG | B316: =CONCATENATE("P",(LEFT('BASE OBZ'!F307,3)),'BASE OBZ'!A307) -> P167SEE | C316: Elemento
A317: =CONCATENATE('BASE OBZ'!A308,"PROG") -> SEEPROG | B317: =CONCATENATE("P",(LEFT('BASE OBZ'!F308,3)),'BASE OBZ'!A308) -> P167SEE | C317: Elemento
A318: =CONCATENATE('BASE OBZ'!A309,"PROG") -> SEEPROG | B318: =CONCATENATE("P",(LEFT('BASE OBZ'!F309,3)),'BASE OBZ'!A309) -> P167SEE | C318: Elemento
A319: =CONCATENATE('BASE OBZ'!A310,"PROG") -> SEEPROG | B319: =CONCATENATE("P",(LEFT('BASE OBZ'!F310,3)),'BASE OBZ'!A310) -> P167SEE | C319: Elemento
A320: =CONCATENATE('BASE OBZ'!#REF!,"PROG") -> #REF! | B320: =CONCATENATE("P",(LEFT('BASE OBZ'!#REF!,3)),'BASE OBZ'!#REF!) -> #REF! | C320: Elemento
A321: =CONCATENATE('BASE OBZ'!A311,"PROG") -> SEEPROG | B321: =CONCATENATE("P",(LEFT('BASE OBZ'!F311,3)),'BASE OBZ'!A311) -> P167SEE | C321: Elemento
A322: =CONCATENATE('BASE OBZ'!A312,"PROG") -> SEEPROG | B322: =CONCATENATE("P",(LEFT('BASE OBZ'!F312,3)),'BASE OBZ'!A312) -> P167SEE | C322: Elemento
A323: =CONCATENATE('BASE OBZ'!A313,"PROG") -> SEEPROG | B323: =CONCATENATE("P",(LEFT('BASE OBZ'!F313,3)),'BASE OBZ'!A313) -> P167SEE | C323: Elemento
A324: =CONCATENATE('BASE OBZ'!A314,"PROG") -> SEEPROG | B324: =CONCATENATE("P",(LEFT('BASE OBZ'!F314,3)),'BASE OBZ'!A314) -> P167SEE | C324: Elemento
A325: =CONCATENATE('BASE OBZ'!A315,"PROG") -> SEEPROG | B325: =CONCATENATE("P",(LEFT('BASE OBZ'!F315,3)),'BASE OBZ'!A315) -> P167SEE | C325: Elemento
A326: =CONCATENATE('BASE OBZ'!A316,"PROG") -> SEEPROG | B326: =CONCATENATE("P",(LEFT('BASE OBZ'!F316,3)),'BASE OBZ'!A316) -> P167SEE | C326: Elemento
A327: =CONCATENATE('BASE OBZ'!#REF!,"PROG") -> #REF! | B327: =CONCATENATE("P",(LEFT('BASE OBZ'!#REF!,3)),'BASE OBZ'!#REF!) -> #REF! | C327: Elemento
A328: =CONCATENATE('BASE OBZ'!#REF!,"PROG") -> #REF! | B328: =CONCATENATE("P",(LEFT('BASE OBZ'!#REF!,3)),'BASE OBZ'!#REF!) -> #REF! | C328: Elemento
A329: =CONCATENATE('BASE OBZ'!#REF!,"PROG") -> #REF! | B329: =CONCATENATE("P",(LEFT('BASE OBZ'!#REF!,3)),'BASE OBZ'!#REF!) -> #REF! | C329: Elemento
A330: =CONCATENATE('BASE OBZ'!#REF!,"PROG") -> #REF! | B330: =CONCATENATE("P",(LEFT('BASE OBZ'!#REF!,3)),'BASE OBZ'!#REF!) -> #REF! | C330: Elemento
A331: =CONCATENATE('BASE OBZ'!#REF!,"PROG") -> #REF! | B331: =CONCATENATE("P",(LEFT('BASE OBZ'!#REF!,3)),'BASE OBZ'!#REF!) -> #REF! | C331: Elemento
A332: =CONCATENATE('BASE OBZ'!#REF!,"PROG") -> #REF! | B332: =CONCATENATE("P",(LEFT('BASE OBZ'!#REF!,3)),'BASE OBZ'!#REF!) -> #REF! | C332: Elemento
A333: =CONCATENATE('BASE OBZ'!#REF!,"PROG") -> #REF! | B333: =CONCATENATE("P",(LEFT('BASE OBZ'!#REF!,3)),'BASE OBZ'!#REF!) -> #REF! | C333: Elemento
A334: =CONCATENATE('BASE OBZ'!#REF!,"PROG") -> #REF! | B334: =CONCATENATE("P",(LEFT('BASE OBZ'!#REF!,3)),'BASE OBZ'!#REF!) -> #REF! | C334: Elemento
A335: =CONCATENATE('BASE OBZ'!#REF!,"PROG") -> #REF! | B335: =CONCATENATE("P",(LEFT('BASE OBZ'!#REF!,3)),'BASE OBZ'!#REF!) -> #REF! | C335: Elemento
A336: =CONCATENATE('BASE OBZ'!#REF!,"PROG") -> #REF! | B336: =CONCATENATE("P",(LEFT('BASE OBZ'!#REF!,3)),'BASE OBZ'!#REF!) -> #REF! | C336: Elemento
A337: =CONCATENATE('BASE OBZ'!#REF!,"PROG") -> #REF! | B337: =CONCATENATE("P",(LEFT('BASE OBZ'!#REF!,3)),'BASE OBZ'!#REF!) -> #REF! | C337: Elemento
A338: =CONCATENATE('BASE OBZ'!#REF!,"PROG") -> #REF! | B338: =CONCATENATE("P",(LEFT('BASE OBZ'!#REF!,3)),'BASE OBZ'!#REF!) -> #REF! | C338: Elemento
... A1998: =CONCATENATE('BASE OBZ'!#REF!,"PROG") -> #REF! | B1998: =CONCATENATE("P",(LEFT('BASE OBZ'!#REF!,3)),'BASE OBZ'!#REF!) -> #REF! | C1998: Elemento

Sheet AÇÕES E PROGRAMAS
A1: AGE | B1: ARMBH | C1: ARMVA | D1: AGÊNCIA DE PROMOÇÃO DE INVESTIMENTOS DE MINAS GERAIS | E1: ARSAE | F1: ASSEMBLEIA LEGISLATIVA DO ESTADO DE MINAS GERAIS | G1: BANCO DE DESENVOLVIMENTO DE MINAS GERAIS S.A | H1: CEMIG DISTRIBUIÇÃO S.A | I1: CEMIG GERAÇÃO E TRANSMISSÃO S.A | J1: COMPANHIA DE DESENVOLVIMENTO DE MINAS GERAIS | K1: COMPANHIA DE DESENVOLVIMENTO ECONÔMICO DE MINAS GERAIS | L1: COMPANHIA DE GÁS DE MINAS GERAIS | M1: COMPANHIA DE HABITAÇÃO DO ESTADO DE MINAS GERAIS | N1: COMPANHIA DE SANEAMENTO DE MINAS GERAIS | O1: COMPANHIA DE TECNOLOGIA DA INFORMAÇÃO DO ESTADO DE MINAS GERAIS | P1: COMPANHIA ENERGÉTICA DE MINAS GERAIS | Q1: CGE | R1: COPASA - SERVIÇOS DE SANEAMENTO INTEGRADO DO NORTE E NORDESTE DE MINAS GERAIS S/A | S1: CBMMG | T1: DEFENSORIA PUBLICA DO ESTADO DE MINAS GERAIS | U1: DER | V1: EGE SEC.FAZENDA-ENCARGOS DIVERSOS | W1: EGE-SECRETARIA DE ESTADO DE PLANEJAMENTO E GESTÃO | X1: EMATER | Y1: EPAMIG | Z1: EMC | AA1: ENCARGOS GERAIS DO ESTADO - INSTRUMENTOS DE ENTRADA DE RECURSOS | AB1: ESPMG | AC1: HEMOMINAS | AD1: FCS | AE1: FAPEMIG | AF1: FAOP | AG1: UTRAMIG | AH1: FUCAM | AI1: FEAM | AJ1: FUNED | AK1: FHA | AL1: FHEMIG | AM1: FJP | AN1: TVMINAS | AO1: FUNDO DE APOIO HABITACIONAL AOS MILITARES DO ESTADO DE MINAS GERAIS | AP1: FUNDO DE APOIO HABITACIONAL DA ASSEMBLEIA LEGISLATIVA DE MINAS GERAIS | AQ1: FUNAPEC | AR1: FUNDO DE ASSISTÊNCIA AO TURISMO | AS1: FUNDO DE ATIVOS IMOBILIÁRIOS DE MINAS GERAIS | AT1: FDM | AU1: FUNDO DE FOMENTO E DESENVOLVIMENTO SOCIOECONÔMICO DO ESTADO DE MINAS GERAIS | AV1: FGP | AW1: FUNDO DE INVESTIMENTO DO ESTADO DE MINAS GERAIS | AX1: FUNDO DE INVESTIMENTOS IMOBILIÁRIOS DE MINAS GERAIS | AY1: FPP | AZ1: FHIDRO | BA1: FUNDO DO TRIBUNAL DE CONTAS DO ESTADO DE MINAS GERAIS | BB1: FUNDO ESPECIAL DE CRÉDITOS INADIMPLIDOS E DÍVIDA ATIVA | BC1: FUNDO ESPECIAL DO MINISTÉRIO PÚBLICO DO ESTADO DE MINAS GERAIS | BD1: FUNDO ESPECIAL DO PODER JUDICIÁRIO DO ESTADO DE MINAS GERAIS | BE1: FEAS | BF1: FUNDO ESTADUAL DE CULTURA | BG1: FUNDO ESTADUAL DE DEFESA DE DIREITOS DIFUSOS | BH1: FUNTRANS | BI1: FUNDO ESTADUAL DE DESENVOLVIMENTO RURAL | BJ1: FUNDO ESTADUAL DE HABITAÇÃO | BK1: FUNDO ESTADUAL DE PREVENÇÃO, FISCALIZAÇÃO E REPRESSÃO DE ENTORPECENTES | BL1: FUNDO ESTADUAL DE PREVIDÊNCIA DO ESTADO DE MINAS GERAIS | BM1: FUNDO ESTADUAL DE PROTEÇÃO E DEFESA DO CONSUMIDOR | BN1: FES | BO1: FUNDO ESTADUAL DE SEGURANÇA PÚBLICA DE MINAS GERAIS | BP1: FUNDO ESTADUAL DO TRABALHO DE MINAS GERAIS | BQ1: FUNDO ESTADUAL DOS DIREITOS DO IDOSO | BR1: FUNDO FINANCEIRO DE PREVIDÊNCIA DO ESTADO DE MINAS GERAIS | BS1: FUNDO PARA A INFÂNCIA E A ADOLESCÊNCIA | BT1: FUNDO PENITENCIÁRIO ESTADUAL | BU1: GMG | BV1: GESTÃO DA DÍVIDA PÚBLICA ESTADUAL | BW1: IDENE | BX1: INSTITUTO DE METROLOGIA E QUALIDADE DO ESTADO DE MINAS GERAIS | BY1: INSTITUTO DE PREVIDÊNCIA DO LEGISLATIVO DO ESTADO DE MINAS GERAIS | BZ1: IPSEMG | CA1: IPSM | CB1: IEF | CC1: IEPHA | CD1: IMA | CE1: IGAM | CF1: JUCEMG | CG1: LEMG | CH1: MINAS GERAIS ADMINISTRAÇÃO E SERVIÇOS S.A | CI1: MINAS GERAIS PARTICIPAÇÕES S.A | CJ1: OGE | CK1: PARTICIPAÇÃO NO AUMENTO DO CAPITAL SOCIAL DE EMPRESAS | CL1: PCMG | CM1: PMMG | CN1: PROCURADORIA GERAL DE JUSTIÇA | CO1: RESERVA DE CONTINGÊNCIA | CP1: SCC | CQ1: SEAPA | CR1: SECOM | CS1: SECULT | CT1: SEDE | CU1: SEDESE | CV1: SEE | CW1: SEF | CX1: SEGOV | CY1: SEINFRA | CZ1: SEJUSP | DA1: SEMAD | DB1: SEPLAG | DC1: SEC.GERAL | DD1: TREM METROPOLITANO DE BELO HORIZONTE S.A | DE1: TRIBUNAL DE CONTAS DO ESTADO DE MINAS GERAIS | DF1: TRIBUNAL DE JUSTIÇA DO ESTADO DE MINAS GERAIS | DG1: TRIBUNAL DE JUSTIÇA MILITAR DO ESTADO DE MINAS GERAIS | DH1: UEMG | DI1: UNIMONTES | DJ1: ARTEMIG
A2: 043 - DESJUDICIALIZA MINAS | B2: 077 - CAMINHOS PARA O DESENVOLVIMENTO INTEGRADO METROPOLITANO | C2: 077 - CAMINHOS PARA O DESENVOLVIMENTO INTEGRADO METROPOLITANO | D2: 142 - MANUTENÇÃO DA INFRAESTRUTURA ADMINISTRATIVA E OPERACIONAL - INVEST MINAS | E2: 010 - REGULAÇÃO E FISCALIZAÇÃO DOS SERVIÇOS DE ABASTECIMENTO DE ÁGUA E DE ESGOTAMENTO SANITÁRIO E ATENDIMENTO AOS USUÁRIOS | F2: 705 - APOIO ÀS POLÍTICAS PÚBLICAS | G2: 014 - FINANCIAMENTO À DESCARBONIZAÇÃO E RESILIÊNCIA CLIMÁTICA ENTRE BDMG E BANCO INTERAMERICANO DE DESENVOLVIMENTO (BDMG PBR) | H2: 072 - DISTRIBUIÇÃO DE ENERGIA ELÉTRICA | I2: 092 - TRANSMISSÃO DE ENERGIA ELÉTRICA | J2: 133 - MINAS GERAÇÃO DE VALOR | K2: 133 - MINAS GERAÇÃO DE VALOR | L2: 133 - MINAS GERAÇÃO DE VALOR | M2: 705 - APOIO ÀS POLÍTICAS PÚBLICAS | N2: 021 - SANEAMENTO E RESÍDUOS ESPECIAIS | O2: 030 - SOLUÇÕES EM TECNOLOGIA DA INFORMAÇÃO E COMUNICAÇÃO | P2: 035 - INVESTIMENTOS CEMIG | Q2: 001 - MINAS ÍNTEGRA E TRANSPARENTE | R2: 021 - SANEAMENTO E RESÍDUOS ESPECIAIS | S2: 047 - SUPORTE ÀS AÇÕES DE COMBATE E RESPOSTA AOS DANOS CAUSADOS PELAS CHUVAS | T2: 705 - APOIO ÀS POLÍTICAS PÚBLICAS | U2: 047 - SUPORTE ÀS AÇÕES DE COMBATE E RESPOSTA AOS DANOS CAUSADOS PELAS CHUVAS | V2: 705 - APOIO ÀS POLÍTICAS PÚBLICAS | W2: 160 - MELHORIA DA GESTÃO LOGÍSTICA E PATRIMONIAL | X2: 090 - ASSISTÊNCIA TECNICA E EXTENSÃO RURAL PARA O ESTADO DE MINAS GERAIS | Y2: 015 - ENSINO SUPERIOR PARA A AGRICULTURA E PECUÁRIA | Z2: 102 - FOMENTO À ECONOMIA DA CRIATIVIDADE | AA2: 705 - APOIO ÀS POLÍTICAS PÚBLICAS | AB2: 028 - DESENVOLVIMENTO DE AÇÕES DE EDUCAÇÃO E PESQUISA PARA O SISTEMA ÚNICO DE SAÚDE | AC2: 087 - ASSISTÊNCIA EM HEMATOLOGIA, HEMOTERAPIA,CÉLULAS E TECIDOS BIOLÓGICOS | AD2: 005 - PROGRAMA MINEIRO DE ACESSIBILIDADE, INCLUSÃO E SAÚDE (PROMAIS) | AE2: 022 - CONSTRUINDO O FUTURO POR MEIO DA CIÊNCIA, DA TECNOLOGIA E DA INOVAÇÃO | AF2: 102 - FOMENTO À ECONOMIA DA CRIATIVIDADE | AG2: 067 - REDE DE DESENVOLVIMENTO DA EDUCAÇÃO PROFISSIONAL | AH2: 005 - PROGRAMA MINEIRO DE ACESSIBILIDADE, INCLUSÃO E SAÚDE (PROMAIS) | AI2: 040 - RECUPERAÇÃO AMBIENTAL E GESTÃO DE BARRAGENS | AJ2: 150 - UNIVERSALIZAÇÃO DO ACESSO AO CONHECIMENTO CIENTÍFICO E TECNOLÓGICO | AK2: 042 - DESENVOLVIMENTO DA EDUCAÇÃO BÁSICA | AL2: 019 - ATENÇÃO HOSPITALAR ESPECIALIZADA | AM2: 091 - APRIMORAMENTO DA GESTÃO PÚBLICA POR MEIO DE ENSINO DE EXCELÊNCIA | AN2: 121 - ACESSO E ALCANCE À COMUNICAÇÃO DE INTERESSE PÚBLICO | AO2: 009 - PROGRAMA DE APOIO HABITACIONAL AOS MILITARES DO ESTADO DE MINAS GERAIS | AP2: 764 - ASSISTÊNCIA COMPLEMENTAR | AQ2: 138 - CONCESSÃO DE AUXÍLIO FINANCEIRO, SEGURO E PECÚLIO | AR2: 102 - FOMENTO À ECONOMIA DA CRIATIVIDADE | AS2: 125 - POLÍTICA DE REGULARIZAÇÃO FUNDIÁRIA E DE GESTÃO DE IMÓVEIS | AT2: 077 - CAMINHOS PARA O DESENVOLVIMENTO INTEGRADO METROPOLITANO | AU2: 024 - DESENVOLVIMENTO SOCIOECONÔMICO | AV2: 085 - PROMOÇÃO DE CONCESSÕES E PARCERIAS | AW2: 020 - FOMENTO E INCENTIVO DE INVESTIMENTOS | AX2: 125 - POLÍTICA DE REGULARIZAÇÃO FUNDIÁRIA E DE GESTÃO DE IMÓVEIS | AY2: 085 - PROMOÇÃO DE CONCESSÕES E PARCERIAS | AZ2: 021 - SANEAMENTO E RESÍDUOS ESPECIAIS | BA2: 704 - MODERNIZAÇÃO INSTITUCIONAL | BB2: 020 - FOMENTO E INCENTIVO DE INVESTIMENTOS | BC2: 737 - MODERNIZAÇÃO INSTITUCIONAL | BD2: 706 - PRESTAÇÃO JURISDICIONAL | BE2: 071 - FORTALECIMENTO DO SISTEMA ÚNICO DE ASSISTÊNCIA SOCIAL - SUAS | BF2: 102 - FOMENTO À ECONOMIA DA CRIATIVIDADE | BG2: 070 - POLÍTICAS DE DIREITOS HUMANOS | BH2: 082 - PROMOÇÃO DA SEGURANÇA VIÁRIA | BI2: 113 - GARANTIA DE CONTINUIDADE DA PRODUÇÃO AGROPECUÁRIA | BJ2: 073 - MORADAS GERAIS | BK2: 141 - POLÍTICAS SOBRE DROGAS | BL2: 705 - APOIO ÀS POLÍTICAS PÚBLICAS | BM2: 738 - PROTEÇÃO E DEFESA DO CONSUMIDOR | BN2: 058 - POLÍTICAS DE ATENÇÃO HOSPITALAR | BO2: 134 - GESTÃO INTEGRADA DE SEGURANÇA PÚBLICA | BP2: 066 - POLÍTICAS DE TRABALHO E EMPREGO | BQ2: 070 - POLÍTICAS DE DIREITOS HUMANOS | BR2: 705 - APOIO ÀS POLÍTICAS PÚBLICAS | BS2: 023 - POLÍTICAS PARA CRIANÇAS E ADOLESCENTES | BT2: 128 - PROGRAMA DE APOIO A AMPLIAÇÃO E A MELHORIA DOS SISTEMAS PRISIONAL E SOCIOEDUCATIVO | BU2: 034 - SUPORTE ÀS AÇÕES DE TRANSPORTE RODOVIÁRIO | BV2: 705 - APOIO ÀS POLÍTICAS PÚBLICAS | BW2: 056 - DESENVOLVIMENTO DA INFRAESTRUTURA DO NORTE E NORDESTE DE MINAS GERAIS | BX2: 012 - POLÍTICA PÚBLICA DE METROLOGIA E AVALIAÇÃO DA CONFORMIDADE | BY2: 705 - APOIO ÀS POLÍTICAS PÚBLICAS | BZ2: 039 - GESTÃO DA ASSISTÊNCIA À SAÚDE | CA2: 006 - ASSISTÊNCIA À SAÚDE DOS SEGURADOS E DOS SEUS DEPENDENTES | CB2: 031 - PROTEÇÃO DAS ÁREAS AMBIENTALMENTE CONSERVADAS, DA FAUNA E DA BIODIVERSIDADE FLORESTAL | CC2: 102 - FOMENTO À ECONOMIA DA CRIATIVIDADE | CD2: 078 - DEFESA SANITÁRIA | CE2: 047 - SUPORTE ÀS AÇÕES DE COMBATE E RESPOSTA AOS DANOS CAUSADOS PELAS CHUVAS | CF2: 029 - REGISTRO PÚBLICO DE EMPRESAS MERCANTIS E ATIVIDADES AFINS | CG2: 126 - EXPLORAÇÃO DE JOGOS LOTÉRICOS E SIMILARES | CH2: 057 - SOLUÇÕES EM SERVIÇOS DE APOIO TÉCNICO-OPERACIONAL | CI2: 013 - APORTE DE CAPITAL E MANUTENÇÃO DA INFRAESTRUTURA DA MGI | CJ2: 054 - GOVERNANÇA PARA INTEGRIDADE E MELHORES RESULTADOS EM SERVIÇOS PÚBLICOS | CK2: 705 - APOIO ÀS POLÍTICAS PÚBLICAS | CL2: 032 - INVESTIGAÇÃO | CM2: 046 - SUPORTE AÉREO AOS SERVIÇOS PÚBLICOS ESTADUAIS | CN2: 703 - PROCESSO JUDICIÁRIO | CO2: 999 - RESERVA DE CONTINGÊNCIA | CP2: 005 - PROGRAMA MINEIRO DE ACESSIBILIDADE, INCLUSÃO E SAÚDE (PROMAIS) | CQ2: 108 - ACESSO A MERCADOS | CR2: 018 - COMUNICAÇÃO INSTITUCIONAL E DE UTILIDADE PÚBLICA | CS2: 100 - MAIS TURISTAS | CT2: 056 - DESENVOLVIMENTO DA INFRAESTRUTURA DO NORTE E NORDESTE DE MINAS GERAIS | CU2: 005 - PROGRAMA MINEIRO DE ACESSIBILIDADE, INCLUSÃO E SAÚDE (PROMAIS) | CV2: 005 - PROGRAMA MINEIRO DE ACESSIBILIDADE, INCLUSÃO E SAÚDE (PROMAIS) | CW2: 033 - GESTÃO DA INFORMAÇÃO COM USO DE TECNOLOGIA E COMUNICAÇÃO | CX2: 109 - GESTÃO DE CERIMONIAL E EVENTOS | CY2: 047 - SUPORTE ÀS AÇÕES DE COMBATE E RESPOSTA AOS DANOS CAUSADOS PELAS CHUVAS | CZ2: 129 - PREVENÇÃO À CRIMINALIDADE | DA2: 021 - SANEAMENTO E RESÍDUOS ESPECIAIS | DB2: 147 - GESTÃO DE PESSOAS | DC2: 011 - ASSESSORAMENTO TÉCNICO E ADMINISTRATIVO AO GOVERNADOR E VICE-GOVERNADOR | DD2: 705 - APOIO ÀS POLÍTICAS PÚBLICAS | DE2: 705 - APOIO ÀS POLÍTICAS PÚBLICAS | DF2: 705 - APOIO ÀS POLÍTICAS PÚBLICAS | DG2: 705 - APOIO ÀS POLÍTICAS PÚBLICAS | DH2: 026 - DESENVOLVIMENTO DO ENSINO SUPERIOR NA UEMG | DI2: 007 - EDUCAÇÃO SUPERIOR | DJ2: 085 - PROMOÇÃO DE CONCESSÕES E PARCERIAS
A3: 044 - REPRESENTAÇÃO JURÍDICA DO ESTADO E ENTIDADES | B3: 705 - APOIO ÀS POLÍTICAS PÚBLICAS | C3: 125 - POLÍTICA DE REGULARIZAÇÃO FUNDIÁRIA E DE GESTÃO DE IMÓVEIS | E3: 705 - APOIO ÀS POLÍTICAS PÚBLICAS | F3: 729 - PROCESSO LEGISLATIVO | G3: 017 - INVESTIMENTO NA INFRAESTRUTURA ADMINISTRATIVA E OPERACIONAL DO BDMG | I3: 094 - GERAÇÃO DE ENERGIA ELÉTRICA | Q3: 002 - AUDITORIA INTERNA PARA O FUTURO | S3: 052 - PROMOÇÃO DE DEFESA CIVIL | T3: 726 - ACESSO À JUSTIÇA | U3: 081 - DESENVOLVIMENTO SUSTENTÁVEL DA INFRAESTRUTURA RODOVIÁRIA | W3: 705 - APOIO ÀS POLÍTICAS PÚBLICAS | X3: 097 - MINAS SEM FOME | Y3: 016 - INOVAÇÕES E SOLUÇÕES TECNOLÓGICAS PARA A AGROPECUÁRIA E A AGROINDÚSTRIA | Z3: 121 - ACESSO E ALCANCE À COMUNICAÇÃO DE INTERESSE PÚBLICO | AB3: 705 - APOIO ÀS POLÍTICAS PÚBLICAS | AC3: 705 - APOIO ÀS POLÍTICAS PÚBLICAS | AD3: 102 - FOMENTO À ECONOMIA DA CRIATIVIDADE | AE3: 143 - MG TECH - POLÍTICAS DE CIÊNCIA, TECNOLOGIA E INOVAÇÃO | AF3: 103 - ESPAÇOS CULTURAIS, CORPOS ARTÍSTICOS E ÓRGÃOS COLEGIADOS | AG3: 705 - APOIO ÀS POLÍTICAS PÚBLICAS | AH3: 104 - ENFRENTAMENTO À VULNERABILIDADE NOS TERRITÓRIOS DE ATUAÇÃO DA FUCAM | AI3: 041 - REGULARIZAÇÃO AMBIENTAL | AJ3: 152 - INOVAÇÃO CIENTÍFICA E TECNOLÓGICA | AK3: 051 - ATENDIMENTO COMUNITÁRIO E PSICOPEDAGOGICO NA FUNDACÃO HELENA ANTIPOFF | AL3: 705 - APOIO ÀS POLÍTICAS PÚBLICAS | AM3: 093 - PROMOÇÃO E PRESERVAÇÃO DA MEMÓRIA TÉCNICO-CIENTÍFICA DO ESTADO DE MINAS GERAIS | AN3: 705 - APOIO ÀS POLÍTICAS PÚBLICAS | AP3: 765 - APOIO HABITACIONAL | AQ3: 705 - APOIO ÀS POLÍTICAS PÚBLICAS | AZ3: 027 - GESTÃO AMBIENTAL. | BB3: 705 - APOIO ÀS POLÍTICAS PÚBLICAS | BE3: 083 - POLÍTICAS DE PROMOÇÃO AO DESENVOLVIMENTO SOCIAL NO CONTEXTO RURAL - PERCURSOS GERAIS: TRAJETÓRIA PARA AUTONOMIA | BH3: 705 - APOIO ÀS POLÍTICAS PÚBLICAS | BN3: 059 - APOIO À GESTÃO DO SUS | BP3: 067 - REDE DE DESENVOLVIMENTO DA EDUCAÇÃO PROFISSIONAL | BS3: 068 - PRIMEIRA INFÂNCIA MINAS | BU3: 046 - SUPORTE AÉREO AOS SERVIÇOS PÚBLICOS ESTADUAIS | BW3: 124 - PROMOÇÃO DO DESENVOLVIMENTO DO NORTE E NORDESTE DE MINAS GERAIS | BX3: 705 - APOIO ÀS POLÍTICAS PÚBLICAS | BY3: 766 - BENEFÍCIOS ASSISTENCIAIS | BZ3: 088 - SERVIÇOS DE SAÚDE PRESTADOS PELO IPSEMG NA REDE PRÓPRIA | CA3: 008 - PRESTAÇÃO DE SERVIÇOS PREVIDENCIÁRIOS | CB3: 046 - SUPORTE AÉREO AOS SERVIÇOS PÚBLICOS ESTADUAIS | CC3: 103 - ESPAÇOS CULTURAIS, CORPOS ARTÍSTICOS E ÓRGÃOS COLEGIADOS | CD3: 080 - SEGURANÇA DE ALIMENTOS | CE3: 065 - FORTALECIMENTO DA POLÍTICA ESTADUAL DE RECURSOS HÍDRICOS | CF3: 705 - APOIO ÀS POLÍTICAS PÚBLICAS | CG3: 705 - APOIO ÀS POLÍTICAS PÚBLICAS | CI3: 024 - DESENVOLVIMENTO SOCIOECONÔMICO | CJ3: 055 - CONTROLE SOCIAL ATRAVÉS DA DEFESA DOS USUÁRIOS DE SERVIÇOS PÚBLICOS | CL3: 036 - IDENTIFICAÇÃO CIVIL E CRIMINAL | CM3: 048 - PROTEÇÃO E DEFESA CIVIL | CN3: 705 - APOIO ÀS POLÍTICAS PÚBLICAS | CP3: 131 - ARTICULAÇÃO INTERFEDERATIVA, ATRAÇÃO DE INVESTIMENTOS, CAPTAÇÃO E TRANSFERÊNCIA DE RECURSOS E PARCERIAS | CQ3: 110 - REGULARIZAÇÃO FUNDIÁRIA - AMPLIAÇÃO DA SEGURANÇA JURÍDICA NO CAMPO | CR3: 705 - APOIO ÀS POLÍTICAS PÚBLICAS | CS3: 102 - FOMENTO À ECONOMIA DA CRIATIVIDADE | CT3: 125 - POLÍTICA DE REGULARIZAÇÃO FUNDIÁRIA E DE GESTÃO DE IMÓVEIS | CU3: 023 - POLÍTICAS PARA CRIANÇAS E ADOLESCENTES | CV3: 043 - DESJUDICIALIZA MINAS | CW3: 038 - TESOURO RESPONSÁVEL E TRANSPARENTE | CX3: 115 - GESTÃO DO PROCESSO LEGISLATIVO ESTADUAL SOB A RESPONSABILIDADE DO PODER EXECUTIVO | CY3: 081 - DESENVOLVIMENTO SUSTENTÁVEL DA INFRAESTRUTURA RODOVIÁRIA | CZ3: 130 - INFRAESTRUTURA DO SISTEMA PRISIONAL | DA3: 025 - MONITORAMENTO, CONTROLE E FISCALIZAÇÃO AMBIENTAL | DB3: 149 - TRANSFORMAÇÃO DIGITAL E ATENDIMENTO AO CIDADÃO | DC3: 705 - APOIO ÀS POLÍTICAS PÚBLICAS | DE3: 746 - CONTROLE EXTERNO DA GESTÃO DOS RECURSOS PÚBLICOS | DF3: 706 - PRESTAÇÃO JURISDICIONAL | DG3: 734 - PRESTAÇÃO JURISDICIONAL MILITAR | DH3: 705 - APOIO ÀS POLÍTICAS PÚBLICAS | DI3: 705 - APOIO ÀS POLÍTICAS PÚBLICAS
A4: 705 - APOIO ÀS POLÍTICAS PÚBLICAS | C4: 705 - APOIO ÀS POLÍTICAS PÚBLICAS | D4: 6008 - MANUTENÇÃO DA INFRAESTRUTURA ADMINISTRATIVA E OPERACIONAL DA INVEST MINAS | G4: 171 - FINANCIAMENTO À INFRAESTRUTURA E AO DESENVOLVIMENTO SUSTENTÁVEL EM MG ENTRE BDMG E NEW DEVELOPMENT BANK (BDMG INFRA ODS) | H4: 3002 - EXECUÇÃO DO PLANO DE DESENVOLVIMENTO DA DISTRIBUIDORA (PDD) | J4: 3015 - GESTÃO DE INFRAESTRUTURA, CONSÓRCIOS E EQUIPAMENTOS CULTURAIS E TURÍSTICOS | K4: 3017 - MANUTENÇÃO E AQUISIÇÕES DA CODEMIG | L4: 3018 - GÁS COMPETITIVO- EXPANSÃO DA REDE DE GÁS NATURAL | M4: 6010 - MANUTENÇÃO E ADEQUAÇÃO DA INFRAESTRUTURA ADMINISTRATIVA - COHAB | N4: 6009 - ADEQUAÇÃO DA INFRA-ESTRUTURA ADMINISTRATIVA E OPERACIONAL - COPASA | O4: 6006 - MANUTENÇÃO DAS UNIDADES PREDIAIS | P4: 3010 - INVESTIMENTOS EM PARTICIPAÇÕES SOCIETÁRIAS CEMIG HOLDING | Q4: 003 - ENFRENTAMENTO DA CORRUPÇÃO E RECUPERAÇÃO DE ATIVOS | R4: 6012 - ADEQUAÇÃO DA INFRAESTRUTURA ADMINISTRATIVA E OPERACIONAL DA COPANOR | S4: 053 - ATENDIMENTO PRÉ-HOSPITALAR | U4: 705 - APOIO ÀS POLÍTICAS PÚBLICAS | V4: 2049 - ENCARGOS DA ADMINISTRAÇÃO FINANCEIRA CENTRAL | X4: 108 - ACESSO A MERCADOS | Y4: 705 - APOIO ÀS POLÍTICAS PÚBLICAS | Z4: 705 - APOIO ÀS POLÍTICAS PÚBLICAS | AA4: 2131 - RECURSOS DE TRANSFERÊNCIAS ESPECIAIS DA UNIÃO | AD4: 103 - ESPAÇOS CULTURAIS, CORPOS ARTÍSTICOS E ÓRGÃOS COLEGIADOS | AE4: 705 - APOIO ÀS POLÍTICAS PÚBLICAS | AF4: 105 - FORMAÇÃO E CAPACITAÇÃO TÉCNICO-CULTURAL | AH4: 705 - APOIO ÀS POLÍTICAS PÚBLICAS | AI4: 705 - APOIO ÀS POLÍTICAS PÚBLICAS | AJ4: 153 - VIGILÂNCIA LABORATORIAL EM SAÚDE PÚBLICA | AK4: 075 - AMPLIAÇÃO E MODERNIZAÇÃO DA FUNDAÇÃO HELENA ANTIPOFF | AM4: 095 - ASSESSORIA E PESQUISA EM POLÍTICAS PÚBLICAS | AO4: 4349 - FINANCIAMENTO HABITACIONAL AOS SERVIDORES MILITARES | AR4: 4497 - APOIO FINANCEIRO AO TURISMO MINEIRO POR MEIO DO FUNDO DE ASSISTÊNCIA AO TURISMO - FASTUR | AS4: 4541 - ATIVOS IMOBILIÁRIOS DE MINAS GERAIS - FAIMG | AT4: 4471 - METRÓPOLE PLANEJADA | AU4: 4041 - FUNDESE GERAMINAS | AV4: 4432 - GESTÃO E APRIMORAMENTO DO FUNDO GARANTIDOR DE PPP | AW4: 4444 - MG INVESTE | AX4: 4549 - FUNDO DE INVESTIMENTOS IMOBILIÁRIOS DE MINAS GERAIS - FIIMG | AY4: 4128 - LOTE OURO PRETO | AZ4: 031 - PROTEÇÃO DAS ÁREAS AMBIENTALMENTE CONSERVADAS, DA FAUNA E DA BIODIVERSIDADE FLORESTAL | BA4: 2056 - REAPARELHAMENTO E APERFEIÇOAMENTO INSTITUCIONAL | BC4: 1009 - REAPARELHAMENTO E APERFEIÇOAMENTO INSTITUICIONAL | BD4: 2025 - GESTÃO DE SERVIÇOS DE TIC | BF4: 4360 - GESTÃO DO SISTEMA DE FINANCIAMENTO À CULTURA | BG4: 4179 - PROJETOS ESPECIAIS DE RECUPERAÇÃO DE DANOS AOS DIREITOS DIFUSOS | BI4: 4401 - FUNDERUR EMERGENCIAL | BJ4: 2075 - ADMINISTRAÇÃO DA CARTEIRA DE FINANCIAMENTOS NO ÂMBITO DO FUNDO ESTADUAL DE HABITAÇÃO - FEH | BK4: 4436 - APOIO ÀS AÇÕES DO FUNDO ESTADUAL DE PREVENÇÃO, FISCALIZAÇÃO E REPRESSÃO DOS ENTORPECENTES - FUNPREN | BL4: 7001 - COBERTURA DO DÉFICIT DO REGIME PRÓPRIO DE PREVIDÊNCIA SOCIAL - RPPS | BM4: 4256 - APOIO ÀS AÇÕES DE PROTEÇÃO E DEFESA AO CONSUMIDOR | BN4: 060 - ATENÇÃO PRIMÁRIA À SAÚDE | BO4: 2071 - APOIO ÀS AÇÕES DO FUNDO DE ESTADUAL DE SEGURANÇA PÚBLICA | BQ4: 4180 - PROJETOS ESPECIAIS DE PROMOÇÃO E PROTEÇÃO DOS DIREITOS DE PESSOAS IDOSAS | BR4: 7004 - PRECATÓRIOS E SENTENÇAS JUDICIÁRIAS | BS4: 070 - POLÍTICAS DE DIREITOS HUMANOS | BT4: 1046 - APOIO À ESTRUTURAÇÃO E AO REAPARELHAMENTO DE UNIDADES PRISIONAIS E SOCIOEDUCATIVAS | BU4: 047 - SUPORTE ÀS AÇÕES DE COMBATE E RESPOSTA AOS DANOS CAUSADOS PELAS CHUVAS | BV4: 7003 - RESTITUIÇÃO AO TJMG DOS DEPÓSITOS JUDICIAIS | BW4: 705 - APOIO ÀS POLÍTICAS PÚBLICAS | BY4: 767 - RESERVA DE BENEFÍCIOS | BZ4: 138 - CONCESSÃO DE AUXÍLIO FINANCEIRO, SEGURO E PECÚLIO | CA4: 705 - APOIO ÀS POLÍTICAS PÚBLICAS | CB4: 705 - APOIO ÀS POLÍTICAS PÚBLICAS | CC4: 105 - FORMAÇÃO E CAPACITAÇÃO TÉCNICO-CULTURAL | CD4: 108 - ACESSO A MERCADOS | CE4: 705 - APOIO ÀS POLÍTICAS PÚBLICAS | CH4: 8002 - INVESTIMENTOS EM ATIVO FIXO PARA PRESTAÇÃO DE SERVIÇO | CI4: 119 - APOIO AO DESENVOLVIMENTO MUNICIPAL E À COORDENAÇÃO DAS TRANSFERÊNCIAS ESTADUAIS DE RECURSOS FINANCEIROS | CJ4: 705 - APOIO ÀS POLÍTICAS PÚBLICAS | CK4: 7054 - PROGRAMAÇÃO A CARGO DO ESTADO PARA A COMPANHIA DE DESENVOLVIMENTO DE MINAS GERAIS - CODEMGE | CL4: 037 - VALORIZAÇÃO E SAÚDE DO SERVIDOR | CM4: 135 - PROTEÇÃO SOCIAL DOS MILITARES | CN4: 714 - AQUISIÇÃO, CONSTRUÇÃO, REPAROS DE BENS IMÓVEIS | CO4: 9999 - RESERVA DE CONTINGÊNCIA | CP4: 705 - APOIO ÀS POLÍTICAS PÚBLICAS | CQ4: 111 - DESENVOLVIMENTO DAS CADEIAS PRODUTIVAS DA AGROPECUÁRIA | CS4: 103 - ESPAÇOS CULTURAIS, CORPOS ARTÍSTICOS E ÓRGÃOS COLEGIADOS | CT4: 132 - MINAS EMPREENDEDORA: ESTADO MAIS SIMPLES E LIVRE PARA SE EMPREENDER | CU4: 066 - POLÍTICAS DE TRABALHO E EMPREGO | CV4: 162 - PROGRAMA DE DESENVOLVIMENTO E GESTÃO DE PESSOAS DA REDE ESTADUAL DE ENSINO | CW4: 045 - RECEITA ESTADUAL DIGITAL, EFICIENTE, MODERNIZADA E MAIS JUSTA | CX4: 119 - APOIO AO DESENVOLVIMENTO MUNICIPAL E À COORDENAÇÃO DAS TRANSFERÊNCIAS ESTADUAIS DE RECURSOS FINANCEIROS | CY4: 085 - PROMOÇÃO DE CONCESSÕES E PARCERIAS | CZ4: 134 - GESTÃO INTEGRADA DE SEGURANÇA PÚBLICA | DA4: 027 - GESTÃO AMBIENTAL. | DB4: 151 - PROMOÇÃO DA INOVAÇÃO E DA GESTÃO ESTRATÉGICA | DD4: 8011 - MANUTENÇÃO E ADEQUAÇÃO DA INFRA-ESTRUTURA ADMINISTRATIVA E OPERACIONAL - TRANSPORTES METROPOLITANOS | DE4: 760 - CAPACITAÇÃO E ORIENTAÇÃO PARA MELHORAR A GESTÃO DOS RECURSOS PÚBLICOS | DJ4: 4118 - LOTE OURO PRETO
B5: 4446 - REGULAÇÃO DA EXPANSÃO URBANA DA REGIÃO METROPOLITANA DE BELO HORIZONTE | E5: 2417 - REMUNERAÇÃO DE PESSOAL ATIVO E ENCARGOS SOCIAIS | F5: 7004 - PRECATÓRIOS E SENTENÇAS JUDICIÁRIAS | H5: 3003 - MANUTENÇÃO DA INFRAESTRUTURA DA DISTRIBUIÇÃO | I5: 3004 - EXPANSÃO DO SISTEMA DE TRANSMISSÃO | N5: 8008 - UNIVERSALIZAÇÃO DOS SERVIÇOS DE SANEAMENTO NA ÁREA DA COPASA | O5: 8001 - AQUISIÇÃO DE HARDWARES E SOFTWARES PARA PRESTAÇÃO DE SERVIÇOS EM TECNOLOGIA DA INFORMAÇÃO E COMUNICAÇÃO | P5: 3011 - MANUTENÇÃO DA INFRAESTRUTURA DA CEMIG HOLDING | Q5: 004 - CGE INTEGRADA E EFICIENTE | R5: 8012 - UNIVERSALIZAÇÃO DOS SERVIÇOS DE SANEAMENTO NA ÁREA DE ATUAÇÃO DA COPANOR | S5: 705 - APOIO ÀS POLÍTICAS PÚBLICAS | T5: 7004 - PRECATÓRIOS E SENTENÇAS JUDICIÁRIAS | V5: 7663 - CAPTAÇÃO DE RECURSOS PARA FORMAÇÃO DO PROGRAMA DE FORMAÇÃO DO PATRIMÔNIO DO SERVIDOR PÚBLICO - PASEP | W5: 4488 - IMPLANTAÇÃO E OPERAÇÃO DO ALMOXARIFADO VIRTUAL | X5: 110 - REGULARIZAÇÃO FUNDIÁRIA - AMPLIAÇÃO DA SEGURANÇA JURÍDICA NO CAMPO | AA5: 2132 - RECURSOS PARA CONTRAPARTIDA A CONVÊNIOS E CONGÊNERES | AB5: 4049 - AÇÕES EDUCACIONAIS NA ÁREA DA SAÚDE | AC5: 4212 - DESENVOLVIMENTO DO PROGRAMA DE SANGUE E HEMODERIVADOS | AD5: 105 - FORMAÇÃO E CAPACITAÇÃO TÉCNICO-CULTURAL | AF5: 106 - PROTEÇÃO E SALVAGUARDA DE ACERVOS E BENS CULTURAIS | AG5: 4300 - EDUCAÇÃO PROFISSIONAL TÉCNICA DE NÍVEL MÉDIO E QUALIFICAÇÃO PROFISSIONAL | AJ5: 154 - DESENVOLVIMENTO E PRODUÇÃO DE MEDICAMENTOS PARA O SISTEMA ÚNICO DE SAÚDE (SUS) | AK5: 076 - DESENVOLVIMENTO DA EDUCAÇÃO PROFISSIONAL TÉCNICA | AL5: 4029 - ATENÇÃO AO SISTEMA ESTADUAL DE TRANSPLANTES | AM5: 096 - PRODUÇÃO DE ESTATÍSTICAS E INFORMAÇÕES | AN5: 4298 - DISPONIBILIZAÇÃO E MANUTENÇÃO DO SINAL DE RETRANSMISSÃO DE TV NO INTERIOR DO ESTADO E REGIÃO METROPOLITANA DE BH | AP5: 4539 - ASSISTÊNCIA COMPLEMENTAR | AQ5: 4404 - ASSISTÊNCIA AO SEGURO E PECÚLIO DOS SERVIDORES DO ESTADO DE MINAS GERAIS | AT5: 4518 - METRÓPOLE DIGITAL | AU5: 4042 - FUNDESE EMPRESA MINEIRA COMPETITIVA | AY5: 4139 - CONCESSÕES DE TRANSPORTES NAS MODALIDADES RODOVIÁRIAS, FERROVIÁRIAS, AEROVIÁRIAS, AQUAVIÁRIAS E HIDROVIÁRIAS | AZ5: 065 - FORTALECIMENTO DA POLÍTICA ESTADUAL DE RECURSOS HÍDRICOS | BB5: 4502 - GESTÃO DO FUNDO ESPECIAL DE CRÉDITOS INADIMPLIDOS E DA DÍVIDA ATIVA - FECIDAT | BD5: 2055 - AUXÍLIOS CONCEDIDOS A MAGISTRADOS E SERVIDORES | BE5: 2074 - APRIMORAMENTO DA REDE SOCIOASSISTENCIAL | BH5: 4201 - CONTROLE DE VELOCIDADE | BI5: 4402 - FUNDERUR DIVERSIFICA | BJ5: 4427 - VIABILIZAÇÃO DO ACESSO À HABITAÇAÕ DE INTERESSE SOCIAL | BN5: 061 - ATENÇÃO ESPECIALIZADA À SAÚDE | BP5: 4152 - FOMENTO ÀS UNIDADES DE ATENDIMENTO AO TRABALHADOR | BR5: 7005 - BENEFÍCIOS PREVIDENCIÁRIOS - SECOM | BU5: 048 - PROTEÇÃO E DEFESA CIVIL | BV5: 7013 - GESTÃO DE GARANTIA E/OU CONTRAGARANTIA EM OPERAÇÕES DE TERCEIROS | BX5: 4024 - EXECUÇÃO DO CONTROLE METROLÓGICO NO ESTADO DE MINAS GERAIS | BZ5: 705 - APOIO ÀS POLÍTICAS PÚBLICAS | CC5: 106 - PROTEÇÃO E SALVAGUARDA DE ACERVOS E BENS CULTURAIS | CD5: 112 - CERTIFICAÇÕES E HABILITAÇÕES DE PRODUTOS AGROPECUÁRIOS E AGROINDUSTRIAIS | CF5: 4051 - REGISTRO EMPRESARIAL | CG5: 4340 - OPERACIONALIZAÇÃO DE JOGOS | CK5: 7541 - PROGRAMAÇÃO A CARGO DO ESTADO PARA A COMPANHIA DE DESENVOLVIMENTO DO ESTADO DE MINAS GERAIS - CODEMIG | CL5: 705 - APOIO ÀS POLÍTICAS PÚBLICAS | CM5: 136 - EDUCAÇÃO ESCOLAR | CQ5: 112 - CERTIFICAÇÕES E HABILITAÇÕES DE PRODUTOS AGROPECUÁRIOS E AGROINDUSTRIAIS | CR5: 2001 - ASSESSORIA DE PUBLICIDADE | CS5: 105 - FORMAÇÃO E CAPACITAÇÃO TÉCNICO-CULTURAL | CT5: 133 - MINAS GERAÇÃO DE VALOR | CU5: 067 - REDE DE DESENVOLVIMENTO DA EDUCAÇÃO PROFISSIONAL | CV5: 163 - ALIMENTAÇÃO ESCOLAR | CW5: 705 - APOIO ÀS POLÍTICAS PÚBLICAS | CX5: 120 - PRODUÇÃO E VEICULAÇÃO DO DIÁRIO OFICIAL ELETRÔNICO MINAS GERAIS | CY5: 099 - DESENVOLVIMENTO DA INFRAESTRUTURA ESTADUAL, MUNICIPAL E REGIONAL | CZ5: 141 - POLÍTICAS SOBRE DROGAS | DA5: 705 - APOIO ÀS POLÍTICAS PÚBLICAS | DB5: 155 - REPARAÇÃO DOS DANOS DOS ROMPIMENTOS EM BRUMADINHO E MARIANA | DC5: 4007 - INFORMAÇÃO, COORDENAÇÃO E SUPORTE À GOVERNADORIA E VICE-GOVERNADORIA | DF5: 7004 - PRECATÓRIOS E SENTENÇAS JUDICIÁRIAS | DG5: 7004 - PRECATÓRIOS E SENTENÇAS JUDICIÁRIAS | DH5: 1018 - CONSTRUÇÃO, AMPLIAÇÃO E REFORMA DAS UNIDADES ACADÊMICAS E DOS CAMPI DA UEMG | DI5: 4001 - OFERTA DE CURSOS DE GRADUAÇÃO | DJ5: 4124 - LOTE OURO PRETO
A6: 1008 - CUMPRIMENTO ADMINISTRATIVO DE DETERMINAÇÕES JUDICIAIS DECORRENTES DO ACESSO GRATUITO À JUSTIÇA | B6: 4447 - GESTÃO METROPOLITANA | C6: 4273 - REGULAÇÃO METROPOLITANA | E6: 4013 - REGULAÇÃO E FISCALIZAÇÃO ECONÔMICO-FINANCEIRA | F6: 7006 - PROVENTOS DE INATIVOS CIVIS E PENSIONISTAS | G6: 8003 - FINANCIAMENTO À DESCARBONIZAÇÃO E RESILIÊNCIA CLIMÁTICA ENTRE BDMG E BANCO INTERAMERICANO DE DESENVOLVIMENTO (BDMG PBR) | I6: 3005 - REFORMAS DE SUBESTAÇÕES E LINHAS DE TRANSMISSÃO | N6: 8009 - PPP SISTEMA ADUTOR RIO MANSO | Q6: 705 - APOIO ÀS POLÍTICAS PÚBLICAS | T6: 7006 - PROVENTOS DE INATIVOS CIVIS E PENSIONISTAS | U6: 4280 - MITIGAÇÃO DE DANOS PONTUAIS NAS RODOVIAS | W6: 4489 - APRIMORAMENTO DA REDE DE POSTOS PRÓPRIOS QUE ATENDE A FROTA ESTADUAL | X6: 705 - APOIO ÀS POLÍTICAS PÚBLICAS | Y6: 4016 - FORMAÇÃO SUPERIOR EM LATICÍNIOS E AGROPECUÁRIA DE PRECISÃO | Z6: 4424 - FOMENTO AO DESENVOLVIMENTO E À DIFUSÃO DO AUDIOVISUAL MINEIRO | AB6: 4050 - PRODUÇÃO CIENTÍFICA NO CAMPO DA SAÚDE | AC6: 4222 - MODERNIZAÇÃO E/OU MELHORIA DA INFRAESTRUTURA FÍSICA E/OU TÉCNOLÓGICA DAS UNIDADES DA FUNDAÇÃO HEMOMINAS | AD6: 705 - APOIO ÀS POLÍTICAS PÚBLICAS | AE6: 4048 - FORMAÇÃO, CAPACITAÇÃO, ATRAÇÃO E FIXAÇÃO DE PESSOAS PARA ATUAÇÃO EM CIÊNCIA, TECNOLOGIA E INOVAÇÃO | AF6: 705 - APOIO ÀS POLÍTICAS PÚBLICAS | AH6: 1011 - CAPACITAÇÃO DOS PROFISSIONAIS DA FUCAM PARA ATENDIMENTO ADEQUADO A PESSOAS COM DEFICIÊNCIAS | AI6: 4069 - GESTÃO DE BARRAGENS | AJ6: 705 - APOIO ÀS POLÍTICAS PÚBLICAS | AK6: 089 - MEMÓRIA VIVA: DIFUSÃO CULTURAL, PATRIMÔNIO MATERIAL E IMATERIAL | AL6: 4030 - ATENÇÃO À SAÚDE NAS UNIDADES ASSISTENCIAIS DE REABILITAÇÃO E CUIDADOS INTEGRADOS | AM6: 705 - APOIO ÀS POLÍTICAS PÚBLICAS | AN6: 4299 - GESTÃO E MANUTENÇÃO DOS SISTEMAS DE TRANSMISSÃO VIA SATÉLITE E OPERAÇÃO DE TV | AT6: 4529 - INTEGRAÇÃO DO PLANEJAMENTO NA REGIÃO METROPOLITANA DO VALE DO AÇO | AU6: 4043 - FUNDESE BASE TECNOLOGICA | AY6: 4213 - AEROPORTOS REGIONAIS | AZ6: 705 - APOIO ÀS POLÍTICAS PÚBLICAS | BD6: 2091 - OBRAS E GESTÃO PREDIAL | BE6: 4025 - APOIO AO CENTRO DIA DE REFERÊNCIA PARA PESSOA COM DEFICIÊNCIA | BH6: 4209 - EDUCAÇÃO PARA O TRÂNSITO | BN6: 062 - ACESSO A SERVIÇOS DE SAÚDE | BR6: 7008 - BENEFÍCIO PREVIDENCIÁRIO DE PENSÃO | BS6: 4207 - PROJETOS ESPECIAIS DE PROMOÇÃO E PROTEÇÃO DE CRIANÇAS E ADOLESCENTES | BU6: 049 - ADMINISTRAÇÃO DOS PRÉDIOS GOVERNAMENTAIS | BV6: 7019 - GESTÃO DE GARANTIA E/OU CONTRAGARANTIA EM OPERAÇÕES DE TERCEIROS | BW6: 1025 - PROMOÇÃO DO ACESSO A EQUIPAMENTOS DE ARMAZENAGEM E DISTRIBUIÇÃO DE RECURSOS HÍDRICOS NO NORTE E NORDESTE DE MINAS GERAIS | BX6: 4026 - AVALIAÇÃO DA CONFORMIDADE DE PRODUTOS E SERVIÇOS NO MERCADO MINEIRO (VISITAS) | BY6: 2009 - DIREÇÃO ADMINISTRATIVA | CA6: 4008 - ASSISTÊNCIA À SAÚDE DOS SEGURADOS E DE SEUS DEPENDENTES | CB6: 4054 - PREVENÇÃO E COMBATE A INCÊNDIOS FLORESTAIS | CC6: 705 - APOIO ÀS POLÍTICAS PÚBLICAS | CD6: 118 - EDUCAÇÃO E SUCESSÃO RURAL | CE6: 4200 - PREVENÇÃO DE EVENTOS HIDROMETEOROLÓGICOS CRÍTICOS | CF6: 4052 - REDESIM MG | CI6: 6001 - INVESTIMENTOS VIA PARTICIPAÇÃO SOCIETÁRIA | CJ6: 1016 - OUVIDORIA 4.0 - APRIMORAMENTO DE SISTEMA ELETRÔNICO | CK6: 7700 - PROGRAMAÇÃO A CARGO DO ESTADO PARA A MINAS GERAIS PARTICIPAÇÕES S/A - MGI | CM6: 137 - POLÍCIA OSTENSIVA | CN6: 2009 - DIREÇÃO ADMINISTRATIVA | CP6: 4111 - COORDENAÇÃO, GOVERNANÇA E COMUNICAÇÃO DO PROMAIS | CQ6: 113 - GARANTIA DE CONTINUIDADE DA PRODUÇÃO AGROPECUÁRIA | CR6: 2002 - ASSESSORIA DE IMPRENSA | CS6: 106 - PROTEÇÃO E SALVAGUARDA DE ACERVOS E BENS CULTURAIS | CT6: 143 - MG TECH - POLÍTICAS DE CIÊNCIA, TECNOLOGIA E INOVAÇÃO | CU6: 068 - PRIMEIRA INFÂNCIA MINAS | CV6: 164 - APOIO AO ENSINO SUPERIOR | CX6: 122 - FORTALECIMENTO DA GESTÃO DAS TRANSFERÊNCIAS ESTADUAIS | CY6: 117 - MOBILIDADE, TRANSPORTES E LOGÍSTICA | CZ6: 146 - PROMOÇÃO DA POLÍTICA SOCIOEDUCATIVA PARA ATENDIMENTO AOS ADOLESCENTES EM CONFLITO COM A LEI | DB6: 156 - GESTÃO DA CIDADE ADMINISTRATIVA | DE6: 2157 - AUXÍLIOS ALIMENTAÇÃO, CRECHE, MORADIA, SAÚDE E OUTROS AUXÍLIOS | DF6: 7006 - PROVENTOS DE INATIVOS CIVIS E PENSIONISTAS | DG6: 7006 - PROVENTOS DE INATIVOS CIVIS E PENSIONISTAS | DH6: 4086 - ATIVIDADE DE ENSINO DE GRADUAÇÃO PRESENCIAL E A DISTÂNCIA | DI6: 4002 - APOIO ÀS ATIVIDADES DE PESQUISA, INOVAÇÃO E TECNOLOGIA. | DJ6: 4156 - GESTÃO DOS PROJETOS ESTRUTURANTES DE MOBILIDADE
A7: 1010 - FOMENTO À UTILIZAÇÃO DE MÉTODOS ALTERNATIVOS DE SOLUÇÃO DE CONFLITOS | C7: 4286 - FOMENTO AO DESENVOLVIMENTO SUSTENTÁVEL DA REGIÃO METROPOLITANA DO VALE DO AÇO | E7: 4014 - REGULAÇÃO OPERACIONAL E FISCALIZAÇÃO DA PRESTAÇÃO DE SERVIÇOS | I7: 3006 - MANUTENÇÃO DA INFRAESTRUTURA DA TRANSMISSÃO | S7: 4142 - GESTÃO DO ATENDIMENTO AO PERÍODO CHUVOSO | Y7: 4370 - ASSISTÊNCIA ESTUDANTIL | AC7: 4237 - CENTRO DE TECIDOS BIOLÓGICOS DE MINAS GERAIS - CETEBIO | AE7: 4362 - COMUNICAÇÃO CIENTÍFICA | AG7: 2417 - REMUNERAÇÃO DE PESSOAL ATIVO E ENCARGOS SOCIAIS | AH7: 1029 - REALIZAÇÃO DE INTERVENÇÕES DE MELHORIA DA ACESSIBILIDADE NOS ESPAÇOS DA FUCAM | AI7: 4070 - GESTÃO E RECUPERAÇÃO DE ÁREAS DEGRADADAS E CONTAMINADAS | AK7: 163 - ALIMENTAÇÃO ESCOLAR | AL7: 4031 - ATENÇÃO À SAÚDE NAS UNIDADES ASSISTENCIAIS DE REFERÊNCIA | AN7: 4302 - PRODUÇÃO E VEICULAÇÃO TELEVISIVA DE PROGRAMAÇÃO DE CARÁTER CULTURAL, INFORMATIVO, EDUCATIVO E DE ENTRETENIMENTO | AP7: 4084 - FINANCIAMENTO HABITACIONAL AOS SERVIDORES DA ASSEMBLEIA LEGISLATIVA | AQ7: 7004 - PRECATÓRIOS E SENTENÇAS JUDICIÁRIAS | AY7: 4214 - COMPLEXO MINEIRÃO | BB7: 7038 - APORTE FINANCEIRO PARA COBERTURA DA NECESSIDADE DE FINANCIAMENTO DA PREVIDÊNCIA DOS SERVIDORES DO ESTADO | BD7: 2109 - FORMAÇÃO, APERFEIÇOAMENTO E DESENVOLVIMENTO CONTÍNUO DE PESSOAS | BE7: 4429 - PROTEÇÃO SOCIAL ESPECIAL DE MÉDIA COMPLEXIDADE | BH7: 4210 - REGULAÇÃO DO USO E OCUPAÇÃO DA FAIXA DE DOMÍNIO | BN7: 063 - VIGILÂNCIA EM SAÚDE | BP7: 4159 - FORMAÇÃO E ORIENTAÇÃO PARA A INSERÇÃO DO TRABALHADOR NO MERCADO DE TRABALHO | BR7: 7009 - BENEFÍCIOS PREVIDENCIÁRIOS - CASA CIVIL | BU7: 050 - SEGURANÇA E INTELIGÊNCIA GOVERNAMENTAL | BV7: 7030 - ENCARGOS DEVIDOS POR FINANCIAMENTO JUNTO AO INSTITUTO NACIONAL DA SEGURIDADE SOCIAL - INSS | BW7: 1026 - ENERGIZAÇÃO DE POÇOS E SISTEMAS DE ABASTECIMENTO DE ÁGUA | BY7: 7004 - PRECATÓRIOS E SENTENÇAS JUDICIÁRIAS | BZ7: 2012 - ASSESSORAMENTO E GESTÃO DA ASSISTÊNCIA À SAÚDE | CA7: 4009 - ASSITÊNCIA ODONTOLÓGICA AOS SEGURADOS MILITARES E A SEUS DEPENDENTES | CB7: 4055 - CONTROLE E MONITORAMENTO DE ATIVIDADES FLORESTAIS | CD7: 705 - APOIO ÀS POLÍTICAS PÚBLICAS | CG7: 2417 - REMUNERAÇÃO DE PESSOAL ATIVO E ENCARGOS SOCIAIS | CI7: 6011 - MANUTENÇÃO E ADEQUAÇÃO DA INFRAESTRUTURA DA MGI | CJ7: 2020 - FORMAÇÃO EM OUVIDORIA - CAPACITAR PARA MELHOR ATENDER O CIDADÃO | CK7: 7707 - PROGRAMAÇÃO A CARGO DO ESTADO PARA A MINAS GERAIS ADMINISTRAÇÃO E SERVIÇOS S/A - MGS | CL7: 1003 - PROCEDIMENTO DE POLÍCIA JUDICIÁRIA ELETRÔNICO - PPJ-E | CM7: 705 - APOIO ÀS POLÍTICAS PÚBLICAS | CN7: 2028 - DIREÇÃO DA POLÍTICA INSTITUCIONAL | CQ7: 114 - INFRAESTRUTURA RURAL E AGRICULTURA SUSTENTÁVEL | CR7: 2003 - ASSESSORIA DE COMUNICAÇÃO DIGITAL | CS7: 705 - APOIO ÀS POLÍTICAS PÚBLICAS | CT7: 705 - APOIO ÀS POLÍTICAS PÚBLICAS | CU7: 069 - FOMENTO AO ESPORTE, À ATIVIDADE FÍSICA E AO LAZER | CV7: 165 - ORGANIZAÇÃO, AVALIAÇÃO E GESTÃO ESCOLAR | CW7: 1002 - DIVISA TRIBUTÁRIA SEGURA | CX7: 705 - APOIO ÀS POLÍTICAS PÚBLICAS | CY7: 128 - PROGRAMA DE APOIO A AMPLIAÇÃO E A MELHORIA DOS SISTEMAS PRISIONAL E SOCIOEDUCATIVO | CZ7: 705 - APOIO ÀS POLÍTICAS PÚBLICAS | DA7: 4028 - PROMOÇÃO DAS POLÍTICAS PÚBLICAS DE ABASTECIMENTO DE ÁGUA, ESGOTAMENTO SANITÁRIO E DRENAGEM DE ÁGUAS PLUVIAIS | DB7: 157 - GESTÃO DO PLANEJAMENTO ORÇAMENTÁRIO GOVERNAMENTAL | DC7: 2417 - REMUNERAÇÃO DE PESSOAL ATIVO E ENCARGOS SOCIAIS | DE7: 7004 - PRECATÓRIOS E SENTENÇAS JUDICIÁRIAS | DG7: 7007 - PROVENTOS DE INATIVOS MILITARES | DH7: 4087 - ATIVIDADES DE PESQUISA CIENTÍFICA | DI7: 4004 - APOIO AOS PROGRAMAS DE PÓS-GRADUAÇÃO STRICTO SENSU. | DJ7: 4160 - REGULAÇÃO DE CONCESSÕES E PPPS
A8: 2030 - CUMPRIMENTO ADMINISTRATIVO DE DETERMINAÇÕES JUDICIAIS DECORRENTES DO ACESSO GRATUITO À JUSTIÇA | B8: 2417 - REMUNERAÇÃO DE PESSOAL ATIVO E ENCARGOS SOCIAIS | E8: 4015 - ATENDIMENTO AO INTERESSADO NA PRESTAÇÃO DE SERVIÇOS | F8: 4239 - ELABORAÇÃO LEGISLATIVA E ACOMPANHAMENTO DAS POLÍTICAS PÚBLICAS | G8: 6004 - MANUTENÇÃO E ADEQUAÇÃO DA INFRA-ESTRUTURA ADMINISTRATIVA E OPERACIONAL DO BDMG | I8: 3009 - INVESTIMENTOS PARTICIPAÇÕES SOCIETÁRIAS DA TRANSMISSÃO | Q8: 4304 - PROMOÇÃO DO ACESSO À INFORMAÇÃO E DA TRANSPARÊNCIA | T8: 1050 - EXPANSÃO DA DEFENSORIA PÚBLICA NO ESTADO | U8: 4162 - SUPORTE À GESTÃO DOS ATIVOS RODOVIÁRIOS | W8: 7024 - PAGAMENTOS MENSAIS DE PROVENTOS AOS ASSISTIDOS E PENSIONISTAS DO PLANO DE PREVIDÊNCIA COMPLEMENTAR MINASCAIXA RP-2 | X8: 4235 - ASSISTÊNCIA TÉCNICA E EXTENSÃO RURAL PARA AGRICULTORES FAMILIARES E DEMAIS PÚBLICOS | Y8: 4371 - APOIO ÀS ATIVIDADES DE PESQUISA, INOVAÇÃO E TECNOLOGIA | Z8: 2031 - GESTÃO DE PROJETOS E AÇÕES DE PUBLICIDADE E PROPAGANDA | AB8: 2417 - REMUNERAÇÃO DE PESSOAL ATIVO E ENCARGOS SOCIAIS | AD8: 4369 - PALÁCIO PARA TODOS | AE8: 4387 - FOMENTO À INOVAÇÃO DE BASE CIENTÍFICA OU TECNOLÓGICA | AF8: 1001 - GESTÃO DO SISTEMA DE FINANCIAMENTO A CULTURA | AG8: 2500 - ASSESSORAMENTO E GERENCIAMENTO DE POLÍTICAS PÚBLICAS | AH8: 1030 - REALIZAÇÃO DE INTERVENÇÕES DE MELHORIA DA ACESSIBILIDADE NOS ESPAÇOS DA FUCAM | AJ8: 4455 - POPULARIZAÇÃO DA CIÊNCIA | AK8: 705 - APOIO ÀS POLÍTICAS PÚBLICAS | AL8: 4032 - ATENÇÃO À SAÚDE NAS UNIDADES ASSISTENCIAIS DE SAÚDE MENTAL | AM8: 4240 - FORMAÇÃO CONTINUADA E EXECUTIVA | AY8: 4215 - COMPLEXO PENAL | AZ8: 4258 - APOIO À IMPLEMENTAÇÃO DE INFRAESTRUTURAS E/OU PROJETOS PARA OS SERVIÇOS DE SANEAMENTO BÁSICO | BD8: 4395 - PROCESSAMENTO JUDICIÁRIO | BE8: 4430 - PROTEÇÃO SOCIAL ESPECIAL DE ALTA COMPLEXIDADE | BH8: 4211 - SERVIÇO DE APOIO INTEGRADO AO USUÁRIO | BN8: 064 - ASSISTÊNCIA FARMACÊUTICA | BR8: 7011 - BENEFÍCIOS PREVIDENCIÁRIOS - ARMBH | BS8: 4428 - PROJETOS ESPECIAIS DE PROMOÇÃO E PROTEÇÃO DA PRIMEIRA INFÂNCIA | BU8: 000 - ENCONTRO DAS ÁGUAS | BV8: 7043 - ENCARGOS DEVIDOS POR FINANCIAMENTO JUNTO AO PROGRAMA DE FORMAÇÃO DO PATRIMÔNIO DO SERVIDOR PÚBLICO - PASEP | BW8: 1027 - PROMOÇÃO DO SANEAMENTO BÁSICO POR MEIO DA INSTALAÇÃO DE MÓDULOS SANITÁRIOS | BX8: 2417 - REMUNERAÇÃO DE PESSOAL ATIVO E ENCARGOS SOCIAIS | BY8: 7208 - PROVENTOS DE INATIVOS PARLAMENTARES, OUTROS CIVIS E PENSIONISTAS | BZ8: 4068 - REDE DE ASSISTÊNCIA À SAÚDE ODONTOLÓGICA CONTRATADA | CB8: 4056 - RECUPERAÇÃO AMBIENTAL | CC8: 4027 - GESTÃO DO FOMENTO E DO SISTEMA DE FINANCIAMENTO À CULTURA | CE8: 4187 - PLANEJAMENTO DE RECURSOS HÍDRICOS | CF8: 2417 - REMUNERAÇÃO DE PESSOAL ATIVO E ENCARGOS SOCIAIS | CG8: 2500 - ASSESSORAMENTO E GERENCIAMENTO DE POLÍTICAS PÚBLICAS | CJ8: 4104 - APRESENTAÇÃO DE RELATÓRIOS DE GESTÃO | CK8: 7723 - PROGRAMAÇÃO A CARGO DO ESTADO PARA A COMPANHIA DE TECNOLOGIA DA INFORMAÇÃO DO ESTADO DE MINAS GERAIS - PRODEMGE | CL8: 1005 - PROJETO DELEGACIA RURAL | CN8: 4493 - OPERACIONALIZAÇÃO DAS ATRIBUIÇÕES INSTITUCIONAIS DO MINISTÉRIO PÚBLICO - PROCURADORIA E PROMOTORIA DE JUSTIÇA | CP8: 2010 - TRANSFERÊNCIAS ESPECIAIS - CASA CIVIL | CQ8: 116 - INOVA AGRO GERAIS | CU8: 070 - POLÍTICAS DE DIREITOS HUMANOS | CV8: 167 - PROGRAMA ESTADUAL DE DESENVOLVIMENTO DA EDUCAÇÃO BÁSICA | CW8: 2004 - MODERNIZAÇÃO DE SISTEMAS FAZENDÁRIOS LEGADOS | CY8: 705 - APOIO ÀS POLÍTICAS PÚBLICAS | DA8: 4037 - GESTÃO DE RESÍDUOS E CENTRO MINEIRO DE REFERÊNCIA EM RESÍDUOS | DB8: 159 - CENTRALIZAÇÃO DO PROCESSAMENTO DE COMPRAS PÚBLICAS | DC8: 2500 - ASSESSORAMENTO E GERENCIAMENTO DE POLÍTICAS PÚBLICAS | DE8: 7006 - PROVENTOS DE INATIVOS CIVIS E PENSIONISTAS | DF8: 2053 - REMUNERAÇÃO DE MAGISTRADOS DA ATIVA E ENCARGOS SOCIAIS | DH8: 4088 - ATIVIDADE DE PÓS-GRADUAÇÃO | DI8: 4005 - ASSISTÊNCIA ESTUDANTIL | DJ8: 4161 - REGULAÇÃO DE CONCESSÕES E PPPS
B9: 2500 - ASSESSORAMENTO E GERENCIAMENTO DE POLÍTICAS PÚBLICAS | C9: 4528 - MINAS REURB ARMVA | E9: 4469 - IMPLANTAÇÃO DO SISTEMA DE INFORMAÇÕES REGULATÓRIAS DA ARSAE-MG | Q9: 4305 - FORTALECIMENTO DA INTEGRIDADE PÚBLICA E PRIVADA | S9: 1098 - POTENCIALIZAÇÃO DO SERVIÇO DE PREVENÇÃO E RESPOSTA CONTRA INCÊNDIO E PÂNICO | T9: 1099 - IMPLANTAÇÃO E ESTRUTURAÇÃO DE DEFENSORIAS ESPECIALIZADAS E NÚCLEOS DA DEFENSORIA PÚBLICA | U9: 4268 - AMPLIAÇÃO DE CAPACIDADE DA MALHA VIÁRIA | W9: 7441 - PENSÕES ESPECIAIS DE RESPONSABILIDADE DO PODER EXECUTIVO ESTADUAL | Z9: 2052 - GESTÃO E OPERAÇÃO DO CENTRO DE CULTURA PRESIDENTE ITAMAR FRANCO | AB9: 2500 - ASSESSORAMENTO E GERENCIAMENTO DE POLÍTICAS PÚBLICAS | AC9: 2417 - REMUNERAÇÃO DE PESSOAL ATIVO E ENCARGOS SOCIAIS | AE9: 4389 - FOMENTO A ESTRUTURAS PARA PESQUISA, DESENVOLVIMENTO E INOVAÇÃO | AF9: 1058 - FORMAÇÃO CULTURAL | AG9: 7004 - PRECATÓRIOS E SENTENÇAS JUDICIÁRIAS | AI9: 4071 - LICENCIAMENTO AMBIENTAL | AL9: 4034 - ATENÇÃO À SAÚDE NO COMPLEXO HOSPITALAR DE BARBACENA | AM9: 4241 - DESENVOLVIMENTO DE PESSOAS NO SETOR PÚBLICO | AN9: 2417 - REMUNERAÇÃO DE PESSOAL ATIVO E ENCARGOS SOCIAIS | AY9: 4216 - RODOVIA MG 050 | BE9: 4431 - PISO MINEIRO DE ASSISTÊNCIA SOCIAL | BH9: 4382 - INTERVENÇÕES DE SEGURANÇA VIÁRIA | BN9: 068 - PRIMEIRA INFÂNCIA MINAS | BR9: 7012 - BENEFÍCIOS PREVIDENCIÁRIOS - ESP-MG | BU9: 705 - APOIO ÀS POLÍTICAS PÚBLICAS | BV9: 7658 - ENCARGOS DEVIDOS POR FINANCIAMENTO JUNTO AOS INSTITUTOS DE PREVIDÊNCIA DOS SERVIDORES MILITARES DO ESTADO DE MINAS GERAIS - IPSM | BW9: 1028 - PROMOÇÃO DE INFRAESTRUTURA HÍDRICA DE PEQUENO PORTE NO NORTE E NORDESTE DE MINAS GERAIS | BX9: 2500 - ASSESSORAMENTO E GERENCIAMENTO DE POLÍTICAS PÚBLICAS | BZ9: 4073 - REDE DE ASSISTÊNCIA À SAÚDE HOSPITALAR CONTRATADA | CA9: 4010 - AUXÍLIOS PREVIDENCIÁRIOS E ASSISTENCIAIS CONCEDIDOS AOS SEGURADOS E AOS SEUS DEPENDENTES | CB9: 4057 - PARC - PROGRAMA DE CONCESSÃO DE PARQUES ESTADUAIS | CC9: 4267 - AÇÕES DE DIFUSÃO E EDUCAÇÃO PARA O PATRIMÔNIO CULTURAL | CD9: 4202 - APRIMORAMENTO DA DEFESA SANITÁRIA - VIGILÂNCIA SANITÁRIA ANIMAL | CE9: 4188 - REGULAÇÃO DE RECURSOS HÍDRICOS | CF9: 2500 - ASSESSORAMENTO E GERENCIAMENTO DE POLÍTICAS PÚBLICAS | CG9: 7004 - PRECATÓRIOS E SENTENÇAS JUDICIÁRIAS | CI9: 6002 - SUPORTE AO DESENVOLVIMENTO ESTADUAL | CJ9: 4108 - QUALIDADE TOTAL E SEGURANÇA DE DADOS | CK9: 7734 - PROGRAMAÇÃO A CARGO DO ESTADO PARA COMPANHIA DE HABITAÇÃO DO ESTADO DE MINAS GERAIS - COHAB | CL9: 1006 - ENFRENTAMENTO À VIOLÊNCIA CONTRA A MULHER | CM9: 4372 - SUPORTE AÉREO AOS SERVIÇOS DE SEGURANÇA PÚBLICA | CP9: 2062 - REPRESENTAÇÃO E DEFESA DOS INTERESSES DO ESTADO DE MINAS GERAIS EM BRASILIA | CQ9: 118 - EDUCAÇÃO E SUCESSÃO RURAL | CR9: 2417 - REMUNERAÇÃO DE PESSOAL ATIVO E ENCARGOS SOCIAIS | CS9: 4324 - DIVULGAÇÃO TURÍSTICA DE MINAS GERAIS | CT9: 1100 - PROMOÇÃO DO DESENVOLVIMENTO SOCIOECONÔMICO E ACESSO À INFRAESTRUTURA DO NORTE E NORDESTE DE MINAS GERAIS | CU9: 071 - FORTALECIMENTO DO SISTEMA ÚNICO DE ASSISTÊNCIA SOCIAL - SUAS | CV9: 168 - GESTÃO DA REDE FÍSICA ESTADUAL DE ENSINO | CW9: 2005 - TRANSFORMAÇÃO DIGITAL | CX9: 2041 - CERIMONIAL E EVENTOS | CZ9: 4344 - PREVENÇÃO SOCIAL ÀS VIOLÊNCIAS E CRIMINALIDADES | DA9: 4044 - BOLSA RECICLAGEM | DB9: 160 - MELHORIA DA GESTÃO LOGÍSTICA E PATRIMONIAL | DF9: 2054 - REMUNERAÇÃO DE SERVIDORES DA ATIVA E ENCARGOS SOCIAIS | DG9: 1019 - APRIMORAMENTO DE SISTEMA ELETRÕNICO | DH9: 4089 - AÇÃO DE EXTENSÃO UNIVERSITÁRIA | DI9: 4006 - OFERTA DE ENSINO TÉCNICO E PROFISSIONAL | DJ9: 4205 - ESTRUTURAÇÃO, MODELAGEM E GESTÃO DE CONCESSÕES E PARCERIAS
A10: 1012 - APERFEIÇOAMENTO DA GESTÃO DA AGE | B10: 7004 - PRECATÓRIOS E SENTENÇAS JUDICIÁRIAS | G10: 8006 - FINANCIAMENTO À INFRAESTRUTURA E AO DESENVOLVIMENTO SUSTENTÁVEL EM MG ENTRE BDMG E NEW DEVELOPMENT BANK (BDMG INFRA ODS) | I10: 3001 - EXPANSÃO DO SISTEMA DE GERAÇÃO | Q10: 4306 - FOMENTO AO CONTROLE SOCIAL | S10: 2021 - ASSISTÊNCIA MÉDICA, ODONTOLÓGICA, PSICOLÓGICA E FISIOTERÁPICA AOS BOMBEIROS MILITARES E SEUS DEPENDENTES | T10: 2068 - CAPACITAÇÃO DE MEMBROS, SERVIDORES E CIDADÃOS POR MEIO DA ESCOLA SUPERIOR DA DEFENSORIA PÚBLICA | U10: 4272 - IMPLANTAÇÃO E RESTAURAÇÃO DE OBRAS DE ARTES ESPECIAIS | X10: 1034 - MELHORAMENTO GENÉTICO DE BOVINOS | Y10: 4018 - DESENVOLVIMENTO DE PESQUISA AGROPECUÁRIA E AGROINDUSTRIAL | Z10: 4294 - DISPONIBILIZAÇÃO E DISTRIBUIÇÃO DE CONTEÚDO MULTIPLATAFORMA EM PRODUTOS DIGITAIS ONLINE | AC10: 7004 - PRECATÓRIOS E SENTENÇAS JUDICIÁRIAS | AD10: 4172 - GESTÃO DO FOMENTO E DO SISTEMA DE FINANCIAMENTO À CULTURA | AE10: 4513 - FOMENTO À PESQUISA CIENTÍFICA BÁSICA E APLICADA E AO DESENVOLVIMENTO TECNOLÓGICO | AH10: 4277 - ATENDIMENTO NO ENSINO FUNDAMENTAL EM TERRITÓRIOS DE ALTA VULNERABILIDADE SOCIAL | AI10: 4072 - APOIO AO LICENCIAMENTO AMBIENTAL MUNICIPAL | AJ10: 4456 - PESQUISA E DESENVOLVIMENTO | AK10: 4075 - FORMAÇÃO CONTINUADA DE PROFESSORES PELO NÚCLO DE FORMAÇÃO PRESENCIAL E A DISTÂNCIA | AL10: 4035 - ATENÇÃO À SAÚDE NO COMPLEXO HOSPITALAR DE ESPECIALIDADES | AM10: 4242 - ESTUDOS E PESQUISAS NA ÁREA DE GESTÃO PÚBLICA | AN10: 2500 - ASSESSORAMENTO E GERENCIAMENTO DE POLÍTICAS PÚBLICAS | AY10: 4217 - UNIDADES DE ATENDIMENTO INTEGRAL UAI FASE I | AZ10: 4064 - PAGAMENTO POR SERVIÇOS AMBIENTAIS | BE10: 4433 - GESTÃO DA POLÍTICA ESTADUAL DE ASSISTÊNCIA SOCIAL | BH10: 4526 - CONTROLE DE CARGAS | BN10: 166 - EXECUÇÃO DESCENTRALIZADA E AUTÔNOMA DAS AÇÕES E SERVIÇOS DE SAÚDE | BR10: 7014 - BENEFÍCIOS PREVIDENCIÁRIOS - SEJUSP | BS10: 4411 - PROJETOS ESPECIAIS DE PROMOÇÃO E PROTEÇÃO DOS DIREITOS DE CRIANÇAS E ADOLESCENTES | BV10: 7886 - GESTÃO DA DÍVIDA FUNDADA CONTRATUAL INTERNA | BW10: 1095 - IMPLANTAÇÃO DE BARRAGENS HIDROAGRÍCOLAS | BX10: 7004 - PRECATÓRIOS E SENTENÇAS JUDICIÁRIAS | BY10: 2113 - PECÚLIO, AUXÍLIO FUNERAL, SAÚDE E OUTRAS ASSISTÊNCIAS | BZ10: 4074 - REDE DE ASSISTÊNCIA À SAÚDE AMBULATORIAL CONTRATADA | CA10: 4011 - AUXÍLIO RECLUSÃO CONCEDIDO AOS DEPENDENTES DO SEGURADO | CB10: 4058 - PROTEÇÃO E CONSERVAÇÃO DA FAUNA SILVESTRE | CC10: 4269 - INCENTIVO À IMPLANTAÇÃO DE POLÍTICAS MUNICIPAIS DE PROTEÇÃO AO PATRIMÔNIO CULTURAL | CD10: 4203 - APRIMORAMENTO DA DEFESA SANITÁRIA - VIGILÂNCIA SANITÁRIA VEGETAL | CE10: 4189 - COBRANÇA PELO USO DE RECURSOS HÍDRICOS | CF10: 7004 - PRECATÓRIOS E SENTENÇAS JUDICIÁRIAS | CJ10: 5001 - GESTÃO DE RISCOS PARA BOA GOVERNANÇA | CK10: 7737 - PROGRAMAÇÃO A CARGO DO ESTADO PARA A COMPANHIA DE SANEAMENTO DE MINAS GERAIS - COPASA | CL10: 1007 - MODERNIZAÇÃO DA POLÍCIA JUDICIÁRIA | CN10: 7004 - PRECATÓRIOS E SENTENÇAS JUDICIÁRIAS | CP10: 2066 - MINAS INTERNACIONAL | CQ10: 705 - APOIO ÀS POLÍTICAS PÚBLICAS | CR10: 2500 - ASSESSORAMENTO E GERENCIAMENTO DE POLÍTICAS PÚBLICAS | CS10: 4327 - MINAS FORMA, MINAS TRANSFORMA | CU10: 073 - MORADAS GERAIS | CV10: 169 - GESTÃO DO SISTEMA ESTADUAL DE EDUCAÇÃO | CW10: 2006 - PROPOSIÇÃO, AMPLIAÇÃO E SUSTENTAÇÃO DE SOLUÇÕES E ATENDIMENTO AOS USUÁRIOS DE TIC | CY10: 4266 - ASSISTENCIA EMERGENCIAL A MUNICIPIOS ATINGIDOS PELAS CHUVAS | CZ10: 4347 - IMPLANTAÇÃO DE UNIDADES DE PREVENÇÃO À CRIMINALIDADE | DB10: 161 - GESTÃO DE TRÂNSITO | DE10: 2009 - DIREÇÃO ADMINISTRATIVA | DG10: 2047 - AUXÍLIOS CONCEDIDOS A MAGISTRADOS E SERVIDORES | DH10: 4090 - FORTALECIMENTO DAS POLÍTICAS DE ASSISTÊNCIA ESTUDANTIL | DI10: 4017 - MANUTENÇÃO DO HOSPITAL DE ENSINO | DJ10: 4208 - REGULAÇÃO DE CONCESSÕES E PPPS
A11: 1013 - REPRESENTAÇÃO JUDICIAL, COBRANÇA DA DÍVIDA ATIVA E ASSESSORAMENTO JURÍDICO AO ESTADO E ENTIDADES | C11: 2417 - REMUNERAÇÃO DE PESSOAL ATIVO E ENCARGOS SOCIAIS | E11: 2417 - REMUNERAÇÃO DE PESSOAL ATIVO E ENCARGOS SOCIAIS | I11: 3007 - REFORMAS, MELHORIAS E AMPLIAÇÕES DE USINAS | S11: 4112 - AMPLIAÇÃO DO SISTEMA DE TECNOLOGIA DA INFORMAÇÃO E COMUNICAÇÃO, NO CBMMG, PARA RESPOSTA A DESASTRES | T11: 4033 - CONSTRUÇÃO E REFORMA DE UNIDADES DA DEFENSORIA PÚBLICA | U11: 4275 - IMPLANTAÇÃO/PAVIMENTAÇÃO DA MALHA | X11: 4236 - FOMENTO PARA O DESENVOLVIMENTO DO SETOR AGROPECUÁRIO | Y11: 4019 - DIVULGAÇÃO DE TECNOLOGIA AGROPECUÁRIA VIA EVENTOS TÉCNICO-CIENTÍFICOS | Z11: 4295 - ATUALIZAÇÃO DE PLATAFORMA DE STREAMING E VOD COM CONTEÚDO INÉDITO | AF11: 1061 - PARCERIAS PARA O PATRIMÔNIO CULTURAL | AH11: 4282 - ATENDIMENTO NO ENSINO MÉDIO EM TERRITÓRIOS DE ALTA VULNERABILIDADE SOCIAL | AK11: 4076 - PASSAPORTE MINEIRO DO CONHECIMENTO | AL11: 4036 - ATENÇÃO À SAÚDE NO COMPLEXO HOSPITALAR DE URGÊNCIA E EMERGÊNCIA | AM11: 4243 - FORMAÇÃO DE PESSOAS NO NÍVEL DE GRADUAÇÃO | AN11: 7004 - PRECATÓRIOS E SENTENÇAS JUDICIÁRIAS | AY11: 4218 - UNIDADES DE ATENDIMENTO INTEGRAL UAI FASE I I | AZ11: 4392 - APOIO À GESTÃO DE RECURSOS HÍDRICOS | BE11: 4434 - FORTALECIMENTO DO CONTROLE SOCIAL DO SUAS | BN11: 705 - APOIO ÀS POLÍTICAS PÚBLICAS | BR11: 7015 - BENEFÍCIOS PREVIDENCIÁRIOS - ARSAE-MG | BU11: 4341 - GESTÃO DO TRANSPORTE RODOVIÁRIO | BV11: 7896 - GESTÃO DA DÍVIDA FUNDADA CONTRATUAL EXTERNA | BZ11: 4410 - ATENDIMENTO DE ORDENS JUDICIAIS PARA ASSISTÊNCIA À SAÚDE | CB11: 4059 - GESTÃO DE UNIDADES E CONSERVAÇÃO | CC11: 4484 - GESTÃO DO FOMENTO E DO SISTEMA DE FINANCIAMENTO À CULTURA | CD11: 4206 - FISCALIZAÇÃO DO TRÂNSITO DE ANIMAIS, VEGETAIS, INSUMOS E PRODUTOS DE ORIGEM ANIMAL. | CE11: 4190 - FORTALECIMENTO DA GESTÃO PARTICIPATIVA | CI11: 6003 - SUPORTE AO DESENVOLVIMENTO ESTADUAL | CJ11: 5004 - PREVENÇÃO E COMBATE À CORRUPÇÃO | CK11: 7752 - PROGRAMAÇÃO A CARGO DO ESTADO PARA O BANCO DE DESENVOLVIMENTO DE MINAS GERAIS - BDMG | CL11: 1051 - IMPLEMENTAÇÃO DA CADEIA DE CUSTÓDIA DA PROVA EM MINAS GERAIS | CM11: 2065 - CAPACITAÇÃO E TREINAMENTO POLICIAL-MILITAR PARA PROTEÇÃO E DEFESA CIVIL | CN11: 7006 - PROVENTOS DE INATIVOS CIVIS E PENSIONISTAS | CP11: 2070 - COORDENAÇÃO DO PROCESSO DE CAPTAÇÃO DE RECURSOS E PARCERIAS, MONITORAMENTO DE CONVÊNIOS DE ENTRADA, INSTRUMENTOS CONGÊNERES E OPERAÇÕES DE CRÉDITO | CS11: 4328 - ESTRUTURAÇÃO DE PRODUTOS TURÍSTICOS | CT11: 1082 - MINAS REURB SEDE | CU11: 074 - SEGURANÇA ALIMENTAR E NUTRICIONAL SUSTENTÁVEL PARA TODOS OS POVOS DO TERRITÓRIO MINEIRO | CV11: 170 - MODALIDADES E TEMATICAS ESPECIAIS DE ENSINO | CW11: 2007 - SUSTENTAÇÃO DO DATA CENTER | CX11: 2042 - ACOMPANHAMENTO DO PROCESSO LEGISLATIVO | DA11: 4038 - FISCALIZAÇÃO AMBIENTAL | DB11: 705 - APOIO ÀS POLÍTICAS PÚBLICAS | DE11: 4445 - FISCALIZAÇÃO DA GESTÃO DE RECURSOS PÚBLICOS E OPERACIONALIZAÇÃO DAS ATRIBUIÇÕES INSTITUCIONAIS | DG11: 2077 - REMUNERAÇÃO DE MAGISTRADOS DA ATIVA E ENCARGOS SOCIAIS | DI11: 4550 - FORNECIMENTO DE REFEIÇÕES NA UNIVERSIDADE | DJ11: 4253 - GESTÃO DE CONCESSÕES E PARCERIAS DE EQUIPAMENTOS PÚBLICOS
A12: 1014 - REESTRUTURAÇÃO LOGÍSTICA, TECNOLÓGICA E DE COBRANÇA DA DÍVIDA ATIVA DA AGE | C12: 2500 - ASSESSORAMENTO E GERENCIAMENTO DE POLÍTICAS PÚBLICAS | E12: 2500 - ASSESSORAMENTO E GERENCIAMENTO DE POLÍTICAS PÚBLICAS | I12: 3008 - MANUTENÇÃO DA INFRAESTRUTURA DA GERAÇÃO | Q12: 4307 - FORTALECIMENTO DE SERVIÇOS DE AUDITORIA INTERNA PARA AGREGAR VALOR À GESTÃO PÚBLICA ESTADUAL | S12: 4113 - MANUTENÇÃO E AMPLIAÇÃO DA INFRAESTRUTURA E SISTEMA DE TECNOLOGIA DA INFORMAÇÃO E COMUNICAÇÃO | T12: 4150 - OPERACIONALIZAÇÃO DAS ATRIBUIÇÕES DA DEFENSORIA PÚBLICA E DIREÇÃO ADMIINISTRATIVA | U12: 4284 - PREVENÇÃO E MITIGAÇÃO DE DANOS AMBIENTAIS | Y12: 4020 - TRANSFERÊNCIA DE TECNOLOGIA VIA SEMENTES DE CULTIVARES MELHORADAS | Z12: 4296 - GESTÃO E MANUTENÇÃO DOS SISTEMAS DE TRANSMISSÃO VIA SATÉLITE E OPERAÇÃO DE TV | AD12: 4417 - FOMENTO DOS ESPAÇOS CULTURAIS | AE12: 1068 - SETOR PRODUTIVO MAIS INOVADOR | AH12: 4283 - EDUCAÇÃO PARA A CIDADANIA E PARA O MUNDO DO TRABALHO EM TERRITÓRIOS DE ALTA VULNERABILIDADE SOCIAL | AI12: 2417 - REMUNERAÇÃO DE PESSOAL ATIVO E ENCARGOS SOCIAIS | AJ12: 4457 - ATENDIMENTO DE ANÁLISES LABORATORIAIS DE INTERESSE DA SAÚDE PÚBLICA | AK12: 4077 - EDUCAÇÃO BÁSICA: AMPLIAÇÃO DA JORNADA ESCOLAR | AM12: 4244 - FORMAÇÃO DE PESSOAS NO NÍVEL DE PÓS-GRADUAÇÃO (LATO SENSU) | AY12: 4219 - UNIDADES DE ATENDIMENTO INTEGRAL UAI FASE I I I | AZ12: 4413 - APOIO À GESTÃO DE RECURSOS HÍDRICOS, RECURSOS REEMBOLSÁVEIS | BE12: 4435 - EDUCAÇÃO PERMANENTE DO SUAS | BH12: 2029 - ADMINISTRAÇÃO E OPERACIONALIZAÇÃO DA ARRECADAÇÃO DO FUNTRANS | BR12: 7016 - COMPENSAÇÃO PREVIDENCIÁRIA FINANCEIRA ENTRE REGIMES DE PREVIDÊNCIA | BW12: 4320 - DISTRIBUIÇÃO DE LEITE ADQUIRIDO DA AGRICULTURA FAMILIAR, PARA BENEFICIÁRIOS EM INSEGURANÇA ALIMENTAR | BY12: 2114 - RESERVA TÉCNICA | CA12: 2017 - APOIO A POLÍTICA DE SAÚDE PARA OS MILITARES | CB12: 4500 - REGULARIZAÇÃO FUNDIÁRIA DE UNIDADES DE CONSERVAÇÃO | CD12: 4228 - FORTALECIMENTO DA ESTRUTURA E DOS PROCESSOS DO INSTITUTO MINEIRO DE AGROPECUÁRIA | CE12: 4191 - MONITORAMENTO HIDROMETEOROLOGICO | CJ12: 5006 - QUALIDADE TOTAL E SEGURANÇA DE DADOS | CK12: 7758 - PROGRAMAÇÃO A CARGO DO ESTADO PARA A COMPANHIA ENEGÉTICA DE MINAS GERAIS - CEMIG | CL12: 1052 - APRIMORAMENTO DA INVESTIGAÇÃO DE HOMICÍDIOS | CP12: 4100 - APOIO AOS MUNICÍPIOS | CQ12: 4357 - AGROEXPORTA - PROMOÇÃO DO AGRONEGÓCIO MINEIRO PARA A EXPORTAÇÃO | CS12: 4330 - PLANEJAMENTO E MONITORAMENTO DO SETOR TURÍSTICO DO ESTADO DE MINAS GERAIS | CT12: 1083 - DISCRIMINAÇÃO E ARRECADAÇÃO DE TERRAS E GESTÃO DOS ARRENDAMENTOS | CU12: 083 - POLÍTICAS DE PROMOÇÃO AO DESENVOLVIMENTO SOCIAL NO CONTEXTO RURAL - PERCURSOS GERAIS: TRAJETÓRIA PARA AUTONOMIA | CV12: 172 - PROGRAMA ESTADUAL DE COOPERACAO ESTADO-MUNICIPIO NA AREA EDUCACIONAL | CY12: 1037 - INTERVENÇÕES NA INFRAESTRUTURA RODOVIARIA ESTADUAL, MUNICIPAL E REGIONAL | CZ12: 1047 - MODERNIZAÇÃO E EXPANSÃO DO SISTEMA PRISIONAL - REPARAÇÃO BRUMADINHO | DA12: 4039 - ATENDIMENTO DE DENÚNCIAS E DE REQUISIÇÕES | DG12: 2078 - REMUNERAÇÃO DE SERVIDORES DA ATIVA E ENCARGOS SOCIAIS | DH12: 2417 - REMUNERAÇÃO DE PESSOAL ATIVO E ENCARGOS SOCIAIS | DJ12: 4345 - GESTÃO DO RODOANEL METROPOLITANO
C13: 7004 - PRECATÓRIOS E SENTENÇAS JUDICIÁRIAS | E13: 7004 - PRECATÓRIOS E SENTENÇAS JUDICIÁRIAS | I13: 3014 - INVESTIMENTOS EM PARTICIPAÇÕES SOCIETÁRIAS DA GERAÇÃO | Q13: 4308 - APRIMORAMENTO DA CAPACIDADE DE AUDITORIA INTERNA NOS PADRÕES INTERNACIONAIS | S13: 4114 - GESTÃO DA PREVENÇÃO, MITIGAÇÃO E PREPARAÇÃO DE DESASTRE | T13: 4193 - REMUNERAÇAO DE PESSOAL ATIVO E ENCARGOS SOCIAIS | U13: 4287 - CONSTRUÇÃO E ADEQUAÇÃO DE RODOVIAS - RIO DOCE | X13: 1044 - APOIO À COMERCIALIZAÇÃO ELETRÔNICA POR MEIO DE PLATAFORMA MARKETPLACE | Y13: 4021 - TRANSFERÊNCIA DE TECNOLOGIA VIA MUDAS QUALIFICADAS | Z13: 4297 - DISPONIBILIZAÇÃO E MANUTENÇÃO DO SINAL DE RETRANSMISSÃO DE TV NO INTERIOR DO ESTADO E REGIÃO METROPOLITANA DE BH | AD13: 4421 - PRODUÇÃO DE ESPETÁCULOS DOS CORPOS ARTÍSTICOS | AE13: 1069 - FORMAÇÃO E RETENÇÃO DE TALENTOS EM ÁREAS TECNOLÓGICAS | AF13: 1062 - QUALIFICAÇÃO PROFFISSIONAL E CURSOS COMPLEMENTARES, LIVRES, DE FORMAÇÃO INICIAL E CONTINUADA | AH13: 4285 - INCLUSÃO SOCIOPRODUTIVA EM TERRITÓRIOS DE ALTA VULNERABILIDADE SOCIAL | AI13: 2500 - ASSESSORAMENTO E GERENCIAMENTO DE POLÍTICAS PÚBLICAS | AK13: 4078 - ENSINO FUNDAMENTAL | AL13: 2417 - REMUNERAÇÃO DE PESSOAL ATIVO E ENCARGOS SOCIAIS | AM13: 4245 - FORMAÇÃO DE PESSOAS NO NÍVEL DE PÓS-GRADUAÇÃO (STRICTO SENSU) | AY13: 4220 - RODOANEL METROPOLITANO DE BELO HORIZONTE | BE13: 4535 - PISO MINEIRO DE PROTEÇÃO SOCIAL ESPECIAL | BN13: 1020 - IMPLANTAÇÃO DOS HOSPITAIS REGIONAIS | BR13: 7017 - BENEFÍCIOS PREVIDENCIÁRIOS - GABINETE MILITAR | BU13: 4426 - GESTÃO DA AVIAÇÃO DO GABINETE MILITAR DO GOVERNADOR | BW13: 4323 - APOIO ÀS FEIRAS LIVRES PARA AMPLIAR A GERAÇÃO DE RENDA E DESENVOLVIMENTO ECONÔMICO LOCAL | BZ13: 4229 - ATENÇÃO À SAÚDE AMBULATORIAL NA REDE PRÓPRIA | CA13: 2018 - APOIO AO SISTEMA DE PROTEÇÃO SOCIAL DOS MILITARES DE MINAS GERAIS | CC13: 4274 - PARCERIAS PARA PROTEÇÃO E SALVAGUARDA DO PATRIMÔNIO CULTURAL | CD13: 4238 - REESTRUTURAÇÃO DO LABORATÓRIO DE QUÍMICA AGROPECUÁRIA DO INSTITUTO MINEIRO DE AGROPECUÁRIA. | CE13: 4192 - SEGURANÇA DE BARRAGENS | CK13: 7759 - PROGRAMAÇÃO A CARGO DO ESTADO PARA TREM METROPOLITANO DE BELO HORIZONTE S/A | CL13: 4060 - GESTÃO DAS UNIDADES POLICIAIS | CM13: 2057 - DEMAIS ASSISTÊNCIAS | CN13: 1064 - CONSTRUÇÃO, AMPLIAÇÃO E REFORMA DE SEDES PRÓPRIAS | CQ13: 4358 - CIRCUITOS DE COMERCIALIZAÇÃO | CS13: 4479 - DESENVOLVIMENTO DA POLÍTICA DE REGIONALIZAÇÃO DO TURISMO | CT13: 1097 - SEGURANÇA HÍDRICA NA RMBH | CU13: 084 - POLÍTICAS DE INTEGRAÇÃO, REGIONALIZAÇÃO E INOVAÇÃO | CW13: 2016 - MODERNIZAÇÃO DA GESTÃO E INOVAÇÃO DO TESOURO ESTADUAL | CX13: 2043 - FISCALIZAÇÃO DOS INSTRUMENTOS DE REPASSES DE RECURSOS NO ÂMBITO DO PROGRAMA DE APOIO AO DESENVOLVIMENTO MUNICIPAL | CZ13: 1048 - MODERNIZAÇÃO E EXPANSÃO DO SISTEMA PRISIONAL | DA13: 4040 - AMPLIAÇÃO DA FISCALIZAÇÃO PREVENTIVA | DB13: 4468 - PROVISÃO DE CARGOS POR CONCURSO PÚBLICO | DE13: 2145 - CAPACITAÇÃO DE SERVIDORES E MEMBROS DO TCEMG, GESTORES E SERVIDORES PÚBLICOS DAS ENTIDADES JURISDICIONADAS E REPRESENTANTES DE ENTIDADES DA SOCIEDADE | DG13: 4003 - FORMAÇÃO, APERFEIÇOAMENTO E DESENVOLVIMENTO CONTÍNUO DE PESSOAS | DH13: 2500 - ASSESSORAMENTO E GERENCIAMENTO DE POLÍTICAS PÚBLICAS | DI13: 1031 - REMUNERAÇÃO DE PESSOAL ATIVO E ENCARGOS SOCIAIS | DJ13: 4346 - METRÔ DA RMBH
A14: 2417 - REMUNERAÇÃO DE PESSOAL ATIVO E ENCARGOS SOCIAIS | Q14: 4309 - ESTRUTURAÇÃO TECNOLÓGICA E INSTITUCIONALIZAÇÃO DA AUDITORIA CONTÍNUA | S14: 4115 - GESTÃO DA RESPOSTA A DESASTRES | U14: 4288 - RECUPERAÇÃO E MANUTENÇÃO DA MALHA VIÁRIA - RECUPERAÇÃO BRUMADINHO | Y14: 4022 - TRANSFERÊNCIA DE TECNOLOGIA VIA MATRIZES E REPRODUTORES | Z14: 4315 - GESTÃO E MANUTENÇÃO DOS SISTEMAS DE TRANSMISSÃO E OPERAÇÃO DE RÁDIO | AD14: 4422 - GERENCIAMENTO DO CONTRATO DE GESTÃO | AE14: 1086 - INOVA GOVERNO DE MINAS GERAIS | AH14: 4515 - MANUTENÇÃO DA OPERAÇÃO DOS CENTROS EDUCACIONAIS | AI14: 7004 - PRECATÓRIOS E SENTENÇAS JUDICIÁRIAS | AJ14: 4459 - PRODUÇÃO DE VACINA, SOROS E OUTROS PRODUTOS BIOLÓGICOS | AK14: 4080 - ENSINO MÉDIO REGULAR | AL14: 2500 - ASSESSORAMENTO E GERENCIAMENTO DE POLÍTICAS PÚBLICAS | AM14: 4246 - PARTICIPAÇÃO EM EXTENSÃO ACADÊMICA | AY14: 4221 - LOTES RODOVIÁRIOS | AZ14: 4151 - BOLSA VERDE: CONSERVAÇÃO DA COBERTURA VEGETAL NATIVA | BN14: 4121 - POLÍTICA DE ATENÇÃO HOSPITALAR E URGÊNCIA E EMERGÊNCIA | BR14: 7018 - BENEFÍCIOS PREVIDENCIÁRIOS - AGE | BW14: 4325 - PROMOÇÃO DO DESENVOLVIMENTO SOCIOECONÔMICO DO NORTE E NORDESTE DE MINAS GERAIS | BZ14: 4230 - ATENÇÃO À SAÚDE ODONTOLÓGICA NA REDE PRÓPRIA | CA14: 2417 - REMUNERAÇÃO DE PESSOAL ATIVO E ENCARGOS SOCIAIS | CB14: 4091 - GESTÃO DE AERONAVES DO SISEMA | CD14: 4252 - REVITALIZAÇÃO DO PARQUE DE EXPOSIÇÕES BOLIVAR DE ANDRADE | CE14: 4194 - PROGRAMAS PROJETOS E PESQUISAS EM RECURSOS HÍDRICOS | CJ14: 1017 - MANUTENÇÃO, DIVERSIFICAÇÃO E EVOLUÇÃO DOS CANAIS DE ATENDIMENTO | CL14: 4061 - PERÍCIAS TÉCNICO-CIENTÍFICAS | CM14: 2060 - ASSISTÊNCIA À SAÚDE | CP14: 2417 - REMUNERAÇÃO DE PESSOAL ATIVO E ENCARGOS SOCIAIS | CQ14: 4359 - COOPERAF | CT14: 4481 - GESTÃO DE ATIVOS IMOBILIÁRIOS ALIENÁVEIS DE MINAS GERAIS | CU14: 086 - POLÍTICA DOS DIREITOS DAS MULHERES | CV14: 2067 - DESENVOLVIMENTO DA EDUCAÇÃO ESPECIAL | CW14: 2019 - GERENCIAMENTO E SUPORTE ÀS ATIVIDADES LIGADAS A CONTADORIA GERAL DO ESTADO DE MINAS GERAIS | CX14: 2045 - EXECUÇÃO DO PROGRAMA DE APOIO AO DESENVOLVIMENTO MUNICIPAL - PADEM | CY14: 4208 - REGULACAO DE CONCESSOES E PPPS | CZ14: 4348 - CUSTÓDIA E RESSOCIALIZAÇÃO DE PRESOS | DA14: 4053 - PREVENÇÃO E ATENDIMENTO A ACIDENTES E EMERGÊNCIAS AMBIENTAIS | DB14: 4475 - ADMINISTRAÇÃO DE PESSOAL | DG14: 4355 - PROCESSAMENTO JUDICIÁRIO MILITAR, AÇÕES DE COMUNICAÇÃO INSTITUCIONAL E PRIORIZAÇÃO DO 1º GRAU | DH14: 7004 - PRECATÓRIOS E SENTENÇAS JUDICIÁRIAS | DI14: 2417 - REMUNERAÇÃO DE PESSOAL ATIVO E ENCARGOS SOCIAIS | DJ14: 4503 - GESTÃO DE CONCESSÕES DO TRANSPORTE COLETIVO E TERMINAIS
A15: 2500 - ASSESSORAMENTO E GERENCIAMENTO DE POLÍTICAS PÚBLICAS | S15: 4116 - FORMAÇÃO E CAPACITAÇÃO TÉCNICO PROFISSIONAL PARA CIVIS | U15: 4289 - CONSTRUÇÃO E ADEQUAÇÃO DE RODOVIAS - RECUPERAÇÃO BRUMADINHO | X15: 1045 - CADASTRAMENTO DE AGRICULTORES/POSSEIROS COM FINS DE REGULARIZAÇÃO FUNDIÁRIA DE TERRAS DEVOLUTAS RURAIS. | Y15: 4023 - INFORMAÇÃO CIENTÍFICA E TECNOLÓGICA VIA PUBLICAÇÕES | Z15: 4316 - PRODUÇÃO E VEICULAÇÃO DE CONTEÚDO EM ÁUDIO COM ÊNFASE NA CULTURA, EDUCAÇÃO, INFORMAÇÃO, PRESTAÇÃO DE SERVIÇO E ENTRETENIMENTO. | AD15: 4423 - FOMENTO A ATIVIDADES ARTÍSTICAS E CULTURAIS DO PALÁCIO DA LIBERDADE | AE15: 1087 - FOMENTO À CIÊNCIA, PESQUISA, DESENVOLVIMENTO, INOVAÇÃO E À TRANSFERÊNCIA DE TECNOLOGIA | AF15: 1066 - ACERVO OU BEM CULTURAL RESTAURADO ENTREGUE | AJ15: 4460 - PRODUÇÃO DE MEDICAMENTOS SINTÉTICOS | AK15: 4175 - PLUG MINAS | AL15: 7004 - PRECATÓRIOS E SENTENÇAS JUDICIÁRIAS | AM15: 4247 - PROMOÇÃO DA INOVAÇÃO NO SETOR PÚBLICO | AY15: 4223 - LOTE 2: SUL DE MINAS | BE15: 1096 - APROXIMAÇÃO SUAS | BN15: 4122 - POLÍTICAS PRÉ E PÓS HOSPITALARES DE URGÊNCIA E EMERGÊNCIA | BR15: 7022 - BENEFÍCIOS PREVIDENCIÁRIOS - FAPEMIG | BU15: 4381 - GESTÃO DE DESASTRE CAUSADOS PELA CHUVA | BW15: 4516 - APOIO À MECANIZAÇÃO DA PRODUÇÃO AGRÍCOLA | BZ15: 4231 - ATENÇÃO À SAÚDE HOSPITALAR NA REDE PRÓPRIA | CA15: 7002 - ENCARGOS COM PENSIONISTAS | CC15: 4271 - FORMAÇÃO E CAPACITAÇÃO PARA O PATRIMÔNIO CULTURAL | CE15: 4195 - PROGRAMA ESTRATÉGICO SOMOS TODOS ÁGUA | CJ15: 4012 - PREVENÇÃO E COMBATE AO ASSÉDIO MORAL E SEXUAL | CL15: 4062 - MODERNIZAÇÃO E AMPLIAÇÃO DO BANCO DE PERFIS GENÉTICOS | CP15: 2500 - ASSESSORAMENTO E GERENCIAMENTO DE POLÍTICAS PÚBLICAS | CQ15: 4361 - MERCADOS INSTITUCIONAIS | CS15: 4331 - PROMOÇÃO DE ATIVIDADES ARTÍSTICO-CULTURAIS | CT15: 4482 - GESTÃO DE ATIVOS IMOBILIÁRIOS ALIENÁVEIS - SEDE | CU15: 148 - APOIO ÀS POLÍTICAS DE DESENVOLVIMENTO SOCIAL | CW15: 2032 - GERENCIAMENTO E SUPORTE ÀS ATIVIDADES LIGADAS À GOVERNANÇA DE ATIVOS, RISCOS FISCAIS E DA DÍVIDA PÚBLICA DO ESTADO DE MINAS GERAIS | CX15: 2046 - ATENDIMENTO ÀS DEMANDAS DA PARTICIPAÇÃO CIDADÃ | CY15: 4253 - GESTAO DE CONCESSOES E PARCERIAS DE EQUIPAMENTOS PUBLICOS | CZ15: 4350 - MANUTENÇÃO E AMPLIAÇÃO DO MONITORAMENTO ELETRÔNICO | DB15: 4476 - SAÚDE DO SERVIDOR | DI15: 2500 - ASSESSORAMENTO E GERENCIAMENTO DE POLÍTICAS PÚBLICAS
A16: 7803 - PRECATÓRIOS E SENTENÇAS JUDICIÁRIAS DA ADMINISTRAÇÃO DIRETA DO PODER EXECUTIVO | Q16: 4303 - EXECUÇÃO DE AÇÕES INVESTIGATIVAS E RECUPERAÇÃO DE ATIVOS | S16: 4117 - BOMBEIRO NAS ESCOLAS | U16: 4293 - CONSERVAÇÃO ROTINEIRA DA MALHA&#8203, VIÁRIA | Z16: 4333 - PRODUÇÃO E VEICULAÇÃO TELEVISIVA DE PROGRAMAÇÃO DE CARÁTER CULTURAL, INFORMATIVO, EDUCATIVO E DE ENTRETENIMENTO | AE16: 1088 - FOMENTO A AMBIENTES E ESTRUTURAS DE APOIO À PESQUISA, DESENVOLVIMENTO E INOVAÇÃO | AF16: 1067 - ASSESSORIA TÉCNICA EM CONSERVAÇÃO E RESTAURAÇÃO DO PATRIMÔNIO | AH16: 2417 - REMUNERAÇÃO DE PESSOAL ATIVO E ENCARGOS SOCIAIS | AK16: 4232 - ASSISTÊNCIA ESTUDANTIL | AY16: 4224 - MODELOS ALTERNATIVOS DE PRESTAÇÃO DA MEDIDA DE ATENDIMENTO SOCIOEDUCATIVA DE PRIVAÇÃO DE LIBERDADE | AZ16: 4259 - APOIO À GESTÃO DE RECURSOS HÍDRICOS | BN16: 4123 - ESTRUTURAÇÃO DA ATENÇÃO HOSPITALAR E DE URGÊNCIA E EMERGÊNCIA | BR16: 7023 - PROVENTOS DE APOSENTADORIA E PENSÃO DE EXTINTOS CONVÊNIOS | CA16: 7004 - PRECATÓRIOS E SENTENÇAS JUDICIÁRIAS | CB16: 2417 - REMUNERAÇÃO DE PESSOAL ATIVO E ENCARGOS SOCIAIS | CD16: 4317 - ANÁLISE LABORATORIAL | CJ16: 4101 - OUVIDORIA MÓVEL | CL16: 4063 - CONSTRUÇÃO NÚCLEO INTEGRADO DE PERÍCIAS | CM16: 2058 - ENSINO FUNDAMENTAL | CS16: 4332 - APOIO A PROJETOS CULTURAIS E TURÍSTICOS REALIZADOS POR INTERMÉDIO DE PARCERIAS | CT16: 4544 - REGULARIZAÇÃO FUNDIÁRIA DE TERRITÓRIOS COLETIVOS | CU16: 705 - APOIO ÀS POLÍTICAS PÚBLICAS | CV16: 2133 - UTILIZAÇÃO DE MÉTODOS ALTERNATIVOS DE SOLUÇÃO DE CONFLITOS DA SEE | CW16: 4095 - CONTROLE E OPERAÇÕES FINANCEIRAS DOS RECURSOS ESTADUAIS. | CX16: 2048 - TRANSFERÊNCIAS ESPECIAIS | CY16: 4345 - GESTAO DO RODOANEL METROPOLITANO | CZ16: 4351 - MANUTENÇÃO E IMPLANTAÇÃO DE METODOLOGIA DE CUSTÓDIAS ALTERNATIVAS | DA16: 4045 - GESTÃO E PLANEJAMENTO AMBIENTAL | DB16: 4477 - DESEMPENHO, DESENVOLVIMENTO E VALORIZAÇÃO DOS SERVIDORES PÚBLICOS | DI16: 7004 - PRECATÓRIOS E SENTENÇAS JUDICIÁRIAS
Q17: 4310 - FORTALECIMENTO DA PREVENÇÃO A ILÍCITOS ADMINISTRATIVOS | S17: 4119 - RECRUTAMENTO, TREINAMENTO E FORMAÇÃO DE BOMBEIROS | U17: 4385 - REABILITAÇÃO DA MALHA VIÁRIA | X17: 2417 - REMUNERAÇÃO DE PESSOAL ATIVO E ENCARGOS SOCIAIS | Y17: 2417 - REMUNERAÇÃO DE PESSOAL ATIVO E ENCARGOS SOCIAIS | AD17: 4425 - ATIVIDADES DE ENSINO E DE EXTENSÃO DO CENTRO DE FORMAÇÃO ARTÍSTICA E TECNOLÓGICA - CEFART | AH17: 2500 - ASSESSORAMENTO E GERENCIAMENTO DE POLÍTICAS PÚBLICAS | AJ17: 2417 - REMUNERAÇÃO DE PESSOAL ATIVO E ENCARGOS SOCIAIS | AM17: 4248 - MANUTENÇÃO DA BIBLIOTECA DIGITAL DE MINAS GERAIS RAYMUNDO NONATO DE CASTRO | AY17: 4225 - MANUTENÇÃO E REFORMA DE ESCOLAS | AZ17: 4260 - APOIO À GESTÃO DE RECURSOS HÍDRICOS, RECURSOS REEMBOLSÁVEIS | BR17: 7027 - BENEFÍCIOS PREVIDENCIÁRIOS - ALMG | BU17: 1089 - PROJETO CONVIVÊNCIA COM A SECA E ESTIAGEM | BW17: 2500 - ASSESSORAMENTO E GERENCIAMENTO DE POLÍTICAS PÚBLICAS | BZ17: 4409 - AUXÍLIO FINANCEIRO AO SEGURADO | CB17: 2500 - ASSESSORAMENTO E GERENCIAMENTO DE POLÍTICAS PÚBLICAS | CC17: 4276 - SALVAGUARDA DO PATRIMÔNIO CULTURAL | CD17: 4318 - INSPEÇÃO DE PRODUTOS DE ORIGEM VEGETAL | CE17: 2417 - REMUNERAÇÃO DE PESSOAL ATIVO E ENCARGOS SOCIAIS | CJ17: 4102 - DIVULGAÇÃO DOS CANAIS E AÇÕES DA OUVIDORIA | CL17: 4067 - IMPLANTAÇÃO DO PLANTÃO DIGITAL | CM17: 2059 - ENSINO MÉDIO | CQ17: 4363 - REGULARIZAÇÃO FUNDIÁRIA DE IMÓVEIS RURAIS | CS17: 4343 - GESTÃO DO FOMENTO E MUNICIPALIZAÇÃO DA CULTURA | CW17: 4096 - GESTÃO ESTRATÉGICA E PLANEJAMENTO FINANCEIRO | CY17: 4503 - GESTAO DE CONCESSOES DO TRANSPORTE COLETIVO E TERMINAIS | CZ17: 4353 - UNIDADES DE SAÚDE DO SISTEMA PRISIONAL | DA17: 4046 - MUDANÇAS CLIMÁTICAS E QUALIDADE AMBIENTAL | DB17: 4478 - TRANSFORMA MINAS
Q18: 4311 - APURAÇÃO DE RESPONSABILIDADE DE AGENTES PÚBLICOS E PESSOAS JURÍDICAS | S18: 4120 - MODERNIZAÇÃO E ESTRUTURAÇÃO DO CORPO DE BOMBEIROS MILITAR DE MINAS GERAIS | U18: 4530 - OPERAÇÃO VIÁRIA E FISCALIZAÇÃO DE TRANSPORTE E TRÂNSITO | X18: 2500 - ASSESSORAMENTO E GERENCIAMENTO DE POLÍTICAS PÚBLICAS | Y18: 2500 - ASSESSORAMENTO E GERENCIAMENTO DE POLÍTICAS PÚBLICAS | Z18: 2500 - ASSESSORAMENTO E GERENCIAMENTO DE POLÍTICAS PÚBLICAS | AE18: 2022 - REMUNERAÇÃO DE PESSOAL ATIVO E ENCARGOS SOCIAIS | AF18: 2417 - REMUNERAÇÃO DE PESSOAL ATIVO E ENCARGOS SOCIAIS | AH18: 7004 - PRECATÓRIOS E SENTENÇAS JUDICIÁRIAS | AJ18: 2500 - ASSESSORAMENTO E GERENCIAMENTO DE POLÍTICAS PÚBLICAS | AK18: 2015 - CERTIFICAÇÕES PELO NÚCLEO DE FORMAÇÃO PRESENCIAL E À DISTÂNCIA | AY18: 4226 - COMPLEXO DE SAÚDE (FHEMIG) | AZ18: 4263 - APOIO AOS COMITÊS DE BACIAS HIDROGRÁFICAS | BN18: 2023 - POLÍTICAS E AÇÕES DE TECNOLOGIAS DA INFORMAÇÃO E COMUNICAÇÃO (TIC) | BR18: 7028 - BENEFÍCIOS PREVIDENCIÁRIOS - TJMG | BU18: 4155 - MODERNIZAÇÃO, ESTRUTURAÇÃO, CAPACITAÇÃO EM DEFESA CIVIL | BW18: 7004 - PRECATÓRIOS E SENTENÇAS JUDICIÁRIAS | CB18: 7004 - PRECATÓRIOS E SENTENÇAS JUDICIÁRIAS | CC18: 4278 - PROTEÇÃO DO PATRIMÔNIO CULTURAL | CD18: 4319 - INSPEÇÃO E FISCALIZAÇÃO DE PRODUTOS DE ORIGEM ANIMAL | CE18: 2500 - ASSESSORAMENTO E GERENCIAMENTO DE POLÍTICAS PÚBLICAS | CJ18: 4109 - FOMENTO À PARTICIPAÇÃO SOCIAL NO ESTADO DE MINAS GERAIS | CS18: 5002 - GESTÃO DA LEI ESTADUAL DE INCENTIVO À CULTURA | CT18: 1071 - MINAS LIVRE PARA CRESCER | CU18: 4480 - FOMENTO À INCLUSÃO SOCIAL, ACESSIBILIDADE E GARANTIA DE DIREITOS PARA PESSOAS COM DEFICIÊNCIA - PROMAIS | CV18: 2038 - SUPORTE FUNCIONAL PARA ÁREA EDUCACIONAL | CW18: 4097 - CONTADORIA TRANSPARENTE | CX18: 2044 - PRODUÇÃO, MODERNIZAÇÃO E AMPLIAÇÃO DO ACESSO AO ACERVO DO DOMG-E | CY18: 4205 - ESTRUTURACAO, MODELAGEM E GESTAO DE CONCESSOES E PARCERIAS | DA18: 4047 - PROMOÇÃO DAS POLÍTICAS PÚBLICAS DE PROTEÇÃO À FAUNA DOMÉSTICA
S19: 4138 - SUPORTE ÀS AÇÕES DE PREVENÇÃO, MITIGAÇÃO, PREPARAÇÃO E RESPOSTA AOS INCÊNDIOS EM VEGETAÇÃO | X19: 7004 - PRECATÓRIOS E SENTENÇAS JUDICIÁRIAS | Y19: 7004 - PRECATÓRIOS E SENTENÇAS JUDICIÁRIAS | Z19: 7004 - PRECATÓRIOS E SENTENÇAS JUDICIÁRIAS | AD19: 2417 - REMUNERAÇÃO DE PESSOAL ATIVO E ENCARGOS SOCIAIS | AE19: 2417 - REMUNERAÇÃO DE PESSOAL ATIVO E ENCARGOS SOCIAIS | AF19: 2500 - ASSESSORAMENTO E GERENCIAMENTO DE POLÍTICAS PÚBLICAS | AJ19: 7004 - PRECATÓRIOS E SENTENÇAS JUDICIÁRIAS | AK19: 4092 - OFICINAS PEDAGÓGICAS : UM OLHAR AO CIDADÃO! | AM19: 4249 - ASSESSORAMENTO EM POLÍTICAS PÚBLICAS | AY19: 4227 - COMPLEXO DE SAÚDE (FUNED) | AZ19: 4264 - MODERNIZAÇÃO DA REDE DE MONITORAMENTO HIDROLÓGICO DO ESTADO DE MINAS GERAIS | BN19: 2024 - GESTÃO REGIONAL EM SAÚDE | BR19: 7031 - BENEFÍCIOS PREVIDENCIÁRIOS - MPMG | BU19: 4356 - GESTÃO DE DESASTRE | BZ19: 2014 - ASSESSORAMENTO E GESTÃO PREVIDENCIÁRIA | CC19: 4279 - CONSERVAÇÃO E RESTAURAÇÃO DO PATRIMÔNIO CULTURAL PROTEGIDO | CE19: 7004 - PRECATÓRIOS E SENTENÇAS JUDICIÁRIAS | CJ19: 4110 - RECEBIMENTO, ANÁLISE E TRATAMENTO DE MANIFESTAÇÕES | CL19: 1004 - MODERNIZAÇÃO DA IDENTIFICAÇÃO CIVIL E CRIMINAL | CM19: 2061 - EDUCAÇÃO PROFISSIONAL DE SEGURANÇA PÚBLICA | CQ19: 1053 - AGROEXTRATIVISMO | CT19: 1072 - DESENVOLVIMENTO DOS ARRANJOS PRODUTIVOS LOCAIS | CU19: 4551 - POLÍTICA DE APOIO E AUXÍLIO BIOPSICOSSOCIAL AOS CUIDADORES EXCLUSIVOS DE PESSOAS COM DEFICIÊNCIA E TRANSTORNOS DO NEURODESENVOLVIVEMENTO | CV19: 2040 - RECRUTAMENTO E SELEÇÃO DE PESSOAL | CW19: 4098 - CONTADORIA LEGAL | CY19: 4346 - METRO DA RMBH | CZ19: 1054 - PRODUÇÃO DE INFORMAÇÕES E CONHECIMENTOS DE JUSTIÇA E SEGURANÇA PÚBLICA | DB19: 4448 - APRIMORAMENTO DA GOVERNANÇA DE TECNOLOGIA DA INFORMAÇÃO E COMUNICAÇÃO
Q20: 4312 - FORTALECIMENTO DO CONTROLE INTERNO E DAS REDES DE CONTROLE | S20: 4140 - MODERNIZAÇÃO E ESTRUTURAÇÃO DO CORPO DE BOMBEIROS MILITAR DE MINAS GERAIS - REPARAÇÃO BRUMADINHO | U20: 2417 - REMUNERAÇÃO DE PESSOAL ATIVO E ENCARGOS SOCIAIS | AD20: 2500 - ASSESSORAMENTO E GERENCIAMENTO DE POLÍTICAS PÚBLICAS | AE20: 2500 - ASSESSORAMENTO E GERENCIAMENTO DE POLÍTICAS PÚBLICAS | AF20: 7004 - PRECATÓRIOS E SENTENÇAS JUDICIÁRIAS | AK20: 4093 - ATENDIMENTO NA CLÍNICA PSICOPEDAGÓGICA ÉDOUARD CLAPARÉDE | AM20: 4250 - FOMENTO À AVALIAÇÃO DE POLÍTICAS PÚBLICAS | AY20: 4334 - IMPLANTAÇÃO, RECUPERAÇÃO, MODERNIZAÇÃO, MANUTENÇÃO E OPERAÇÃO DE TERMINAIS E ESTAÇÕES DE TRANSPORTE DE PASSAGEIROS | BN20: 2026 - SATISFAÇÃO, RECONHECIMENTO E EDUCAÇÃO NA SAÚDE | BR20: 7032 - BENEFÍCIOS PREVIDENCIÁRIOS - TJMMG | BU20: 4390 - GESTÃO DO RISCO DE DESASTRES | BZ20: 2039 - ASSESSORAMENTO E GESTÃO DAS UNIDADES REGIONAIS DO IPSEMG | CC20: 4281 - VISTORIAS TÉCNICAS NO PATRIMÔNIO CULTURAL | CD20: 4498 - APOIO À AGROINDÚSTRIA FAMILIAR | CJ20: 5005 - PREVENÇÃO E COMBATE AO ASSÉDIO MORAL E SEXUAL | CL20: 4065 - IDENTIFICAÇÃO CIVIL E CRIMINAL | CM20: 2063 - COMUNICAÇÕES OPERACIONAIS | CQ20: 4383 - APOIO ÀS CADEIAS PRODUTIVAS DA AGROPECUÁRIA | CS20: 4322 - GESTÃO, MANUTENÇÃO E MODERNIZAÇÃO DE EQUIPAMENTOS CULTURAIS PARA ATENDIMENTO AO PÚBLICO | CT20: 1073 - FOMENTO AOS PEQUENOS NEGÓCIOS | CV20: 2080 - EDUCAÇÃO INTEGRAL - ENSINO FUNDAMENTAL | CW20: 4103 - GOVERNANÇA DO SISTEMA INTEGRADO UTILIZADO PARA A EXECUÇÃO ORÇAMENTÁRIA, FINANCEIRA, PATRIMONIAL E CONTÁBIL | CX20: 2050 - GESTÃO, OTIMIZAÇÃO E MANUTENÇÃO DOS REGULAMENTOS E SISTEMAS DE COORDENAÇÃO E OPERACIONALIZAÇÃO DAS TRANSFERÊNCIAS DE RECURSOS PARA PARCEIROS ESTADUAIS | CY20: 4156 - GESTÃO DOS PROJETOS ESTRUTURANTES DE MOBILIDADE | CZ20: 4375 - ESTRUTURAÇÃO E MANUTENÇÃO DE UM SISTEMA ESTADUAL DE INTELIGÊNCIA DE SEGURANÇA PÚBLICA EM MINAS GERAIS | DA20: 1074 - TRANSFORMAÇÃO DIGITAL DO SISEMA | DB20: 4450 - DISPONIBILIZAÇÃO DE PROCESSOS E DOCUMENTOS DIGITAIS NO ESTADO
Q21: 4313 - COORDENAÇÃO DAS UNIDADES DESCENTRALIZADAS DA CGE | S21: 4141 - MANUTENÇÃO E AMPLIAÇÃO DO SISTEMA DE TIC PARA POTENCIALIZAÇÃO DO SERVIÇO DE SEGURANÇA CONTRA INCÊNDIO E PÂNICO - REPARAÇÃO BRUMADINHO | U21: 2500 - ASSESSORAMENTO E GERENCIAMENTO DE POLÍTICAS PÚBLICAS | AD21: 7004 - PRECATÓRIOS E SENTENÇAS JUDICIÁRIAS | AE21: 7004 - PRECATÓRIOS E SENTENÇAS JUDICIÁRIAS | AM21: 4251 - PESQUISAS EM POLÍTICAS PÚBLICAS | AZ21: 2500 - ASSESSORAMENTO E GERENCIAMENTO DE POLÍTICAS PÚBLICAS | BN21: 2027 - PROGRAMA ESTADUAL DE MUNICIPALIZAÇÃO | BR21: 7033 - BENEFÍCIOS PREVIDENCIÁRIOS - TCEMG | BZ21: 2417 - REMUNERAÇÃO DE PESSOAL ATIVO E ENCARGOS SOCIAIS | CM21: 4365 - POLICIAMENTO OSTENSIVO GERAL | CQ21: 4384 - FORTALECIMENTO E DESENVOLVIMENTO FLORESTAL | CS21: 4326 - GESTÃO DE ÓRGÃOS COLEGIADOS | CT21: 4474 - ARTESANATO EMPREENDEDOR | CU21: 4186 - PROGRAMA DE PROTEÇÃO A CRIANÇAS E ADOLESCENTES AMEAÇADOS DE MORTE - PPCAAM | CV21: 2081 - ENSINO FUNDAMENTAL - APOIO ADMINISTRATIVO | CW21: 4105 - GESTÃO DE ATIVOS E HAVERES | CX21: 2051 - GESTÃO E OPERACIONALIZAÇÃO DE EMENDAS PARLAMENTARES ESTADUAIS | CZ21: 4376 - INTEGRAÇÃO OPERACIONAL E AÇÕES DE COMANDO E CONTROLE NO ATENDIMENTO DE DENÚNCIAS E CHAMADAS DE EMERGÊNCIA POLICIAL E DE BOMBEIRO | DA21: 2417 - REMUNERAÇÃO DE PESSOAL ATIVO E ENCARGOS SOCIAIS | DB21: 4451 - GESTÃO DOS CANAIS DIGITAIS DE ATENDIMENTO AO CIDADÃO
Q22: 4314 - GOVERNANÇA TIC PARA O CONTROLE INTERNO | U22: 7004 - PRECATÓRIOS E SENTENÇAS JUDICIÁRIAS | AK22: 1023 - CENTRO DE PESQUISA AMBIENTAL E INOVAÇÃO TECNOLÓGICA | BN22: 4458 - PROMOÇÃO E FORTALECIMENTO DA PARTICIPAÇÃO DO CONTROLE SOCIAL NA ÁREA DA SAÚDE | BR22: 7034 - BENEFÍCIOS PREVIDENCIÁRIOS - DEF PUB | BU22: 4354 - GESTÃO DE BENS,SERVIÇOS E LOGISTICA DOS PRÉDIOS GOVERNAMENTAIS | BZ22: 2500 - ASSESSORAMENTO E GERENCIAMENTO DE POLÍTICAS PÚBLICAS | CC22: 2417 - REMUNERAÇÃO DE PESSOAL ATIVO E ENCARGOS SOCIAIS | CD22: 4440 - CERTIFICAÇÃO DE PRODUTOS E DE PROPRIEDADES AGROPECUÁRIAS E AGROINDUSTRIAIS | CJ22: 2417 - REMUNERAÇÃO DE PESSOAL ATIVO E ENCARGOS SOCIAIS | CL22: 2008 - SAÚDE DO SERVIDOR | CM22: 4366 - ESTRUTURAÇÃO E MODERNIZAÇÃO | CQ22: 4420 - MECANIZAÇÃO NO CAMPO | CS22: 4329 - ORQUESTRA FILARMÔNICA DE MINAS GERAIS | CU22: 4270 - FORMAÇÃO E CAPACITAÇÃO DO SISTEMA DE GARANTIA DE DIREITOS | CV22: 2082 - ENSINO FUNDAMENTAL - EDUCAÇÃO DE JOVENS E ADULTOS - EJA | CW22: 4106 - ENDIVIDAMENTO SUSTENTÁVEL | CX22: 2138 - RESERVA PARA ATENDIMENTO DAS EMENDAS PARLAMENTARES INDIVIDUAIS E DE BLOCOS E BANCADAS | CY22: 1035 - REQUALIFICAÇÃO URBANA E AMBIENTAL DO RIBEIRÃO ARRUDAS - PAC ARRUDAS COMPLEMENTO | CZ22: 4377 - MANUTENÇÃO DE MORADIAS FUNCIONAIS PARA SERVIDORES EM SITUAÇÃO DE RISCO | DA22: 2500 - ASSESSORAMENTO E GERENCIAMENTO DE POLÍTICAS PÚBLICAS | DB22: 4452 - GESTÃO DAS UNIDADES DE ATENDIMENTO INTEGRADO - UAI
S23: 4094 - SUPORTE BÁSICO E AVANÇADO DE VIDA | AK23: 1024 - COMPLEXO ESPORTIVO HELENA ANTIPOFF | AM23: 4254 - MANUTENÇÃO DA DIVISÃO TERRITORIAL, CONSTRUÇÃO DE MAPEAMENTO DE MINAS GERAIS E GESTÃO DA IEDE | BR23: 7037 - BENEFÍCIOS PREVIDENCIÁRIOS - SEF | BZ23: 7004 - PRECATÓRIOS E SENTENÇAS JUDICIÁRIAS | CC23: 2500 - ASSESSORAMENTO E GERENCIAMENTO DE POLÍTICAS PÚBLICAS | CJ23: 2500 - ASSESSORAMENTO E GERENCIAMENTO DE POLÍTICAS PÚBLICAS | CL23: 2011 - COLÉGIO ORDEM E PROGRESSO | CM23: 4373 - POLICIAMENTO DE PROXIMIDADE | CT23: 1075 - FONTES RENOVÁVEIS DE ENERGIA | CU23: 4301 - APOIO AOS ÓRGÃOS COLEGIADOS DE CRIANÇAS E ADOLESCENTES | CV23: 2083 - ENSINO FUNDAMENTAL - EDUCAÇÃO ESPECIAL | CW23: 4107 - GERENCIAMENTO DE RISCOS FISCAIS | CY23: 1036 - CONTENÇÃO DE ENCOSTAS EM ÁREAS DE RISCO - PAC ENCOSTAS | CZ23: 4378 - OPERACIONALIZAÇÃO DA POLÍTICA DE INTEGRAÇÃO DA SEGURANÇA PÚBLICA DE MINAS GERAIS | DB23: 4483 - APRIMORAMENTO DA GOVERNANÇA DE TECNOLOGIA DA INFORMAÇÃO E COMUNICAÇÃO
Q24: 2417 - REMUNERAÇÃO DE PESSOAL ATIVO E ENCARGOS SOCIAIS | AM24: 4255 - SISTEMATIZAÇÃO DAS INFORMAÇÕES ESTATÍSTICAS E GEOINFORMAÇÕES DE MG | BN24: 1022 - SAÚDE EM REDE | BR24: 7039 - BENEFÍCIOS PREVIDENCIÁRIOS - ARMVA | BU24: 4335 - SERVIÇO ESPECIAL DE SEGURANÇA GOVERNAMENTAL | CC24: 7004 - PRECATÓRIOS E SENTENÇAS JUDICIÁRIAS | CD24: 4439 - EDUCAÇÃO SANITÁRIA | CL24: 4066 - FORMAÇÃO E CAPACITAÇÃO | CM24: 4374 - POLICIAMENTO ESPECIALIZADO | CQ24: 4397 - CERTIFICA MINAS | CS24: 4336 - ASSESSORIAS TÉCNICAS PARA GESTÃO DE BIBLIOTECAS E MUSEUS | CT24: 1076 - REGULAÇÃO DO GÁS NATURAL E DERIVADOS | CU24: 4321 - ARTICULAÇÃO INSTITUCIONAL E APOIO A SISTEMA DE GARANTIA DE DIREITOS | CV24: 2085 - ENSINO FUNDAMENTAL - PROFISSIONAIS DO MAGISTÉRIO | CX24: 2417 - REMUNERAÇÃO DE PESSOAL ATIVO E ENCARGOS SOCIAIS | CY24: 1038 - REQUALIFICAÇÃO URBANA E AMBIENTAL DO RIBEIRÃO ARRUDAS - PAC FNHIS | CZ24: 4379 - RECRUTAMENTO, SELEÇÃO, FORMAÇÃO, CAPACITAÇÃO E TREINAMENTO DOS PROFISSIONAIS DO SISTEMA DE JUSTIÇA E SEGURANÇA PÚBLICA | DB24: 5003 - ALÔ, MINAS! - IMPLANTAÇÃO DE SINAL DE TELEFONIA CELULAR NAS LOCALIDADES E DISTRITOS DOS MUNICÍPIOS MINEIROS
Q25: 2500 - ASSESSORAMENTO E GERENCIAMENTO DE POLÍTICAS PÚBLICAS | S25: 2500 - ASSESSORAMENTO E GERENCIAMENTO DE POLÍTICAS PÚBLICAS | AK25: 4198 - ATENDIMENTO NO ENSINO TECNICO PROFISSIONALIZANTE | AM25: 4257 - TRANSFORMAÇÃO DIGITAL | BN25: 4125 - FORTALECIMENTO DA ATENÇÃO PRIMÁRIA À SAÚDE | BR25: 7040 - BENEFÍCIOS PREVIDENCIÁRIOS - SEC GERAL | CQ25: 4403 - PLANO QUEIJO MINAS LEGAL | CS25: 4337 - CAPACITAÇÕES TÉCNICO-CULTURAIS | CT25: 1077 - GESTÃO DA POLÍTICA MINERÁRIA | CU25: 4352 - PREVENÇÃO, MONITORAMENTO E ENFRENTAMENTO DAS VIOLÊNCIAS E VIOLAÇÕES CONTRA CRIANÇAS E ADOLESCENTES. | CV25: 2086 - ENSINO MÉDIO - APOIO ADMINISTRATIVO | CW25: 1015 - REVITALIZAÇÃO DAS UNIDADES FAZENDÁRIAS | CX25: 2500 - ASSESSORAMENTO E GERENCIAMENTO DE POLÍTICAS PÚBLICAS | CY25: 1039 - REQUALIFICAÇÃO URBANA E AMBIENTAL E CONTROLE DE CHEIAS DO CÓRREGO FERRUGEM - PAC FERRUGEM
S26: 4556 - AMPLIAÇÃO DE POSTOS DE ABASTECIMENTO PRÓPRIOS DO ESTADO - CBMMG | AK26: 4199 - ENSINO MÉDIO EM TEMPO INTEGRAL - EMTI | BN26: 4126 - PROMOÇÃO À SAÚDE E POLÍTICAS DE EQUIDADE | BR26: 7044 - BENEFÍCIOS PREVIDENCIÁRIOS - CGE | BU26: 2417 - REMUNERAÇÃO DE PESSOAL ATIVO E ENCARGOS SOCIAIS | CD26: 2417 - REMUNERAÇÃO DE PESSOAL ATIVO E ENCARGOS SOCIAIS | CL26: 2417 - REMUNERAÇÃO DE PESSOAL ATIVO E ENCARGOS SOCIAIS | CM26: 2500 - ASSESSORAMENTO E GERENCIAMENTO DE POLÍTICAS PÚBLICAS | CQ26: 4406 - PROMOÇÃO DA CACHAÇA DE ALAMBIQUE | CT26: 1078 - LOGÍSTICA E MOBILIDADE DO FUTURO | CV26: 2088 - ENSINO MÉDIO - EDUCAÇÃO DE JOVENS E ADULTOS - EJA | CW26: 4079 - GESTÃO EFICENTE E TRANSPARÊNCIA DO CONTENCIOSO ADMINISTRATIVO TRIBUTÁRIO | CY26: 1040 - REQUALIFICAÇÃO URBANA E AMBIENTAL E CONTROLE DE CHEIAS DO CÓRREGO FERRUGEM - PAC FERRUGEM (VALE) | CZ26: 4437 - APOIO À REDE COMPLEMENTAR DE SUPORTE SOCIAL NA ATENÇÃO AO DEPENDENTE QUÍMICO | DB26: 4380 - AUTOMATIZA.MG
S27: 7007 - PROVENTOS DE INATIVOS MILITARES | AM27: 2417 - REMUNERAÇÃO DE PESSOAL ATIVO E ENCARGOS SOCIAIS | BN27: 4127 - ESTRUTURAÇÃO DA ATENÇÃO PRIMÁRIA | BR27: 7046 - BENEFÍCIOS PREVIDENCIÁRIOS - UNIMONTES | BU27: 2500 - ASSESSORAMENTO E GERENCIAMENTO DE POLÍTICAS PÚBLICAS | CD27: 2500 - ASSESSORAMENTO E GERENCIAMENTO DE POLÍTICAS PÚBLICAS | CL27: 2500 - ASSESSORAMENTO E GERENCIAMENTO DE POLÍTICAS PÚBLICAS | CM27: 7007 - PROVENTOS DE INATIVOS MILITARES | CQ27: 4407 - DIGA SIM AO SERVIÇO DE INSPEÇÃO MUNICIPAL - SIM | CS27: 4338 - CONSERVAÇÃO PREVENTIVA E CURATIVA, RESTAURAÇÃO, AQUISIÇÃO E GESTÃO TÉCNICA DE ACERVOS | CT27: 1079 - PROMOÇÃO DO COMÉRCIO EXTERIOR MINEIRO | CU27: 4153 - ASSESSORAMENTO DAS UNIDADES DE ATENDIMENTO AO TRABALHADOR | CV27: 2089 - ENSINO MÉDIO - EDUCAÇÃO ESPECIAL | CW27: 4081 - RECEITA ESTADUAL MAIS JUSTA | CY27: 1041 - REQUALIFICAÇÃO URBANA E AMBIENTAL E DE CONTROLE DE CHEIAS DO CÓRREGO RIACHO DAS PEDRAS - PAC RIACHO | CZ27: 4438 - DESCENTRALIZAÇÃO DA POLÍTICA SOBRE DROGAS | DB27: 4453 - PROMOÇÃO DA INOVAÇÃO NA GESTÃO PÚBLICA
S28: 7010 - BENEFÍCIOS ASSISTENCIAIS | AK28: 4233 - MUSEU HELENA ANTIPOFF | AM28: 2500 - ASSESSORAMENTO E GERENCIAMENTO DE POLÍTICAS PÚBLICAS | BR28: 7047 - BENEFÍCIOS PREVIDENCIÁRIOS - IPEM/MG | CD28: 7004 - PRECATÓRIOS E SENTENÇAS JUDICIÁRIAS | CL28: 7010 - BENEFÍCIOS ASSISTENCIAIS | CM28: 7010 - BENEFÍCIOS ASSISTENCIAIS | CQ28: 4408 - MINAS + VERDE | CS28: 4339 - ORGANIZAÇÃO, DESCRIÇÃO E PRESERVAÇÃO DE ACERVOS ARQUIVÍSTICOS | CT28: 1081 - INVISTA EM MINAS - PROMOÇÃO DE INVESTIMENTOS | CU28: 4154 - FOMENTO PARA ECONOMIA POPULAR SOLIDÁRIA E PROMOÇÃO DA INCLUSÃO PRODUTIVA | CV28: 2090 - ENSINO MÉDIO - PROFISSIONAIS DO MAGISTÉRIO | CW28: 4082 - RECEITA ESTADUAL EFICIENTE | CY28: 1042 - REQUALIFICAÇÃO URBANA E AMBIENTAL E DE CONTROLE DE CHEIAS DO CÓRREGO RIACHO DAS PEDRAS (VALE) | DB28: 4454 - GESTÃO DOS PROJETOS ESTRATÉGICOS
AK29: 4234 - FORMAÇÃO NA PERSPECTIVA ANTIPOFFIANA | AM29: 7004 - PRECATÓRIOS E SENTENÇAS JUDICIÁRIAS | BN29: 4129 - APOIO E FORTALECIMENTO DA REDE DE CUIDADO À PESSOA COM DEFICIÊNCIA | BR29: 7048 - BENEFÍCIOS PREVIDENCIÁRIOS - PCMG | BU29: 0000 - PROJETO CONVIVÊNCIA COM A SECA E ESTIAGEM | CS29: 4342 - ASSESSORIAS TÉCNICAS EM GESTÃO DE DOCUMENTOS, CRIAÇÃO E MANUTENÇÃO DE ARQUIVOS PÚBLICOS | CT29: 1090 - IMPLEMENTAÇÃO DA POLÍTICA DE DESESTATIZAÇÃO | CU29: 4157 - FOMENTO À INCLUSÃO PRODUTIVA DE MULHERES | CV29: 2092 - EDUCAÇÃO INFANTIL | CW29: 4083 - RECEITA ESTADUAL DIGITAL | CY29: 4261 - DESENVOLVIMENTO DA INFRAESTRUTURA PÚBLICA NO ESTADO DE MINAS GERAIS | CZ29: 4441 - ADEQUAÇÃO, MANUTENÇÃO E DESENVOLVIMENTO DO ATENDIMENTO SOCIOEDUCATIVO
BN30: 4130 - APOIO E FORTALECIMENTO DA REDE DE ATENÇÃO PSICOSSOCIAL | BR30: 7049 - BENEFÍCIOS PREVIDENCIÁRIOS - SEPLAG | BU30: 0000 - OPERAÇÃO CAMINHÃO PIPA | CQ30: 4399 - GARANTIA SAFRA | CT30: 1091 - INTEGRAÇÃO DAS CADEIAS PRODUTIVAS | CV30: 2093 - EDUCAÇÃO INTEGRAL - ENSINO MÉDIO | CW30: 4085 - RECEITA ESTADUAL MODERNIZADA | CY30: 4262 - FOMENTO À INFRAESTRUTURA PÚBLICA MUNICIPAL | CZ30: 4442 - FORMAÇÃO EDUCACIONAL E PROFISSIONAL DO ADOLESCENTE EM CUMPRIMENTO DE MEDIDA SOCIOEDUCATIVA | DB30: 4461 - RECUPERAÇÃO E COMPENSAÇÃO DOS DANOS EM FUNÇÃO DO DESASTRE MINERÁRIO DA SAMARCO EM MARIANA
AK31: 2130 - MELHORIA NA ALIMENTAÇÃO | BN31: 4131 - ATENÇÃO ESPECIALIZADA AMBULATORIAL | BR31: 7051 - BENEFÍCIOS PREVIDENCIÁRIOS - SEGOV | CQ31: 4400 - AGRO SEGURO | CS31: 2417 - REMUNERAÇÃO DE PESSOAL ATIVO E ENCARGOS SOCIAIS | CT31: 4499 - GOVERNANÇA DAS EMPRESAS ESTATAIS | CU31: 4158 - QUALIFICAÇÃO PROFISSIONAL | CV31: 2094 - EDUCAÇÃO PROFISSIONAL | CY31: 4265 - DESENVOLVIMENTO DA INFRAESTRUTURA GOVERNAMENTAL | CZ31: 4443 - ATENDIMENTO À SAÚDE DO ADOLESCENTE EM CONFLITO COM A LEI | DB31: 4462 - RECUPERAÇÃO E COMPENSAÇÃO DOS DANOS EM FUNÇÃO DO DESASTRE MINERÁRIO DA VALE S.A EM BRUMADINHO
BN32: 4132 - APOIO E FORTALECIMENTO DA REDE DE ATENÇÃO À SAÚDE BUCAL | BR32: 7052 - BENEFÍCIOS PREVIDENCIÁRIOS - SEDESE | CS32: 2500 - ASSESSORAMENTO E GERENCIAMENTO DE POLÍTICAS PÚBLICAS | CV32: 2095 - DESENVOLVIMENTO E CAPACITAÇÃO DE PESSOAL | CW32: 2417 - REMUNERAÇÃO DE PESSOAL ATIVO E ENCARGOS SOCIAIS
AK33: 2500 - ASSESSORAMENTO E GERENCIAMENTO DE POLÍTICAS PÚBLICAS | BR33: 7055 - BENEFÍCIOS PREVIDENCIÁRIOS - OGE | CQ33: 4393 - GESTÃO DE BARRAGENS | CT33: 4449 - APOIO À GESTÃO DE PROJETOS DE INOVAÇÃO TECNOLÓGICA | CU33: 4364 - ALIMENTAÇÃO COMPLEMENTAR NA PRIMEIRA INFÂNCIA | CV33: 2096 - PROFISSIONAIS DO ÓRGÃO CENTRAL | CW33: 2500 - ASSESSORAMENTO E GERENCIAMENTO DE POLÍTICAS PÚBLICAS | CY33: 4290 - MELHORIA DA MOBILIDADE E INFRAESTRUTURA DE TRANSPORTES EM MINAS GERAIS | CZ33: 2417 - REMUNERAÇÃO DE PESSOAL ATIVO E ENCARGOS SOCIAIS | DB33: 1085 - ABRIGOS E CAMINHOS NA CA
AK34: 7004 - PRECATÓRIOS E SENTENÇAS JUDICIÁRIAS | BN34: 4133 - ATENDIMENTO ÀS MEDIDAS JUDICIAIS | BR34: 7056 - BENEFÍCIOS PREVIDENCIÁRIOS - SEDE | CQ34: 4394 - PROJETO JAÍBA | CT34: 4472 - APOIO À GESTÃO DE PROJETOS DE PESQUISA E TECNOLOGIA | CU34: 4367 - CAPACITA MINAS PRIMEIRA INFÂNCIA | CV34: 2097 - PROFISSIONAIS DAS SUPERINTENDÊNCIAS REGIONAIS DE ENSINO - SRE | CY34: 4291 - PESQUISA E DESENVOLVIMENTO TECNOLÓGICO EM TRANSPORTES, LOGÍSTICA E MOBILIDADE | CZ34: 2500 - ASSESSORAMENTO E GERENCIAMENTO DE POLÍTICAS PÚBLICAS | DB34: 4465 - GESTÃO DA INFRAESTRUTURA DA CIDADE ADMINISTRATIVA
BN35: 4134 - ACESSO DE URGÊNCIA E EMERGÊNCIA | BR35: 7058 - BENEFÍCIOS PREVIDENCIÁRIOS - SEAPA | CQ35: 4396 - RECUPERAÇÃO INTEGRADA DA CAPACIDADE PRODUTIVA DAS BACIAS | CU35: 4368 - POLÍTICA ESTADUAL PARA REGISTRO CIVIL DE NASCIMENTO | CV35: 2098 - PROFISSIONAIS DO CONSELHO ESTADUAL DE EDUCAÇÃO | CY35: 4292 - GESTÃO DE AEROPORTOS REGIONAIS EM MINAS GERAIS | DB35: 4466 - GESTÃO DE TECNOLOGIA DA INFORMAÇÃO E COMUNICAÇÃO (TIC) DA CIDADE ADMINISTRATIVA
BN36: 4135 - ACESSO ELETIVO | BR36: 7059 - BENEFÍCIOS PREVIDENCIÁRIOS - SECULT | CQ36: 4398 - IRRIGA MINAS - AGRICULTURA IRRIGADA SUSTENTÁVEL | CT36: 2417 - REMUNERAÇÃO DE PESSOAL ATIVO E ENCARGOS SOCIAIS | CV36: 2099 - TRILHAS DE FUTURO - EDUCADORES | CY36: 4501 - TRANSPORTE FERROVIÁRIO | DB36: 4467 - GESTÃO DOS SERVIÇOS OPERACIONAIS E LOGÍSTICOS DA CIDADE ADMINISTRATIVA
BN37: 4136 - SERVIÇOS MÓVEIS DE URGÊNCIA E EMERGÊNCIA | BR37: 7060 - BENEFÍCIOS PREVIDENCIÁRIOS - UEMG | CQ37: 4419 - ESTRADAS E INFRAESTRUTURA RURAL | CT37: 2500 - ASSESSORAMENTO E GERENCIAMENTO DE POLÍTICAS PÚBLICAS | CU37: 4163 - PROMOÇÃO DOS JOGOS DO INTERIOR DE MINAS | CV37: 4504 - RECRUTAMENTO E SELEÇÃO DE PESSOAL
BN38: 4137 - PROGRAMAÇÃO, CONTRATAÇÃO E PROCESSAMENTO DE SERVIÇOS DE SAÚDE | BR38: 7061 - BENEFÍCIOS PREVIDENCIÁRIOS - SEINFRA | CU38: 4164 - PROJETOS VIABILIZADOS PELA LEI ESTADUAL DE INCENTIVO AO ESPORTE | CY38: 1055 - PROJETOS, CONSTRUÇÕES, REFORMAS E AMPLIAÇÕES DE UNIDADES DE SEGURANÇA PÚBLICA | DB38: 4463 - PARCERIAS COM ORGANIZAÇÕES DA SOCIEDADE CIVIL DE INTERESSE PÚBLICO - OSCIP E ORGANIZAÇÕES SOCIAIS - OS.
BR39: 7063 - BENEFÍCIOS PREVIDENCIÁRIOS - SEMAD | CQ39: 4386 - AGRODADOS | CU39: 4165 - GESTÃO DO ICMS ESPORTIVO | CV39: 2100 - APOIO AOS PROGRAMAS DE ALIMENTAÇÃO ESCOLAR | DB39: 4464 - GESTÃO DO PROCESSO DE ELABORAÇÃO E ACOMPANHAMENTO DO PLANEJAMENTO E ORÇAMENTO ESTADUAL
BN40: 1021 - VACINA MAIS MINAS | BR40: 7064 - BENEFÍCIOS PREVIDENCIÁRIOS - PMMG | CQ40: 4391 - AGRITECH | CU40: 4166 - PROMOÇÃO DO ESPORTE EDUCACIONAL COMO INSTRUMENTO DE DESENVOLVIMENTO SOCIAL | CV40: 2101 - PROGRAMA ESTADUAL DE ALIMENTAÇÃO ESCOLAR - PEAE | CY40: 2417 - REMUNERAÇÃO DE PESSOAL ATIVO E ENCARGOS SOCIAIS
BN41: 4143 - ASSESSORAMENTO E GERENCIAMENTO DE POLÍTICAS DE VIGILÂNCIA EM SAÚDE | BR41: 7065 - BENEFÍCIOS PREVIDENCIÁRIOS - CBMMG | CU41: 4167 - APOIO À GESTÃO ESPORTIVA | CV41: 2102 - PROGRAMA NACIONAL DE ALIMENTAÇÃO ESCOLAR - PNAE | CY41: 2500 - ASSESSORAMENTO E GERENCIAMENTO DE POLÍTICAS PÚBLICAS | DB41: 4470 - AMPLIAÇÃO DA CENTRALIZAÇÃO DAS COMPRAS E CONTRATAÇÕES
BN42: 4144 - VIGILÂNCIA DE CONDIÇÕES CRÔNICAS | BR42: 7088 - BENEFÍCIOS PREVIDENCIÁRIOS - IMA | CQ42: 4405 - APOIO AO JOVEM RURAL | CU42: 4168 - PROMOÇÃO DOS JOGOS ESCOLARES DE MINAS GERAIS | DB42: 4473 - MODERNIZAÇÃO EM GESTÃO DE COMPRAS
BN43: 4145 - VIGILÂNCIA DE DOENÇAS TRANSMISSÍVEIS E IMUNIZAÇÃO | BR43: 7089 - BENEFÍCIOS PREVIDENCIÁRIOS - FHA | CU43: 4169 - BOLSA ATLETA E BOLSA TÉCNICO | CV43: 2104 - ATENDIMENTO AS INSTITUIÇÕES PÚBLICAS DE ENSINO SUPERIOR
BN44: 4146 - VIGILÂNCIA EM SAÚDE AMBIENTAL E SAÚDE DO TRABALHADOR | BR44: 7091 - BENEFÍCIOS PREVIDENCIÁRIOS - FUCAM | CQ44: 2417 - REMUNERAÇÃO DE PESSOAL ATIVO E ENCARGOS SOCIAIS | CU44: 4170 - APOIO À REALIZAÇÃO DE AÇÕES ESPORTIVAS | DB44: 1084 - MODERNIZAÇÃO DA GESTÃO DOS IMÓVEIS DO ESTADO DE MINAS GERAIS
BN45: 4147 - VIGILÂNCIA SANITÁRIA | BR45: 7094 - BENEFÍCIOS PREVIDENCIÁRIOS - FAOP | CQ45: 2500 - ASSESSORAMENTO E GERENCIAMENTO DE POLÍTICAS PÚBLICAS | CU45: 4514 - PROMOÇÃO DO ESPORTE DE PARTICIPAÇÃO E RENDIMENTO COMO INSTRUMENTO DE DESENVOLVIMENTO SOCIAL | CV45: 1094 - GESTAO PELA APRENDIZAGEM | DB45: 4485 - GESTÃO DOS PROCESSOS DE LOGÍSTICA CORPORATIVA
BR46: 7096 - BENEFÍCIOS PREVIDENCIÁRIOS - FCS | CV46: 2105 - PROJETO SOMAR | DB46: 4486 - GESTÃO DA DESTINAÇÃO DE IMÓVEIS
BN47: 4148 - ABASTECIMENTO DE MEDICAMENTOS | BR47: 7104 - BENEFÍCIOS PREVIDENCIÁRIOS - IEPHA | CU47: 4171 - IMPLEMENTAÇÃO E MANUTENÇÃO DOS CENTROS DE REFERÊNCIA EM DIREITOS HUMANOS | CV47: 2107 - AVALIAÇÕES EDUCACIONAIS | DB47: 4487 - GESTÃO E DISPONIBILIZAÇÃO DOS SISTEMAS CORPORATIVOS DE GESTÃO LOGÍSTICA E PATRIMONIAL
BN48: 4149 - POLÍTICAS DE ASSISTÊNCIA FARMACÊUTICA | BR48: 7105 - BENEFÍCIOS PREVIDENCIÁRIOS - TV MINAS | CU48: 4173 - PROGRAMA DE PROTEÇÃO A VÍTIMAS E TESTEMUNHAS AMEAÇADAS - PROVITA | CV48: 2127 - ORGANIZAÇÃO E FUNCIONAMENTO ESCOLAR
BR49: 7205 - BENEFÍCIOS PREVIDENCIÁRIOS - DEER | CU49: 4174 - PROMOÇÃO, PROTEÇÃO E REPARAÇÃO DE DIREITOS HUMANOS | DB49: 4491 - APREENSÃO E LIBERAÇÃO DE VEÍCULOS
BN50: 4490 - FILHOS DE MINAS | BR50: 7209 - BENEFÍCIOS PREVIDENCIÁRIOS - FUNED | CU50: 4176 - PROGRAMA DE PROTEÇÃO AOS DEFENSORES DE DIREITOS HUMANOS - PPDDH | CV50: 1032 - MODALLIDADES E TEMÁTICAS ESPECIAIS | DB50: 4492 - FISCALIZAÇÃO, PREVENÇÃO E CONTROLE DE INFRAÇÕES DE TRÂNSITO
BR51: 7225 - BENEFÍCIOS PREVIDENCIÁRIOS - FHEMIG | CU51: 4177 - PROGRAMA DE PROTEÇÃO A CRIANÇAS E ADOLESCENTES AMEAÇADOS DE MORTE - PPCAAM | CV51: 1033 - MODALIDADES E TEMÁTICAS ESPECIAIS | DB51: 4494 - REGISTRO DE CONDUTORES
BN52: 2110 - DESENVOLVIMENTO DAS AÇÕES DE SAÚDE NO ÂMBITO DA ESCOLA DE SAÚDE PÚBLICA DO ESTADO DE MINAS GERAIS- ESP | BR52: 7312 - BENEFÍCIOS PREVIDENCIÁRIOS - HEMOMINAS | CU52: 4178 - MANUTENÇÃO E APOIO AOS ÓRGÃOS COLEGIADOS DE DIREITOS HUMANOS | CV52: 1092 - DESENVOLVIMENTO DO ESPORTE ESCOLAR | DB52: 4495 - REGISTRO DE VEÍCULOS
BN53: 2111 - DESENVOLVIMENTO DAS AÇÕES DE SAÚDE NO ÂMBITO DA FUNDAÇÃO HOSPITALAR DO ESTADO DE MINAS GERAIS- FHEMIG | BR53: 7428 - BENEFÍCIOS PREVIDENCIÁRIOS - FEAM | CU53: 4181 - OPERACIONALIZAÇÃO DOS SERVIÇOS DE TRADUÇÃO E INTERPRETAÇÃO DE LIBRAS | CV53: 1093 - PLANO DE RECOMPOSIÇAO DAS APRENDIZAGENS - PRA | DB53: 4496 - ATENDIMENTO E TRANSFORMAÇÃO DE SERVIÇOS DE TRÂNSITO
BN54: 2112 - DESENVOLVIMENTO DAS AÇÕES DE SAÚDE NO ÂMBITO DA SECRETARIA DE ESTADO DE JUSTIÇA E SEGURANÇA PÚBLICA - SEJUSP | BR54: 7473 - BENEFÍCIOS PREVIDENCIÁRIOS - IEF | CU54: 4182 - ARTICULAÇÃO INSTITUCIONAL, MANUTENÇÃO DE EQUIPAMENTOS E POLÍTICAS DE DIREITOS HUMANOS | CV54: 2116 - PROJETO SAÚDE NA ESCOLA
BN55: 2115 - DESENVOLVIMENTO DAS AÇÕES DE SAÚDE NO ÂMBITO DO CORPO DE BOMBEIROS MILITAR DO ESTADO DE MINAS GERAIS | BR55: 7484 - BENEFÍCIOS PREVIDENCIÁRIOS - IGAM | CU55: 4183 - FOMENTO À INCLUSÃO SOCIAL, ACESSIBILIDADE E GARANTIA DE DIREITOS PARA PESSOAS COM DEFICIÊNCIA | CV55: 2117 - PROJETO SAÚDE EM CICLO | DB55: 2417 - REMUNERAÇÃO DE PESSOAL ATIVO E ENCARGOS SOCIAIS
BN56: 2135 - DESENVOLVIMENTO DAS AÇÕES DE SAÚDE NO ÂMBITO DA FUNDAÇÃO CENTRO DE HEMATOLOGIA E HEMOTERAPIA DE MINAS GERAIS- HEMOMINAS | BR56: 7529 - BENEFÍCIOS PREVIDENCIÁRIOS - JUCEMG | CV56: 2118 - TRILHAS DE FUTURO - ESTUDANTES | DB56: 2500 - ASSESSORAMENTO E GERENCIAMENTO DE POLÍTICAS PÚBLICAS
BN57: 2136 - DESENVOLVIMENTO DAS AÇÕES DE SAÚDE NO ÂMBITO DA FUNDAÇÃO EZEQUIEL DIAS- FUNED | BR57: 7586 - BENEFÍCIOS PREVIDENCIÁRIOS - UTRAMIG | CU57: 2134 - ASSESSORAMENTO À POLÍTICA ESTADUAL DE ASSISTÊNCIA SOCIAL | CV57: 2119 - DESENVOLVIMENTO DA EDUCAÇÃO DE JOVENS E ADULTOS - EJA
BN58: 2137 - DESENVOLVIMENTO DAS AÇÕES DE SAÚDE NO ÂMBITO DA ADMINISTRAÇÃO PÚBLICA ESTADUAL | BR58: 7617 - BENEFÍCIOS PREVIDENCIÁRIOS - LEMG | CV58: 2120 - DESENVOLVIMENTO DA EDUCAÇÃO ESPECIAL
BR59: 7722 - BENEFÍCIOS PREVIDENCIÁRIOS - FJP | CU59: 4184 - APOIO AOS MUNICÍPIOS NA IMPLEMENTAÇÃO DA POLÍTICA HABITACIONAL E NA ELABORAÇÃO E REVISÃO DE PLANOS LOCAIS DE HABITAÇÃO DE INTERESSE SOCIAL (PLHIS) | CV59: 2122 - DESENVOLVIMENTO DO ENSINO FUNDAMENTAL
BN60: 2034 - REMUNERAÇÃO DE PESSOAL ATIVO E ENCARGOS SOCIAIS | BR60: 7725 - BENEFÍCIOS PREVIDENCIÁRIOS - IPSEMG | CU60: 4185 - APOIO À PRODUÇÃO E À AQUISIÇÃO DE UNIDADES HABITACIONAIS | CV60: 2123 - ESCOLA DE FORMAÇÃO PROFISSIONAL
BN61: 2087 - RESERVA PARA ATENDIMENTO DAS EMENDAS PARLAMENTARES INDIVIDUAIS VINCULADAS ÀS AÇÕES E SERVIÇOS PÚBLICOS DE SAÚDE | BR61: 7840 - BENEFÍCIOS PREVIDENCIÁRIOS - IPSM | CU61: 4388 - REFORMA E MELHORIAS DE UNIDADES HABITACIONAIS | CV61: 4505 - DESENVOLVIMENTO DA EDUCAÇÃO QUILOMBOLA
BN62: 2417 - REMUNERAÇÃO DE PESSOAL ATIVO E ENCARGOS SOCIAIS | BR62: 7939 - BENEFÍCIOS PREVIDENCIÁRIOS - IDENE | CV62: 4506 - DESENVOLVIMENTO DA EDUCAÇÃO INDIGENA
BN63: 2500 - ASSESSORAMENTO E GERENCIAMENTO DE POLÍTICAS PÚBLICAS | BR63: 7957 - BENEFÍCIOS PREVIDENCIÁRIOS - SEE | CU63: 2033 - DESENVOLVIMENTO DO SISTEMA DE SEGURANÇA ALIMENTAR E NUTRICIONAL EM MINAS GERAIS - SISAN MG | CV63: 4507 - DESENVOLVIMENTO DA EDUCAÇÃO DO CAMPO
BR64: 7959 - BENEFÍCIOS PREVIDENCIÁRIOS - SES | CU64: 4196 - APOIO, FOMENTO E ARTICULAÇÃO DE AÇÕES, PROJETOS E PROGRAMAS RELATIVOS À TEMÁTICA DE SEGURANÇA ALIMENTAR E NUTRICIONAL SUSTENTÁVEL | CV64: 4508 - DESENVOLVIMENTO DA EDUCAÇÃO INTEGRAL
CU65: 4197 - APOIO ÀS AÇÕES DESENVOLVIDAS PELO CONSELHO DE SEGURANÇA ALIMENTAR E NUTRICIONAL SUSTENTÁVEL DE MINAS GERAIS (CONSEA-MG) | CV65: 4509 - DESENVOLVIMENTO DA EDUCAÇÃO PRISIONAL E SOCIOEDUCATIVA
CV66: 4511 - DESENVOLVIMENTO DO ENSINO MEDIO
CU67: 2035 - APOIO E COORDENAÇÃO DE POLÍTICAS INTERSETORIAIS DE DESENVOLVIMENTO SOCIAL NO CONTEXTO DO PROGRAMA PERCURSOS GERAIS: TRAJETÓRIA PARA AUTONOMIA | CV67: 4512 - DESENVOLVIMENTO DA EDUCAÇÃO PROFISSIONAL
CU68: 4412 - ACESSO AO TRABALHO E À RENDA
CU69: 4416 - RAÍZES DE MINAS | CV69: 2124 - PREVENÇÃO À VIOLÊNCIA E SEGURANÇA NAS ESCOLAS
CU70: 4418 - REFORMA E MELHORIAS DE UNIDADES HABITACIONAIS | CV70: 2125 - PREVENÇÃO ÀS CHUVAS
CV71: 2126 - RENOVAÇÃO DE MOBILIÁRIO E/OU EQUIPAMENTO
CU72: 2036 - DESENVOLVIMENTO DE ESTUDOS, PESQUISAS, FERRAMENTAS DE MONITORAMENTO E AVALIAÇÃO EM DESENVOLVIMENTO SOCIAL E DE PREVENÇÃO E RESPOSTA À SITUAÇÕES DE CALAMIDADE PÚBLICA E DESASTRE | CV72: 4510 - ATENDIMENTO ÀS ESCOLAS FAMÍLIA AGRÍCOLA
CU73: 2037 - FOMENTO A INOVAÇÃO E APRIMORAMENTO DE PROJETOS DE DESENVOLVIMENTO SOCIAL | CV73: 4517 - ACESSIBILIDADE E IMPLEMENTAÇÃO DE PROJETOS DE INCÊNDIO NAS UNIDADES ESCOLARES
CU74: 4204 - APOIO TÉCNICO AOS MUNICÍPIOS PARA PROMOÇÃO DO DESENVOLVIMENTO REGIONAL | CV74: 4519 - MÃOS À OBRA
CV75: 4520 - APOIO A GESTÃO DE INFRAESTRUTURA EDUCACIONAL
CU76: 4414 - ENFRENTAMENTO À VIOLÊNCIA DOMÉSTICA E INTRAFAMILIAR CONTRA AS MULHERES | CV76: 4521 - CONECTIVIDADE ESCOLAR
CU77: 4415 - PROMOÇÃO, DEFESA E GARANTIA DOS DIREITOS DAS MULHERES | CV77: 4522 - RENOVAÇÃO DA REDE LÓGICA E ELÉTRICA E IMPLEMENTAÇÃO DE ENERGIA ALTERNATIVA
CU78: 4542 - ENFRENTAMENTO À VIOLÊNCIA POLÍTICA CONTRA AS MULHERES | CV78: 4523 - REALIZAÇÃO DE OBRAS ESTRUTURAIS
CV79: 4524 - MANUTENÇÃO PREDIAL
CU80: 2076 - GESTÃO E MONITORAMENTO DE CONVÊNIOS E PARCERIAS | CV80: 4525 - ATENDIMENTO AS INSTITUICOES PUBLICAS DE ENSINO SUPERIOR
CU81: 2079 - APOIO FINANCEIRO E MATERIAL ÀS INSTITUIÇÕES NA PROMOÇÃO DO DESENVOLVIMENTO SOCIAL | CV81: 4527 - CUSTEIO DAS UNIDADES ESCOLARES
CU82: 2417 - REMUNERAÇÃO DE PESSOAL ATIVO E ENCARGOS SOCIAIS
CV83: 2064 - GESTÃO DAS SUPERINTENDÊNCIAS REGIONAIS DE ENSINO
CU84: 2417 - REMUNERAÇÃO DE PESSOAL ATIVO E ENCARGOS SOCIAIS | CV84: 2128 - GESTÃO DO ÓRGÃO CENTRAL
CU85: 2500 - ASSESSORAMENTO E GERENCIAMENTO DE POLÍTICAS PÚBLICAS | CV85: 2129 - OPERACIONALIZAÇÃO DAS AÇÕES DOS CONSELHOS
CV87: 4099 - FORMAÇÃO CIDADÃ
CV88: 4531 - EDUCAÇÃO QUILOMBOLA
CV89: 4532 - EDUCAÇÃO INDIGENA
CV90: 4533 - EDUCAÇÃO DO CAMPO
CV91: 4534 - EDUCAÇÃO DAS RELAÇÕES ÉTNICO-RACIAIS
CV92: 4536 - MOBILIZAÇÃO DAS JUVENTUDES
CV93: 4537 - ENSINO DO SISTEMA PRISIONAL E SOCIOEDUCATIVO
CV94: 4538 - ATENDIMENTO ÀS ESCOLAS FAMÍLIA AGRÍCOLA
CV95: 4540 - PROGRAMA CONVIVÊNCIA DEMOCRÁTICA
CV97: 4543 - PROGRAMA MÃOS DADAS
CV98: 4545 - PROGRAMA DE FORTALECIMENTO DAS ESCOLAS MUNICIPAIS
CV99: 4546 - APOIO AO TRANSPORTE ESCOLAR
... CV101: 4548 - REGIME DE COLABORAÇÃO ESTADO-MUNICÍPIO NA ÁREA EDUCACIONAL

Sheet AGRUPAMENTO
A1: UO_COD | B1: nome | C1: EI | D1: concatagrup | E1: AGRUPAMENTO | G1: 3983 - SERVICOS DE REALIZACAO DE PROCESSO DE CERTIFICACAO OCUPACIONAL | H1: 4501 | I1: 8201 | K1: Elementos itens | N1: SEINFRA | O1: FPP
A2: 1071 | B2: GMG | C2: 0810 - SALÁRIO-FAMÍLIA | D2: =CONCATENATE(B2,LEFT(C2,4)) -> GMG0810 | E2: Auxílios diversos (transp alim funeral e etc) | K2: 0802 - AUXILIO-FUNERAL
A3: 1071 | B3: GMG | C3: 1401 - DIARIAS CIVIL | D3: =CONCATENATE(B3,LEFT(C3,4)) -> GMG1401 | E3: Diárias e viagens | K3: 0803 - AUXILIO-CRECHE OU ASSISTENCIA PRE-ESCOLAR
A4: 1071 | B4: GMG | C4: 1501 - DIARIAS MILITAR | D4: =CONCATENATE(B4,LEFT(C4,4)) -> GMG1501 | E4: Diárias e viagens | K4: 0805 - AUXILIO-NATALIDADE
A5: 1071 | B5: GMG | C5: 3001 - ARTIGOS PARA CONFECCAO E VESTUARIO | D5: =CONCATENATE(B5,LEFT(C5,4)) -> GMG3001 | E5: Material de consumo | K5: 0809 - AUXILIO RECLUSAO
A6: 1071 | B6: GMG | C6: 3002 - ARTIGOS PARA ESPORTE | D6: =CONCATENATE(B6,LEFT(C6,4)) -> GMG3002 | E6: Material de consumo | K6: 0810 - SALARIO FAMILIA
A7: 1071 | B7: GMG | C7: 3003 - UTENSILIOS PARA COPA, REFEITORIO E COZINHA | D7: =CONCATENATE(B7,LEFT(C7,4)) -> GMG3003 | E7: Material de consumo | K7: 0811 - PECULIO E SEGURO COLETIVO
A8: 1071 | B8: GMG | C8: 3004 - MATERIAL GRAFICO E IMPRESSOS | D8: =CONCATENATE(B8,LEFT(C8,4)) -> GMG3004 | E8: Material de consumo | K8: 0899 - AUXILIOS DIVERSOS
A9: 1071 | B9: GMG | C9: 3005 - MATERIAL PARA ESCRITORIO | D9: =CONCATENATE(B9,LEFT(C9,4)) -> GMG3005 | E9: Material de consumo | K9: 1314 - OBRIGACAO PATRONAL - ENCARGOS POR PAGAMENTO EM ATRASO
A10: 1071 | B10: GMG | C10: 3008 - PRODUTOS ALIMENTICIOS | D10: =CONCATENATE(B10,LEFT(C10,4)) -> GMG3008 | E10: Material de consumo | K10: 1317 - INSS - DEMAIS DESPESAS
A11: 1071 | B11: GMG | C11: 3009 - FORRAGENS E OUTROS ALIMENTOS PARA ANIMAIS | D11: =CONCATENATE(B11,LEFT(C11,4)) -> GMG3009 | E11: Material de consumo | K11: 1401 - DIARIAS - CIVIL
A12: 1071 | B12: GMG | C12: 3010 - MATERIAL MEDICO E HOSPITALAR | D12: =CONCATENATE(B12,LEFT(C12,4)) -> GMG3010 | E12: Serviços de saúde e medicamentos | K12: 1501 - DIARIAS - MILITAR
A13: 1071 | B13: GMG | C13: 3013 - MATERIAIS DE LABORATORIO E PRODUTOS QUIMICOS EM GERAL | D13: =CONCATENATE(B13,LEFT(C13,4)) -> GMG3013 | E13: Material de consumo | K13: 1502 - DIARIAS MILITAR - SCDP
... A267: 1191 | B267: SEF | C267: 3011 - MATERIAL ODONTOLÓGICO | D267: =CONCATENATE(B267,LEFT(C267,4)) -> SEF3011 | E267: Material de consumo | K267: 9399 - OUTRAS INDENIZACOES E RESTITUICOES
A268: 1191 | B268: SEF | C268: 3013 - MATERIAIS DE LABORATORIO E PRODUTOS QUIMICOS EM GERAL | D268: =CONCATENATE(B268,LEFT(C268,4)) -> SEF3013 | E268: Material de consumo
A269: 1191 | B269: SEF | C269: 3015 - MATERIAL FOTOGRAFICO, CINEMATOGRAFICO E DE COMUNICACAO | D269: =CONCATENATE(B269,LEFT(C269,4)) -> SEF3015 | E269: Material de consumo
A270: 1191 | B270: SEF | C270: 3016 - MATERIAL DE INFORMATICA | D270: =CONCATENATE(B270,LEFT(C270,4)) -> SEF3016 | E270: Material de consumo
A271: 1191 | B271: SEF | C271: 3017 - ARTIGOS PARA LIMPEZA E HIGIENE | D271: =CONCATENATE(B271,LEFT(C271,4)) -> SEF3017 | E271: Material de consumo
A272: 1191 | B272: SEF | C272: 3018 - MATÉRIAS-PRIMAS E PRODUTOS PARA MANIPULAÇÃO E INDÚSTRIAS DE TRANSFORMAÇÃO | D272: =CONCATENATE(B272,LEFT(C272,4)) -> SEF3018 | E272: Material de consumo
A273: 1191 | B273: SEF | C273: 3019 - MATERIAL PARA MANUTENCAO E REPAROS DE IMOVEIS DE PROPRIEDADE DA ADMINISTRACAO PUBLICA | D273: =CONCATENATE(B273,LEFT(C273,4)) -> SEF3019 | E273: Reparo de imóveis
A274: 1191 | B274: SEF | C274: 3020 - MATERIAL ELETRICO E ELETRONICO | D274: =CONCATENATE(B274,LEFT(C274,4)) -> SEF3020 | E274: Material de consumo
A275: 1191 | B275: SEF | C275: 3021 - MATERIAL PARA MANUTENCAO E REPAROS DE BENS DE DOMINIO PUBLICO OU DE TERCEIROS | D275: =CONCATENATE(B275,LEFT(C275,4)) -> SEF3021 | E275: Material de consumo
A276: 1191 | B276: SEF | C276: 3022 - FERRAMENTAS, FERRAGENS E UTENSÍLIOS | D276: =CONCATENATE(B276,LEFT(C276,4)) -> SEF3022 | E276: Material de consumo
A277: 1191 | B277: SEF | C277: 3023 - MATERIAL PARA MANUTENCAO DE VEICULOS AUTOMOTORES | D277: =CONCATENATE(B277,LEFT(C277,4)) -> SEF3023 | E277: Frota
A278: 1191 | B278: SEF | C278: 3024 - PEÇAS E ACESSÓRIOS PARA EQUIPAMENTOS E OUTROS MATERIAIS PERMANENTES | D278: =CONCATENATE(B278,LEFT(C278,4)) -> SEF3024 | E278: Material de consumo
A279: 1191 | B279: SEF | C279: 3025 - MATERIAL DE SEGURANCA, APETRECHOS OPERACIONAIS E POLICIAIS | D279: =CONCATENATE(B279,LEFT(C279,4)) -> SEF3025 | E279: Material de consumo
... A1442: 1401 | B1442: CBMMG | C1442: 9399 - OUTRAS INDENIZACOES E RESTITUICOES | D1442: =CONCATENATE(B1442,LEFT(C1442,4)) -> CBMMG9399 | E1442: Demais despesas de custeio
A1443: 1411 | B1443: #N/A | C1443: 1401 - DIARIAS CIVIL | D1443: =CONCATENATE(B1443,LEFT(C1443,4)) -> #N/A | E1443: Diárias e viagens
A1444: 1411 | B1444: #N/A | C1444: 3001 - ARTIGOS PARA CONFECCAO E VESTUARIO | D1444: =CONCATENATE(B1444,LEFT(C1444,4)) -> #N/A | E1444: Material de consumo
