Workbook
Name AGEPROG: 'AÇÕES E PROGRAMAS'!$A$2:$A$4
Name ARMBHPROG: 'AÇÕES E PROGRAMAS'!$B$2:$B$3
Name ARMVAPROG: 'AÇÕES E PROGRAMAS'!$C$2:$C$4
Name ARSAEPROG: 'AÇÕES E PROGRAMAS'!$E$2:$E$3
Name ARTEMIGPROG: 'AÇÕES E PROGRAMAS'!$DJ$2
Name CBMMGPROG: 'AÇÕES E PROGRAMAS'!$S$2:$S$5
Name CGEPROG: 'AÇÕES E PROGRAMAS'!$Q$2:$Q$6
Name DERPROG: 'AÇÕES E PROGRAMAS'!$U$2:$U$4
Name EAGE: AGRUPAMENTO!$C$115:$C$210
Name EGMG: AGRUPAMENTO!$C$2:$C$114
Name ELEMENTO: AGRUPAMENTO!$K$2:$K$262
Name EMATERPROG: 'AÇÕES E PROGRAMAS'!$X$2:$X$6
Name EMCPROG: 'AÇÕES E PROGRAMAS'!$Z$2:$Z$4
Name EOGE: AGRUPAMENTO!$C$211:$C$256
Name EPAMIGPROG: 'AÇÕES E PROGRAMAS'!$Y$2:$Y$4
Name EPMMG: AGRUPAMENTO!$C$573:$C$749
Name ESEAPA: AGRUPAMENTO!$C$473:$C$572
Name ESEDE: AGRUPAMENTO!$C$381:$C$472
Name ESEE: AGRUPAMENTO!$C$750:$C$946
Name ESEF: AGRUPAMENTO!$C$257:$C$380
Name ESPMGPROG: 'AÇÕES E PROGRAMAS'!$AB$2:$AB$3
Name FAOPPROG: 'AÇÕES E PROGRAMAS'!$AF$2:$AF$6
Name FAPEMIGPROG: 'AÇÕES E PROGRAMAS'!$AE$2:$AE$4
Name FCSPROG: 'AÇÕES E PROGRAMAS'!$AD$2:$AD$6
Name FDMPROG: 'AÇÕES E PROGRAMAS'!$AT$2
Name FEAMPROG: 'AÇÕES E PROGRAMAS'!$AI$2:$AI$4
Name FEASPROG: 'AÇÕES E PROGRAMAS'!$BE$2:$BE$3
Name FESPROG: 'AÇÕES E PROGRAMAS'!$BN$2:$BN$11
Name FHAPROG: 'AÇÕES E PROGRAMAS'!$AK$2:$AK$8
Name FHEMIGPROG: 'AÇÕES E PROGRAMAS'!$AL$2:$AL$3
Name FHIDROPROG: 'AÇÕES E PROGRAMAS'!$AZ$2:$AZ$6
Name FJPPROG: 'AÇÕES E PROGRAMAS'!$AM$2:$AM$6
Name FONTEARMBH: 'FONTE 1.0'!$A$2:$A$3
Name FONTEARMVA: 'FONTE 1.0'!$B$2:$B$3
Name FONTEARSAE: 'FONTE 1.0'!$C$2:$C$3
Name FONTEDER: 'FONTE 1.0'!$D$2:$D$10
Name FONTEFAOP: 'FONTE 1.0'!$F$2:$F$4
Name FONTEFCS: 'FONTE 1.0'!$G$2:$G$3
Name FONTEFDM: 'FONTE 1.0'!$R$2:$R$3
Name FONTEFEAM: 'FONTE 1.0'!$H$2:$H$5
Name FONTEFEAS: 'FONTE 1.0'!$S$2:$S$4
Name FONTEFJP: 'FONTE 1.0'!$I$2:$I$4
Name FONTEFUNTRANS: 'FONTE 1.0'!$E$2
Name FONTEIDENE: 'FONTE 1.0'!$J$2:$J$3
Name FONTEIEF: 'FONTE 1.0'!$K$2:$K$8
Name FONTEIEPHA: 'FONTE 1.0'!$L$2:$L$4
Name FONTEIGAM: 'FONTE 1.0'!$M$2:$M$6
Name FONTEIMA: 'FONTE 1.0'!$N$2:$N$4
Name FONTEJUCEMG: 'FONTE 1.0'!$O$2
Name FONTELEMG: 'FONTE 1.0'!$P$2
Name FONTESEDESE: 'FONTE 1.0'!$Q$2:$Q$7
Name FUCAMPROG: 'AÇÕES E PROGRAMAS'!$AH$2:$AH$4
Name FUNAPECPROG: 'AÇÕES E PROGRAMAS'!$AQ$2:$AQ$3
Name FUNEDPROG: 'AÇÕES E PROGRAMAS'!$AJ$2:$AJ$6
Name FUNTRANSPROG: 'AÇÕES E PROGRAMAS'!$BH$2:$BH$3
Name GMGPROG: 'AÇÕES E PROGRAMAS'!$BU$2:$BU$8
Name HEMOMINASPROG: 'AÇÕES E PROGRAMAS'!$AC$2:$AC$3
Name IDENEPROG: 'AÇÕES E PROGRAMAS'!$BW$2:$BW$4
Name IEFPROG: 'AÇÕES E PROGRAMAS'!$CB$2:$CB$4
Name IEPHAPROG: 'AÇÕES E PROGRAMAS'!$CC$2:$CC$6

Sheet INDICE
D7: ORÇAMENTO BASE ZERO (OBZ) 2026
B11: MATERIAL DE APOIO | D11: BASE OBZ | F11: MATERIAL DE APOIO
B12: CLASSIFICADOR ORÇAMENTÁRIO | F12: CONCEITOS METODOLÓGICOS IMPORTANTES
B13: DECRETO DIÁRIAS | D13: BASE OBZ - EXEMPLO

Sheet BASE OBZ - EXEMPLO
F1: INDICE | H1: PROJETO ORÇAMENTO BASE-ZERO
A2: UNIDADE ORÇAMENTÁRIA | B2: N2 | C2: SUB SIGLA | D2: N3 | E2: PROGRAMAUO | F2: PROGRAMA | G2: prog cod | H2: AÇÃO | I2: ELEMENTO | J2: ELEMENTO_ITEM | K2: Agrupamento | L2: GRUPO | M2: FONTEUO | N2: FONTE | O2: DESCRIÇÃO DO ITEM | P2: NOVO? | Q2: PREMISSA VOLUME | R2: VOLUME | S2: PREMISSA DE PREÇO | T2: PREÇO UNITÁRIO | U2: FREQUÊNCIA PAGAMENTO | V2: VALOR TOTAL ITEM | W2: CLASSIFICAÇÃO CENÁRIO | X2: DESCRIÇÃO DO CENÁRIO | Y2: RISCO DE NÃO FAZER | Z2: BENEFICIO AO FAZER | AA2: PRIORIDADE N3 | AB2: PRIORIDADE N2 | AC2: PRIORIDADE N1 | AD2: PRIORIDADE N2 | AE2: PRIORIDADE N1
A3: FAOP | B3: Subsecretaria de Promoção Cultural | D3: Superintendência de artes | E3: =CONCATENATE(A3,"PROG") -> FAOPPROG | F3: 060 - FORMACAO CULTURAL | G3: =CONCATENATE("P",(LEFT(F3,3)),A3) -> P060FAOP | H3: 1029 - ATIVIDADES DE ENSINO, FORMACAO E QUALIFICACAO PROFISSIONAL E TECNICA EM CULTURA E PATRIMONIO | I3: 1401 - DIÁRIAS CIVIL | J3: =CONCATENATE("ELEM",LEFT(#REF!,2)) -> #REF! | K3: Diárias e viagens | L3: 3 - Outras Despesas de Custeio | M3: =VLOOKUP(L3,#REF!,2,FALSE) -> #REF! | N3: 10 | O3: DIÁRIA PARA ATENDER HOSPEDAGEM DE PROFESSOR CONVIDADO PARA LECIONAR | P3: NÃO | Q3: NÚMERO DE DIÁRIAS UTILIZADAS (2) X NUMERO DE SERVIDORES FAVORECIDOS (1) | R3: 2 | S3: VALOR DA DIÁRIA DE ACORDO COM DECRETO 47.045/2016 (FAIXA 1 - MUNICÍPIO ESPECIAL) | T3: 294 | U3: 1 | V3: =R3*T3*U3 -> 588 | W3: LIMIAR | X3: REALIZAÇÃO DE CURSO COM APENAS UM PROFESSOR CONVIDADO | Y3: CURSO PRECISA DE PELO MENOS UM PROFESSOR PARA SER REALIZADO | Z3: NÃO É POSSÍVEL REALIZAR CURSO SEM PROFESSOR | AA3: CURSO PRECISA DE PELO MENOS UM PROFESSOR PARA SER REALIZADO | AB3: NÃO É POSSÍVEL REALIZAR CURSO SEM PROFESSOR
A4: FAOP | B4: Subsecretaria de Promoção Cultural | D4: Superintendência de artes | E4: =CONCATENATE(A4,"PROG") -> FAOPPROG | F4: 060 - FORMACAO CULTURAL | G4: =CONCATENATE("P",(LEFT(F4,3)),A4) -> P060FAOP | H4: 1029 - ATIVIDADES DE ENSINO, FORMACAO E QUALIFICACAO PROFISSIONAL E TECNICA EM CULTURA E PATRIMONIO | I4: 3301 - PASSAGENS - PESSOA FÍSICA | J4: =CONCATENATE("ELEM",LEFT(#REF!,2)) -> #REF! | K4: Diárias e viagens | L4: 3 - Outras Despesas de Custeio | M4: Diárias e viagens | N4: 10 | O4: PASSAGEM DE IDA E VOLTA PARA ATENDER DESLOCAMENTO DE PROFESSOR CONVIDADO PARA LECIONAR | P4: NÃO | Q4: 1 PASSAGEM DE IDA E VOLTA DE CONTAGEM PARA BH | R4: 1 | S4: VALOR DA PASSAGEM IDA E VOLTA | T4: 20 | U4: 1 | V4: =R4*T4*U4 -> 20 | W4: LIMIAR | X4: REALIZAÇÃO DE CURSO COM APENAS UM PROFESSOR CONVIDADO | Y4: CURSO PRECISA DE PELO MENOS UM PROFESSOR PARA SER REALIZADO | Z4: NÃO É POSSÍVEL REALIZAR CURSO SEM PROFESSOR | AA4: CURSO PRECISA DE PELO MENOS UM PROFESSOR PARA SER REALIZADO | AB4: NÃO É POSSÍVEL REALIZAR CURSO SEM PROFESSOR
A5: FAOP | B5: Subsecretaria de Promoção Cultural | D5: Superintendência de artes | E5: =CONCATENATE(A5,"PROG") -> FAOPPROG | F5: 060 - FORMACAO CULTURAL | G5: =CONCATENATE("P",(LEFT(F5,3)),A5) -> P060FAOP | H5: 1029 - ATIVIDADES DE ENSINO, FORMACAO E QUALIFICACAO PROFISSIONAL E TECNICA EM CULTURA E PATRIMONIO | I5: 1401 - DIÁRIAS CIVIL | J5: =CONCATENATE("ELEM",LEFT(#REF!,2)) -> #REF! | K5: Diárias e viagens | L5: 3 - Outras Despesas de Custeio | M5: Diárias e viagens | N5: 10 | O5: DIÁRIA PARA ATENDER HOSPEDAGEM DE PROFESSOR EXTRA CONVIDADO PARA LECIONAR | P5: SIM | Q5: NÚMERO DE DIÁRIAS UTILIZADAS (2) X NUMERO DE SERVIDORES FAVORECIDOS (1) | R5: 2 | S5: VALOR DA DIÁRIA DE ACORDO COM DECRETO 47.045/2016 (FAIXA 1 - MUNICÍPIO ESPECIAL) | T5: 294 | U5: 1 | V5: =R5*T5*U5 -> 588 | W5: LIMIAR | X5: CURSO MINISTRADO COM UM PROFESSOR EXTRA CONVIDADO | Y5: CURSO MENOS INTERESSANTE, MENOR CARGA HORÁRIO E POSSÍVEL MENOR ADESÃO DO PÚBLICO | Z5: CURSO COM MAIOR QUALIDADE E ADESÃO DO PÚBLICO | AA5: CURSO MENOS INTERESSANTE, MENOR CARGA HORÁRIO E POSSÍVEL MENOR ADESÃO DO PÚBLICO | AB5: CURSO COM MAIOR QUALIDADE E ADESÃO DO PÚBLICO
A6: FAOP | B6: Subsecretaria de Promoção Cultural | D6: Superintendência de artes | E6: =CONCATENATE(A6,"PROG") -> FAOPPROG | F6: 060 - FORMACAO CULTURAL | G6: =CONCATENATE("P",(LEFT(F6,3)),A6) -> P060FAOP | H6: 1029 - ATIVIDADES DE ENSINO, FORMACAO E QUALIFICACAO PROFISSIONAL E TECNICA EM CULTURA E PATRIMONIO | I6: 3301 - PASSAGENS - PESSOA FÍSICA | J6: =CONCATENATE("ELEM",LEFT(#REF!,2)) -> #REF! | K6: Diárias e viagens | L6: 3 - Outras Despesas de Custeio | M6: Diárias e viagens | N6: 10 | O6: PASSAGEM DE IDA E VOLTA PARA ATENDER DESLOCAMENTO DE PROFESSOR EXTRA CONVIDADO PARA LECIONAR | P6: SIM | Q6: 1 PASSAGEM DE IDA E VOLTA DE CONTAGEM PARA BH | R6: 1 | S6: VALOR DA PASSAGEM IDA E VOLTA | T6: 20 | U6: 1 | V6: =R6*T6*U6 -> 20 | W6: LIMIAR | X6: CURSO MINISTRADO COM UM PROFESSOR EXTRA CONVIDADO | Y6: CURSO MENOS INTERESSANTE, MENOR CARGA HORÁRIO E POSSÍVEL MENOR ADESÃO DO PÚBLICO | Z6: CURSO COM MAIOR QUALIDADE E ADESÃO DO PÚBLICO | AA6: CURSO MENOS INTERESSANTE, MENOR CARGA HORÁRIO E POSSÍVEL MENOR ADESÃO DO PÚBLICO | AB6: CURSO COM MAIOR QUALIDADE E ADESÃO DO PÚBLICO
A7: FAOP | B7: Subsecretaria de Promoção Cultural | D7: Superintendência de artes | E7: =CONCATENATE(A7,"PROG") -> FAOPPROG | F7: 060 - FORMACAO CULTURAL | G7: =CONCATENATE("P",(LEFT(F7,3)),A7) -> P060FAOP | H7: 1029 - ATIVIDADES DE ENSINO, FORMACAO E QUALIFICACAO PROFISSIONAL E TECNICA EM CULTURA E PATRIMONIO | I7: 3952 - CONTRATAÇÃO DE ESTAGIÁRIOS | J7: =CONCATENATE("ELEM",LEFT(#REF!,2)) -> #REF! | K7: Estagiários | L7: 3 - Outras Despesas de Custeio | M7: Estagiários | N7: 60 | O7: ESTAGIÁRIO CARGA HORÁRIA 30 HORAS SEMANAIS | P7: SIM | Q7: NÚMERO DE ESTAGIÁRIOS | R7: 2 | S7: VALOR DA BOLSA ESTAGIÁRIO + VALE TRANSPORTE | T7: 900 | U7: 12 | V7: =R7*T7*U7 -> 21600 | W7: INCREMENTAL | X7: EXPANSÃO DOS CURSOS PARA A MODALIDADE EAD | Y7: MAIOR DEMORA PARA A REALIZAÇÃO DOS PROCESSOS DE TESTE DA PLATAFORMA; CURSO MAIS DESORGANIZADO E ACÚMULO DE TAREFAS AOS SERVIDORES | Z7: PROCESSOS MAIS ÁGEIS; CURSO MAIS ORGANIZADO E SERVIDORES MENOS SOBRECARREGADOS | AA7: MAIOR DEMORA PARA A REALIZAÇÃO DOS PROCESSOS DE TESTE DA PLATAFORMA; CURSO MAIS DESORGANIZADO E ACÚMULO DE TAREFAS AOS SERVIDORES | AB7: PROCESSOS MAIS ÁGEIS; CURSO MAIS ORGANIZADO E SERVIDORES MENOS SOBRECARREGADOS | AC7: 3 | AD7: 3
A8: FAOP | B8: Subsecretaria de Promoção Cultural | D8: Superintendência de artes | E8: =CONCATENATE(A8,"PROG") -> FAOPPROG | F8: 060 - FORMACAO CULTURAL | G8: =CONCATENATE("P",(LEFT(F8,3)),A8) -> P060FAOP | H8: 1029 - ATIVIDADES DE ENSINO, FORMACAO E QUALIFICACAO PROFISSIONAL E TECNICA EM CULTURA E PATRIMONIO | I8: 3005 - MATERIAL PARA ESCRITÓRIO | J8: =CONCATENATE("ELEM",LEFT(#REF!,2)) -> #REF! | K8: Aquisição de material de consumo | L8: 3 - Outras Despesas de Custeio | M8: Aquisição de material de consumo | N8: 10 | O8: PACOTE DE FOLHA A4 BRANCA COM 100 UNIDADES | P8: NÃO | Q8: MÉDIA DE CONSUMO PARA UM CURSO DE 2 DIAS | R8: 1 | S8: CONSULTA DO VALOR DO ITEM NO SIAD | T8: 25 | U8: 1 | V8: =R8*T8*U8 -> 25 | W8: LIMIAR | X8: REALIZAÇÃO DE CURSO COM APENAS UM PROFESSOR CONVIDADO | Y8: ALUNOS PRECISAM DE FOLHA PARA REALIZAR AS ATIVIDADES AVALIATIVAS | Z8: NÃO É POSSÍVEL REALIZAR AS ATIVIDADES SEM QUE OS ALUNOS TENHAM ONDE ESCREVER AS RESPOSTAS | AA8: ALUNOS PRECISAM DE FOLHA PARA REALIZAR AS ATIVIDADES AVALIATIVAS | AB8: NÃO É POSSÍVEL REALIZAR AS ATIVIDADES SEM QUE OS ALUNOS TENHAM ONDE ESCREVER AS RESPOSTAS
A9: FAOP | B9: Subsecretaria de Promoção Cultural | D9: Superintendência de artes | E9: =CONCATENATE(A9,"PROG") -> FAOPPROG | F9: 060 - FORMACAO CULTURAL | G9: =CONCATENATE("P",(LEFT(F9,3)),A9) -> P060FAOP | H9: 1029 - ATIVIDADES DE ENSINO, FORMACAO E QUALIFICACAO PROFISSIONAL E TECNICA EM CULTURA E PATRIMONIO | I9: 3005 - MATERIAL PARA ESCRITÓRIO | J9: =CONCATENATE("ELEM",LEFT(#REF!,2)) -> #REF! | K9: Aquisição de material de consumo | L9: 3 - Outras Despesas de Custeio | M9: Aquisição de material de consumo | N9: 60 | O9: KIT DE MATERIAL PARA CURSO (CANETA ESFEROGRÁFICA AZUL, LÁPIS, BORRACHA) | P9: NÃO | Q9: 1 KIT POR PESSOA X MÉDIA DE INSCRIÇÕES NO CURSO (100) | R9: 100 | S9: CONSULTA DO VALOR DOS ITENS QUE COMPÕES O KIT NO SIAD | T9: 8 | U9: 1 | V9: =R9*T9*U9 -> 800 | W9: INCREMENTAL | X9: FORNECIMENTO DE ITENS DE SUPORTE AO PARTICIPANTE DOS CURSOS | Y9: MENOR ADESÃO AO CURSO DEVIDO AO PÚBLICO ALVO NÃO POSSUIR CONDIÇÕES FINANCEIRAS DE ADQUIRIR OS MATERIAIS DO KIT | Z9: MAIOR ADESÃO DO PÚBLICO ALVO E MELHOR DESEMPENHO DOS ALUNOS | AA9: MENOR ADESÃO AO CURSO DEVIDO AO PÚBLICO ALVO NÃO POSSUIR CONDIÇÕES FINANCEIRAS DE ADQUIRIR OS MATERIAIS DO KIT | AB9: MAIOR ADESÃO DO PÚBLICO ALVO E MELHOR DESEMPENHO DOS ALUNOS | AC9: 1 | AD9: 2
A10: FAOP | B10: Subsecretaria de Promoção Cultural | D10: Superintendência de artes | E10: =CONCATENATE(A10,"PROG") -> FAOPPROG | F10: 060 - FORMACAO CULTURAL | G10: =CONCATENATE("P",(LEFT(F10,3)),A10) -> P060FAOP | H10: 1029 - ATIVIDADES DE ENSINO, FORMACAO E QUALIFICACAO PROFISSIONAL E TECNICA EM CULTURA E PATRIMONIO | I10: 3903 - FORNECIMENTO DE ALIMENTAÇÃO | J10: =CONCATENATE("ELEM",LEFT(#REF!,2)) -> #REF! | K10: Alimentação | L10: 3 - Outras Despesas de Custeio | M10: Alimentação | N10: 60 | O10: FORNECIMENTO DE COFFEE BREAK PARA O CURSO | P10: SIM | Q10: CONTRATO FIRMADO | R10: 1 | S10: VALOR HISTÓRICO DOS CONTRADOS FIRMADOS | T10: 500 | U10: 1 | V10: =R10*T10*U10 -> 500 | W10: INCREMENTAL | X10: FORNECIMENTO DE ITENS DE SUPORTE AO PARTICIPANTE DOS CURSOS | Y10: POSSIBILIDADE DO PÚBLICO ALVO NÃO ADERIR AO CURSO POR QUESTÕES FINANCEIRAS QUE IMPOSSIBILITEM A AQUISIÇÃO DE LANCHE DURANTE O DIA; MAIOR TEMPO DE INTERVALO DURANTE O CURSO E MENOR ADESÃO DO PÚBLICO AO CURSO | Z10: CURSO MAIS ATRATIVO, GERANDO MAIOR ADESÃO DO PÚBLICO ALVO | AA10: POSSIBILIDADE DO PÚBLICO ALVO NÃO ADERIR AO CURSO POR QUESTÕES FINANCEIRAS QUE IMPOSSIBILITEM A AQUISIÇÃO DE LANCHE DURANTE O DIA; MAIOR TEMPO DE INTERVALO DURANTE O CURSO E MENOR ADESÃO DO PÚBLICO AO CURSO | AB10: CURSO MAIS ATRATIVO, GERANDO MAIOR ADESÃO DO PÚBLICO ALVO | AC10: 1 | AD10: 2
A11: FAOP | B11: Subsecretaria de Promoção Cultural | D11: Superintendência de artes | E11: =CONCATENATE(A11,"PROG") -> FAOPPROG | F11: 060 - FORMACAO CULTURAL | G11: =CONCATENATE("P",(LEFT(F11,3)),A11) -> P060FAOP | H11: 1029 - ATIVIDADES DE ENSINO, FORMACAO E QUALIFICACAO PROFISSIONAL E TECNICA EM CULTURA E PATRIMONIO | I11: 4007 - AQUISIÇÃO DE SOFTWARE DESENVOLVIDOS PELA PRODEMGE | J11: =CONCATENATE("ELEM",LEFT(#REF!,2)) -> #REF! | K11: PRODEMGE | L11: 4 - Investimento | M11: PRODEMGE | N11: 10 | O11: DESENVOLVIMENTO DE PLATAFORMA MOODLE PARA CURSO EAD | P11: SIM | Q11: CONTRATO FIRMADO | R11: 1 | S11: TABELA DE SERVIÇOS PRODEMGE | T11: 5000 | U11: 1 | V11: =R11*T11*U11 -> 5000 | W11: INCREMENTAL | X11: EXPANSÃO DOS CURSOS PARA A MODALIDADE EAD | Y11: MENOR PÚBLICO DEVIDO À OFERTA DE CURSOS SOMENTE NA MODALIDADE PRESENCIAL | Z11: ATINGIR MAIOR PÚBLICO | AA11: MENOR PÚBLICO DEVIDO À OFERTA DE CURSOS SOMENTE NA MODALIDADE PRESENCIAL | AB11: ATINGIR MAIOR PÚBLICO | AC11: 3 | AD11: 3
A12: FAOP | B12: Subsecretaria de Promoção Cultural | D12: Superintendência de artes | E12: =CONCATENATE(A12,"PROG") -> FAOPPROG | F12: 056 - FOMENTO, DEMOCRATIZACAO E ACESSO A CULTURA E AO TURISMO | G12: =CONCATENATE("P",(LEFT(F12,3)),A12) -> P056FAOP | H12: 1027 - ACOES DE DIFUSAO DAS ARTES E DO PATRIMONIO CULTURAL | I12: 3702 - LOCAÇÃO DE SERVIÇOS DE APOIO ADMINISTRATIVO | J12: =CONCATENATE("ELEM",LEFT(#REF!,2)) -> #REF! | K12: Demais terceirizados | L12: 3 - Outras Despesas de Custeio | M12: Demais terceirizados | N12: 10 | O12: POSTO DE TRABALHO DE SEGURANÇA 24H | P12: NÃO | Q12: CONTRATATO FIRMADO COM A EMPRESA "SECURITY" | R12: 1 | S12: VALOR MENSAL DO CONTRATO | T12: 2000 | U12: 12 | V12: =R12*T12*U12 -> 24000 | W12: LIMIAR | X12: SEGURANÇA MÍNIMA NECESSÁRIA PARA ATENDER A GUARDA DO MUSEU DURANTE 12H | Y12: AUSÊNCIA DE SEGURANÇA DO MUSEU, DEIXANDO O PRÉDIO COMPLETAMENTE VULNERÁVEL | Z12: REDUÇÃO DO RISCO DE DEPREDAÇÃO DO MUSEU | AA12: AUSÊNCIA DE SEGURANÇA DO MUSEU, DEIXANDO O PRÉDIO COMPLETAMENTE VULNERÁVEL | AB12: REDUÇÃO DO RISCO DE DEPREDAÇÃO DO MUSEU
A13: FAOP | B13: Subsecretaria de Promoção Cultural | D13: Superintendência de artes | E13: =CONCATENATE(A13,"PROG") -> FAOPPROG | F13: 056 - FOMENTO, DEMOCRATIZACAO E ACESSO A CULTURA E AO TURISMO | G13: =CONCATENATE("P",(LEFT(F13,3)),A13) -> P056FAOP | H13: 1027 - ACOES DE DIFUSAO DAS ARTES E DO PATRIMONIO CULTURAL | I13: 3702 - LOCAÇÃO DE SERVIÇOS DE APOIO ADMINISTRATIVO | J13: =CONCATENATE("ELEM",LEFT(#REF!,2)) -> #REF! | K13: Demais terceirizados | L13: 3 - Outras Despesas de Custeio | M13: Demais terceirizados | N13: 60 | O13: ADITIVO PARA SEGURANÇA 24 HORAS (ADICIONAL DE 1 SEGURANÇA) | P13: SIM | Q13: ADITIVO CONTRATUAL COM A EMPRESA "SECURITY" | R13: 1 | S13: VALOR MENSAL DO ADITIVO (NÚMERO DE POSTOS DE TRABALHO X VALOR DO POSTO) | T13: 2000 | U13: 12 | V13: =R13*T13*U13 -> 24000 | W13: LIMIAR | X13: AUMENTO DA SEGURANÇA DO MUSEU, VIABILIZANDO GUARDA NOS PERÍODOS DIURNO E NOTURNO | Y13: MAIOR RISCO DE DEPREDAÇÃO, VISTO QUE SÓ HÁ SEGURANÇA NO LOCAL DURANTE UM PERÍODO DO DIA | Z13: MAIOR SEGURANÇA NO PRÉDIO DA FUNDAÇÃO COM VIGILÂNCIA 24 HORAS | AA13: MAIOR RISCO DE DEPREDAÇÃO, VISTO QUE SÓ HÁ SEGURANÇA NO LOCAL DURANTE UM PERÍODO DO DIA | AB13: MAIOR SEGURANÇA NO PRÉDIO DA FUNDAÇÃO COM VIGILÂNCIA 24 HORAS
A14: FAOP | B14: Subsecretaria de Promoção Cultural | D14: Superintendência de artes | E14: =CONCATENATE(A14,"PROG") -> FAOPPROG | F14: 056 - FOMENTO, DEMOCRATIZACAO E ACESSO A CULTURA E AO TURISMO | G14: =CONCATENATE("P",(LEFT(F14,3)),A14) -> P056FAOP | H14: 1027 - ACOES DE DIFUSAO DAS ARTES E DO PATRIMONIO CULTURAL | I14: 3703 - LOCAÇÃO DE SERVIÇOS DE CONSERVAÇÃO E LIMPEZA REALIZADOS PELA MGS | J14: =CONCATENATE("ELEM",LEFT(#REF!,2)) -> #REF! | K14: Terceirizados - MGS | L14: 3 - Outras Despesas de Custeio | M14: Terceirizados - MGS | N14: 10 | O14: POSTO DE TRABALHO DE MANUTENÇÃO E LIMPEZA | P14: NÃO | Q14: NÚMERO DE POSTOS DE TRABALHO PARA MANUTENÇÃO DO MUSEU | R14: 3 | S14: VALOR MENSAL DO POSTO DE TRABALHO CONFORME CONTRATO | T14: 1500 | U14: 12 | V14: =R14*T14*U14 -> 54000 | W14: LIMIAR | X14: LIMPEZA EFETUADA DE TRÊS EM TRÊS HORAS NOS SALÕES DO MUSEU | Y14: SALÃO DO MUSEU PODE COM ACÚMULO DE SUJEIRA, GERANDO MÁ IMPRESSÃO AOS FREQUENTADORES E DINIMUINDO A VISITAÇÃO | Z14: MUSEU MINIMAMENTE LIMPO | AA14: SALÃO DO MUSEU PODE COM ACÚMULO DE SUJEIRA, GERANDO MÁ IMPRESSÃO AOS FREQUENTADORES E DINIMUINDO A VISITAÇÃO | AB14: MUSEU MINIMAMENTE LIMPO
A15: FAOP | B15: Subsecretaria de Promoção Cultural | D15: Superintendência de artes | E15: =CONCATENATE(A15,"PROG") -> FAOPPROG | F15: 056 - FOMENTO, DEMOCRATIZACAO E ACESSO A CULTURA E AO TURISMO | G15: =CONCATENATE("P",(LEFT(F15,3)),A15) -> P056FAOP | H15: 1027 - ACOES DE DIFUSAO DAS ARTES E DO PATRIMONIO CULTURAL | I15: 3703 - LOCAÇÃO DE SERVIÇOS DE CONSERVAÇÃO E LIMPEZA REALIZADOS PELA MGS | J15: =CONCATENATE("ELEM",LEFT(#REF!,2)) -> #REF! | K15: Terceirizados - MGS | L15: 3 - Outras Despesas de Custeio | M15: Terceirizados - MGS | N15: 60 | O15: POSTO DE TRABALHO DE MANUTENÇÃO E LIMPEZA | P15: SIM | Q15: NÚMERO DE POSTOS DE TRABALHO PARA MANUTENÇÃO DO MUSEU | R15: 2 | S15: VALOR MENSAL DO POSTO DE TRABALHO CONFORME CONTRATO | T15: 1500 | U15: 12 | V15: =R15*T15*U15 -> 36000 | W15: INCREMENTAL | X15: LIMPEZA EFETUADA DE HORA EM HORA NOS SALÕES DO MUSEU | Y15: SALÃO DO MUSEU PODE FICAR SUJO ENTRE UMA E OUTRA VISITA, GERANDO INSATISFAÇÃO DOS FREQUENTADORES | Z15: MUSEU MAIS LIMPO, USUÁRIOS SATISFEITOS E MAIOR VISITAÇÃO | AA15: SALÃO DO MUSEU PODE FICAR SUJO ENTRE UMA E OUTRA VISITA, GERANDO INSATISFAÇÃO DOS FREQUENTADORES | AB15: MUSEU MAIS LIMPO, USUÁRIOS SATISFEITOS E MAIOR VISITAÇÃO | AC15: 2 | AD15: 1
E16: =CONCATENATE(A16,"PROG") -> PROG | G16: =CONCATENATE("P",(LEFT(F16,3)),A16) -> P | J16: =CONCATENATE("ELEM",LEFT(I16,2)) -> ELEM | M16: #N/A
E17: =CONCATENATE(A17,"PROG") -> PROG | G17: =CONCATENATE("P",(LEFT(F17,3)),A17) -> P | J17: =CONCATENATE("ELEM",LEFT(I17,2)) -> ELEM | M17: #N/A
E18: =CONCATENATE(A18,"PROG") -> PROG | G18: =CONCATENATE("P",(LEFT(F18,3)),A18) -> P | J18: =CONCATENATE("ELEM",LEFT(I18,2)) -> ELEM | M18: #N/A
E19: =CONCATENATE(A19,"PROG") -> PROG | G19: =CONCATENATE("P",(LEFT(F19,3)),A19) -> P | J19: =CONCATENATE("ELEM",LEFT(I19,2)) -> ELEM | M19: #N/A
E20: =CONCATENATE(A20,"PROG") -> PROG | G20: =CONCATENATE("P",(LEFT(F20,3)),A20) -> P | J20: =CONCATENATE("ELEM",LEFT(I20,2)) -> ELEM | M20: #N/A
E21: =CONCATENATE(A21,"PROG") -> PROG | G21: =CONCATENATE("P",(LEFT(F21,3)),A21) -> P | J21: =CONCATENATE("ELEM",LEFT(I21,2)) -> ELEM | M21: #N/A
E22: =CONCATENATE(A22,"PROG") -> PROG | G22: =CONCATENATE("P",(LEFT(F22,3)),A22) -> P | J22: =CONCATENATE("ELEM",LEFT(I22,2)) -> ELEM | M22: #N/A
E23: =CONCATENATE(A23,"PROG") -> PROG | G23: =CONCATENATE("P",(LEFT(F23,3)),A23) -> P | J23: =CONCATENATE("ELEM",LEFT(I23,2)) -> ELEM | M23: #N/A
E24: =CONCATENATE(A24,"PROG") -> PROG | G24: =CONCATENATE("P",(LEFT(F24,3)),A24) -> P | J24: =CONCATENATE("ELEM",LEFT(I24,2)) -> ELEM | M24: #N/A
E25: =CONCATENATE(A25,"PROG") -> PROG | G25: =CONCATENATE("P",(LEFT(F25,3)),A25) -> P | J25: =CONCATENATE("ELEM",LEFT(I25,2)) -> ELEM | M25: #N/A
E26: =CONCATENATE(A26,"PROG") -> PROG | G26: =CONCATENATE("P",(LEFT(F26,3)),A26) -> P | J26: =CONCATENATE("ELEM",LEFT(I26,2)) -> ELEM | M26: #N/A
E27: =CONCATENATE(A27,"PROG") -> PROG | G27: =CONCATENATE("P",(LEFT(F27,3)),A27) -> P | J27: =CONCATENATE("ELEM",LEFT(I27,2)) -> ELEM | M27: #N/A
... E501: =CONCATENATE(A501,"PROG") -> PROG | G501: =CONCATENATE("P",(LEFT(F501,3)),A501) -> P | J501: =CONCATENATE("ELEM",LEFT(I501,2)) -> ELEM | M501: #N/A

Sheet EXEMPLO PREENCHIMENTO OBZ
A1: UNIDADE ORÇAMENTÁRIA (NÍVEL 1) | B1: SUBSECRETARIA (NÍVEL 2) | C1: SUB SIGLA | D1: SUPERINTENDENCIA (NÍVEL 3) | E1: PROGRAMAUO | F1: PROGRAMA | G1: prog cod | H1: AÇÃO | I1: ENTREGA | J1: ELEMENTO | K1: elem cod | L1: ELEMENTO_ITEM | M1: GRUPO | N1: FONTEUO | O1: FONTE (OPCIONAL) | P1: ITEM DE MATERIAL (OPCIONAL) | Q1: NOVO? | R1: PREMISSA VOLUME | S1: VOLUME | T1: PREMISSA DE PREÇO | U1: PREÇO UNITÁRIO | V1: FREQUÊNCIA PAGAMENTO | W1: VALOR TOTAL ITEM | X1: CLASSIFICAÇÃO CENÁRIO | Y1: DESCRIÇÃO DO CENÁRIO - pacotes de despesa / gera valor agregado | Z1: RISCO DE NÃO FAZER | AA1: BENEFICIO AO FAZER | AB1: PRIORIDADE N3 | AC1: PRIORIDADE N2 | AD1: PRIORIDADE N1
A2: FAOP | E2: =CONCATENATE(A2,"PROG") -> FAOPPROG | F2: 060 - FORMACAO CULTURAL | G2: =CONCATENATE("P",(LEFT(F2,3)),A2) -> P060FAOP | H2: 1029 - ATIVIDADES DE ENSINO, FORMACAO E QUALIFICACAO PROFISSIONAL E TECNICA EM CULTURA E PATRIMONIO | I2: CURSO DE CAPACITAÇÃO | J2: 30 - MATERIAL DE CONSUMO | K2: =CONCATENATE("ELEM",LEFT(J2,2)) -> ELEM30 | L2: 3012 - MEDICAMENTOS | M2: 3 - Outras Despesas de Custeio | N2: =CONCATENATE("FONTE",A2) -> FONTEFAOP | O2: 45 | Q2: NÃO | R2: NÚMERO DE DIÁRIAS UTILIZADAS (2) X NUMERO DE SERVIDORES FAVORECIDOS (1) | S2: 2 | T2: VALOR DA DIÁRIA | U2: 200 | V2: 1 | W2: =S2*U2*V2 -> 400 | X2: LIMIAR | Y2: curso com um professor | Z2: curso precisa de pelo menos um professor | AA2: não tem como ter curso sem professor
A3: FAOP | E3: =CONCATENATE(A3,"PROG") -> FAOPPROG | F3: 060 - FORMACAO CULTURAL | G3: =CONCATENATE("P",(LEFT(F3,3)),A3) -> P060FAOP | H3: 1029 - ATIVIDADES DE ENSINO, FORMACAO E QUALIFICACAO PROFISSIONAL E TECNICA EM CULTURA E PATRIMONIO | I3: CURSO DE CAPACITAÇÃO | J3: 33 - PASSAGENS E DESPESAS COM LOCOMOÇÃO | K3: =CONCATENATE("ELEM",LEFT(J3,2)) -> ELEM33 | L3: 3301 - PASSAGENS - PESSOA FÍSICA | M3: 3 - Outras Despesas de Custeio | N3: =CONCATENATE("FONTE",A3) -> FONTEFAOP | O3: 45 | Q3: NÃO | R3: 1 PASSAGEM DE IDA E VOLTA DE OURO PRETO PARA BH | S3: 1 | T3: VALOR DA PASSAGEM IDA E VOLTA | U3: 45 | V3: 1 | W3: =S3*U3*V3 -> 45 | X3: LIMIAR | Y3: curso com um professor | Z3: curso precisa de pelo menos um professor | AA3: não tem como ter curso sem professor
A4: FAOP | E4: =CONCATENATE(A4,"PROG") -> FAOPPROG | F4: 060 - FORMACAO CULTURAL | G4: =CONCATENATE("P",(LEFT(F4,3)),A4) -> P060FAOP | H4: 1029 - ATIVIDADES DE ENSINO, FORMACAO E QUALIFICACAO PROFISSIONAL E TECNICA EM CULTURA E PATRIMONIO | I4: CURSO DE CAPACITAÇÃO | J4: 14 - DIÁRIAS - CIVIL | K4: =CONCATENATE("ELEM",LEFT(J4,2)) -> ELEM14 | L4: 1401 - DIÁRIAS CIVIL | M4: 3 - Outras Despesas de Custeio | N4: =CONCATENATE("FONTE",A4) -> FONTEFAOP | O4: 45 | Q4: NÃO | R4: NÚMERO DE DIÁRIAS UTILIZADAS (2) X NUMERO DE SERVIDORES FAVORECIDOS (1) | S4: 2 | T4: VALOR DA DIÁRIA | U4: 200 | V4: 1 | W4: =S4*U4*V4 -> 400 | X4: INCREMENTAL | Y4: curso com professor convidado | Z4: CURSO MENOS INTERESSANTE, MENOR CARGA HORÁRIO E POSSÍVEL MENOS ADESÃO DO PÚBLICO | AA4: 1 | AB4: 1
A5: FAOP | E5: =CONCATENATE(A5,"PROG") -> FAOPPROG | F5: 060 - FORMACAO CULTURAL | G5: =CONCATENATE("P",(LEFT(F5,3)),A5) -> P060FAOP | H5: 1029 - ATIVIDADES DE ENSINO, FORMACAO E QUALIFICACAO PROFISSIONAL E TECNICA EM CULTURA E PATRIMONIO | I5: CURSO DE CAPACITAÇÃO EM RESTAURAÇÃO | J5: 33 - PASSAGENS E DESPESAS COM LOCOMOÇÃO | K5: =CONCATENATE("ELEM",LEFT(J5,2)) -> ELEM33 | L5: 3301 - PASSAGENS - PESSOA FÍSICA | M5: 3 - Outras Despesas de Custeio | N5: =CONCATENATE("FONTE",A5) -> FONTEFAOP | O5: 45 | Q5: NÃO | R5: 1 PASSAGEM DE IDA E VOLTA DE OURO PRETO PARA BH | S5: 1 | T5: VALOR DA PASSAGEM IDA E VOLTA | U5: 45 | V5: 1 | W5: =S5*U5*V5 -> 45 | X5: INCREMENTAL | Y5: curso com professor convidado | Z5: CURSO MENOS INTERESSANTE, MENOR CARGA HORÁRIO E POSSÍVEL MENOS ADESÃO DO PÚBLICO | AA5: CURSO COM MAIOR QUALIDADE E ADESÃO DO PÚBLICO | AB5: 1
A6: FAOP | E6: =CONCATENATE(A6,"PROG") -> FAOPPROG | F6: 060 - FORMACAO CULTURAL | G6: =CONCATENATE("P",(LEFT(F6,3)),A6) -> P060FAOP | H6: 1029 - ATIVIDADES DE ENSINO, FORMACAO E QUALIFICACAO PROFISSIONAL E TECNICA EM CULTURA E PATRIMONIO | I6: CURSO DE CAPACITAÇÃO EM RESTAURAÇÃO | J6: 30 - MATERIAL DE CONSUMO | K6: =CONCATENATE("ELEM",LEFT(J6,2)) -> ELEM30 | L6: 3004 - MATERIAL GRÁFICO E IMPRESSOS | M6: 3 - Outras Despesas de Custeio | N6: =CONCATENATE("FONTE",A6) -> FONTEFAOP | O6: 45 | P6: IMPRESSÃO DE FLYER PARA DIVULGAÇÃO (TAMANHO MEIO OFÍCIO) | Q6: NÃO | R6: QUANTITATIVO DE FLYERS NECESSÁRIOS PARA DIVULGAÇÃO DO EVENTO | S6: 300 | T6: PESQUISA DE PREÇO NA INTERNET | U6: 0.3 | V6: 1 | W6: =S6*U6*V6 -> 90 | X6: INCREMENTAL | Y6: curso com um professor | Z6: POUCAS INSCRIÇÕES NO CURSO DEVIDO A FALTA DE DIVULGAÇÃO - TER QUE DIVULGAR SOMENTE PELA INTERNET | AA6: MAIS PESSOAS CONHECENDO O CURSO E MAIORES CHANCES DE INSCRIÇÕES | AB6: 1
A7: FAOP | E7: =CONCATENATE(A7,"PROG") -> FAOPPROG | F7: 060 - FORMACAO CULTURAL | G7: =CONCATENATE("P",(LEFT(F7,3)),A7) -> P060FAOP | H7: 1029 - ATIVIDADES DE ENSINO, FORMACAO E QUALIFICACAO PROFISSIONAL E TECNICA EM CULTURA E PATRIMONIO | I7: CURSO DE CAPACITAÇÃO EM RESTAURAÇÃO | J7: 30 - MATERIAL DE CONSUMO | K7: =CONCATENATE("ELEM",LEFT(J7,2)) -> ELEM30 | L7: 3004 - MATERIAL GRÁFICO E IMPRESSOS | M7: 3 - Outras Despesas de Custeio | N7: =CONCATENATE("FONTE",A7) -> FONTEFAOP | O7: 45 | P7: IMPRESSÃO DE FLYER PARA DIVULGAÇÃO (TAMANHO MEIO OFÍCIO) | Q7: SIM | R7: QUANTITATIVO DE FLYERS NECESSÁRIOS PARA DIVULGAÇÃO DO EVENTO | S7: 200 | T7: PESQUISA DE PREÇO NA INTERNET | U7: 0.3 | V7: 1 | W7: =S7*U7*V7 -> 60 | X7: INCREMENTAL | Y7: curso com um professor e professor convidado | Z7: POUCAS INSCRIÇÕES NO CURSO DEVIDO A FALTA DE DIVULGAÇÃO | AA7: MAIS PESSOAS CONHECENDO O CURSO E MAIORES CHANCES DE INSCRIÇÕES | AB7: 2
A8: FAOP | E8: =CONCATENATE(A8,"PROG") -> FAOPPROG | F8: 060 - FORMACAO CULTURAL | G8: =CONCATENATE("P",(LEFT(F8,3)),A8) -> P060FAOP | H8: 1029 - ATIVIDADES DE ENSINO, FORMACAO E QUALIFICACAO PROFISSIONAL E TECNICA EM CULTURA E PATRIMONIO | I8: CURSO DE CAPACITAÇÃO EM RESTAURAÇÃO | J8: 30 - MATERIAL DE CONSUMO | K8: =CONCATENATE("ELEM",LEFT(J8,2)) -> ELEM30 | L8: 3005 - MATERIAL PARA ESCRITÓRIO | M8: 3 - Outras Despesas de Custeio | N8: =CONCATENATE("FONTE",A8) -> FONTEFAOP | O8: 45 | P8: PACOTE DEFOLHA A4 BRANCA COM 100 UNIDADES | Q8: NÃO | R8: MÉDIA DE CONSUMO PARA UM CURSO DE 2 DIAS | S8: 1 | T8: CONSULTA DO VALOR DO ITEM NO SIAD | U8: 25 | V8: 1 | W8: =S8*U8*V8 -> 25 | X8: LIMIAR | Y8: curso com um professor e professor convidado
A9: FAOP | E9: =CONCATENATE(A9,"PROG") -> FAOPPROG | F9: 060 - FORMACAO CULTURAL | G9: =CONCATENATE("P",(LEFT(F9,3)),A9) -> P060FAOP | H9: 1029 - ATIVIDADES DE ENSINO, FORMACAO E QUALIFICACAO PROFISSIONAL E TECNICA EM CULTURA E PATRIMONIO | I9: CURSO DE CAPACITAÇÃO EM RESTAURAÇÃO | J9: 30 - MATERIAL DE CONSUMO | K9: =CONCATENATE("ELEM",LEFT(J9,2)) -> ELEM30 | L9: 3005 - MATERIAL PARA ESCRITÓRIO | M9: 3 - Outras Despesas de Custeio | N9: =CONCATENATE("FONTE",A9) -> FONTEFAOP | O9: 45 | P9: PACOTE DEFOLHA A4 BRANCA COM 100 UNIDADES | Q9: NÃO | R9: MÉDIA DE CONSUMO PARA UM CURSO DE 2 DIAS | S9: 1 | T9: CONSULTA DO VALOR DO ITEM NO SIAD | U9: 25 | V9: 1 | W9: =S9*U9*V9 -> 25 | X9: LIMIAR | Y9: curso com um professor
X10: INCREMENTAL | Y10: curso com coffe break
X11: INCREMENTAL | Y11: curso com coffe break
A12: FAOP | E12: =CONCATENATE(A12,"PROG") -> FAOPPROG | F12: 060 - FORMACAO CULTURAL | G12: =CONCATENATE("P",(LEFT(F12,3)),A12) -> P060FAOP | H12: 1029 - ATIVIDADES DE ENSINO, FORMACAO E QUALIFICACAO PROFISSIONAL E TECNICA EM CULTURA E PATRIMONIO | I12: MANUTENÇÃO DO ESPAÇO DE REALIZAÇÃO DOS CURSOS | J12: 37 - LOCAÇÃO DE MÃO-DE-OBRA | K12: =CONCATENATE("ELEM",LEFT(J12,2)) -> ELEM37 | L12: 3703 - LOCAÇÃO DE SERVIÇOS DE CONSERVAÇÃO E LIMPEZA REALIZADOS PELA MGS | M12: 3 - Outras Despesas de Custeio | N12: =CONCATENATE("FONTE",A12) -> FONTEFAOP | Q12: NÃO | R12: NÚMERO DE VIGIAS NECESSÁRIOS PARA SEGURANÇA MEIO TURNO | S12: 2 | T12: VALOR MENSAL DO POSTO DE TRABALHO CONFORME CONTRATO | U12: 2000 | V12: 12 | W12: =S12*U12*V12 -> 48000 | X12: LIMIAR
A13: FAOP | E13: =CONCATENATE(A13,"PROG") -> FAOPPROG | F13: 060 - FORMACAO CULTURAL | G13: =CONCATENATE("P",(LEFT(F13,3)),A13) -> P060FAOP | H13: 1029 - ATIVIDADES DE ENSINO, FORMACAO E QUALIFICACAO PROFISSIONAL E TECNICA EM CULTURA E PATRIMONIO | I13: MANUTENÇÃO DO ESPAÇO DE REALIZAÇÃO DOS CURSOS | J13: 37 - LOCAÇÃO DE MÃO-DE-OBRA | K13: =CONCATENATE("ELEM",LEFT(J13,2)) -> ELEM37 | L13: 3703 - LOCAÇÃO DE SERVIÇOS DE CONSERVAÇÃO E LIMPEZA REALIZADOS PELA MGS | M13: 3 - Outras Despesas de Custeio | N13: =CONCATENATE("FONTE",A13) -> FONTEFAOP | Q13: SIM | R13: NÚMERO DE VIGIAS NECESSÁRIOS PARA SEGURANÇA 24 HORAS | S13: 2 | T13: VALOR MENSAL DO POSTO DE TRABALHO CONFORME CONTRATO | U13: 2000 | V13: 12 | W13: =S13*U13*V13 -> 48000 | X13: INCREMENTAL
A14: FAOP | E14: =CONCATENATE(A14,"PROG") -> FAOPPROG | F14: 060 - FORMACAO CULTURAL | G14: =CONCATENATE("P",(LEFT(F14,3)),A14) -> P060FAOP | H14: 1029 - ATIVIDADES DE ENSINO, FORMACAO E QUALIFICACAO PROFISSIONAL E TECNICA EM CULTURA E PATRIMONIO | I14: MANUTENÇÃO DO ESPAÇO DE REALIZAÇÃO DOS CURSOS | J14: 37 - LOCAÇÃO DE MÃO-DE-OBRA | K14: =CONCATENATE("ELEM",LEFT(J14,2)) -> ELEM37 | L14: 3703 - LOCAÇÃO DE SERVIÇOS DE CONSERVAÇÃO E LIMPEZA REALIZADOS PELA MGS | M14: 3 - Outras Despesas de Custeio | N14: =CONCATENATE("FONTE",A14) -> FONTEFAOP | Q14: NÃO | R14: NÚMERO DE FAXINEIRAS PARA MANUTENÇÃO DO ESPAÇO DOS CURSOS | S14: 1 | T14: VALOR MENSAL DO POSTO DE TRABALHO CONFORME CONTRATO | U14: 1500 | V14: 12 | W14: =S14*U14*V14 -> 18000 | X14: LIMIAR | Y14: segurança 24 horas | AB14: 1
A15: FAOP | E15: =CONCATENATE(A15,"PROG") -> FAOPPROG | F15: 060 - FORMACAO CULTURAL | G15: =CONCATENATE("P",(LEFT(F15,3)),A15) -> P060FAOP | H15: 1029 - ATIVIDADES DE ENSINO, FORMACAO E QUALIFICACAO PROFISSIONAL E TECNICA EM CULTURA E PATRIMONIO | I15: MANUTENÇÃO DO ESPAÇO DE REALIZAÇÃO DOS CURSOS | J15: 39 - OUTROS SERVIÇOS DE TERCEIROS - PESSOA JURÍDICA | K15: =CONCATENATE("ELEM",LEFT(J15,2)) -> ELEM39 | L15: 3912 - TARIFA DE ENERGIA ELÉTRICA | M15: 3 - Outras Despesas de Custeio | N15: =CONCATENATE("FONTE",A15) -> FONTEFAOP | Q15: NÃO | R15: fazer o rateio | S15: 1 | T15: VALOR MENSAL DO POSTO DE TRABALHO CONFORME CONTRATO | U15: 1500 | V15: 12 | W15: =S15*U15*V15 -> 18000 | X15: LIMIAR
J16: 39 - OUTROS SERVIÇOS DE TERCEIROS - PESSOA JURÍDICA
A18: DER | E18: =CONCATENATE(A18,"PROG") -> DERPROG | F18: 081 - INFRAESTRUTURA RODOVIARIA | G18: =CONCATENATE("P",(LEFT(F18,3)),A18) -> P081DER | H18: 2039 - RECUPERACAO E MANUTENCAO DA MALHA VIARIA | I18: RECAPEAMENTO DE VIAS | J18: 51 - OBRAS E INSTALAÇÕES | K18: =CONCATENATE("ELEM",LEFT(J18,2)) -> ELEM51 | L18: 5107 - EXECUÇÃO DE OBRAS POR CONTRATO DE BENS NÃO PATRIMONIÁVEIS | M18: 4 - Investimento | N18: =CONCATENATE("FONTE",A18) -> FONTEDER | Q18: NÃO | R18: KM DE RODOVIA A SEREM PAVIMENTADOS | S18: 500 | T18: VALOR MÉDIO POR KM PAVIMENTADO | U18: 50000 | V18: 1 | W18: =S18*U18*V18 -> 25000000
A19: DER | E19: =CONCATENATE(A19,"PROG") -> DERPROG | F19: 081 - INFRAESTRUTURA RODOVIARIA | G19: =CONCATENATE("P",(LEFT(F19,3)),A19) -> P081DER | H19: 2039 - RECUPERACAO E MANUTENCAO DA MALHA VIARIA | I19: RECAPEAMENTO DE VIAS | J19: 35 - SERVIÇOS DE CONSULTORIA | K19: =CONCATENATE("ELEM",LEFT(J19,2)) -> ELEM35 | L19: 3502 - SERVIÇOS DE CONSULTORIA ? PESSOA JURÍDICA | M19: 3 - Outras Despesas de Custeio | N19: =CONCATENATE("FONTE",A19) -> FONTEDER | P19: CONTRATAÇÃO DE CONSULTORIA PARA REALIZAÇÃO DE PROJETO DE ENGENHARIA | Q19: SIM | R19: CONTRATO FIRMADO | S19: 1 | T19: VALOR MÉDIO DE MERCADO | U19: 25000 | V19: 1 | W19: =S19*U19*V19 -> 25000
E20: =CONCATENATE(A20,"PROG") -> PROG | G20: =CONCATENATE("P",(LEFT(F20,3)),A20) -> P | K20: =CONCATENATE("ELEM",LEFT(J20,2)) -> ELEM | N20: =CONCATENATE("FONTE",A20) -> FONTE | W20: =S20*U20*V20 -> 0
E21: =CONCATENATE(A21,"PROG") -> PROG | G21: =CONCATENATE("P",(LEFT(F21,3)),A21) -> P | K21: =CONCATENATE("ELEM",LEFT(J21,2)) -> ELEM | N21: =CONCATENATE("FONTE",A21) -> FONTE | W21: =S21*U21*V21 -> 0
E22: =CONCATENATE(A22,"PROG") -> PROG | G22: =CONCATENATE("P",(LEFT(F22,3)),A22) -> P | K22: =CONCATENATE("ELEM",LEFT(J22,2)) -> ELEM | N22: =CONCATENATE("FONTE",A22) -> FONTE | W22: =S22*U22*V22 -> 0
E23: =CONCATENATE(A23,"PROG") -> PROG | G23: =CONCATENATE("P",(LEFT(F23,3)),A23) -> P | K23: =CONCATENATE("ELEM",LEFT(J23,2)) -> ELEM | N23: =CONCATENATE("FONTE",A23) -> FONTE | W23: =S23*U23*V23 -> 0
E24: =CONCATENATE(A24,"PROG") -> PROG | G24: =CONCATENATE("P",(LEFT(F24,3)),A24) -> P | K24: =CONCATENATE("ELEM",LEFT(J24,2)) -> ELEM | N24: =CONCATENATE("FONTE",A24) -> FONTE | W24: =S24*U24*V24 -> 0
E25: =CONCATENATE(A25,"PROG") -> PROG | G25: =CONCATENATE("P",(LEFT(F25,3)),A25) -> P | K25: =CONCATENATE("ELEM",LEFT(J25,2)) -> ELEM | N25: =CONCATENATE("FONTE",A25) -> FONTE | W25: =S25*U25*V25 -> 0
E26: =CONCATENATE(A26,"PROG") -> PROG | G26: =CONCATENATE("P",(LEFT(F26,3)),A26) -> P | K26: =CONCATENATE("ELEM",LEFT(J26,2)) -> ELEM | N26: =CONCATENATE("FONTE",A26) -> FONTE | W26: =S26*U26*V26 -> 0
E27: =CONCATENATE(A27,"PROG") -> PROG | G27: =CONCATENATE("P",(LEFT(F27,3)),A27) -> P | K27: =CONCATENATE("ELEM",LEFT(J27,2)) -> ELEM | N27: =CONCATENATE("FONTE",A27) -> FONTE | W27: =S27*U27*V27 -> 0
E28: =CONCATENATE(A28,"PROG") -> PROG | G28: =CONCATENATE("P",(LEFT(F28,3)),A28) -> P | K28: =CONCATENATE("ELEM",LEFT(J28,2)) -> ELEM | N28: =CONCATENATE("FONTE",A28) -> FONTE | W28: =S28*U28*V28 -> 0
E29: =CONCATENATE(A29,"PROG") -> PROG | G29: =CONCATENATE("P",(LEFT(F29,3)),A29) -> P | K29: =CONCATENATE("ELEM",LEFT(J29,2)) -> ELEM | N29: =CONCATENATE("FONTE",A29) -> FONTE | W29: =S29*U29*V29 -> 0
E30: =CONCATENATE(A30,"PROG") -> PROG | G30: =CONCATENATE("P",(LEFT(F30,3)),A30) -> P | K30: =CONCATENATE("ELEM",LEFT(J30,2)) -> ELEM | N30: =CONCATENATE("FONTE",A30) -> FONTE | W30: =S30*U30*V30 -> 0
E31: =CONCATENATE(A31,"PROG") -> PROG | G31: =CONCATENATE("P",(LEFT(F31,3)),A31) -> P | K31: =CONCATENATE("ELEM",LEFT(J31,2)) -> ELEM | N31: =CONCATENATE("FONTE",A31) -> FONTE | W31: =S31*U31*V31 -> 0
... E215: =CONCATENATE(A215,"PROG") -> PROG | G215: =CONCATENATE("P",(LEFT(F215,3)),A215) -> P | K215: =CONCATENATE("ELEM",LEFT(J215,2)) -> ELEM | N215: =CONCATENATE("FONTE",A215) -> FONTE | W215: =S215*U215*V215 -> 0

Sheet PONTOS IMPORTANTES
H1: INDICE
B2: PONTOS IMPORTANTES NA ELABORAÇÃO DO OBZ
B4: Cenário Limiar: nível de serviço mínimo aceitável para garantir a execução de entregas (políticas públicas) essenciais às condições de sobrevivência do órgão | E4: Cenário Incremental: despesas que geram nível de serviço e de qualidade superiores, realizadas para melhorar os resultados ou diminuir riscos. (Por exemplo: cenários intermediários e ótimo).
B6: O OBZ terá como foco a margem discricionária do orçamento de cada órgão: despesas de custeio e capital sobre as quais a unidade tem liberdade de alocação. As Planilhas OBZ não conterão, portanto: Despesas com pessoal (Grupo 1) e auxílios (IPU 7); Fontes de recursos vinculadas a instrumentos jurídicos (exemplos: convênios e contrapartidas, fontes federais, recursos da Vale, etc.); Emendas parlamentares e de CPP (IPUs 8 e 4); Despesas com precatórios (IPU 9); Despesas de Recursos Recebidos para Contrapartida (IPU 3 e 6) e Despesas de Exercícios Anteriores (DEA - Elemento de despesa 92)
B8: PONTOS DE ATENÇÃO – PREENCHIMENTO DA PLANILHA
B10: Preencher riscos de não fazer e benefícios de fazer para: Cenários Limiar e Incremental | E10: Não existe prioridade entre cenários limiares de diferentes níveis N3. Todo cenário limiar será prioridade 0 (zero).
B12: Se atentar ao número de cenários por ação, com intuito de viabilizar análise gerencial: o nível N1 analisará toda a planilha, portanto é necessário que a forma de construção dos cenários permita uma visão consolidada dos dados, e apresente um valor significante em relação ao orçamento do órgão.

Sheet ELEMENTO
A1: 13 - OBRIGAÇÕES PATRONAIS | B1: 14 - DIÁRIAS - CIVIL | C1: 15 - DIÁRIAS - MILITAR | D1: 16 - OUTRAS DESPESAS VARIÁVEIS - PESSOAL CIVIL | E1: 17 - OUTRAS DESPESAS VARIÁVEIS - PESSOAL MILITAR | F1: 18 - AUXÍLIO FINANCEIRO A ESTUDANTES | G1: 19 - AUXÍLIO-FARDAMENTO | H1: 20 - AUXÍLIO FINANCEIRO A PESQUISADORES | I1: 30 - MATERIAL DE CONSUMO | J1: 31 - PREMIAÇÕES CULTURAIS, ARTÍSTICAS, CIENTÍFICAS, DESPORTIVAS E OUTRAS. | K1: 32 - MATERIAL, BEM OU SERVIÇO PARA DISTRIBUIÇÃO GRATUITA | L1: 33 - PASSAGENS E DESPESAS COM LOCOMOÇÃO | M1: 34 - OUTRAS DESPESAS DE PESSOAL DECORRENTES DE CONTRATOS DE TERCEIRIZAÇÃO | N1: 35 - SERVIÇOS DE CONSULTORIA | O1: 36 - OUTROS SERVIÇOS DE TERCEIROS - PESSOA FÍSICA | P1: 37 - LOCAÇÃO DE MÃO-DE-OBRA | Q1: 38 - ARRENDAMENTO MERCANTIL | R1: 39 - OUTROS SERVIÇOS DE TERCEIROS - PESSOA JURÍDICA | S1: 40 - SERVIÇOS DE TECNOLOGIA DA INFORMAÇÃO E COMUNICAÇÃO - PESSOA JURÍDICA | T1: 41 - CONTRIBUIÇÕES | U1: 42 - AUXÍLIOS | V1: 43 - SUBVENÇÕES SOCIAIS | W1: 45 - SUBVENÇÕES ECONÔMICAS | X1: 47 - OBRIGAÇÕES TRIBUTÁRIAS E CONTRIBUTIVAS | Y1: 48 - OUTROS AUXÍLIOS FINANCEIROS A PESSOAS FÍSICAS | Z1: 51 - OBRAS E INSTALAÇÕES | AA1: 52 - EQUIPAMENTOS E MATERIAL PERMANENTE | AB1: 61 - AQUISIÇÃO DE IMÓVEIS | AC1: 62 - AQUISIÇÃO DE PRODUTOS PARA REVENDA | AD1: 63 - AQUISIÇÃO DE TÍTULOS DE CRÉDITO | AE1: 64 - AQUISIÇÃO DE TÍTULOS REPRESENTATIVOS DE CAPITAL JÁ INTEGRALIZADO | AF1: 65 - CONSTITUIÇÃO OU AUMENTO DE CAPITAL DE EMPRESAS | AG1: 66 - CONCESSÃO DE EMPRÉSTIMOS E FINANCIAMENTOS | AH1: 67 - DEPÓSITOS COMPULSÓRIOS | AI1: 93 - INDENIZAÇÕES E RESTITUIÇÕES | AJ1: 94 - INDENIZAÇÕES E RESTITUIÇÕES TRABALHISTAS | AK1: 95 - INDENIZAÇÃO PELA EXECUÇÃO DE TRABALHOS DE CAMPO
A2: 1304 - INSS | B2: 1401 - DIÁRIAS CIVIL | C2: 1501 - DIÁRIAS MILITAR | D2: 1601 - SERVIÇO EXTRAORDINÁRIO | E2: 1701 - OUTRAS DESPESAS VARIÁVEIS ? PESSOAL MILITAR | F2: 1801 - AUXÍLIO FINANCEIRO A ESTUDANTES | G2: 1901 - AUXÍLIO-FARDAMENTO | H2: 2001 - AUXÍLIO FINANCEIRO A PESQUISADORES | I2: 3001 - ARTIGOS PARA CONFECÇÃO E VESTUÁRIO | J2: 3101 - PRÊMIOS, DIPLOMAS, CONDECORAÇÕES E MEDALHAS | K2: 3201 - MATERIAL DE DISTRIBUIÇÃO GRATUITA | L2: 3301 - PASSAGENS - PESSOA FÍSICA | M2: 3401 - OUTRAS DESPESAS DE PESSOAL DECORRENTES DE CONTRATOS DE TERCEIRIZAÇÃO | N2: 3501 - SERVIÇOS DE CONSULTORIA ? PESSOA FÍSICA | O2: 3601 - ESTAGIÁRIOS | P2: 3701 - LOCAÇÃO DE SERVIÇOS DE CONSERVAÇÃO E LIMPEZA | Q2: 3801 - ARRENDAMENTO MERCANTIL | R2: 3901 - VALE-TRANSPORTE | S2: 4002 - SERVIÇOS DE TECNOLOGIA DA INFORMAÇÃO | T2: 4101 - CONTRIBUIÇÕES | U2: 4201 - AUXÍLIOS | V2: 4301 - SUBVENÇÕES SOCIAIS | W2: 4501 - SUBVENÇÕES ECONÔMICAS | X2: 4702 - IMPOSTO DE RENDA - IR | Y2: 4801 - OUTROS AUXÍLIOS FINANCEIROS A PESSOAS FÍSICAS | Z2: 5101 - ESTUDOS E PROJETOS DE BENS PATRIMONIÁVEIS | AA2: 5201 - AERONAVES E COMPONENTES ESTRUTURAIS | AB2: 6101 - TERRENOS | AC2: 6201 - AQUISIÇÃO DE PRODUTOS PARA REVENDA | AD2: 6301 - AQUISIÇÃO DE TÍTULOS DE CRÉDITO | AE2: 6401 - AQUISIÇÃO DE TÍTULOS REPRESENTATIVOS DE CAPITAL JÁ INTEGRALIZADO | AF2: 6501 - CONSTITUIÇÃO OU AUMENTO DE CAPITAL DE EMPRESAS | AG2: 6601 - CONCESSÃO DE EMPRÉSTIMOS E FINANCIAMENTOS | AH2: 6701 - DEPÓSITOS COMPULSÓRIOS | AI2: 9301 - AJUDA DE CUSTO | AJ2: 9401 - INDENIZAÇÕES E RESTITUIÇÕES TRABALHISTAS | AK2: 9501 - INDENIZAÇÃO PELA EXECUÇÃO DE TRABALHOS DE CAMPO
A3: 1305 - OBRIGAÇÃO PATRONAL - PESSOAL ATIVO - PREVIDÊNCIA | D3: 1602 - SUBSTITUIÇÃO EM CARGOS EM COMISSÃO | G3: 1902 - ADIANTAMENTO ? FARDAMENTO | I3: 3002 - ARTIGOS PARA ESPORTE | J3: 3102 - PRÊMIOS LOTÉRICOS | K3: 3202 - MATERIAL DE ASSISTÊNCIA HUMANITÁRIA | L3: 3302 - DESPESAS COM TRANSPORTE URBANO, PEDÁGIO E ESTACIONAMENTO - PESSOA FÍSICA | M3: 3402 - AGENTES PENITENCIÁRIOS | N3: 3502 - SERVIÇOS DE CONSULTORIA ? PESSOA JURÍDICA | O3: 3602 - MÉDICOS RESIDENTES | P3: 3702 - LOCAÇÃO DE SERVIÇOS DE APOIO ADMINISTRATIVO | R3: 3902 - VALE-REFEIÇÃO | S3: 4003 - SERVIÇOS DE INFORMÁTICA EXECUTADOS PELA PRODEMGE | T3: 4102 - TRANSFERÊNCIAS AO FUNDHAB | X3: 4703 - IMPOSTO PREDIAL TERRITORIAL URBANO - IPTU | Y3: 4802 - AUXILIO FINANCEIRO ? PROGRAMA POUPANÇA JOVEM | Z3: 5102 - EXECUÇÃO DIRETA DE OBRAS DE BENS PATRIMONIÁVEIS | AA3: 5202 - ANIMAIS DE TRABALHO, PRODUÇÃO E / OU REPRODUÇÃO | AB3: 6102 - SALAS E ESCRITÓRIOS | AF3: 6502 - CONSTITUIÇÃO OU AUMENTO DE CAPITAL DE EMPRESAS ? CAPITAL INTEGRALIZADO | AG3: 6602 - EMPRÉSTIMOS E FINANCIAMENTOS ? FUNDOS DE DESENVOLVIMENTO | AI3: 9302 - AJUDA DE CUSTO ESPECIAL | AJ3: 9330 - REEMBOLSO DE DESPESA REALIZADA E CONTRATOS OU CONVÊNIOS FIRMADOS EM REGIME DE PARCERIA
A4: 1306 - OBRIGAÇÃO PATRONAL - PESSOAL INATIVO - PREVIDÊNCIA | D4: 1603 - AULAS FACULTATIVAS | G4: 1903 - AUXILIO FARDAMENTO PAGO A PESSOAL CONTRATADO | I4: 303 - UTENSÍLIOS PARA COPA, REFEITÓRIO E COZINHA | J4: 3103 - COMISSÕES LOTÉRICAS | L4: 3303 - FRETAMENTO E LOCAÇÃO - PESSOA FÍSICA | M4: 3403 - OBRIGAÇÃO PATRONAL – INSS | N4: 3503 - SERVIÇOS DE CONSULTORIA ? ORGANISMO INTERNACIONAL | O4: 3603 - SALÁRIOS DE INTERNOS | P4: 3703 - LOCAÇÃO DE SERVIÇOS DE CONSERVAÇÃO E LIMPEZA REALIZADOS PELA MGS | R4: 3903 - FORNECIMENTO DE ALIMENTAÇÃO | S4: 4004 - SERVIÇO DE TELECOMUNICAÇÃO | T4: 4103 - CONTRIBUIÇÕES AO IPLEMG | X4: 4704 - IMPOSTO SOBRE OPERAÇÕES FINANCEIRAS - IOF | Y4: 4803 - AUXÍLIO PARA PROFISSIONAIS DE PROGRAMAS DE CAPACITAÇÃO E FORMAÇÃO | Z4: 5103 - EXECUÇÃO DE OBRAS POR CONTRATO DE BENS PATRIMONIÁVEIS | AA4: 5203 - ARMAMENTO E EQUIPAMENTO DE USO POLICIAL | AB4: 6103 - FAZENDAS | AG4: 6603 - CONCESSÃO DE FINANCIAMENTOS HABITACIONAIS | AI4: 9303 - PERDAS DECORRENTES DE APLICAÇÕES FINANCEIRAS
A5: 1308 - OBRIGAÇÃO PATRONAL - PENSIONISTAS - PREVIDÊNCIA | D5: 1604 - GRATIFICAÇÃO POR ENCARGOS EXTRAORDINÁRIOS | I5: 3004 - MATERIAL GRÁFICO E IMPRESSOS | J5: 3104 - PREMIAÇÕES | L5: 3304 - PASSAGENS - PESSOA JURÍDICA | M5: 3404 - OBRIGAÇÃO PATRONAL – ASSISTÊNCIA À SAÚDE | O5: 3604 - DIÁRIAS A COLABORADORES EVENTUAIS | P5: 3704 - LOCAÇÃO DE SERVIÇOS DE APOIO ADMINISTRATIVO REALIZADOS PELA MGS | R5: 3904 - CONFECÇÃO EM GERAL | S5: 4005 - REDE IP MULTISSERVIÇOS | T5: 4104 - CONTRIBUIÇÕES DO FUNDO ESTADUAL DE SAUDE - FES - LC 141/2012 | X5: 4705 - IMPOSTO SOBRE A PROPRIEDADE DE VEÍCULOS AUTOMOTORES - IPVA | Z5: 5104 - INSTALAÇÕES PARA OBRAS EM ANDAMENTO | AA5: 5204 - MÁQUINAS, APARELHOS, UTENSÍLIOS E EQUIPAMENTOS DE USO INDUSTRIAL | AB5: 6104 - EDIFÍCIOS | AI5: 9304 - DESPESAS REFERENTES A RESSARCIMENTO PREVISTO NO PROGRAMA PRIMEIRO EMPREGO DO ESTADO DE MINA GERAIS
A6: 1309 - OBRIGAÇÃO PATRONAL - PRECATÓRIOS - PREVIDÊNCIA | D6: 1605 - FÉRIAS-PRÊMIO | I6: 3005 - MATERIAL PARA ESCRITÓRIO | L6: 3305 - SERVIÇOS DE TRANSPORTES DE PASSAGEIROS, FRETAMENTO E LOCAÇÃO - PESSOA JURÍDICA | M6: 3405 - SALÁRIO-FAMÍLIA | O6: 3606 - FORNECIMENTO DE ALIMENTAÇÃO | P6: 3705 - DESPESAS COM O PAGAMENTO DE ENCARGOS TRABALHISTAS À MGS | R6: 3905 - TRANSPORTE E ACONDICIONAMENTO DE ANIMAIS | S6: 4006 - AQUISIÇÃO DE SOFTWARE | T6: 4105 - CONTRIBUIÇÕES À FUNDAÇÃO DE PREVIDÊNCIA COMPLEMENTAR DO ESTADO DE MINAS GERAIS -PREVCOM?MG | X6: 4706 - CONTRIBUIÇÃO PARA A FORMAÇÃO DO PASEP/PIS | Z6: 5106 - ESTUDOS E PROJETOS DE BENS NÃO PATRIMONIÁVEIS | AA6: 5205 - EMBARCAÇÕES, PONTÕES, DIQUES, FLUTUANTES E COMPONENTES ESTRUTURAIS | AB6: 6105 - IMÓVEIS PARA FINS DE TRANSFERÊNCIA A TERCEIROS | AI6: 9305 - DESPESAS DECORRENTES DE CONTRATOS DE CONCESSÃO OU PERMISSÃO
A7: 1310 - OBRIGAÇÃO PATRONAL - OUTRAS SENTENÇAS JUDICIAIS - PREVIDÊNCIA | D7: 1606 - JORNADA COMPLEMENTAR DE TRABALHO | I7: 3006 - MATERIAL DE DESENHO | O7: 3607 - CONFECÇÃO EM GERAL | P7: 3706 - LOCAÇÃO DE SERVIÇOS DE SAÚDE | R7: 3906 - TRANSPORTE E ACONDICIONAMENTO DE MATERIAIS E EQUIPAMENTOS | S7: 4007 - AQUISIÇÃO DE SOFTWARE DESENVOLVIDOS PELA PRODEMGE | T7: 4106 - TRANSFERÊNCIAS PARA FINANCIAMENTO DO TRANSPORTE ESCOLAR | X7: 4707 - TAXA DE LIMPEZA PÚBLICA E COLETA DE RESÍDUOS | Z7: 5107 - EXECUÇÃO DE OBRAS POR CONTRATO DE BENS NÃO PATRIMONIÁVEIS | AA7: 5206 - EQUIPAMENTOS DE COMUNICAÇÃO E TELEFONIA | AB7: 6106 - IMÓVEIS NECESSÁRIOS À REALIZAÇÃO DE OBRAS DE BENS PATRIMONIAVEIS | AI7: 9306 - RESTITUIÇÃO DE RECURSOS DE CONVÊNIO E DE CONTRAPARTIDA
A8: 1314 - OBRIGAÇÃO PATRONAL - ENCARGOS POR PAGAMENTO EM ATRASO | I8: 3007 - MATERIAL DE ENSINO | O8: 3608 - MÉDICOS | P8: 3707 - DESPESAS COM O PAGAMENTO DE OBRIGAÇÕES TRABALHISTAS | R8: 3909 - PUBLICIDADE | T8: 4107 - TRANSFERÊNCIAS ENTRE FUNDOS ESTADUAIS | X8: 4708 - TAXA DE ILUMINAÇÃO PÚBLICA | Z8: 5109 - EXECUÇÃO DIRETA DE OBRAS DE BENS NÃO PATRIMONIÁVEIS | AA8: 5207 - EQUIPAMENTOS DE INFORMÁTICA | AB8: 6107 - IMÓVEIS NECESSÁRIOS À REALIZAÇÃO DE OBRAS DE BENS NÃO-PATRIMONIAVEIS | AI8: 9307 - RESSARCIMENTO REFERENTE A PESSOAL REQUISITADO DA ADMINISTRAÇÃO ESTADUAL
A9: 1315 - OBRIGAÇÃO PATRONAL - PRÊMIO DE PRODUTIVIDADE | I9: 3008 - PRODUTOS ALIMENTÍCIOS | O9: 3609 - DENTISTAS | R9: 3910 - PRÊMIOS DE SEGUROS | T9: 4108 - TRANSFERÊNCIAS ESPECIAIS A MUNICÍPIOS | X9: 4709 - TAXAS AMBIENTAIS | Z9: 5110 - MATERIAL PARA OBRAS - BENS PATRIMONIÁVEIS | AA9: 5208 - EQUIPAMENTOS DE SOM, VÍDEO, FOTOGRÁFICO E CINEMATOGRÁFICO | AB9: 6108 - CASAS | AI9: 9308 - DESPESAS DE CARÁTER INDENIZATÓRIO RELATIVAS AO MANDADO PARLAMENTAR
A10: 1317 - INSS – DEMAIS DESPESAS | I10: 3009 - FORRAGENS E OUTROS ALIMENTOS PARA ANIMAIS | O10: 3610 - EVENTUAL DE GABINETE | R10: 3911 - ASSINATURAS DE JORNAIS, REVISTAS E PERIÓDICOS | X10: 4710 - PASEP - ADESÃO AO PARCELAMENTO DECORRENTE DE LEI ESPECÍFICA | Z10: 5111 - CONTRUÇÃO DE UNIDADES HABITACIONAIS | AA10: 5209 - EQUIPAMENTOS HOSPITALARES, ODONTOLÓGICOS E DE LABORATÓRIO | AI10: 9309 - PREMIO DE PRODUTIVIDADE
A11: 1318 - OBRIGAÇÃO PATRONAL PESSOAL INATIVO – ENTIDADES CONVENIADAS – ASSISTÊNCIA À SAÚDE | I11: 3010 - MATERIAL MÉDICO E HOSPITALAR | O11: 3611 - LOCAÇÃO DE BENS IMÓVEIS | R11: 3912 - TARIFA DE ENERGIA ELÉTRICA | X11: 4799 - OUTROS - OBRIGAÇÕES TRIBUTÁRIAS E CONTRIBUTIVAS | Z11: 5112 - MATERIAL PARA OBRAS - BENS NÃO PATRIMONIÁVEIS | AA11: 5210 - FERRAMENTAS, EQUIPAMENTOS E INSTRUMENTOS PARA OFICINA, MEDIÇÃO E INSPEÇÃO | AI11: 9310 - RESTITUIÇÃO DE RECEITA - EXERCÍCIO ANTERIOR
A12: 1319 - OBRIGAÇÃO PATRONAL PESSOAL MILITAR INATIVO LC 125/2012 – PREVIDÊNCIA | I12: 3011 - MATERIAL ODONTOLÓGICO | O12: 3612 - DESPESAS MIÚDAS DE PRONTO PAGAMENTO | R12: 3913 - TARIFA DE ÁGUA E ESGOTO | Z12: 5113 - INSTALAÇÕES PARA INCORPORAÇÃO A BENS IMÓVEIS | AA12: 5211 - INSTRUMENTOS DE LABORATÓRIO, MÉDICOS E ODONTOLÓGICOS | AI12: 9311 - COMPENSAÇÃO FINANCEIRA DOS REGIMES DE PREVIDÊNCIA
A13: 1320 - OBRIGAÇÃO PATRONAL PESSOAL MILITAR ATIVO LC 125/2012 - PREVIDÊNCIA | I13: 3012 - MEDICAMENTOS | O13: 3613 - PESSOAL DE ENFERMAGEM | R13: 3914 - SERVIÇO DE TELEFONIA | Z13: 5114 - EXECUÇÃO DE OBRAS POR EMPRESAS CONTROLADAS | AA13: 5212 - MÁQUINAS, APARELHOS, UTENSÍLIOS E EQUIPAMENTOS DE USO ADMINISTRATIVO | AI13: 9312 - INDENIZAÇÃO POR UTILIZAÇÃO DE BENS DE TERCEIROS
A14: 1321 - OBRIGAÇÃO PATRONAL - PESSOAL ATIVO - ASSISTÊNCIA À SAÚDE | I14: 3013 - MATERIAIS DE LABORATÓRIO E PRODUTOS QUÍMICOS EM GERAL | O14: 3614 - MONITORES, FISCAIS E EXAMINADORES | R14: 3915 - SERVIÇO POSTAL-TELEGRÁFICO | AA14: 5213 - MATERIAL ESPORTIVO E RECREATIVO | AI14: 9313 - REEMBOLSO DE DESPESAS MÉDICO-HOSPITALARES
A15: 1322 - OBRIGAÇÃO PATRONAL - PESSOAL INATIVO - ASSISTÊNCIA À SAÚDE | I15: 3014 - MATERIAL RADIOLÓGICO | O15: 3615 - ENCARGOS FINANCEIROS | R15: 3916 - LOCAÇÃO DE TV POR ASSINATURA | AA15: 5214 - MOBILIÁRIO | AI15: 9314 - INDENIZAÇÕES DETERMINADAS POR DECISÕES JUDICIAIS
A16: 1324 - OBRIGAÇÃO PATRONAL - PENSIONISTAS - ASSISTÊNCIA À SAÚDE | I16: 3015 - MATERIAL FOTOGRÁFICO, CINEMATOGRÁFICO E DE COMUNICAÇÃO | O16: 3616 - REPARO E MANUTENÇÃO DE VEÍCULOS | R16: 3917 - LOCAÇÃO DE VEÍCULOS | AA16: 5215 - OBJETOS DE ARTE E ANTIGÜIDADES | AI16: 9315 - INDENIZAÇÃO DECORRENTE DE RESCISÃO UNILATERAL
A17: 1325 - OBRIGAÇÃO PATRONAL - ADESÃO AO PARCELAMENTO DECORRENTE DE LEI ESPECÍFICA - PREVIDÊNCIA | I17: 3016 - MATERIAL DE INFORMÁTICA | O17: 3617 - REPAROS DE EQUIPAMENTOS, INSTALAÇÕES E MATERIAL PERMANENTE | R17: 3918 - REPAROS DE VEÍCULOS | AA17: 5216 - TRATORES, SIMILARES E IMPLEMENTOS | AI17: 9316 - INDENIZAÇÕES DETERMINADAS POR LEI ESPECÍFICA
A18: 1326 - OBRIGAÇÃO PATRONAL SUPLEMENTAR – PESSOAL ATIVO | I18: 3017 - ARTIGOS PARA LIMPEZA E HIGIENE | O18: 3618 - REPAROS DE BENS IMÓVEIS | R18: 3919 - LOCAÇÃO DE MÁQUINAS E EQUIPAMENTOS | AA18: 5217 - VEÍCULOS | AI18: 9317 - INDENIZAÇÃO DECORRENTE DO EXERCÍCIO DO CARGO DE CONSELHEIRO-PRESIDENTE E PROCURADOR-GERAL JUNTO AO TRIBUNAL DE CONTAS
I19: 3018 - MATÉRIAS-PRIMAS E PRODUTOS PARA MANIPULAÇÃO E INDÚSTRIAS DE TRANSFORMAÇÃO | O19: 3619 - CONFERÊNCIAS E EXPOSIÇÕES | R19: 3920 - LOCAÇÃO DE BENS IMÓVEIS | AA19: 5218 - COLEÇÕES E MATERIAIS BIBLIOGRÁFICOS | AI19: 9318 - DESPESAS COM AUXILIO MORADIA DE CARÁTER INDENIZATÓRIO RELATIVAS AO MANDADO PARLAMENTAR
I20: 3019 - MATERIAL PARA MANUTENÇÃO E REPAROS DE IMÓVEIS DE PROPRIEDADE DA ADMINISTRAÇÃO PÚBLICA | O20: 3620 - JETONS A CONSELHEIROS | R20: 3921 - INSTALAÇÃO, REPARAÇÃO, ADAPTAÇÃO E CONSERVAÇÃO DE EQUIPAMENTO E MATERIAL PERMANENTE | AA20: 5219 - INSTRUMENTOS MUSICAIS E ARTÍSTICOS | AI20: 9319 - INDENIZAÇÕES DECORRENTES DA UTILIZAÇÃO DE LEITOS DE INSTITUIÇÕES DE SAÚDE PRIVADAS
I21: 3020 - MATERIAL ELÉTRICO E ELETRÔNICO | O21: 3621 - ADVOGADOS DATIVOS | R21: 3922 - REPAROS DE BENS IMÓVEIS | AA21: 5220 - EQUIPAMENTOS DE SEGURANÇA ELETRÔNICA | AI21: 9323 - INDENIZAÇÃO DECORRENTE DE AUXÍLIO-SAÚDE
I22: 3021 - MATERIAL PARA MANUTENÇÃO E REPAROS DE BENS DE DOMÍNIO PÚBLICO OU DE TERCEIROS | O22: 3622 - TAXA DE CONDOMÍNIO | R22: 3923 - RECEPÇÕES, HOSPEDAGENS, HOMENAGENS E FESTIVIDADES | AA22: 5221 - MATERIAL DIDÁTICO | AI22: 9324 - AUXÍLIO-MORADIA DE CARÁTER INDENIZATÓRIO DEVIDO A MAGISTRADO
I23: 3022 - FERRAMENTAS, FERRAGENS E UTENSÍLIOS | O23: 3623 - GRATIFICAÇÃO POR ENCARGO DE CURSO OU CONCURSO | R23: 3924 - CURSOS, EXPOSIÇÕES, CONGRESSOS E CONFERÊNCIAS | AA23: 5222 - ESTRUTURAS E COMPONENTES | AI23: 9325 - AUXÍLIO-MORADIA DE CARÁTER INDENIZATÓRIO DEVIDO PELO TCE
I24: 3023 - MATERIAL PARA MANUTENÇÃO DE VEÍCULOS AUTOMOTORES | O24: 3624 - SERVIÇOS TÉCNICOS JUDICIAIS ? HONORÁRIOS PERICIAIS ? JUSTIÇA GRATUITA | R24: 3925 - ENCARGOS JUDICIAIS | AA24: 5223 - MÁQUINAS E EQUIPAMENTOS GRÁFICOS | AI24: 9326 - RESTITUICAO REFERENTE A TAXA DE INSCRIÇÃO, MATERIAL E SIMILARES
I25: 3024 - PEÇAS E ACESSÓRIOS PARA EQUIPAMENTOS E OUTROS MATERIAIS PERMANENTES | O25: 3625 - CONTRATAÇÃO PARA PRESTAÇÃO DE SERVIÇO POR CREDENCIADOS | R25: 3926 - ENCARGOS FINANCEIROS | AA25: 5224 - MÁQUINAS, INSTALAÇÕES E UTENSÍLIOS DE ESCRITÓRIO | AI25: 9327 - INDENIZAÇÃO DE TRANSPORTE DEVIDA AO OFICIAL DE JUSTIÇA E OFICIAL DE CARTÓRIO
I26: 3025 - MATERIAL DE SEGURANÇA, APETRECHOS OPERACIONAIS E POLICIAIS | O26: 3626 - SERVIÇOS DE ABASTECIMENTO E DISTRIBUIÇÃO DE ÁGUA | R26: 3928 - SERVIÇOS DE SAÚDE EXECUTADOS COM RECURSOS DO SUS | AA26: 5225 - APARELHOS E UTENSÍLIOS DOMÉSTICOS | AI26: 9328 - PENSÃO ACIDENTÁRIA
I27: 3026 - COMBUSTÍVEIS E LUBRIFICANTES PARA VEÍCULOS AUTOMOTORES | O27: 3627 - JUÍZES LEIGOS | R27: 3929 - SERVIÇOS MÉDICOS, ODONTOLÓGICOS E LABORATORIAIS | AA27: 5226 - EQUIPAMENTOS DE PROTEÇÃO, SEGURANÇA E SOCORRO | AI27: 9329 - DESPESA REFERENTE A RESSARCIMENTO SOBRE A REMUNERAÇÃO DOS PRESOS EM TRABALHO
I28: 3027 - COMBUSTÍVEIS E LUBRIFICANTES PARA EQUIPAMENTOS E OUTROS MATERIAIS PERMANENTES | O28: 3628 - SERVICOS TECNICOS JUDICIAIS - HONORARIOS PERICIAIS | R28: 3930 - MULTAS DE TRÂNSITO | AA28: 5299 - OUTROS MATERIAIS PERMANENTES | AI28: 9399 - OUTRAS INDENIZAÇÕES E RESTITUIÇÕES
I29: 3028 - ANIMAIS DESTINADOS A ESTUDOS, À PREPARAÇÃO DE PRODUTOS E AO ABATE | O29: 3629 - DIREITOS AUTORAIS | R29: 3931 - LOCAÇÃO DE SERVIÇOS GRÁFICOS
I30: 3029 - - SEMENTES, MUDAS DE PLANTAS E INSUMOS | O30: 3630 - SERVIÇOS MÉDICOS PRESTADOS POR CONTRATO | R30: 3933 - TAXA DE ADMINISTRAÇÃO
I31: 3030 - MATERIAIS PARA ACONDICIONAMENTO E EMBALAGEM | O31: 3631 - SERVIÇOS DE TREINAMENTO, CAPACITAÇÃO E APERFEIÇOAMENTO DE PESSOAL | R31: 3934 - SEGURO DE AERONAVES
I32: 3031 - LIVROS TÉCNICOS | O32: 3699 - OUTRAS DESPESAS PAGAS A PESSOAS FÍSICAS | R32: 3935 - REPARO E MANUTENÇÃO DE AERONAVES
I33: 3032 - MATERIAL CÍVICO E EDUCATIVO | R33: 3937 - TAXA DE CONDOMÍNIO
I34: 3033 - COMBUSTÍVEIS E LUBRIFICANTES PARA AERONAVES | R34: 3938 - SERVIÇOS DE IMPRESSÃO E ENCADERNAÇÃO
I35: 3034 - PEÇAS E ACESSÓRIOS PARA AERONAVES | R35: 3939 - SERVIÇOS DE PUBLICAÇÃO E DIVULGAÇÃO
I36: 3036 - MATERIAL BIBLIOGRÁFICO PARA BIBLIOTECAS PÚBLICAS | R36: 3941 - ANUIDADES, CERTIFICADOS E REGISTROS
I37: 3037 - MEDICAMENTOS ? DECISÃO JUDICIAL | R37: 3942 - SERVIÇOS GRÁFICOS DE SEGURANÇA
I38: 3038 - LEITE ? PROGRAMA LEITE PELA VIDA | R38: 3943 - SERVIÇOS DE ADMINISTRAÇÃO E GERENCIAMENTO DE FROTA DE VEÍCULOS
I39: 3039 - MATERIAL DE CONFECÇÃO EM GERAL | R39: 3944 - SERVIÇO DE SEGURANÇA FAZENDÁRIA
I40: 3040 - MATERIAL DE CAMA, MESA E BANHO | R40: 3946 - TERMO DE PARCERIA COM ORGANIZAÇÃO DA SOCIEDADE CIVIL DE INTERESSE PÚBLICO - OSCIP
I41: 3041 - MATERIAL DE PROTEÇÃO E SEGURANÇA | R41: 3947 - TAXA DE ADMINISTRAÇÃO DE CRÉDITO DE FINANCIAMENTOS HABITACIONAIS
I42: 3099 - OUTROS MATERIAIS | R42: 3948 - CURSOS DE FORMAÇÃO, CAPACITAÇÃO E PÓS-GRADUAÇÃO PARA SERVIDORES
R43: 3949 - CURSOS DE FORMAÇÃO E CAPACITAÇÃO PARA O CIDADÃO
R44: 3950 - SERVIÇOS DE AGENCIAMENTO DE VIAGENS
R45: 3951 - SERVIÇO DE GERENCIAMENTO, SUPERVISÃO E FISCALIZAÇÃO DE OBRAS
R46: 3952 - CONTRATAÇÃO DE ESTAGIÁRIOS
R47: 3953 - CURSOS DE FORMAÇÃO E CAPACITAÇÃO PROMOVIDOS PELO ESTADO
R48: 3954 - CONTRATO DE PARCERIA PÚBLICO-PRIVADA
R49: 3955 - EVENTOS DE COMUNICAÇÃO INSTITUCIONAL
R50: 3956 - SERVIÇOS DE PESQUISAS
R51: 3957 - COMISSÃO PELA CONSTRUÇÃO DE UNIDADES HABITACIONAIS
R52: 3958 - CONTRATAÇÃO DE PROJETOS EM PESQUISA DE CIÊNCIA, INOVAÇÃO E TECNOLOGIA
R53: 3959 - SERVIÇOS SANITÁRIOS E TRATAMENTO DE RESÍDUOS
R54: 3960 - SERVIÇOS DE ATENDIMENTO AO CIDADÃO
... R90: 3999 - OUTROS SERVIÇOS-PESSOA JURÍDICA

Sheet DECRETO DIÁRIAS
G1: INDICE
B3: DECRETO 47045, DE 14/09/2016 DISPÕE SOBRE VIAGEM A SERVIÇO E CONCESSÃO DE DIÁRIA NO ÂMBITO DA ADMINISTRAÇÃO PÚBLICA DIRETA, AUTÁRQUICA E FUNDACIONAL DO PODER EXECUTIVO E DÁ OUTRAS PROVIDÊNCIAS.
B5: Tabela de Valores – Viagens Nacionais | F5: Tabela de Valores – Viagens ao Exterior
B6: DESTINO | C6: FAIXA I (R$) | D6: FAIXA II (R$) | F6: SERVIDORES | G6: LOCALIDADE/VALOR (U$)
B7: Capitais, inclusive Belo Horizonte | C7: 470 | D7: 665 | G7: América do Sul e América Central | H7: Demais Localidades no exterior
B8: Municípios especiais e municípios de outros Estados que não sejam capitais | C8: 362 | D8: 608 | F8: Governador do Estado; Vice-Governador do Estado | G8: 400 | H8: 550
B9: Demais municípios | C9: 258 | D9: 354 | F9: Secretário-Geral, Secretário de Estado, Secretário Adjunto de Estado | G9: 350 | H9: 450
B10: Faixa I: Servidor que exerça cargo efetivo que exija até o nível médio ou superior de escolaridade, servidor investido em cargo de provimento em comissão, servidor que exerça função pública que exija até o nível médio ou superior de escolaridade, e os membros de conselhos estaduais. | F10: Demais autoridades – Subsecretário, dirigente máximo de órgão autônomo, fundação e autarquia e seus respectivos Vices e servidor investido em cargo de provimento em comissão do Grupo de Direção e Assessoramento que esteja no nível DAD-8 a DAD-12 ou DAI-26 a DAI-40 e exerça atividades inerentes à chefia de Gabinete do Vice-Governador ou de Secretaria de Estado ou de entidades ou às assessorias especiais do Governador. | G10: 300 | H10: 400
B14: Faixa II: Secretário-Geral, Secretário de Estado, Secretário Adjunto, Subsecretário, dirigente máximo de órgão autônomo, fundação e autarquia e seus respectivos vices, Comandante de Aeronave, Comandante de Avião, Comandante de Avião a jato, Piloto de Helicóptero, Primeiro Oficial de Aeronave e servidor investido em cargo de provimento em comissão do Grupo de Direção e Assessoramento que esteja no nível DAD-8 a DAD-12 ou DAI-25 a DAI-40 e exerça atividades inerentes à chefia de gabinete do Vice-Governador, de Secretaria de Estado ou de entidades ou às assessorias especiais do Governador.
B15: Relação dos Municípios Especiais: Araxá, Caxambú, Contagem, Ipatinga, Juiz de Fora, Ouro Preto, Patos de Minas, Tiradentes, Uberlândia. | F15: Demais servidores | G15: 300 | H15: 300
B18: Link para o Decreto: | C18: https://www.almg.gov.br/consulte/legislacao/completa/completa.html?num=47045&ano=2016&tipo=DEC

Sheet ORGANOGRAMA
A1: AGE | B1: ARMBH | C1: ARMVA | D1: ARSAE | E1: ARTEMIG | F1: CBMMG | G1: CGE | H1: DER | I1: EMATER | J1: EMC | K1: EPAMIG | L1: ESPMG | M1: FAOP | N1: FAPEMIG | O1: FCS | P1: FDM | Q1: FEAM | R1: FEAS | S1: FES | T1: FHA | U1: FHEMIG | V1: FHIDRO | W1: FJP | X1: FUCAM | Y1: FUNAPEC | Z1: FUNED | AA1: FUNTRANS | AB1: GMG | AC1: HEMOMINAS | AD1: IDENE | AE1: IEF | AF1: IEPHA | AG1: IGAM | AH1: IMA | AI1: IPSEMG | AJ1: IPSM | AK1: JUCEMG | AL1: LEMG | AM1: OGE | AN1: PCMG | AO1: PMMG | AP1: SCC | AQ1: SEAPA | AR1: SEC.GERAL | AS1: SECOM | AT1: SECULT | AU1: SEDE | AV1: SEDESE | AW1: SEE | AX1: SEF | AY1: SEGOV | AZ1: SEINFRA | BA1: SEJUSP | BB1: SEMAD | BC1: SEPLAG | BD1: TVMINAS | BE1: UEMG | BF1: UNIMONTES | BG1: UTRAMIG
A2: SUB DE ADMINISTRAÇÃO | B2: dsadasdas | C2: DSADAA
A3: dsadasj | B3: dksadsa | C3: FFDSSA
A4: kfdsafas | B4: kdsasa

Sheet CENÁRIO
A1: Cenário | C1: Novo
A2: LIMIAR | C2: SIM
A3: INCREMENTAL | C3: NÃO
C4: SIM
A7: GRUPO DE DESPESA
A8: 3 - Outras Despesas de Custeio
A9: 4 - Investimento
A10: 5 - Inversões Financeiras

Sheet Planilha1

Sheet BASE OBZ
F1: INDICE | H1: PROJETO ORÇAMENTO BASE-ZERO
A2: UNIDADE ORÇAMENTÁRIA | B2: N2 | C2: SUB SIGLA | D2: N3 | E2: PROGRAMAUO | F2: PROGRAMA | G2: prog cod | H2: AÇÃO | I2: ELEMENTO | J2: ELEMENTO_ITEM | K2: Agrupamento | L2: GRUPO | M2: FONTEUO | N2: FONTE | O2: DESCRIÇÃO DO ITEM | P2: NOVO? | Q2: PREMISSA VOLUME | R2: VOLUME | S2: PREMISSA DE PREÇO | T2: PREÇO UNITÁRIO | U2: FREQUÊNCIA PAGAMENTO | V2: VALOR TOTAL ITEM | W2: CLASSIFICAÇÃO CENÁRIO | X2: DESCRIÇÃO DO CENÁRIO | Y2: RISCO DE NÃO FAZER | Z2: BENEFICIO AO FAZER | AA2: PRIORIDADE N3 | AB2: PRIORIDADE N2 | AC2: PRIORIDADE N1 | AD2: PARECER DCMEFO | AE2: DELIBERAÇÃO COFIN
A3: SEJUSP | B3: SUPEC | D3: Superintendência de Políticas de Prevenção Social à Criminalidade | E3: =CONCATENATE(A3,"PROG") -> SEJUSPPROG | F3: 129 - PREVENÇÃO À CRIMINALIDADE | G3: =CONCATENATE("P",(LEFT(F3,3)),A3) -> P129SEJUSP | H3: 4344 - PREVENÇÃO SOCIAL ÀS VIOLÊNCIAS E CRIMINALIDADES | I3: ELEMENTO | J3: 8501 - CONTRATO DE GESTAO COM ORGANIZACAO SOCIAL - OS | K3: =VLOOKUP(CONCATENATE(A3,LEFT(J3,4)),AGRUPAMENTO!$D$2:$E$6783,2,FALSE) -> Termos de parceria e contratos de gestão | L3: 3 - Outras Despesas de Custeio | M3: =CONCATENATE("FONTE",A3) -> FONTESEJUSP | N3: 60 | O3: Contrato de Gestão 02/2019 com Instituto Elo, para co-execução da Política Estadual de Prevenção Social à Criminalidade | P3: NÃO | Q3: 1 Termo Aditivo XI do Contrato de Gestão assinado para co-execução da Política Estadual de Prevenção Social à Criminalidade, com os mesmos parâmetros aprovados em 2025 | R3: 1 | S3: Valor aprovado em 2025 e ajustado em 7% conforme a CCT | T3: 14252122 | U3: 4 | V3: =R3*T3*U3 -> 57008489 | W3: LIMIAR | X3: Entrega de 4 programas de prevenção social à criminalidade em 55 Unidades de Prevenção à Criminalidade localizadas em 21 municípios e mais de 200 territórios. Expectativa de realização de mais de 350 mil atendimentos aos diversos públicos dos programas, contribuindo para a prevenção à criminalidade e violências e aumento da sensação de segurança em Minas Gerais | Y3: Interrupção da implementação da Política de Prevenção Social à Criminalidade em todo o estado, com prejuízo para a entrega do serviço público | Z3: Maior qualidade na implementação da Política Estadual de Prevenção Social à Criminalidade, aumento da sensação de segurança em MG, redução das taxas de homicídios e criminalidade violenta, atendimento ao público para acesso a direitos e superação de vulnerabilidades e responsabilização penal Caso haja aprovação de valor incremental para novo edital de seleção de parcerias, o valor será abatido da previsão global do Contrato de Gestão 02/2019 | AA3: 0 | AB3: 0 | AC3: 0 | AD3: 0.734368 | AE3: 0.734368 | AF3: =AE3*V3 -> 41865210
A4: SEJUSP | B4: DEPEN | D4: SUPERINTENDÊNCIA DE SEGURANÇA | E4: =CONCATENATE(A4,"PROG") -> SEJUSPPROG | F4: 130 - INFRAESTRUTURA DO SISTEMA PRISIONAL | G4: =CONCATENATE("P",(LEFT(F4,3)),A4) -> P130SEJUSP | H4: 1048 - MODERNIZAÇÃO E EXPANSÃO DO SISTEMA PRISIONAL | I4: ELEMENTO | J4: 5217 - VEICULOS | K4: =VLOOKUP(CONCATENATE(A4,LEFT(J4,4)),AGRUPAMENTO!$D$2:$E$6783,2,FALSE) -> Demais despesas de capital | L4: 4 - Investimento | N4: 10 | O4: AQUISIÇÃO DE VIATURA PARA TRANSPORTE DA TROPA DO GRUPO DE INTERVERNÇÃO RÁPIDA (GIR) EQUIPAMENTO DE PROTEÇÃO IMNDIVIDUAL E COLETIVA | P4: NÃO | Q4: VALOR MÉDIO UNITÁRIO | R4: 25 | S4: VALOR MÉDIO UNITÁRIO | T4: 828900 | U4: 1 | V4: =R4*T4*U4 -> 20722500 | W4: INCREMENTAL | X4: DEMANDA DE VIATURAS ESPECÍFICAS PARA GARANTIR A PRONTA RESPOSTA DO GIR EM SITUAÇÕES DE CRISE, INTERVENÇÕES EM UNIDADES PRISIONAIS E OPERAÇÕES DE SEGURANÇA, COM DESLOCAMENTO RÁPIDO E ADEQUADO DO EFETIVO E EQUIPAMENTOS | Y4: PEJUÍZO A CAPACIDADE DE RESPOSTA RÁPIDA, COMPROMETIMNETO DAS OPERAÇÕES TÀTICAS E RISCO A SEGURANÇA EM INTERVENÇÕES EMERGENCIAIS | Z4: AUMENTO DA HABILIDADE TÁTICA, AGILIDADE NAS RESPOSTA OPERACIONAIS E FORTALECIMENTO DAS AÇÕES DO GIR EM SITUAÇÕES CRITICAS | AA4: 1 | AB4: 1 | AC4: 1 | AD4: 0 | AE4: 0 | AF4: =AE4*V4 -> 0
A5: SEJUSP | B5: SULOT | D5: SIEL - Superintendência de Infraestrutura e Logística | E5: =CONCATENATE(A5,"PROG") -> SEJUSPPROG | F5: 130 - INFRAESTRUTURA DO SISTEMA PRISIONAL | G5: =CONCATENATE("P",(LEFT(F5,3)),A5) -> P130SEJUSP | H5: 4348 - CUSTÓDIA E RESSOCIALIZAÇÃO DE PRESOS | I5: ELEMENTO | J5: 3999 - OUTROS SERVICOS-PESSOA JURIDICA | K5: =VLOOKUP(CONCATENATE(A5,LEFT(J5,4)),AGRUPAMENTO!$D$2:$E$6783,2,FALSE) -> Demais despesas de custeio | L5: 3 - Outras Despesas de Custeio | M5: =CONCATENATE("FONTE",A5) -> FONTESEJUSP | N5: 60 | O5: SERVICOS DE OPERACAO LOGISTICA INTEGRADA,INCLUINDO ARMAZENA GEM, GESTAO DE ESTOQUE, DISTRIBUICAO E GESTAO DE TRANSPORTE CDM | P5: SIM | Q5: OPERAÇÃO LOGÍSTICA CDM | R5: 1 | S5: PRÉVIA DE PROPOSTA COMERCIAL APRESENTADA PELOS CORREIOS | T5: 400000 | U5: 12 | V5: =R5*T5*U5 -> 4800000 | W5: INCREMENTAL | X5: CONTRATAÇÃO DE SERVIÇO DE OPERADOR LOGÍSTICO | Y5: OPERAÇÃO LOGÍSTICA NÃO ESPECIALIZADA | Z5: OPERAÇÃO LOGÍSTICA INTEGRADA E ESPECIALIZADA | AA5: 1 | AB5: 1 | AC5: 2 | AD5: 0 | AE5: 0 | AF5: =AE5*V5 -> 0
A6: SEJUSP | B6: SUPEC | D6: Gabinete da Subsecretaria de Prevenção Social à Criminalidade | E6: =CONCATENATE(A6,"PROG") -> SEJUSPPROG | F6: 129 - PREVENÇÃO À CRIMINALIDADE | G6: =CONCATENATE("P",(LEFT(F6,3)),A6) -> P129SEJUSP | H6: 4344 - PREVENÇÃO SOCIAL ÀS VIOLÊNCIAS E CRIMINALIDADES | I6: ELEMENTO | J6: 1401 - DIARIAS - CIVIL | K6: =VLOOKUP(CONCATENATE(A6,LEFT(J6,4)),AGRUPAMENTO!$D$2:$E$6783,2,FALSE) -> Diárias e viagens | L6: 3 - Outras Despesas de Custeio | M6: =CONCATENATE("FONTE",A6) -> FONTESEJUSP | N6: 60 | O6: Diárias de viagens para acompanhamento da execução da Política Estadual de Prevenção Social à Criminalidade | P6: NÃO | Q6: Viagens realizadas para acompanhamento de GIE, Comissões Municipais, Fiscalização de MGS e outras não agendadas | R6: 1 | S6: Valor necessário para custeio das viagens dos servidores e MGS | T6: 10000 | U6: 12 | V6: =R6*T6*U6 -> 120000 | W6: LIMIAR | Y6: Interrupção do acompanhamento e implementação da Política de Prevenção Social à Criminalidade no interior do estado | Z6: Maior qualidade no acompanhamento e implementação da Política Estadual de Prevenção Social à Criminalidade no interior do estado | AA6: 0 | AB6: 0 | AC6: 0 | AD6: 0.86749885 | AE6: 0.86749885 | AF6: =AE6*V6 -> 104099.86
A7: SEJUSP | B7: SUPEC | D7: Gabinete da Subsecretaria de Prevenção Social à Criminalidade | E7: =CONCATENATE(A7,"PROG") -> SEJUSPPROG | F7: 129 - PREVENÇÃO À CRIMINALIDADE | G7: =CONCATENATE("P",(LEFT(F7,3)),A7) -> P129SEJUSP | H7: 4344 - PREVENÇÃO SOCIAL ÀS VIOLÊNCIAS E CRIMINALIDADES | I7: ELEMENTO | J7: 3302 - DESPESAS COM TRANSPORTE URBANO, PEDAGIO E ESTACIONAMETO PESSOA FISICA | K7: =VLOOKUP(CONCATENATE(A7,LEFT(J7,4)),AGRUPAMENTO!$D$2:$E$6783,2,FALSE) -> Diárias e viagens | L7: 3 - Outras Despesas de Custeio | M7: =CONCATENATE("FONTE",A7) -> FONTESEJUSP | N7: 60 | O7: Despesa com transporte urbano para execução da Política Estadual de Prevenção Social à Criminalidade | P7: NÃO | Q7: Voucher para apoio às viagens realizadas | R7: 1 | S7: Valor necessário para custeio dos vouchers | T7: 300 | U7: 12 | V7: =R7*T7*U7 -> 3600 | W7: LIMIAR | Y7: Interrupção do acompanhamento e implementação da Política de Prevenção Social à Criminalidade no interior do estado | Z7: Maior qualidade no acompanhamento e implementação da Política Estadual de Prevenção Social à Criminalidade no interior do estado | AA7: 0 | AB7: 0 | AC7: 0 | AD7: 0.86749885 | AE7: 0.86749885 | AF7: =AE7*V7 -> 3122.9958
A8: SEJUSP | B8: SUPEC | D8: Gabinete da Subsecretaria de Prevenção Social à Criminalidade | E8: =CONCATENATE(A8,"PROG") -> SEJUSPPROG | F8: 129 - PREVENÇÃO À CRIMINALIDADE | G8: =CONCATENATE("P",(LEFT(F8,3)),A8) -> P129SEJUSP | H8: 4344 - PREVENÇÃO SOCIAL ÀS VIOLÊNCIAS E CRIMINALIDADES | I8: ELEMENTO | J8: 3612 - DESPESAS MIUDAS DE PRONTO PAGAMENTO | K8: =VLOOKUP(CONCATENATE(A8,LEFT(J8,4)),AGRUPAMENTO!$D$2:$E$6783,2,FALSE) -> Pronto Pagamento | L8: 3 - Outras Despesas de Custeio | M8: =CONCATENATE("FONTE",A8) -> FONTESEJUSP | N8: 60 | O8: Despesas muídas de pronto pagamento, para apoio às atividades realizadas pelos Programas de Prevenção Social à Criminalidade | P8: NÃO | Q8: Pronto pagamento mensal | R8: 1 | S8: Valor mínimo mensal de pronto pagamento | T8: 200 | U8: 12 | V8: =R8*T8*U8 -> 2400 | W8: LIMIAR | Y8: Dificuldade e prejuízo no acompanhamento e implementação da Política de Prevenção Social à Criminalidade | Z8: Maior qualidade no acompanhamento e implementação da Política Estadual de Prevenção Social à Criminalidade no interior do estado | AA8: 0 | AB8: 0 | AC8: 0 | AD8: 1 | AE8: 1 | AF8: =AE8*V8 -> 2400
A9: SEJUSP | B9: SUPEC | D9: Gabinete da Subsecretaria de Prevenção Social à Criminalidade | E9: =CONCATENATE(A9,"PROG") -> SEJUSPPROG | F9: 129 - PREVENÇÃO À CRIMINALIDADE | G9: =CONCATENATE("P",(LEFT(F9,3)),A9) -> P129SEJUSP | H9: 4344 - PREVENÇÃO SOCIAL ÀS VIOLÊNCIAS E CRIMINALIDADES | I9: ELEMENTO | J9: 3912 - TARIFA DE ENERGIA ELETRICA | K9: =VLOOKUP(CONCATENATE(A9,LEFT(J9,4)),AGRUPAMENTO!$D$2:$E$6783,2,FALSE) -> Utilidade Pública | L9: 3 - Outras Despesas de Custeio | M9: =CONCATENATE("FONTE",A9) -> FONTESEJUSP | N9: 60 | O9: Despesa de energia elétrica das Unidades de Prevenção à Criminalidade | P9: NÃO | Q9: Pagamentos para a CEMIG | R9: 22 | S9: Valores das faturas mensais | T9: 193.18 | U9: 12 | V9: =R9*T9*U9 -> 50999.52 | W9: LIMIAR | Y9: Dificuldade e prejuízo no acompanhamento e implementação da Política de Prevenção Social à Criminalidade | Z9: Maior qualidade no acompanhamento e implementação da Política Estadual de Prevenção Social à Criminalidade no interior do estado | AA9: 0 | AB9: 0 | AC9: 0 | AD9: 0.9695783 | AE9: 0.9695783 | AF9: =AE9*V9 -> 49448.028
A10: SEJUSP | B10: SUPEC | D10: Gabinete da Subsecretaria de Prevenção Social à Criminalidade | E10: =CONCATENATE(A10,"PROG") -> SEJUSPPROG | F10: 129 - PREVENÇÃO À CRIMINALIDADE | G10: =CONCATENATE("P",(LEFT(F10,3)),A10) -> P129SEJUSP | H10: 4344 - PREVENÇÃO SOCIAL ÀS VIOLÊNCIAS E CRIMINALIDADES | I10: ELEMENTO | J10: 3913 - TARIFA DE AGUA E ESGOTO | K10: =VLOOKUP(CONCATENATE(A10,LEFT(J10,4)),AGRUPAMENTO!$D$2:$E$6783,2,FALSE) -> Utilidade Pública | L10: 3 - Outras Despesas de Custeio | M10: =CONCATENATE("FONTE",A10) -> FONTESEJUSP | N10: 60 | O10: Despesa de água e esgoto das Unidades de Prevenção à Criminalidade | P10: NÃO | Q10: Pagamentos para Copasa | R10: 19 | S10: Valores das faturas mensais | T10: 144.74 | U10: 12 | V10: =R10*T10*U10 -> 33000.72 | W10: LIMIAR | Y10: Dificuldade e prejuízo no acompanhamento e implementação da Política de Prevenção Social à Criminalidade | Z10: Maior qualidade no acompanhamento e implementação da Política Estadual de Prevenção Social à Criminalidade no interior do estado | AA10: 0 | AB10: 0 | AC10: 0 | AD10: 0.9695783 | AE10: 0.9695783 | AF10: =AE10*V10 -> 31996.782
A11: SEJUSP | B11: SUPEC | D11: Gabinete da Subsecretaria de Prevenção Social à Criminalidade | E11: =CONCATENATE(A11,"PROG") -> SEJUSPPROG | F11: 129 - PREVENÇÃO À CRIMINALIDADE | G11: =CONCATENATE("P",(LEFT(F11,3)),A11) -> P129SEJUSP | H11: 4344 - PREVENÇÃO SOCIAL ÀS VIOLÊNCIAS E CRIMINALIDADES | I11: ELEMENTO | J11: 3937 - TAXA DE CONDOMINIO | K11: =VLOOKUP(CONCATENATE(A11,LEFT(J11,4)),AGRUPAMENTO!$D$2:$E$6783,2,FALSE) -> Aluguéis e condomínios | L11: 3 - Outras Despesas de Custeio | M11: =CONCATENATE("FONTE",A11) -> FONTESEJUSP | N11: 60 | O11: Despesa de taxa de condomínio das Unidades de Prevenção à Criminalidade | P11: NÃO | Q11: Contratos de locação dos imóveis | R11: 1 | S11: Valores acordados em contratos | T11: 5033.3333 | U11: 12 | V11: =R11*T11*U11 -> 60400 | W11: LIMIAR | Y11: Dificuldade e prejuízo no acompanhamento e implementação da Política de Prevenção Social à Criminalidade | Z11: Maior qualidade no acompanhamento e implementação da Política Estadual de Prevenção Social à Criminalidade no interior do estado | AA11: 0 | AB11: 0 | AC11: 0 | AD11: 1 | AE11: 1 | AF11: =AE11*V11 -> 60400
A12: SEJUSP | B12: SUPEC | D12: Gabinete da Subsecretaria de Prevenção Social à Criminalidade | E12: =CONCATENATE(A12,"PROG") -> SEJUSPPROG | F12: 129 - PREVENÇÃO À CRIMINALIDADE | G12: =CONCATENATE("P",(LEFT(F12,3)),A12) -> P129SEJUSP | H12: 4344 - PREVENÇÃO SOCIAL ÀS VIOLÊNCIAS E CRIMINALIDADES | I12: ELEMENTO | J12: 4703 - IMPOSTO PREDIAL TERRITORIAL URBANO - IPTU | K12: =VLOOKUP(CONCATENATE(A12,LEFT(J12,4)),AGRUPAMENTO!$D$2:$E$6783,2,FALSE) -> Obrigações tributárias | L12: 3 - Outras Despesas de Custeio | M12: =CONCATENATE("FONTE",A12) -> FONTESEJUSP | N12: 60 | O12: Despesa de IPTU das Unidades de Prevenção à Criminalidade | P12: NÃO | Q12: Contratos de locação dos imóveis | R12: 9 | S12: Valores acordados em contratos | T12: 333.33 | U12: 1 | V12: =R12*T12*U12 -> 2999.97 | W12: LIMIAR | Y12: Dificuldade e prejuízo no acompanhamento e implementação da Política de Prevenção Social à Criminalidade | Z12: Maior qualidade no acompanhamento e implementação da Política Estadual de Prevenção Social à Criminalidade no interior do estado | AA12: 0 | AB12: 0 | AC12: 0 | AD12: 0.20034174 | AE12: 0.20034174 | AF12: =AE12*V12 -> 601.01922
A13: SEJUSP | B13: SULOT | D13: Superintendência de Recursos Humanos - SRHU | E13: =CONCATENATE(A13,"PROG") -> SEJUSPPROG | F13: 705 - APOIO ÀS POLÍTICAS PÚBLICAS | G13: =CONCATENATE("P",(LEFT(F13,3)),A13) -> P705SEJUSP | H13: 2500 - ASSESSORAMENTO E GERENCIAMENTO DE POLÍTICAS PÚBLICAS | I13: ELEMENTO | J13: 3702 - LOCACAO DE SERVICOS DE APOIO ADMINISTRATIVO | K13: =VLOOKUP(CONCATENATE(A13,LEFT(J13,4)),AGRUPAMENTO!$D$2:$E$6783,2,FALSE) -> Terceirizados - Demais empresas | L13: 3 - Outras Despesas de Custeio | M13: =CONCATENATE("FONTE",A13) -> FONTESEJUSP | N13: 10 | O13: NÃO | P13: NÃO | Q13: Base previsão salário mínimo (2025)R$1.518,00 | R13: 2 | S13: Adolescente Trebalhador 10% | T13: 4290 | U13: 12 | V13: =R13*T13*U13 -> 102960 | W13: LIMIAR | X13: Contratação de Assprom | Y13: Atraso e/ou impedimento de realização das atividades dos setores. | Z13: Manutenção da capacidades dos setores em realizar as atividades. | AA13: 0 | AB13: 0 | AC13: 0 | AD13: 0.35233925 | AE13: 0.35233925 | AF13: =AE13*V13 -> 36276.849
A14: SEJUSP | B14: SULOT | D14: Superintendência de Recursos Humanos - SRHU | E14: =CONCATENATE(A14,"PROG") -> SEJUSPPROG | F14: 705 - APOIO ÀS POLÍTICAS PÚBLICAS | G14: =CONCATENATE("P",(LEFT(F14,3)),A14) -> P705SEJUSP | H14: 2500 - ASSESSORAMENTO E GERENCIAMENTO DE POLÍTICAS PÚBLICAS | I14: ELEMENTO | J14: 3702 - LOCACAO DE SERVICOS DE APOIO ADMINISTRATIVO | K14: =VLOOKUP(CONCATENATE(A14,LEFT(J14,4)),AGRUPAMENTO!$D$2:$E$6783,2,FALSE) -> Terceirizados - Demais empresas | L14: 3 - Outras Despesas de Custeio | M14: =CONCATENATE("FONTE",A14) -> FONTESEJUSP | N14: 10 | O14: NÃO | P14: NÃO | Q14: Base previsão salário mínimo (2025)R$1.518,00 | R14: 6 | S14: Adolescente Trebalhador 10% | T14: 4290 | U14: 12 | V14: =R14*T14*U14 -> 308880 | W14: LIMIAR | X14: Contratação de Assprom | Y14: Atraso e/ou impedimento de realização das atividades dos setores. | Z14: Manutenção da capacidades dos setores em realizar as atividades. | AA14: 0 | AB14: 0 | AC14: 0 | AD14: 0.35233925 | AE14: 0.35233925 | AF14: =AE14*V14 -> 108830.55
A15: SEJUSP | B15: SULOT | D15: Superintendência de Recursos Humanos - SRHU | E15: =CONCATENATE(A15,"PROG") -> SEJUSPPROG | F15: 141 - POLÍTICAS SOBRE DROGAS | G15: =CONCATENATE("P",(LEFT(F15,3)),A15) -> P141SEJUSP | H15: 4438 - DESCENTRALIZAÇÃO DA POLÍTICA SOBRE DROGAS | I15: ELEMENTO | J15: 3952 - CONTRATACAO DE ESTAGIARIOS | K15: =VLOOKUP(CONCATENATE(A15,LEFT(J15,4)),AGRUPAMENTO!$D$2:$E$6783,2,FALSE) -> Estagiários | L15: 3 - Outras Despesas de Custeio | M15: =CONCATENATE("FONTE",A15) -> FONTESEJUSP | N15: 10 | O15: NÃO | P15: NÃO | Q15: Estagiário AGIEL | R15: 95 | S15: Base RH reajuste TX Administrativa 10% | T15: 21 | U15: 12 | V15: =R15*T15*U15 -> 23940 | W15: LIMIAR | X15: Contratação de estagiários - AGIEL | Y15: Atraso e/ou impedimento de realização das atividades dos setores. | Z15: Manutenção da capacidades dos setores em realizar as atividades. | AA15: 0 | AB15: 0 | AC15: 0 | AD15: 1 | AE15: 1 | AF15: =AE15*V15 -> 23940
A16: SEJUSP | B16: SULOT | D16: Superintendência de Recursos Humanos - SRHU | E16: =CONCATENATE(A16,"PROG") -> SEJUSPPROG | F16: 146 - PROMOÇÃO DA POLÍTICA SOCIOEDUCATIVA PARA ATENDIMENTO AOS ADOLESCENTES EM CONFLITO COM A LEI | G16: =CONCATENATE("P",(LEFT(F16,3)),A16) -> P146SEJUSP | H16: 4441 - ADEQUAÇÃO, MANUTENÇÃO E DESENVOLVIMENTO DO ATENDIMENTO SOCIOEDUCATIVO | I16: ELEMENTO | J16: 3952 - CONTRATACAO DE ESTAGIARIOS | K16: =VLOOKUP(CONCATENATE(A16,LEFT(J16,4)),AGRUPAMENTO!$D$2:$E$6783,2,FALSE) -> Estagiários | L16: 3 - Outras Despesas de Custeio | M16: =CONCATENATE("FONTE",A16) -> FONTESEJUSP | N16: 10 | O16: NÃO | P16: NÃO | Q16: Estagiário AGIEL | R16: 2 | S16: Base RH reajuste TX Administrativa 10% | T16: 21 | U16: 12 | V16: =R16*T16*U16 -> 504 | W16: LIMIAR | X16: Contratação de estagiários - AGIEL | Y16: Atraso e/ou impedimento de realização das atividades dos setores. | Z16: Manutenção da capacidades dos setores em realizar as atividades. | AA16: 0 | AB16: 0 | AC16: 0 | AD16: 1 | AE16: 1 | AF16: =AE16*V16 -> 504
A17: SEJUSP | B17: SULOT | D17: Superintendência de Recursos Humanos - SRHU | E17: =CONCATENATE(A17,"PROG") -> SEJUSPPROG | F17: 134 - GESTÃO INTEGRADA DE SEGURANÇA PÚBLICA | G17: =CONCATENATE("P",(LEFT(F17,3)),A17) -> P134SEJUSP | H17: 4378 - OPERACIONALIZAÇÃO DA POLÍTICA DE INTEGRAÇÃO DA SEGURANÇA PÚBLICA DE MINAS GERAIS | I17: ELEMENTO | J17: 3952 - CONTRATACAO DE ESTAGIARIOS | K17: =VLOOKUP(CONCATENATE(A17,LEFT(J17,4)),AGRUPAMENTO!$D$2:$E$6783,2,FALSE) -> Estagiários | L17: 3 - Outras Despesas de Custeio | M17: =CONCATENATE("FONTE",A17) -> FONTESEJUSP | N17: 10 | O17: NÃO | P17: NÃO | Q17: Estagiário AGIEL | R17: 3 | S17: Base RH reajuste TX Administrativa 10% | T17: 21 | U17: 12 | V17: =R17*T17*U17 -> 756 | W17: LIMIAR | X17: Contratação de estagiários - AGIEL | Y17: Atraso e/ou impedimento de realização das atividades dos setores. | Z17: Manutenção da capacidades dos setores em realizar as atividades. | AA17: 0 | AB17: 0 | AC17: 0 | AD17: 1 | AE17: 1 | AF17: =AE17*V17 -> 756
A18: SEJUSP | B18: SULOT | D18: Superintendência de Recursos Humanos - SRHU | E18: =CONCATENATE(A18,"PROG") -> SEJUSPPROG | F18: 129 - PREVENÇÃO À CRIMINALIDADE | G18: =CONCATENATE("P",(LEFT(F18,3)),A18) -> P129SEJUSP | H18: 4344 - PREVENÇÃO SOCIAL ÀS VIOLÊNCIAS E CRIMINALIDADES | I18: ELEMENTO | J18: 3952 - CONTRATACAO DE ESTAGIARIOS | K18: =VLOOKUP(CONCATENATE(A18,LEFT(J18,4)),AGRUPAMENTO!$D$2:$E$6783,2,FALSE) -> Estagiários | L18: 3 - Outras Despesas de Custeio | M18: =CONCATENATE("FONTE",A18) -> FONTESEJUSP | N18: 60 | O18: NÃO | P18: NÃO | Q18: Estagiário AGIEL | R18: 2 | S18: Base RH reajuste TX Administrativa 10% | T18: 21 | U18: 12 | V18: =R18*T18*U18 -> 504 | W18: LIMIAR | X18: Contratação de estagiários - AGIEL | Y18: Atraso e/ou impedimento de realização das atividades dos setores. | Z18: Manutenção da capacidades dos setores em realizar as atividades. | AA18: 0 | AB18: 0 | AC18: 0 | AD18: 1 | AE18: 1 | AF18: =AE18*V18 -> 504
A19: SEJUSP | B19: SULOT | D19: Superintendência de Recursos Humanos - SRHU | E19: =CONCATENATE(A19,"PROG") -> SEJUSPPROG | F19: 130 - INFRAESTRUTURA DO SISTEMA PRISIONAL | G19: =CONCATENATE("P",(LEFT(F19,3)),A19) -> P130SEJUSP | H19: 4348 - CUSTÓDIA E RESSOCIALIZAÇÃO DE PRESOS | I19: ELEMENTO | J19: 3952 - CONTRATACAO DE ESTAGIARIOS | K19: =VLOOKUP(CONCATENATE(A19,LEFT(J19,4)),AGRUPAMENTO!$D$2:$E$6783,2,FALSE) -> Estagiários | L19: 3 - Outras Despesas de Custeio | M19: =CONCATENATE("FONTE",A19) -> FONTESEJUSP | N19: 60 | O19: NÃO | P19: NÃO | Q19: Estagiário AGIEL | R19: 3 | S19: Base RH reajuste TX Administrativa 10% | T19: 21 | U19: 12 | V19: =R19*T19*U19 -> 756 | W19: LIMIAR | X19: Contratação de estagiários - AGIEL | Y19: Atraso e/ou impedimento de realização das atividades dos setores. | Z19: Manutenção da capacidades dos setores em realizar as atividades. | AA19: 0 | AB19: 0 | AC19: 0 | AD19: 1 | AE19: 1 | AF19: =AE19*V19 -> 756
A20: SEJUSP | B20: SULOT | D20: Superintendência de Recursos Humanos - SRHU | E20: =CONCATENATE(A20,"PROG") -> SEJUSPPROG | F20: 705 - APOIO ÀS POLÍTICAS PÚBLICAS | G20: =CONCATENATE("P",(LEFT(F20,3)),A20) -> P705SEJUSP | H20: 2500 - ASSESSORAMENTO E GERENCIAMENTO DE POLÍTICAS PÚBLICAS | I20: ELEMENTO | J20: 3952 - CONTRATACAO DE ESTAGIARIOS | K20: =VLOOKUP(CONCATENATE(A20,LEFT(J20,4)),AGRUPAMENTO!$D$2:$E$6783,2,FALSE) -> Estagiários | L20: 3 - Outras Despesas de Custeio | M20: =CONCATENATE("FONTE",A20) -> FONTESEJUSP | N20: 10 | O20: NÃO | P20: NÃO | Q20: Estagiário AGIEL | R20: 23 | S20: Base RH reajuste TX Administrativa 10% | T20: 21 | U20: 12 | V20: =R20*T20*U20 -> 5796 | W20: LIMIAR | X20: Contratação de estagiários - AGIEL | Y20: Atraso e/ou impedimento de realização das atividades dos setores. | Z20: Manutenção da capacidades dos setores em realizar as atividades. | AA20: 0 | AB20: 0 | AC20: 0 | AD20: 1 | AE20: 1 | AF20: =AE20*V20 -> 5796
A21: SEJUSP | B21: SULOT | D21: Superintendência de Recursos Humanos - SRHU | E21: =CONCATENATE(A21,"PROG") -> SEJUSPPROG | F21: 705 - APOIO ÀS POLÍTICAS PÚBLICAS | G21: =CONCATENATE("P",(LEFT(F21,3)),A21) -> P705SEJUSP | H21: 2500 - ASSESSORAMENTO E GERENCIAMENTO DE POLÍTICAS PÚBLICAS | I21: ELEMENTO | J21: 3704 - LOCACAO DE SERVICOS DE APOIO ADMINISTRATIVO REALIZADOS PELA MGS | K21: =VLOOKUP(CONCATENATE(A21,LEFT(J21,4)),AGRUPAMENTO!$D$2:$E$6783,2,FALSE) -> Terceirizados - MGS | L21: 3 - Outras Despesas de Custeio | M21: =CONCATENATE("FONTE",A21) -> FONTESEJUSP | N21: 10 | O21: NÃO | P21: NÃO | Q21: Empregados de apoio MGS | R21: 117 | S21: Base RH reajuste 10% | T21: 7137.17 | U21: 12 | V21: =R21*T21*U21 -> 10020587 | W21: LIMIAR | X21: Contratação empregados MGS | Y21: Prejuízo às atividades das unidades, aumentando o prazo para resolução das demandas. Risco de depredação do patrimônio público e falta de controle na entrada. Diminuição na capacidade de gestão, análise, fiscalização dos contratos da SEJSUP. | Z21: Manutenção das atividades de apoio, às unidades de Segurança Pública de Minas Gerais. | AA21: 0 | AB21: 0 | AC21: 0 | AD21: 1 | AE21: 1 | AF21: =AE21*V21 -> 10020587
A22: SEJUSP | B22: SULOT | D22: Superintendência de Recursos Humanos - SRHU | E22: =CONCATENATE(A22,"PROG") -> SEJUSPPROG | F22: 705 - APOIO ÀS POLÍTICAS PÚBLICAS | G22: =CONCATENATE("P",(LEFT(F22,3)),A22) -> P705SEJUSP | H22: 2500 - ASSESSORAMENTO E GERENCIAMENTO DE POLÍTICAS PÚBLICAS | I22: ELEMENTO | J22: 3703 - LOCACAO DE SERVICOS DE CONSERVACAO E LIMPEZA REALIZADOS PELA MGS | K22: =VLOOKUP(CONCATENATE(A22,LEFT(J22,4)),AGRUPAMENTO!$D$2:$E$6783,2,FALSE) -> Terceirizados - MGS | L22: 3 - Outras Despesas de Custeio | M22: =CONCATENATE("FONTE",A22) -> FONTESEJUSP | N22: 10 | O22: NÃO | P22: NÃO | Q22: Empregados de apoio MGS | R22: 19 | S22: Base RH reajuste 10% | T22: 6214.9 | U22: 12 | V22: =R22*T22*U22 -> 1416997.2 | W22: LIMIAR | X22: Contratação empregados MGS | Y22: Prejuízo às atividades das unidades, aumentando o prazo para resolução das demandas. Risco de depredação do patrimônio público e falta de controle na entrada. Diminuição na capacidade de gestão, análise, fiscalização dos contratos da SEJSUP. | Z22: Manutenção das atividades de apoio, às unidades de Segurança Pública de Minas Gerais. | AA22: 0 | AB22: 0 | AC22: 0 | AD22: 1 | AE22: 1 | AF22: =AE22*V22 -> 1416997.2
A23: SEJUSP | B23: SULOT | D23: Superintendência de Recursos Humanos - SRHU | E23: =CONCATENATE(A23,"PROG") -> SEJUSPPROG | F23: 129 - PREVENÇÃO À CRIMINALIDADE | G23: =CONCATENATE("P",(LEFT(F23,3)),A23) -> P129SEJUSP | H23: 4344 - PREVENÇÃO SOCIAL ÀS VIOLÊNCIAS E CRIMINALIDADES | I23: ELEMENTO | J23: 3705 - DESPESAS COM O PAGAMENTO DE ENCARGOS TRABALHISTAS A MGS | K23: =VLOOKUP(CONCATENATE(A23,LEFT(J23,4)),AGRUPAMENTO!$D$2:$E$6783,2,FALSE) -> Terceirizados - MGS | L23: 3 - Outras Despesas de Custeio | M23: =CONCATENATE("FONTE",A23) -> FONTESEJUSP | N23: 60 | O23: NÃO | P23: NÃO | Q23: Empregados de apoio MGS | R23: 1 | S23: Base RH reajuste 10% | T23: 172000 | U23: 12 | V23: =R23*T23*U23 -> 2064000 | W23: LIMIAR | X23: Contratação empregados MGS | Y23: Prejuízo às atividades das unidades, aumentando o prazo para resolução das demandas. Risco de depredação do patrimônio público e falta de controle na entrada. Diminuição na capacidade de gestão, análise, fiscalização dos contratos da SEJSUP. | Z23: Manutenção das atividades de apoio, às unidades de Segurança Pública de Minas Gerais. | AA23: 0 | AB23: 0 | AC23: 0 | AD23: 1 | AE23: 1 | AF23: =AE23*V23 -> 2064000
A24: SEJUSP | B24: SULOT | D24: Superintendência de Recursos Humanos - SRHU | E24: =CONCATENATE(A24,"PROG") -> SEJUSPPROG | F24: 129 - PREVENÇÃO À CRIMINALIDADE | G24: =CONCATENATE("P",(LEFT(F24,3)),A24) -> P129SEJUSP | H24: 4344 - PREVENÇÃO SOCIAL ÀS VIOLÊNCIAS E CRIMINALIDADES | I24: ELEMENTO | J24: 3704 - LOCACAO DE SERVICOS DE APOIO ADMINISTRATIVO REALIZADOS PELA MGS | K24: =VLOOKUP(CONCATENATE(A24,LEFT(J24,4)),AGRUPAMENTO!$D$2:$E$6783,2,FALSE) -> Terceirizados - MGS | L24: 3 - Outras Despesas de Custeio | M24: =CONCATENATE("FONTE",A24) -> FONTESEJUSP | N24: 60 | O24: NÃO | P24: NÃO | Q24: Empregados de apoio MGS | R24: 33 | S24: Base RH reajuste 10% | T24: 8581.78 | U24: 12 | V24: =R24*T24*U24 -> 3398384.9 | W24: LIMIAR | X24: Contratação empregados MGS | Y24: Prejuízo às atividades das unidades, aumentando o prazo para resolução das demandas. Risco de depredação do patrimônio público e falta de controle na entrada. Diminuição na capacidade de gestão, análise, fiscalização dos contratos da SEJSUP. | Z24: Manutenção das atividades de apoio, às unidades de Segurança Pública de Minas Gerais. | AA24: 0 | AB24: 0 | AC24: 0 | AD24: 1 | AE24: 1 | AF24: =AE24*V24 -> 3398384.9
... A40: SEJUSP | B40: SULOT | D40: Superintendência de Recursos Humanos - SRHU | E40: =CONCATENATE(A40,"PROG") -> SEJUSPPROG | F40: 705 - APOIO ÀS POLÍTICAS PÚBLICAS | G40: =CONCATENATE("P",(LEFT(F40,3)),A40) -> P705SEJUSP | H40: 2500 - ASSESSORAMENTO E GERENCIAMENTO DE POLÍTICAS PÚBLICAS | I40: ELEMENTO | J40: 3622 - TAXA DE CONDOMINIO | K40: =VLOOKUP(CONCATENATE(A40,LEFT(J40,4)),AGRUPAMENTO!$D$2:$E$6783,2,FALSE) -> Aluguéis e condomínios | L40: 3 - Outras Despesas de Custeio | M40: =CONCATENATE("FONTE",A40) -> FONTESEJUSP | N40: 10 | O40: Despesa de condomínio do Centro de Atenção Biopsicossocial DAS Belo Horizonte | P40: NÃO | Q40: Estimativa de meses pagos de despesa de taxa de condomínio, referente ao Centro de Atenção Biopsicossocial DAS Belo Horizonte. | R40: 12 | S40: Média de valores pagos anual | T40: 62 | U40: 1 | V40: =R40*T40*U40 -> 744 | W40: LIMIAR | X40: Despesa para pagamento de condomínio do Centro de Atenção Biopsicossocial DAS Belo Horizonte | Y40: Multa, inscrição na dívida ativa do município e devolução do espaço. | Z40: Dar continuidade nos atendimentos biopsicossociais aos servidores da SEJUSP. | AA40: 0 | AB40: 0 | AC40: 0 | AD40: 1 | AE40: 1 | AF40: =AE40*V40 -> 744
A41: SEJUSP | B41: SULOT | D41: Superintendência de Recursos Humanos - SRHU | E41: =CONCATENATE(A41,"PROG") -> SEJUSPPROG | F41: 705 - APOIO ÀS POLÍTICAS PÚBLICAS | G41: =CONCATENATE("P",(LEFT(F41,3)),A41) -> P705SEJUSP | H41: 2500 - ASSESSORAMENTO E GERENCIAMENTO DE POLÍTICAS PÚBLICAS | I41: ELEMENTO | J41: 4703 - IMPOSTO PREDIAL TERRITORIAL URBANO - IPTU | K41: =VLOOKUP(CONCATENATE(A41,LEFT(J41,4)),AGRUPAMENTO!$D$2:$E$6783,2,FALSE) -> Obrigações tributárias | L41: 3 - Outras Despesas de Custeio | M41: =CONCATENATE("FONTE",A41) -> FONTESEJUSP | N41: 10 | P41: NÃO | Q41: Quantidade de pagamentos realizados anual. | R41: 11 | S41: Média dos valores pagos anual | T41: 92 | U41: 1 | V41: =R41*T41*U41 -> 1012 | W41: LIMIAR | X41: Despesa para pagamento condomínio do imóvel Itamaraty, sede do Centro de Atenção Biopsicossocial DAS Belo Horizonte | Y41: Multas, juros e a perda e devolução do espaço. | Z41: Dar continuidade nos atendimentos biopsicossociais aos servidores da SEJUSP. | AA41: 0 | AB41: 0 | AC41: 0 | AD41: 0.20034174 | AE41: 0.20034174 | AF41: =AE41*V41 -> 202.74584
A42: SEJUSP | B42: SULOT | D42: Superintendência de Recursos Humanos - SRHU | E42: =CONCATENATE(A42,"PROG") -> SEJUSPPROG | F42: 705 - APOIO ÀS POLÍTICAS PÚBLICAS | G42: =CONCATENATE("P",(LEFT(F42,3)),A42) -> P705SEJUSP | H42: 2500 - ASSESSORAMENTO E GERENCIAMENTO DE POLÍTICAS PÚBLICAS | I42: ELEMENTO | J42: 1401 - DIARIAS - CIVIL | K42: =VLOOKUP(CONCATENATE(A42,LEFT(J42,4)),AGRUPAMENTO!$D$2:$E$6783,2,FALSE) -> Diárias e viagens | L42: 3 - Outras Despesas de Custeio | M42: =CONCATENATE("FONTE",A42) -> FONTESEJUSP | N42: 10 | O42: Viagens de servidores da DAS | P42: NÃO | Q42: Média de viagens realizadas pela Diretoria de Atenção à Saúde do Servidor anual. | R42: 42 | S42: VALOR DA MÉDIA DAS DIÁRIAS FAIXA PARA MUNICÍPIOS ESPECIAIS E DEMAIS MUNICÍPIOS | T42: 470 | U42: 1 | V42: =R42*T42*U42 -> 19740 | W42: LIMIAR | X42: Realização de levantamento técnico de avaliação ambiental e visitas técnicas realizadas em Unidades Prisionais, Socioeducativas e Administrativas; Visitas nos Centros de Atenção Biopsicossocial DAS Regionais para alinhamento e de equipe e visitação de imóveis para implantação dos Centros da DAS. | Y42: Agravamento das condições ambientais do trabalho; Ausência de ações preventivas de saúde, falta de acolhimento dos servidores adoecidos; Falta da expansão do projeto Cuidar bem de que Cuida. | Z42: Propor medidas para a melhoria de condições no ambiente de trabalho; Visar a prevenção, promoção e proteção à saúde dos servidores da SEJUSP, Ampliar o projeto de reestruturação da DAS | AA42: 0 | AB42: 0 | AC42: 0 | AD42: 0.86749885 | AE42: 0.86749885 | AF42: =AE42*V42 -> 17124.427
A43: SEJUSP | B43: SULOT | D43: Superintendência de Recursos Humanos - SRHU | E43: =CONCATENATE(A43,"PROG") -> SEJUSPPROG | F43: 705 - APOIO ÀS POLÍTICAS PÚBLICAS | G43: =CONCATENATE("P",(LEFT(F43,3)),A43) -> P705SEJUSP | H43: 2500 - ASSESSORAMENTO E GERENCIAMENTO DE POLÍTICAS PÚBLICAS | I43: ELEMENTO | J43: 3913 - TARIFA DE AGUA E ESGOTO | K43: =VLOOKUP(CONCATENATE(A43,LEFT(J43,4)),AGRUPAMENTO!$D$2:$E$6783,2,FALSE) -> Utilidade Pública | L43: 3 - Outras Despesas de Custeio | M43: =CONCATENATE("FONTE",A43) -> FONTESEJUSP | N43: 10 | O43: Serviço de fornecimento de água | P43: NÃO | Q43: Estimativa de meses pagos de despesa de água, referente ao Centro de Atenção Biopsicossocial DAS Uberlândia | R43: 12 | S43: Média de consumo anual | T43: 85 | U43: 1 | V43: =R43*T43*U43 -> 1020 | W43: LIMIAR | X43: Despesa com fornecimento de água para funcionamento do Centro de Atenção Biopsicossocial DAS Uberlândia. | Y43: Falta de saneamento básico e propagação de doenças prejudicando a saúde dos servidores e visitantes. | Z43: Garantia de abastecimento contínuo para promover a continuidade do funcionamento do Centro. | AA43: 0 | AB43: 0 | AC43: 0 | AD43: 0.9695783 | AE43: 0.9695783 | AF43: =AE43*V43 -> 988.96987
A44: SEJUSP | B44: SULOT | D44: Superintendência de Recursos Humanos - SRHU | E44: =CONCATENATE(A44,"PROG") -> SEJUSPPROG | F44: 705 - APOIO ÀS POLÍTICAS PÚBLICAS | G44: =CONCATENATE("P",(LEFT(F44,3)),A44) -> P705SEJUSP | H44: 2500 - ASSESSORAMENTO E GERENCIAMENTO DE POLÍTICAS PÚBLICAS | I44: ELEMENTO | J44: 3612 - DESPESAS MIUDAS DE PRONTO PAGAMENTO | K44: =VLOOKUP(CONCATENATE(A44,LEFT(J44,4)),AGRUPAMENTO!$D$2:$E$6783,2,FALSE) -> Pronto Pagamento | L44: 3 - Outras Despesas de Custeio | M44: =CONCATENATE("FONTE",A44) -> FONTESEJUSP | N44: 10 | O44: Despesa miúda SIPO | P44: Não | Q44: Conforme demanda | R44: 4 | S44: Valor disponibilizado a partir de deliberação da SEJUSP para despesas urgentes e inadiáveis | T44: 4000 | U44: 1 | V44: =R44*T44*U44 -> 16000 | W44: LIMIAR | X44: Atendimento das demandas urgentes e inadiáveis para reparo/manutenção dos Centos Regionais desta Diretoria de Atenção à Saúde do Servidor. | Y44: Não proporcionar ambiente adequado para os atendimentos aos servidores da SEJUSP. | Z44: Espaço adequado para desempenhar as atividades de saúde desta DAS. | AA44: 0 | AB44: 0 | AC44: 0 | AD44: 1 | AE44: 1 | AF44: =AE44*V44 -> 16000
A45: SEJUSP | B45: SULOT | D45: Superintendência de Recursos Humanos - SRHU | E45: =CONCATENATE(A45,"PROG") -> SEJUSPPROG | F45: 705 - APOIO ÀS POLÍTICAS PÚBLICAS | G45: =CONCATENATE("P",(LEFT(F45,3)),A45) -> P705SEJUSP | H45: 2500 - ASSESSORAMENTO E GERENCIAMENTO DE POLÍTICAS PÚBLICAS | I45: ELEMENTO | J45: 4703 - IMPOSTO PREDIAL TERRITORIAL URBANO - IPTU | K45: =VLOOKUP(CONCATENATE(A45,LEFT(J45,4)),AGRUPAMENTO!$D$2:$E$6783,2,FALSE) -> Obrigações tributárias | L45: 3 - Outras Despesas de Custeio | M45: =CONCATENATE("FONTE",A45) -> FONTESEJUSP | N45: 10 | O45: Despesas de IPTU | P45: Não | Q45: Estimativa de quantitativo de meses pagos de IPTU, referente ao Centro de Atenção Biopsicossocial DAS Belo Horizonte. | R45: 11 | S45: Média dos valores pagos anual. | T45: 92 | U45: 1 | V45: =R45*T45*U45 -> 1012 | W45: LIMIAR | X45: Despesa para pagamento de IPTU do Centro de Atenção Biopsicossocial DAS Belo Horizonte, situado no Edifício Itamaraty. | Y45: Multas, juros e a perda e devolução do espaço. | Z45: Dar continuidade nos atendimentos biopsicossociais aos servidores da SEJUSP. | AA45: 0 | AB45: 0 | AC45: 0 | AD45: 0.20034174 | AE45: 0.20034174 | AF45: =AE45*V45 -> 202.74584
A46: SEJUSP | B46: SULOT | D46: Superintendência de Recursos Humanos - SRHU | E46: =CONCATENATE(A46,"PROG") -> SEJUSPPROG | F46: 146 - PROMOÇÃO DA POLÍTICA SOCIOEDUCATIVA PARA ATENDIMENTO AOS ADOLESCENTES EM CONFLITO COM A LEI | G46: =CONCATENATE("P",(LEFT(F46,3)),A46) -> P146SEJUSP | H46: 4441 - ADEQUAÇÃO, MANUTENÇÃO E DESENVOLVIMENTO DO ATENDIMENTO SOCIOEDUCATIVO | I46: ELEMENTO | J46: 3702 - LOCACAO DE SERVICOS DE APOIO ADMINISTRATIVO | K46: =VLOOKUP(CONCATENATE(A46,LEFT(J46,4)),AGRUPAMENTO!$D$2:$E$6783,2,FALSE) -> Terceirizados - Demais empresas | L46: 3 - Outras Despesas de Custeio | M46: =CONCATENATE("FONTE",A46) -> FONTESEJUSP | N46: 10 | O46: NÃO | P46: NÃO | Q46: Base previsão salário mínimo (2025)R$1.518,00 | R46: 1 | S46: Adolescente Trebalhador 10% | T46: 4290 | U46: 12 | V46: =R46*T46*U46 -> 51480 | W46: LIMIAR | X46: Contratação de Assprom | Y46: Atraso e/ou impedimento de realização das atividades dos setores. | Z46: Manutenção da capacidades dos setores em realizar as atividades. | AA46: 0 | AB46: 0 | AC46: 0 | AD46: 0.35233925 | AE46: 0.35233925 | AF46: =AE46*V46 -> 18138.425
A47: SEJUSP | B47: SULOT | D47: Superintendência de Recursos Humanos - SRHU | E47: =CONCATENATE(A47,"PROG") -> SEJUSPPROG | F47: 705 - APOIO ÀS POLÍTICAS PÚBLICAS | G47: =CONCATENATE("P",(LEFT(F47,3)),A47) -> P705SEJUSP | H47: 2500 - ASSESSORAMENTO E GERENCIAMENTO DE POLÍTICAS PÚBLICAS | I47: ELEMENTO | J47: 3702 - LOCACAO DE SERVICOS DE APOIO ADMINISTRATIVO | K47: =VLOOKUP(CONCATENATE(A47,LEFT(J47,4)),AGRUPAMENTO!$D$2:$E$6783,2,FALSE) -> Terceirizados - Demais empresas | L47: 3 - Outras Despesas de Custeio | M47: =CONCATENATE("FONTE",A47) -> FONTESEJUSP | N47: 10 | O47: NÃO | P47: NÃO | Q47: Base previsão salário mínimo (2025)R$1.518,00 | R47: 4 | S47: Adolescente Trebalhador 10% | T47: 4290 | U47: 12 | V47: =R47*T47*U47 -> 205920 | W47: LIMIAR | X47: Contratação de Assprom | Y47: Atraso e/ou impedimento de realização das atividades dos setores. | Z47: Manutenção da capacidades dos setores em realizar as atividades. | AA47: 0 | AB47: 0 | AC47: 0 | AD47: 0.35233925 | AE47: 0.35233925 | AF47: =AE47*V47 -> 72553.699
A48: SEJUSP | B48: SULOT | D48: SAGA | E48: =CONCATENATE(A48,"PROG") -> SEJUSPPROG | F48: 130 - INFRAESTRUTURA DO SISTEMA PRISIONAL | G48: =CONCATENATE("P",(LEFT(F48,3)),A48) -> P130SEJUSP | H48: 4353 - UNIDADES DE SAÚDE DO SISTEMA PRISIONAL | I48: ELEMENTO | J48: 3903 - FORNECIMENTO DE ALIMENTACAO | K48: =VLOOKUP(CONCATENATE(A48,LEFT(J48,4)),AGRUPAMENTO!$D$2:$E$6783,2,FALSE) -> Alimentação | L48: 3 - Outras Despesas de Custeio | M48: =CONCATENATE("FONTE",A48) -> FONTESEJUSP | N48: 10 | O48: Nº do contrato portal de compras: 9275521​​/2021 - Pregão: 295/2020 - Unidade: CENTRO DE APOIO MEDICO E PERICIAL - Comensal: IPL | P48: NÃO | Q48: Média de refeições servidas (volume servido por mês) em 2024 considerando as taxas de crescimento da população carcerária de 0,228% ao mês informada pela Diretoria de Estatística e Análise de Informações de Justiça e Parcerias (DIJ). | R48: 2517.7658 | S48: Valor da diária de acordo com os dados contratuais de 2025 *já acrescidos os 3,00% do centro da meta anual do IPCA para 2025. | T48: 20.4558 | U48: 12 | V48: =R48*T48*U48 -> 618034.96 | W48: LIMIAR | X48: Prestação do serviço de alimentação aos IPLs nas Unidades Prisionais. | Y48: IPLs em cumprimento de pena sem o recebimento de refeições e risco à segurança das Unidades. | Z48: IPLs alimentados. | AA48: 0 | AB48: 0 | AC48: 0 | AD48: 0.89857111 | AE48: 0.89857111 | AF48: =AE48*V48 -> 555348.37
A49: SEJUSP | B49: SULOT | D49: SAGA | E49: =CONCATENATE(A49,"PROG") -> SEJUSPPROG | F49: 130 - INFRAESTRUTURA DO SISTEMA PRISIONAL | G49: =CONCATENATE("P",(LEFT(F49,3)),A49) -> P130SEJUSP | H49: 4353 - UNIDADES DE SAÚDE DO SISTEMA PRISIONAL | I49: ELEMENTO | J49: 3903 - FORNECIMENTO DE ALIMENTACAO | K49: =VLOOKUP(CONCATENATE(A49,LEFT(J49,4)),AGRUPAMENTO!$D$2:$E$6783,2,FALSE) -> Alimentação | L49: 3 - Outras Despesas de Custeio | M49: =CONCATENATE("FONTE",A49) -> FONTESEJUSP | N49: 10 | O49: Nº do contrato portal de compras: 9337104/2022 - Pregão: 020/2022 - Unidade: CENTRO DE REFERENCIA A GESTANTE PRIVADA DE LIBERDADE - Comensal: IPL | P49: NÃO | Q49: Média de refeições servidas (volume servido por mês) em 2024 considerando as taxas de crescimento da população carcerária de 0,228% ao mês informada pela Diretoria de Estatística e Análise de Informações de Justiça e Parcerias (DIJ). | R49: 734.0695 | S49: Valor da diária de acordo com os dados contratuais de 2025 *já acrescidos os 3,00% do centro da meta anual do IPCA para 2025. | T49: 32.2493 | U49: 12 | V49: =R49*T49*U49 -> 284078.73 | W49: LIMIAR | X49: Prestação do serviço de alimentação aos IPLs nas Unidades Prisionais. | Y49: IPLs em cumprimento de pena sem o recebimento de refeições e risco à segurança das Unidades. | Z49: IPLs alimentados. | AA49: 0 | AB49: 0 | AC49: 0 | AD49: 0.89857111 | AE49: 0.89857111 | AF49: =AE49*V49 -> 255264.94
A50: SEJUSP | B50: SULOT | D50: SAGA | E50: =CONCATENATE(A50,"PROG") -> SEJUSPPROG | F50: 130 - INFRAESTRUTURA DO SISTEMA PRISIONAL | G50: =CONCATENATE("P",(LEFT(F50,3)),A50) -> P130SEJUSP | H50: 4353 - UNIDADES DE SAÚDE DO SISTEMA PRISIONAL | I50: ELEMENTO | J50: 3903 - FORNECIMENTO DE ALIMENTACAO | K50: =VLOOKUP(CONCATENATE(A50,LEFT(J50,4)),AGRUPAMENTO!$D$2:$E$6783,2,FALSE) -> Alimentação | L50: 3 - Outras Despesas de Custeio | M50: =CONCATENATE("FONTE",A50) -> FONTESEJUSP | N50: 10 | O50: Nº do contrato portal de compras: 9441322/2024 - Pregão: 238/2024 - Unidade: HOSPITAL PSIQUATRICO JUDICIARIO JORGE VAZ - Comensal: IPL | P50: NÃO | Q50: Média de refeições servidas (volume servido por mês) em 2024 considerando as taxas de crescimento da população carcerária de 0,228% ao mês informada pela Diretoria de Estatística e Análise de Informações de Justiça e Parcerias (DIJ). | R50: 5728.6293 | S50: Valor da diária de acordo com os dados contratuais de 2025 *já acrescidos os 3,00% do centro da meta anual do IPCA para 2025. | T50: 25.8839 | U50: 12 | V50: =R50*T50*U50 -> 1779351.2 | W50: LIMIAR | X50: Prestação do serviço de alimentação aos IPLs nas Unidades Prisionais. | Y50: IPLs em cumprimento de pena sem o recebimento de refeições e risco à segurança das Unidades. | Z50: IPLs alimentados. | AA50: 0 | AB50: 0 | AC50: 0 | AD50: 0.89857111 | AE50: 0.89857111 | AF50: =AE50*V50 -> 1598873.6
A51: SEJUSP | B51: SULOT | D51: SAGA | E51: =CONCATENATE(A51,"PROG") -> SEJUSPPROG | F51: 146 - PROMOÇÃO DA POLÍTICA SOCIOEDUCATIVA PARA ATENDIMENTO AOS ADOLESCENTES EM CONFLITO COM A LEI | G51: =CONCATENATE("P",(LEFT(F51,3)),A51) -> P146SEJUSP | H51: 4441 - ADEQUAÇÃO, MANUTENÇÃO E DESENVOLVIMENTO DO ATENDIMENTO SOCIOEDUCATIVO | I51: ELEMENTO | J51: 3903 - FORNECIMENTO DE ALIMENTACAO | K51: =VLOOKUP(CONCATENATE(A51,LEFT(J51,4)),AGRUPAMENTO!$D$2:$E$6783,2,FALSE) -> Alimentação | L51: 3 - Outras Despesas de Custeio | M51: =CONCATENATE("FONTE",A51) -> FONTESEJUSP | N51: 10 | O51: Nº do contrato no portal de compras 9445204 - PREGÃO 354/2024 - Unidade Centro de Internação Provisória Dom Bosco - Comensal: Adolescente | P51: NÃO | Q51: Média de refeições (volume servido por mês) considerando como referência o número de refeições servidas aos adolescentes em 2024. | R51: 366.25 | S51: Valor da diária de acordo com os dados contratuais de 2025 *já acrescidos os 3,00% do centro da meta anual do IPCA para 2025. | T51: 47.1946 | U51: 12 | V51: =R51*T51*U51 -> 207420.27 | W51: LIMIAR | X51: Prestação do serviço de alimentação aos Adolescentes nas Unidades Socioeducativas. | Y51: Prestação do serviço de alimentação aos Adolescentes nas Unidades Socioeducativas. | Z51: Adolescentes alimentados. | AA51: 0 | AB51: 0 | AC51: 0 | AD51: 0.89857111 | AE51: 0.89857111 | AF51: =AE51*V51 -> 186381.86
A52: SEJUSP | B52: SULOT | D52: SAGA | E52: =CONCATENATE(A52,"PROG") -> SEJUSPPROG | F52: 146 - PROMOÇÃO DA POLÍTICA SOCIOEDUCATIVA PARA ATENDIMENTO AOS ADOLESCENTES EM CONFLITO COM A LEI | G52: =CONCATENATE("P",(LEFT(F52,3)),A52) -> P146SEJUSP | H52: 4441 - ADEQUAÇÃO, MANUTENÇÃO E DESENVOLVIMENTO DO ATENDIMENTO SOCIOEDUCATIVO | I52: ELEMENTO | J52: 3903 - FORNECIMENTO DE ALIMENTACAO | K52: =VLOOKUP(CONCATENATE(A52,LEFT(J52,4)),AGRUPAMENTO!$D$2:$E$6783,2,FALSE) -> Alimentação | L52: 3 - Outras Despesas de Custeio | M52: =CONCATENATE("FONTE",A52) -> FONTESEJUSP | N52: 10 | O52: Nº do contrato no portal de compras 9445204 - PREGÃO 354/2024 - Unidade Centro Integrado de Atendimento ao Adolescente Autor de Ato Infracional - Comensal: Adolescente | P52: NÃO | Q52: Média de refeições (volume servido por mês) considerando como referência o número de refeições servidas aos adolescentes em 2024. | R52: 617.0777 | S52: Valor da diária de acordo com os dados contratuais de 2025 *já acrescidos os 3,00% do centro da meta anual do IPCA para 2025. | T52: 47.1946 | U52: 12 | V52: =R52*T52*U52 -> 349472.82 | W52: LIMIAR | X52: Prestação do serviço de alimentação aos Adolescentes nas Unidades Socioeducativas. | Y52: Prestação do serviço de alimentação aos Adolescentes nas Unidades Socioeducativas. | Z52: Adolescentes alimentados. | AA52: 0 | AB52: 0 | AC52: 0 | AD52: 0.89857111 | AE52: 0.89857111 | AF52: =AE52*V52 -> 314026.18
A53: SEJUSP | B53: SULOT | D53: SAGA | E53: =CONCATENATE(A53,"PROG") -> SEJUSPPROG | F53: 146 - PROMOÇÃO DA POLÍTICA SOCIOEDUCATIVA PARA ATENDIMENTO AOS ADOLESCENTES EM CONFLITO COM A LEI | G53: =CONCATENATE("P",(LEFT(F53,3)),A53) -> P146SEJUSP | H53: 4441 - ADEQUAÇÃO, MANUTENÇÃO E DESENVOLVIMENTO DO ATENDIMENTO SOCIOEDUCATIVO | I53: ELEMENTO | J53: 3903 - FORNECIMENTO DE ALIMENTACAO | K53: =VLOOKUP(CONCATENATE(A53,LEFT(J53,4)),AGRUPAMENTO!$D$2:$E$6783,2,FALSE) -> Alimentação | L53: 3 - Outras Despesas de Custeio | M53: =CONCATENATE("FONTE",A53) -> FONTESEJUSP | N53: 10 | O53: Nº do contrato no portal de compras 9441309 - PREGÃO 147/2024 - Unidade Centro Socioeducativo Horto - Comensal: Adolescente | P53: NÃO | Q53: Média de refeições (volume servido por mês) considerando como referência o número de refeições servidas aos adolescentes em 2024. | R53: 1164.1212 | S53: Valor da diária de acordo com os dados contratuais de 2025 *já acrescidos os 3,00% do centro da meta anual do IPCA para 2025. | T53: 28.5825 | U53: 12 | V53: =R53*T53*U53 -> 399281.93 | W53: LIMIAR | X53: Prestação do serviço de alimentação aos Adolescentes nas Unidades Socioeducativas. | Y53: Prestação do serviço de alimentação aos Adolescentes nas Unidades Socioeducativas. | Z53: Adolescentes alimentados. | AA53: 0 | AB53: 0 | AC53: 0 | AD53: 0.89857111 | AE53: 0.89857111 | AF53: =AE53*V53 -> 358783.21
... A261: SEJUSP | B261: SULOT | D261: DIN | E261: =CONCATENATE(A261,"PROG") -> SEJUSPPROG | F261: 130 - INFRAESTRUTURA DO SISTEMA PRISIONAL | G261: =CONCATENATE("P",(LEFT(F261,3)),A261) -> P130SEJUSP | H261: 1048 - MODERNIZAÇÃO E EXPANSÃO DO SISTEMA PRISIONAL | I261: ELEMENTO | J261: 5101 - ESTUDOS E PROJETOS DE BENS PATRIMONIAVEIS | K261: =VLOOKUP(CONCATENATE(A261,LEFT(J261,4)),AGRUPAMENTO!$D$2:$E$6783,2,FALSE) -> Obras e projetos de obras | L261: 4 - Investimento | M261: =CONCATENATE("FONTE",A261) -> FONTESEJUSP | N261: 60 | O261: Projeto de Extensão da rede de abastecimento de água e esgoto do Presídio de Itaúna | P261: SIM | Q261: Valor total para conclusão da intervenção | R261: 1 | S261: Valor de referência de obras e proejtos da SEINFRA | T261: 1000000 | U261: 1 | V261: =R261*T261*U261 -> 1000000 | W261: LIMIAR | X261: Nessecidade de elaboração de projeto para extensão da rede de abastecimento de água e esgoto para funcionamento da nova unidade | Y261: Impossibilidade de inauguração da unidade construída com sua capacidade máxima | Z261: Inauguração total da unidade com geração de 306 vagas para o sistema prisional e atendimento a requisições judiciais para redução da taxa de ocupação das unidades prisionais | AA261: 0 | AB261: 0 | AC261: 0 | AD261: 0 | AE261: 0 | AF261: =AE261*V261 -> 0
A262: SEJUSP | B262: SULOT | D262: DIN | E262: =CONCATENATE(A262,"PROG") -> SEJUSPPROG | F262: 130 - INFRAESTRUTURA DO SISTEMA PRISIONAL | G262: =CONCATENATE("P",(LEFT(F262,3)),A262) -> P130SEJUSP | H262: 1048 - MODERNIZAÇÃO E EXPANSÃO DO SISTEMA PRISIONAL | I262: ELEMENTO | J262: 5103 - EXECUCAO DE OBRAS POR CONTRATO DE BENS PATRIMONIAVEIS | K262: =VLOOKUP(CONCATENATE(A262,LEFT(J262,4)),AGRUPAMENTO!$D$2:$E$6783,2,FALSE) -> Obras e projetos de obras | L262: 4 - Investimento | M262: =CONCATENATE("FONTE",A262) -> FONTESEJUSP | N262: 60 | O262: Obra de Extensão da rede de abastecimento de água e esgoto do Presídio de Itaúna | P262: SIM | Q262: Valor total para conclusão da intervenção | R262: 1 | S262: Valor de referência de obras e proejtos da SEINFRA | T262: =2000000/12 -> 166666.67 | U262: 12 | V262: =R262*T262*U262 -> 2000000 | W262: LIMIAR | X262: Nessecidade de obra de extensão da rede de abastecimento de água e esgoto para funcionamento da nova unidade | Y262: Impossibilidade de inauguração da unidade construída com sua capacidade máxima | Z262: Inauguração total da unidade com geração de 306 vagas para o sistema prisional e atendimento a requisições judiciais para redução da taxa de ocupação das unidades prisionais | AA262: 0 | AB262: 0 | AC262: 0 | AD262: 0 | AE262: 0 | AF262: =AE262*V262 -> 0
A263: SEJUSP | B263: SULOT | D263: DIN | E263: =CONCATENATE(A263,"PROG") -> SEJUSPPROG | F263: 130 - INFRAESTRUTURA DO SISTEMA PRISIONAL | G263: =CONCATENATE("P",(LEFT(F263,3)),A263) -> P130SEJUSP | H263: 1048 - MODERNIZAÇÃO E EXPANSÃO DO SISTEMA PRISIONAL | I263: ELEMENTO | J263: 5103 - EXECUCAO DE OBRAS POR CONTRATO DE BENS PATRIMONIAVEIS | K263: =VLOOKUP(CONCATENATE(A263,LEFT(J263,4)),AGRUPAMENTO!$D$2:$E$6783,2,FALSE) -> Obras e projetos de obras | L263: 4 - Investimento | M263: =CONCATENATE("FONTE",A263) -> FONTESEJUSP | N263: 60 | O263: Reforma e Ampliação do prédio - Construção de anexo no CERESP de Governador Valadares | P263: SIM | Q263: Valor restante para integralizar o recurso para execução do contrato celebrado pela SEINFRA | R263: 1 | S263: Valor de referência de obras e proejtos da SEINFRA | T263: 3356838.2 | U263: 1 | V263: =R263*T263*U263 -> 3356838.2 | W263: LIMIAR | X263: Complemento de recurso para continuidade de obra | Y263: Paralisação de obra ou atraso de pagamento para a empresa | Z263: Continuidade das obras para atendimento da demanda por geração de vagas da SEJUSP e atendimento a requisições judiciais para redução da taxa de ocupação das unidades prisionais | AA263: 0 | AB263: 0 | AC263: 0 | AD263: 0 | AE263: 0 | AF263: =AE263*V263 -> 0
A264: SEJUSP | B264: SULOT | D264: DIN | E264: =CONCATENATE(A264,"PROG") -> SEJUSPPROG | F264: 134 - GESTÃO INTEGRADA DE SEGURANÇA PÚBLICA | G264: =CONCATENATE("P",(LEFT(F264,3)),A264) -> P134SEJUSP | H264: 4378 - OPERACIONALIZAÇÃO DA POLÍTICA DE INTEGRAÇÃO DA SEGURANÇA PÚBLICA DE MINAS GERAIS | I264: ELEMENTO | J264: 5101 - ESTUDOS E PROJETOS DE BENS PATRIMONIAVEIS | K264: =VLOOKUP(CONCATENATE(A264,LEFT(J264,4)),AGRUPAMENTO!$D$2:$E$6783,2,FALSE) -> Obras e projetos de obras | L264: 4 - Investimento | M264: =CONCATENATE("FONTE",A264) -> FONTESEJUSP | N264: 10 | O264: Projeto de Reforma e Reforço Estrutural da 11ª RISP Montes Claros | P264: NÃO | Q264: Valor total para conclusão da intervenção | R264: 1 | S264: Valor de referência de obras e proejtos da SEINFRA | T264: 22046.98 | U264: 12 | V264: =R264*T264*U264 -> 264563.76 | W264: LIMIAR | X264: Contratação de nova etapa para continuidade dos trabalhos envolvendo a unidade | Y264: Paralisação de obra ou projeto já em andamento na SEJUSP | Z264: Atendimento da demanda da Subsecretaria de Inteligência e Atuação Integrada para reforma de sua edificação que atende aos órgãos de justiça | AA264: 0 | AB264: 0 | AC264: 0 | AD264: 1 | AE264: 0 | AF264: =AE264*V264 -> 0
A265: SEJUSP | B265: SULOT | D265: DIN | E265: =CONCATENATE(A265,"PROG") -> SEJUSPPROG | F265: 130 - INFRAESTRUTURA DO SISTEMA PRISIONAL | G265: =CONCATENATE("P",(LEFT(F265,3)),A265) -> P130SEJUSP | H265: 1048 - MODERNIZAÇÃO E EXPANSÃO DO SISTEMA PRISIONAL | I265: ELEMENTO | J265: 5101 - ESTUDOS E PROJETOS DE BENS PATRIMONIAVEIS | K265: =VLOOKUP(CONCATENATE(A265,LEFT(J265,4)),AGRUPAMENTO!$D$2:$E$6783,2,FALSE) -> Obras e projetos de obras | L265: 4 - Investimento | M265: =CONCATENATE("FONTE",A265) -> FONTESEJUSP | N265: 60 | O265: Projeto de Extensão da rede de abastecimento de água e esgoto na Penitenciária Doutor Manoel Martins Lisoba Júnior - Muriaé | P265: SIM | Q265: Valor total para conclusão da intervenção | R265: 1 | S265: Valor de referência de obras e proejtos da SEINFRA | T265: 83333.333 | U265: 12 | V265: =R265*T265*U265 -> 1000000 | W265: LIMIAR | X265: Nessecidade de construção da rede de abastecimento de água e esgoto para atender demandas judiciais | Y265: Manutenção dos problemas de abastecimento de água e tratamento de esgoto, gerando prejuízos para a unidade e seu entorno | Z265: Adequado fornecimento de água potável e tratamento de esgoto, redução do desperdício e economia aos cofres públicos | AA265: 0 | AB265: 0 | AC265: 0 | AD265: 0 | AE265: 0 | AF265: =AE265*V265 -> 0
A266: SEJUSP | B266: SULOT | D266: DIN | E266: =CONCATENATE(A266,"PROG") -> SEJUSPPROG | F266: 130 - INFRAESTRUTURA DO SISTEMA PRISIONAL | G266: =CONCATENATE("P",(LEFT(F266,3)),A266) -> P130SEJUSP | H266: 1048 - MODERNIZAÇÃO E EXPANSÃO DO SISTEMA PRISIONAL | I266: ELEMENTO | J266: 5103 - EXECUCAO DE OBRAS POR CONTRATO DE BENS PATRIMONIAVEIS | K266: =VLOOKUP(CONCATENATE(A266,LEFT(J266,4)),AGRUPAMENTO!$D$2:$E$6783,2,FALSE) -> Obras e projetos de obras | L266: 4 - Investimento | M266: =CONCATENATE("FONTE",A266) -> FONTESEJUSP | N266: 60 | O266: Obra de Extensão da rede de abastecimento de água e esgoto na Penitenciária Doutor Manoel Martins Lisoba Júnior - Muriaé | P266: SIM | Q266: Valor total para conclusão da intervenção | R266: 1 | S266: Valor de referência de obras e proejtos da SEINFRA | T266: =5000000/12 -> 416666.67 | U266: 12 | V266: =R266*T266*U266 -> 5000000 | W266: LIMIAR | X266: Nessecidade de construção da rede de abastecimento de água e esgoto para atender demandas judiciais | Y266: Manutenção dos problemas de abastecimento de água e tratamento de esgoto, gerando prejuízos para a unidade e seu entorno | Z266: Adequado fornecimento de água potável e tratamento de esgoto, redução do desperdício e economia aos cofres públicos | AA266: 0 | AB266: 0 | AC266: 0 | AD266: 0 | AE266: 0 | AF266: =AE266*V266 -> 0
A267: SEJUSP | B267: SULOT | D267: DIN | E267: =CONCATENATE(A267,"PROG") -> SEJUSPPROG | F267: 130 - INFRAESTRUTURA DO SISTEMA PRISIONAL | G267: =CONCATENATE("P",(LEFT(F267,3)),A267) -> P130SEJUSP | H267: 1048 - MODERNIZAÇÃO E EXPANSÃO DO SISTEMA PRISIONAL | I267: ELEMENTO | J267: 5101 - ESTUDOS E PROJETOS DE BENS PATRIMONIAVEIS | K267: =VLOOKUP(CONCATENATE(A267,LEFT(J267,4)),AGRUPAMENTO!$D$2:$E$6783,2,FALSE) -> Obras e projetos de obras | L267: 4 - Investimento | M267: =CONCATENATE("FONTE",A267) -> FONTESEJUSP | N267: 60 | O267: Projeto de reforma e PSCIP Presídio de São Lourenço | P267: NÃO | Q267: Valor total para conclusão da intervenção | R267: 1 | S267: Valor restante para integralizar o recurso para execução do contrato celebrado pela SEINFRA considerando reajuste | T267: =140000/12 -> 11666.667 | U267: 12 | V267: =R267*T267*U267 -> 140000 | W267: LIMIAR | X267: Continuidade de obra ou projeto de engenharia já em execução | Y267: Paralisação de obra ou projeto já em andamento na SEJUSP | Z267: Atendimento das unidades prisionais às normas de segurança constra incêndio exaradas pelo Corpo de Bombeiros Militar de Minas Gerais | AA267: 0 | AB267: 0 | AC267: 0 | AD267: 1 | AE267: 0 | AF267: =AE267*V267 -> 0
A268: SEJUSP | B268: SULOT | D268: DIN | E268: =CONCATENATE(A268,"PROG") -> SEJUSPPROG | F268: 130 - INFRAESTRUTURA DO SISTEMA PRISIONAL | G268: =CONCATENATE("P",(LEFT(F268,3)),A268) -> P130SEJUSP | H268: 1048 - MODERNIZAÇÃO E EXPANSÃO DO SISTEMA PRISIONAL | I268: ELEMENTO | J268: 3973 - SERVICO DE ENGENHARIA PARA OPERACAO DE BENS DE DOMINIO PUBLICO | K268: =VLOOKUP(CONCATENATE(A268,LEFT(J268,4)),AGRUPAMENTO!$D$2:$E$6783,2,FALSE) -> Demais despesas de custeio | L268: 3 - Outras Despesas de Custeio | M268: =CONCATENATE("FONTE",A268) -> FONTESEJUSP | N268: 60 | O268: Contrato de Manutenção das ETEs : Penitenciária de Francisco Sá, Presídio de Teófilo Otoni, Penitenciária de Unaí, Penitenciária Francisco Floriano de Paula, Penitenciária Professor João Pimenta da Veiga,Penitenciária de Muriaé, Presídio de Barão de Cocais, Presídio de Caratinga, Presídio Dr. Nelson Pires, Penitenciária de Três Corações, Presídio de Guaranésia/Guaxupé, Penitenciária de Deputado Expedito de Faria Tavares, Itauna. | P268: SIM | Q268: NECESSIDADE DE MANUTENÇÃO NAS ETES DAS UNIDADES | R268: 1 | S268: CONTRATO LICITADO SIMILAR | T268: =40000*13 -> 520000 | U268: 12 | V268: =R268*T268*U268 -> 6240000 | W268: LIMIAR | X268: Cumprimento de sentenças judiciais e execução dos diagnósticos apresentados pela empresa com contrato em andamento. Além disso, há necessitadade de manter operação e monitoramento do correto funcionamento das ETEs para atender as normas ambientais e condições dignas dos individuos da unidade | Y268: Multas judiciais, falta de estrutura para cumprimento da pena pelos individuos privados de liberdade, degradação ao meio ambiente, etc | Z268: Atendimento as normas ambientais as condições de saúde de qualidade e oferecimento de condições mínimas de trabalho e ressocialização | AA268: 0 | AB268: 0 | AC268: 0 | AD268: 0 | AE268: 0 | AF268: =AE268*V268 -> 0
A269: SEJUSP | B269: SULOT | D269: DIN | E269: =CONCATENATE(A269,"PROG") -> SEJUSPPROG | F269: 130 - INFRAESTRUTURA DO SISTEMA PRISIONAL | G269: =CONCATENATE("P",(LEFT(F269,3)),A269) -> P130SEJUSP | H269: 1048 - MODERNIZAÇÃO E EXPANSÃO DO SISTEMA PRISIONAL | I269: ELEMENTO | J269: 3973 - SERVICO DE ENGENHARIA PARA OPERACAO DE BENS DE DOMINIO PUBLICO | K269: =VLOOKUP(CONCATENATE(A269,LEFT(J269,4)),AGRUPAMENTO!$D$2:$E$6783,2,FALSE) -> Demais despesas de custeio | L269: 3 - Outras Despesas de Custeio | M269: =CONCATENATE("FONTE",A269) -> FONTESEJUSP | N269: 60 | O269: Contrato de construção ou reforma das ETEs conforme diagnostico elaborado das Unidades: Penitenciária de Francisco Sá, Presídio de Teófilo Otoni, Penitenciária de Unaí, Penitenciária Francisco Floriano de Paula, Penitenciária Professor João Pimenta da Veiga,Penitenciária de Muriaé, Presídio de Barão de Cocais, Presídio de Caratinga, Presídio Dr. Nelson Pires, Penitenciária de Três Corações, Presídio de Guaranésia/Guaxupé, Penitenciária de Deputado Expedito de Faria Tavares, Itauna. | P269: SIM | Q269: NECESSIDADE DE CONSTRUÇÃO/REFORMA DAS ETES DAS UNIDADES | R269: 1 | S269: CONTRATO LICITADO SIMILAR | T269: 3000000 | U269: 12 | V269: =R269*T269*U269 -> 36000000 | W269: LIMIAR | X269: Cumprimento de sentenças judiciais e execução dos diagnósticos apresentados pela empresa com contrato em andamento. Além disso, há necessitadade de manter operação e monitoramento do correto funcionamento das ETEs para atender as normas ambientais e condições digninas dos individuos da unidade | Y269: Multas judiciais, falta de estrutura para cumprimento da pena pelos individuos privados de liberdade, degradação ao meio ambiente, etc | Z269: Atendimento as normas ambientais as condições de saúde de qualidade e oferecimento de condições mínimas de trabalho e ressocialização | AA269: 0 | AB269: 0 | AC269: 0 | AD269: 0 | AE269: 0 | AF269: =AE269*V269 -> 0
A270: SEJUSP | B270: SULOT | D270: DIN | E270: =CONCATENATE(A270,"PROG") -> SEJUSPPROG | F270: 130 - INFRAESTRUTURA DO SISTEMA PRISIONAL | G270: =CONCATENATE("P",(LEFT(F270,3)),A270) -> P130SEJUSP | H270: 4348 - CUSTÓDIA E RESSOCIALIZAÇÃO DE PRESOS | I270: ELEMENTO | J270: 3922 - REPAROS DE BENS IMOVEIS | K270: =VLOOKUP(CONCATENATE(A270,LEFT(J270,4)),AGRUPAMENTO!$D$2:$E$6783,2,FALSE) -> Reparo de imóveis | L270: 3 - Outras Despesas de Custeio | M270: =CONCATENATE("FONTE",A270) -> FONTESEJUSP | N270: 60 | O270: Contrato de automação - Francisco Sá | P270: NÃO | Q270: Necessidade de uma solução de modernização eficiente para a unidade | R270: 1 | S270: contrato licitado | T270: =305555.55*1.12 -> 342222.22 | U270: 12 | V270: =R270*T270*U270 -> 4106666.6 | W270: LIMIAR | X270: A unidade é de segurança maxima e a muitos anos não recebe nenhum tipo de manutenção e necessita da modernização em suas estruturas. | Y270: Aumento do numero de servidores para atender a demanda da unidade. | Z270: Redução do numero de servidores para atender a demanda da unidade, melhoria na segurança. | AA270: 0 | AB270: 0 | AC270: 0 | AD270: 0.24450815 | AE270: 0.24450815 | AF270: =AE270*V270 -> 1004113.5
A271: SEJUSP | B271: SULOT | D271: DIN | E271: =CONCATENATE(A271,"PROG") -> SEJUSPPROG | F271: 134 - GESTÃO INTEGRADA DE SEGURANÇA PÚBLICA | G271: =CONCATENATE("P",(LEFT(F271,3)),A271) -> P134SEJUSP | H271: 4378 - OPERACIONALIZAÇÃO DA POLÍTICA DE INTEGRAÇÃO DA SEGURANÇA PÚBLICA DE MINAS GERAIS | I271: ELEMENTO | J271: 5107 - EXECUCAO DE OBRAS POR CONTRATO DE BENS NAO PATRIMONIAVEIS | K271: =VLOOKUP(CONCATENATE(A271,LEFT(J271,4)),AGRUPAMENTO!$D$2:$E$6783,2,FALSE) -> Obras e projetos de obras | L271: 4 - Investimento | M271: =CONCATENATE("FONTE",A271) -> FONTESEJUSP | N271: 10 | O271: Reforma de pelo menos 03 RISPs - incluindo reformas para atendimento/expansão do CIAD - Montes Claros e Uberlandia. | P271: NÃO | Q271: Valor total para conclusão da intervenção | R271: 1 | S271: Média das Manutenções | T271: =8000000/3 -> 2666666.7 | U271: 3 | V271: =R271*T271*U271 -> 8000000 | W271: LIMIAR | X271: Demanda de reforma do prédio das RISPs e expansão do CIAD | Y271: Manutenção de problemas na infraestrutura, aumento do gasto público e geração de riscos para segurança prisional | Z271: Adequado condição de infraestrutura para trabalho das eqipes, redução do desperdício e economia aos cofres públicos | AA271: 0 | AB271: 0 | AC271: 0 | AD271: 1 | AE271: 0 | AF271: =AE271*V271 -> 0
A272: SEJUSP | B272: SULOT | D272: DIN | E272: =CONCATENATE(A272,"PROG") -> SEJUSPPROG | F272: 130 - INFRAESTRUTURA DO SISTEMA PRISIONAL | G272: =CONCATENATE("P",(LEFT(F272,3)),A272) -> P130SEJUSP | H272: 4348 - CUSTÓDIA E RESSOCIALIZAÇÃO DE PRESOS | I272: ELEMENTO | J272: 3922 - REPAROS DE BENS IMOVEIS | K272: =VLOOKUP(CONCATENATE(A272,LEFT(J272,4)),AGRUPAMENTO!$D$2:$E$6783,2,FALSE) -> Reparo de imóveis | L272: 3 - Outras Despesas de Custeio | M272: =CONCATENATE("FONTE",A272) -> FONTESEJUSP | N272: 60 | O272: MANUTENÇÃO em geral - recurso TJ - Pelo menos 19 unidades prisionais | P272: NÃO | Q272: Necessidade de execução de manutenção preventiva e corretiva nas unidades prisionais com problemas estruturais que carecem de intervenção imediata | R272: 19 | S272: Análise paramétrica baseada em obras similares realizadas no atual contrato de manutenção. | T272: 87720 | U272: 12 | V272: =R272*T272*U272 -> 20000160 | W272: LIMIAR | X272: A maioria das unidades necessitam de reforma geral, principalmente intervenções na redes elétricas e hidrossanitarias. | Y272: Escassez no fornecimento de água, aumento do gasto público e geração de riscos para segurança prisional | Z272: Adequado fornecimento de água potável e enegia elétrica, redução do desperdício e economia aos cofres públicos | AA272: 0 | AB272: 0 | AC272: 0 | AD272: 0.24450815 | AE272: 0.24450815 | AF272: =AE272*V272 -> 4890202.2
A273: SEJUSP | B273: SULOT | D273: DIN | E273: =CONCATENATE(A273,"PROG") -> SEJUSPPROG | F273: 130 - INFRAESTRUTURA DO SISTEMA PRISIONAL | G273: =CONCATENATE("P",(LEFT(F273,3)),A273) -> P130SEJUSP | H273: 4348 - CUSTÓDIA E RESSOCIALIZAÇÃO DE PRESOS | I273: ELEMENTO | J273: 5103 - EXECUCAO DE OBRAS POR CONTRATO DE BENS PATRIMONIAVEIS | K273: =VLOOKUP(CONCATENATE(A273,LEFT(J273,4)),AGRUPAMENTO!$D$2:$E$6783,2,FALSE) -> Obras e projetos de obras | L273: 4 - Investimento | M273: =CONCATENATE("FONTE",A273) -> FONTESEJUSP | N273: 60 | O273: Reforma prevista para 15 unidades prisionais - recurso TJ - Dênio Moreira de Carvalho, Antonio Dutra Ladeira, Ceresp Betim, José Maria Alkimin, Francisco Floriano de Paula, Nelson Hungria, Uberaba, Jacy de Assis, Penit. e Presídio de Teófilo Otorni, Ponte Nova, Conselheiro Pena, Doutor Nelson Pires e Ariosvaldo Campos Pires | P273: NÃO | Q273: Necessidade de execução de reforma geral nas unidades prisionais com problemas estruturais que carecem de intervenção imediata | R273: 15 | S273: Análise paramétrica baseada em obras similares realizadas no atual contrato de manutenção. | T273: 728500 | U273: 12 | V273: =R273*T273*U273 -> 131130000 | W273: LIMIAR | X273: A maioria das unidades necessitam de reforma geral, principalmente intervenções na redes elétricas e hidrossanitarias. | Y273: escassez no fornecimento de água, aumento do gasto público e geração de riscos para segurança prisional | Z273: Adequado fornecimento de água potável e enegia elétrica, redução do desperdício e economia aos cofres públicos | AA273: 0 | AB273: 0 | AC273: 0 | AD273: 0 | AE273: 0 | AF273: =AE273*V273 -> 0
A274: SEJUSP | B274: SULOT | D274: DIN | E274: =CONCATENATE(A274,"PROG") -> SEJUSPPROG | F274: 134 - GESTÃO INTEGRADA DE SEGURANÇA PÚBLICA | G274: =CONCATENATE("P",(LEFT(F274,3)),A274) -> P134SEJUSP | H274: 4378 - OPERACIONALIZAÇÃO DA POLÍTICA DE INTEGRAÇÃO DA SEGURANÇA PÚBLICA DE MINAS GERAIS | I274: ELEMENTO | J274: 5103 - EXECUCAO DE OBRAS POR CONTRATO DE BENS PATRIMONIAVEIS | K274: =VLOOKUP(CONCATENATE(A274,LEFT(J274,4)),AGRUPAMENTO!$D$2:$E$6783,2,FALSE) -> Obras e projetos de obras | L274: 4 - Investimento | M274: =CONCATENATE("FONTE",A274) -> FONTESEJUSP | N274: 10 | O274: Obra de Reforma e Reforço Estrutural da 11ª RISP Montes Claros | P274: SIM | Q274: Valor total para conclusão da intervenção | R274: 1 | S274: Valor de referência de obras e projetos da SEINFRA | T274: 266666.67 | U274: 12 | V274: =R274*T274*U274 -> 3200000 | W274: LIMIAR | X274: Contratação de nova etapa para continuidade dos trabalhos envolvendo a unidade | Y274: Paralisação de obra ou projeto já em andamento na SEJUSP | Z274: Atendimento da demanda da Subsecretaria de Inteligência e Atuação Integrada para reforma de sua edificação que atende aos órgãos de justiça | AA274: 0 | AB274: 0 | AC274: 0 | AD274: 0 | AE274: 0 | AF274: =AE274*V274 -> 0
A275: SEJUSP | B275: SULOT | D275: DIN | E275: =CONCATENATE(A275,"PROG") -> SEJUSPPROG | F275: 130 - INFRAESTRUTURA DO SISTEMA PRISIONAL | G275: =CONCATENATE("P",(LEFT(F275,3)),A275) -> P130SEJUSP | H275: 1048 - MODERNIZAÇÃO E EXPANSÃO DO SISTEMA PRISIONAL | I275: ELEMENTO | J275: 3973 - SERVICO DE ENGENHARIA PARA OPERACAO DE BENS DE DOMINIO PUBLICO | K275: =VLOOKUP(CONCATENATE(A275,LEFT(J275,4)),AGRUPAMENTO!$D$2:$E$6783,2,FALSE) -> Demais despesas de custeio | L275: 3 - Outras Despesas de Custeio | M275: =CONCATENATE("FONTE",A275) -> FONTESEJUSP | N275: 60 | O275: Contrato de Prestação de serviço de Consultoria | P275: NÃO | Q275: NECESSIDADE DE ATENDER AS DEMANDAS DE MANUTENÇÃO DAS UNIDADES | R275: 1 | S275: CONTRATO LICITADO | T275: 375000 | U275: 12 | V275: =R275*T275*U275 -> 4500000 | W275: LIMIAR | X275: Contrato vigente tendo em vista a necessitadade ampliar e agilizar os atendimentos das áreas de engenharia | Y275: Encerramento do contrato e não atendimento das demandas | Z275: ampliar e agilizar os atendimentos das áreas de engenharia | AA275: 0 | AB275: 0 | AC275: 0 | AD275: 0.29138261 | AE275: 0.29138261 | AF275: =AE275*V275 -> 1311221.8
A276: SEJUSP | B276: SUASE | D276: SGES - Superintendência de Gestão Socioeducativa | E276: =CONCATENATE(A276,"PROG") -> SEJUSPPROG | F276: 146 - PROMOÇÃO DA POLÍTICA SOCIOEDUCATIVA PARA ATENDIMENTO AOS ADOLESCENTES EM CONFLITO COM A LEI | G276: =CONCATENATE("P",(LEFT(F276,3)),A276) -> P146SEJUSP | H276: 4441 - ADEQUAÇÃO, MANUTENÇÃO E DESENVOLVIMENTO DO ATENDIMENTO SOCIOEDUCATIVO | I276: ELEMENTO | J276: 5208 - EQUIPAMENTOS DE SOM, VIDEO, FOTOGRAFICO E CINEMATOGRAFICO | K276: =VLOOKUP(CONCATENATE(A276,LEFT(J276,4)),AGRUPAMENTO!$D$2:$E$6783,2,FALSE) -> Aquisições de itens de TIC | L276: 4 - Investimento | M276: =CONCATENATE("FONTE",A276) -> FONTESEJUSP | N276: 10 | O276: Padronização e revitalização dos CFTVs das unidades - CSE Horto | P276: SIM | Q276: Unidade | R276: 1 | S276: Orçamentos recebidos pela STIC | T276: 1400332.8 | U276: 1 | V276: =R276*T276*U276 -> 1400332.8 | W276: INCREMENTAL | X276: Necessidade de aprimorar a infraestrutura do sistema de CFTV das unidades. Os equipamentos atualmente instalados são, em sua maioria, analógicos, com pouca modernização, e demandam revitalização para garantir pleno funcionamento. O monitoramento integral dos espaços das unidades proporciona maior segurança para servidores e adolescentes. | Y276: A manutenção de um sistema de CFTV ultrapassado compromete a eficácia do monitoramento, o que pode dificultar a prevenção de incidentes, evasões, atos de violência ou outras irregularidades. Além disso, falhas na captação de imagens e na cobertura dos espaços podem impactar diretamente na segurança de servidores e adolescentes. | Z276: A modernização do sistema de CFTV garante um monitoramento mais eficiente, com maior qualidade de imagem, maior capacidade de armazenamento e melhor cobertura dos ambientes fortalecendo todo o ambiente das unidades. | AA276: 1 | AB276: 1 | AC276: 3 | AD276: 0 | AE276: 0 | AF276: =AE276*V276 -> 0
A277: SEJUSP | B277: SUASE | D277: SGES - Superintendência de Gestão Socioeducativa | E277: =CONCATENATE(A277,"PROG") -> SEJUSPPROG | F277: 146 - PROMOÇÃO DA POLÍTICA SOCIOEDUCATIVA PARA ATENDIMENTO AOS ADOLESCENTES EM CONFLITO COM A LEI | G277: =CONCATENATE("P",(LEFT(F277,3)),A277) -> P146SEJUSP | H277: 4441 - ADEQUAÇÃO, MANUTENÇÃO E DESENVOLVIMENTO DO ATENDIMENTO SOCIOEDUCATIVO | I277: ELEMENTO | J277: 5208 - EQUIPAMENTOS DE SOM, VIDEO, FOTOGRAFICO E CINEMATOGRAFICO | K277: =VLOOKUP(CONCATENATE(A277,LEFT(J277,4)),AGRUPAMENTO!$D$2:$E$6783,2,FALSE) -> Aquisições de itens de TIC | L277: 4 - Investimento | M277: =CONCATENATE("FONTE",A277) -> FONTESEJUSP | N277: 10 | O277: Padronização e revitalização dos CFTVs das unidades - CIA BH | P277: SIM | Q277: Unidade | R277: 1 | S277: Orçamentos recebidos pela STIC | T277: 546004.53 | U277: 1 | V277: =R277*T277*U277 -> 546004.53 | W277: INCREMENTAL | X277: Necessidade de aprimorar a infraestrutura do sistema de CFTV das unidades. Os equipamentos atualmente instalados são, em sua maioria, analógicos, com pouca modernização, e demandam revitalização para garantir pleno funcionamento. O monitoramento integral dos espaços das unidades proporciona maior segurança para servidores e adolescentes. | Y277: A manutenção de um sistema de CFTV ultrapassado compromete a eficácia do monitoramento, o que pode dificultar a prevenção de incidentes, evasões, atos de violência ou outras irregularidades. Além disso, falhas na captação de imagens e na cobertura dos espaços podem impactar diretamente na segurança de servidores e adolescentes. | Z277: A modernização do sistema de CFTV garante um monitoramento mais eficiente, com maior qualidade de imagem, maior capacidade de armazenamento e melhor cobertura dos ambientes fortalecendo todo o ambiente das unidades. | AA277: 1 | AB277: 1 | AC277: 3 | AD277: 0 | AE277: 0 | AF277: =AE277*V277 -> 0
A278: SEJUSP | B278: SUASE | D278: SGES - Superintendência de Gestão Socioeducativa | E278: =CONCATENATE(A278,"PROG") -> SEJUSPPROG | F278: 146 - PROMOÇÃO DA POLÍTICA SOCIOEDUCATIVA PARA ATENDIMENTO AOS ADOLESCENTES EM CONFLITO COM A LEI | G278: =CONCATENATE("P",(LEFT(F278,3)),A278) -> P146SEJUSP | H278: 4441 - ADEQUAÇÃO, MANUTENÇÃO E DESENVOLVIMENTO DO ATENDIMENTO SOCIOEDUCATIVO | I278: ELEMENTO | J278: 5208 - EQUIPAMENTOS DE SOM, VIDEO, FOTOGRAFICO E CINEMATOGRAFICO | K278: =VLOOKUP(CONCATENATE(A278,LEFT(J278,4)),AGRUPAMENTO!$D$2:$E$6783,2,FALSE) -> Aquisições de itens de TIC | L278: 4 - Investimento | M278: =CONCATENATE("FONTE",A278) -> FONTESEJUSP | N278: 10 | O278: Padronização e revitalização dos CFTVs das unidades - CSE Ribeirão das Neves | P278: SIM | Q278: Unidade | R278: 1 | S278: Orçamentos recebidos pela STIC | T278: 1976530.4 | U278: 1 | V278: =R278*T278*U278 -> 1976530.4 | W278: INCREMENTAL | X278: Necessidade de aprimorar a infraestrutura do sistema de CFTV das unidades. Os equipamentos atualmente instalados são, em sua maioria, analógicos, com pouca modernização, e demandam revitalização para garantir pleno funcionamento. O monitoramento integral dos espaços das unidades proporciona maior segurança para servidores e adolescentes. | Y278: A manutenção de um sistema de CFTV ultrapassado compromete a eficácia do monitoramento, o que pode dificultar a prevenção de incidentes, evasões, atos de violência ou outras irregularidades. Além disso, falhas na captação de imagens e na cobertura dos espaços podem impactar diretamente na segurança de servidores e adolescentes. | Z278: A modernização do sistema de CFTV garante um monitoramento mais eficiente, com maior qualidade de imagem, maior capacidade de armazenamento e melhor cobertura dos ambientes fortalecendo todo o ambiente das unidades. | AA278: 1 | AB278: 1 | AC278: 3 | AD278: 0 | AE278: 0 | AF278: =AE278*V278 -> 0
A279: SEJUSP | B279: SULOT | D279: DIN | E279: =CONCATENATE(A279,"PROG") -> SEJUSPPROG | F279: 130 - INFRAESTRUTURA DO SISTEMA PRISIONAL | G279: =CONCATENATE("P",(LEFT(F279,3)),A279) -> P130SEJUSP | H279: 4348 - CUSTÓDIA E RESSOCIALIZAÇÃO DE PRESOS | I279: ELEMENTO | J279: 5103 - EXECUCAO DE OBRAS POR CONTRATO DE BENS PATRIMONIAVEIS | K279: =VLOOKUP(CONCATENATE(A279,LEFT(J279,4)),AGRUPAMENTO!$D$2:$E$6783,2,FALSE) -> Obras e projetos de obras | L279: 4 - Investimento | M279: =CONCATENATE("FONTE",A279) -> FONTESEJUSP | N279: 60 | O279: Construção de cozinha no Complexo Penitenciário de Juiz de Fora | P279: NÃO | Q279: Necessidade de construção de cozinha para promoção de alimentação administrada | R279: 1 | S279: Análise paramétrica baseada em obras similares | T279: 350000 | U279: 12 | V279: =R279*T279*U279 -> 4200000 | W279: LIMIAR | X279: Necessidade de construção de cozinha para promoção de alimentação administrada | Y279: Falta de fornecimento de alimentação adequada, aumento do gasto público e geração de riscos para segurança prisional | Z279: Adequado fornecimento de alimentação administrada, gerando maior nutrição, redução do desperdício e economia aos cofres públicos | AA279: 0 | AB279: 0 | AC279: 0 | AD279: 1 | AE279: 0 | AF279: =AE279*V279 -> 0
A280: SEJUSP | B280: SUASE | D280: SGES - Superintendência de Gestão Socioeducativa | E280: =CONCATENATE(A280,"PROG") -> SEJUSPPROG | F280: 146 - PROMOÇÃO DA POLÍTICA SOCIOEDUCATIVA PARA ATENDIMENTO AOS ADOLESCENTES EM CONFLITO COM A LEI | G280: =CONCATENATE("P",(LEFT(F280,3)),A280) -> P146SEJUSP | H280: 4441 - ADEQUAÇÃO, MANUTENÇÃO E DESENVOLVIMENTO DO ATENDIMENTO SOCIOEDUCATIVO | I280: ELEMENTO | J280: 5208 - EQUIPAMENTOS DE SOM, VIDEO, FOTOGRAFICO E CINEMATOGRAFICO | K280: =VLOOKUP(CONCATENATE(A280,LEFT(J280,4)),AGRUPAMENTO!$D$2:$E$6783,2,FALSE) -> Aquisições de itens de TIC | L280: 4 - Investimento | M280: =CONCATENATE("FONTE",A280) -> FONTESEJUSP | N280: 10 | O280: Padronização e revitalização dos CFTVs das unidades - CEIP Dom Bosco | P280: SIM | Q280: Unidade | R280: 1 | S280: Orçamentos recebidos pela STIC | T280: 2791864.9 | U280: 1 | V280: =R280*T280*U280 -> 2791864.9 | W280: INCREMENTAL | X280: Necessidade de aprimorar a infraestrutura do sistema de CFTV das unidades. Os equipamentos atualmente instalados são, em sua maioria, analógicos, com pouca modernização, e demandam revitalização para garantir pleno funcionamento. O monitoramento integral dos espaços das unidades proporciona maior segurança para servidores e adolescentes. | Y280: A manutenção de um sistema de CFTV ultrapassado compromete a eficácia do monitoramento, o que pode dificultar a prevenção de incidentes, evasões, atos de violência ou outras irregularidades. Além disso, falhas na captação de imagens e na cobertura dos espaços podem impactar diretamente na segurança de servidores e adolescentes. | Z280: A modernização do sistema de CFTV garante um monitoramento mais eficiente, com maior qualidade de imagem, maior capacidade de armazenamento e melhor cobertura dos ambientes fortalecendo todo o ambiente das unidades. | AA280: 1 | AB280: 1 | AC280: 3 | AD280: 0 | AE280: 0 | AF280: =AE280*V280 -> 0
A281: SEJUSP | B281: SULOT | D281: DIN | E281: =CONCATENATE(A281,"PROG") -> SEJUSPPROG | F281: 130 - INFRAESTRUTURA DO SISTEMA PRISIONAL | G281: =CONCATENATE("P",(LEFT(F281,3)),A281) -> P130SEJUSP | H281: 1048 - MODERNIZAÇÃO E EXPANSÃO DO SISTEMA PRISIONAL | I281: ELEMENTO | J281: 3973 - SERVICO DE ENGENHARIA PARA OPERACAO DE BENS DE DOMINIO PUBLICO | K281: =VLOOKUP(CONCATENATE(A281,LEFT(J281,4)),AGRUPAMENTO!$D$2:$E$6783,2,FALSE) -> Demais despesas de custeio | L281: 3 - Outras Despesas de Custeio | M281: =CONCATENATE("FONTE",A281) -> FONTESEJUSP | N281: 60 | O281: Contrato de Manutenção das ETEs : São Joaquim de Bicas, Ubá e Iturama | P281: NÃO | Q281: NECESSIDADE DE MANUTENÇÃO NAS ETES DAS UNIDADES | R281: 1 | S281: CONTRATO LICITADO | T281: 133537.4 | U281: 12 | V281: =R281*T281*U281 -> 1602448.8 | W281: LIMIAR | X281: necessitadade de manter a operação e monitoramento do correto funcionamento das ETEs para atender as normas ambientais e condições digninas dos individuos da unidade | Y281: Multas judiciais, falta de estrutura para cumprimento da pena pelos individuos privados de liberdade, degradação ao meio ambiente, etc | Z281: Atendimento as normas ambientais as condições de saúde de qualidade e oferecimento de condições mínimas de trabalho e ressocialização | AA281: 0 | AB281: 0 | AC281: 0 | AD281: 0.29138261 | AE281: 0.29138261 | AF281: =AE281*V281 -> 466925.73
A282: SEJUSP | B282: SULOT | D282: DIN | E282: =CONCATENATE(A282,"PROG") -> SEJUSPPROG | F282: 130 - INFRAESTRUTURA DO SISTEMA PRISIONAL | G282: =CONCATENATE("P",(LEFT(F282,3)),A282) -> P130SEJUSP | H282: 1048 - MODERNIZAÇÃO E EXPANSÃO DO SISTEMA PRISIONAL | I282: ELEMENTO | J282: 5101 - ESTUDOS E PROJETOS DE BENS PATRIMONIAVEIS | K282: =VLOOKUP(CONCATENATE(A282,LEFT(J282,4)),AGRUPAMENTO!$D$2:$E$6783,2,FALSE) -> Obras e projetos de obras | L282: 4 - Investimento | M282: =CONCATENATE("FONTE",A282) -> FONTESEJUSP | N282: 60 | O282: Elaboração de Projetos de Segurança Contra Incêndio para mais 16 Unidades prisionais prioritárias | P282: NÃO | Q282: Valor total para conclusão da intervenção | R282: 1 | S282: Valor restante para integralizar o recurso para execução do contrato celebrado pela SEINFRA considerando reajuste | T282: 111116.37 | U282: 12 | V282: =R282*T282*U282 -> 1333396.4 | W282: LIMIAR | X282: Continuidade de obra ou projeto de engenharia já em execução | Y282: Paralisação de obra ou projeto já em andamento na SEJUSP | Z282: Atendimento das unidades prisionais às normas de segurança constra incêndio exaradas pelo Corpo de Bombeiros Militar de Minas Gerais | AA282: 0 | AB282: 0 | AC282: 0 | AD282: 1 | AE282: 0 | AF282: =AE282*V282 -> 0
A283: SEJUSP | B283: SULOT | D283: DIN | E283: =CONCATENATE(A283,"PROG") -> SEJUSPPROG | F283: 130 - INFRAESTRUTURA DO SISTEMA PRISIONAL | G283: =CONCATENATE("P",(LEFT(F283,3)),A283) -> P130SEJUSP | H283: 1048 - MODERNIZAÇÃO E EXPANSÃO DO SISTEMA PRISIONAL | I283: ELEMENTO | J283: 5103 - EXECUCAO DE OBRAS POR CONTRATO DE BENS PATRIMONIAVEIS | K283: =VLOOKUP(CONCATENATE(A283,LEFT(J283,4)),AGRUPAMENTO!$D$2:$E$6783,2,FALSE) -> Obras e projetos de obras | L283: 4 - Investimento | M283: =CONCATENATE("FONTE",A283) -> FONTESEJUSP | N283: 60 | O283: Obra de reforma e PSCIP Presídio de São Lourenço | P283: SIM | Q283: Valor total para conclusão da intervenção | R283: 1 | S283: Valor de referência de obras e projetos da SEINFRA | T283: 350000 | U283: 12 | V283: =R283*T283*U283 -> 4200000 | W283: LIMIAR | X283: Contratação de nova etapa para continuidade dos trabalhos envolvendo as unidades | Y283: Paralisação de obra ou projeto já em andamento na SEJUSP | Z283: Atendimento das unidades prisionais às normas de segurança constra incêndio exaradas pelo Corpo de Bombeiros Militar de Minas Gerais | AA283: 0 | AB283: 0 | AC283: 0 | AD283: 0 | AE283: 0 | AF283: =AE283*V283 -> 0
A284: SEJUSP | B284: SULOT | D284: DIN | E284: =CONCATENATE(A284,"PROG") -> SEJUSPPROG | F284: 130 - INFRAESTRUTURA DO SISTEMA PRISIONAL | G284: =CONCATENATE("P",(LEFT(F284,3)),A284) -> P130SEJUSP | H284: 1048 - MODERNIZAÇÃO E EXPANSÃO DO SISTEMA PRISIONAL | I284: ELEMENTO | J284: 3973 - SERVICO DE ENGENHARIA PARA OPERACAO DE BENS DE DOMINIO PUBLICO | K284: =VLOOKUP(CONCATENATE(A284,LEFT(J284,4)),AGRUPAMENTO!$D$2:$E$6783,2,FALSE) -> Demais despesas de custeio | L284: 3 - Outras Despesas de Custeio | M284: =CONCATENATE("FONTE",A284) -> FONTESEJUSP | N284: 60 | O284: Contrato de Manutenção de 7 poços de abastecimento de água, neste processo inclui manutenção das bombas | P284: SIM | Q284: NECESSIDADE DE MANUTENÇÃO DOS POÇOS NAS UNIDADES | R284: 1 | S284: CONTRATO EM PROCESSO DE LICITAÇÃO | T284: =26000*7 -> 182000 | U284: 12 | V284: =R284*T284*U284 -> 2184000 | W284: LIMIAR | X284: Contratação em andamento para atender ordem/cronograma jurdicial e para manter a operação e monitoramento do correto funcionamento dos poços para atender as normas ambientais e condições digninas dos individuos da unidade | Y284: Multas judiciais, falta de estrutura para cumprimento da pena pelos individuos privados de liberdade, degradação ao meio ambiente, etc | Z284: Atendimento as normas ambientais as condições de saúde de qualidade e oferecimento de condições mínimas de trabalho e ressocialização | AA284: 0 | AB284: 0 | AC284: 0 | AD284: 0 | AE284: 0 | AF284: =AE284*V284 -> 0
A285: SEJUSP | B285: SULOT | D285: DIN | E285: =CONCATENATE(A285,"PROG") -> SEJUSPPROG | F285: 130 - INFRAESTRUTURA DO SISTEMA PRISIONAL | G285: =CONCATENATE("P",(LEFT(F285,3)),A285) -> P130SEJUSP | H285: 1048 - MODERNIZAÇÃO E EXPANSÃO DO SISTEMA PRISIONAL | I285: ELEMENTO | J285: 3973 - SERVICO DE ENGENHARIA PARA OPERACAO DE BENS DE DOMINIO PUBLICO | K285: =VLOOKUP(CONCATENATE(A285,LEFT(J285,4)),AGRUPAMENTO!$D$2:$E$6783,2,FALSE) -> Demais despesas de custeio | L285: 3 - Outras Despesas de Custeio | M285: =CONCATENATE("FONTE",A285) -> FONTESEJUSP | N285: 60 | O285: Contrato de MANUTENÇÃO E OPERAÇÃO DA ETA INSTALADO NA PENITENCIARIA FRANCISCO FLORIANO DE PAULA EM GOVERNADOR VALADARES | P285: SIM | Q285: NECESSIDADE DE MANUTENÇÃO E OPERAÇÃO DA ETA INSTALADO NA PENITENCIARIA FRANCISCO FLORIANO DE PAULA EM GOVERNADOR VALADARES | R285: 1 | S285: CONTRATO EM PROCESSO DE LICITAÇÃO | T285: 76000 | U285: 12 | V285: =R285*T285*U285 -> 912000 | W285: LIMIAR | X285: Contratação em andamento para atender ordem/cronograma jurdicial e para manter a operação e monitoramento do correto funcionamento dos poços para atender as normas ambientais e condições digninas dos individuos da unidade | Y285: Multas judiciais, falta de estrutura para cumprimento da pena pelos individuos privados de liberdade, degradação ao meio ambiente, etc | Z285: Atendimento as normas ambientais as condições de saúde de qualidade e oferecimento de condições mínimas de trabalho e ressocialização | AA285: 0 | AB285: 0 | AC285: 0 | AD285: 0 | AE285: 0 | AF285: =AE285*V285 -> 0
A286: SEJUSP | B286: SUINT | D286: SUPERINTENDÊNCIA DE INTEGRAÇÃO E PLANEJAMENTO OPERACIONAL - SIPO | E286: =CONCATENATE(A286,"PROG") -> SEJUSPPROG | F286: 134 - GESTÃO INTEGRADA DE SEGURANÇA PÚBLICA | G286: =CONCATENATE("P",(LEFT(F286,3)),A286) -> P134SEJUSP | H286: 4378 - OPERACIONALIZAÇÃO DA POLÍTICA DE INTEGRAÇÃO DA SEGURANÇA PÚBLICA DE MINAS GERAIS | I286: ELEMENTO | J286: 3612 - DESPESAS MIUDAS DE PRONTO PAGAMENTO | K286: =VLOOKUP(CONCATENATE(A286,LEFT(J286,4)),AGRUPAMENTO!$D$2:$E$6783,2,FALSE) -> Pronto Pagamento | L286: 3 - Outras Despesas de Custeio | M286: =CONCATENATE("FONTE",A286) -> FONTESEJUSP | N286: 10 | O286: DESPESA MIÚDA DDU | P286: NÃO | Q286: R$ 3.000/MÊS CONFORME DEMANDA | R286: 1 | S286: VALOR DISPONIBILIZADO A PARTIR DE DELIBERAÇÃO DA SEJUSP PARA DESPESAS URGENTES E INADIÁVEIS | T286: 3000 | U286: 12 | V286: =R286*T286*U286 -> 36000 | W286: LIMIAR | X286: ATENDIMENTO DE DEMANDAS URGENTES E INADIÁVEIS QUE NÃO PUDERAM SER PREVIAMENTE EMPENHADAS | Y286: NÃO REALIZAÇÃO DE PEQUENAS MANUTENÇÕES IMPREVISTAS, SUCATEAMENTO E INDISPONIBILIDADE DO SERVIÇO | Z286: COBERTURA DE IMPREVISTOS E MANUTENÇÃO DOS SERVIÇOS | AA286: 0 | AB286: 0 | AC286: 0 | AD286: 1 | AE286: 1 | AF286: =AE286*V286 -> 36000
A287: SEJUSP | B287: SUINT | D287: SUPERINTENDÊNCIA DE INTEGRAÇÃO E PLANEJAMENTO OPERACIONAL - SIPO | E287: =CONCATENATE(A287,"PROG") -> SEJUSPPROG | F287: 134 - GESTÃO INTEGRADA DE SEGURANÇA PÚBLICA | G287: =CONCATENATE("P",(LEFT(F287,3)),A287) -> P134SEJUSP | H287: 4378 - OPERACIONALIZAÇÃO DA POLÍTICA DE INTEGRAÇÃO DA SEGURANÇA PÚBLICA DE MINAS GERAIS | I287: ELEMENTO | J287: 3612 - DESPESAS MIUDAS DE PRONTO PAGAMENTO | K287: =VLOOKUP(CONCATENATE(A287,LEFT(J287,4)),AGRUPAMENTO!$D$2:$E$6783,2,FALSE) -> Pronto Pagamento | L287: 3 - Outras Despesas de Custeio | M287: =CONCATENATE("FONTE",A287) -> FONTESEJUSP | N287: 10 | O287: DESPESA MIÚDA CIAD | P287: NÃO | Q287: R$ 3.000/MÊS CONFORME DEMANDA | R287: 1 | S287: VALOR DISPONIBILIZADO A PARTIR DE DELIBERAÇÃO DA SEJUSP PARA DESPESAS URGENTES E INADIÁVEIS | T287: 3000 | U287: 12 | V287: =R287*T287*U287 -> 36000 | W287: LIMIAR | X287: ATENDIMENTO DE DEMANDAS URGENTES E INADIÁVEIS QUE NÃO PUDERAM SER PREVIAMENTE EMPENHADAS | Y287: NÃO REALIZAÇÃO DE PEQUENAS MANUTENÇÕES IMPREVISTAS, SUCATEAMENTO E INDISPONIBILIDADE DO SERVIÇO | Z287: COBERTURA DE IMPREVISTOS E MANUTENÇÃO DOS SERVIÇOS | AA287: 0 | AB287: 0 | AC287: 0 | AD287: 1 | AE287: 1 | AF287: =AE287*V287 -> 36000
A288: SEJUSP | B288: SUINT | D288: SUPERINTENDÊNCIA DE INTEGRAÇÃO E PLANEJAMENTO OPERACIONAL - SIPO | E288: =CONCATENATE(A288,"PROG") -> SEJUSPPROG | F288: 134 - GESTÃO INTEGRADA DE SEGURANÇA PÚBLICA | G288: =CONCATENATE("P",(LEFT(F288,3)),A288) -> P134SEJUSP | H288: 4378 - OPERACIONALIZAÇÃO DA POLÍTICA DE INTEGRAÇÃO DA SEGURANÇA PÚBLICA DE MINAS GERAIS | I288: ELEMENTO | J288: 3612 - DESPESAS MIUDAS DE PRONTO PAGAMENTO | K288: =VLOOKUP(CONCATENATE(A288,LEFT(J288,4)),AGRUPAMENTO!$D$2:$E$6783,2,FALSE) -> Pronto Pagamento | L288: 3 - Outras Despesas de Custeio | M288: =CONCATENATE("FONTE",A288) -> FONTESEJUSP | N288: 10 | O288: DESPESA MIÚDA DCI | P288: NÃO | Q288: R$ 3.000/MÊS CONFORME DEMANDA | R288: 1 | S288: VALOR DISPONIBILIZADO A PARTIR DE DELIBERAÇÃO DA SEJUSP PARA DESPESAS URGENTES E INADIÁVEIS | T288: 3000 | U288: 12 | V288: =R288*T288*U288 -> 36000 | W288: LIMIAR | X288: ATENDIMENTO DE DEMANDAS URGENTES E INADIÁVEIS QUE NÃO PUDERAM SER PREVIAMENTE EMPENHADAS | Y288: NÃO REALIZAÇÃO DE PEQUENAS MANUTENÇÕES IMPREVISTAS, SUCATEAMENTO E INDISPONIBILIDADE DO SERVIÇO | Z288: COBERTURA DE IMPREVISTOS E MANUTENÇÃO DOS SERVIÇOS | AA288: 0 | AB288: 0 | AC288: 0 | AD288: 1 | AE288: 1 | AF288: =AE288*V288 -> 36000
A289: SEJUSP | B289: SUINT | D289: SUPERINTENDÊNCIA DE INTEGRAÇÃO E PLANEJAMENTO OPERACIONAL - SIPO | E289: =CONCATENATE(A289,"PROG") -> SEJUSPPROG | F289: 134 - GESTÃO INTEGRADA DE SEGURANÇA PÚBLICA | G289: =CONCATENATE("P",(LEFT(F289,3)),A289) -> P134SEJUSP | H289: 4378 - OPERACIONALIZAÇÃO DA POLÍTICA DE INTEGRAÇÃO DA SEGURANÇA PÚBLICA DE MINAS GERAIS | I289: ELEMENTO | J289: 3612 - DESPESAS MIUDAS DE PRONTO PAGAMENTO | K289: =VLOOKUP(CONCATENATE(A289,LEFT(J289,4)),AGRUPAMENTO!$D$2:$E$6783,2,FALSE) -> Pronto Pagamento | L289: 3 - Outras Despesas de Custeio | M289: =CONCATENATE("FONTE",A289) -> FONTESEJUSP | N289: 10 | O289: DESPESA MIÚDA SIPO | P289: NÃO | Q289: R$ 4.000/MÊS CONFORME DEMANDA | R289: 1 | S289: VALOR DISPONIBILIZADO A PARTIR DE DELIBERAÇÃO DA SEJUSP PARA DESPESAS URGENTES E INADIÁVEIS | T289: 4000 | U289: 12 | V289: =R289*T289*U289 -> 48000 | W289: LIMIAR | X289: ATENDIMENTO DE DEMANDAS URGENTES E INADIÁVEIS QUE NÃO PUDERAM SER PREVIAMENTE EMPENHADAS | Y289: NÃO REALIZAÇÃO DE PEQUENAS MANUTENÇÕES IMPREVISTAS, SUCATEAMENTO E INDISPONIBILIDADE DO SERVIÇO | Z289: COBERTURA DE IMPREVISTOS E MANUTENÇÃO DOS SERVIÇOS | AA289: 0 | AB289: 0 | AC289: 0 | AD289: 1 | AE289: 1 | AF289: =AE289*V289 -> 48000
A290: SEJUSP | B290: SUINT | D290: SUPERINTENDÊNCIA DE INTEGRAÇÃO E PLANEJAMENTO OPERACIONAL - SIPO | E290: =CONCATENATE(A290,"PROG") -> SEJUSPPROG | F290: 134 - GESTÃO INTEGRADA DE SEGURANÇA PÚBLICA | G290: =CONCATENATE("P",(LEFT(F290,3)),A290) -> P134SEJUSP | H290: 4378 - OPERACIONALIZAÇÃO DA POLÍTICA DE INTEGRAÇÃO DA SEGURANÇA PÚBLICA DE MINAS GERAIS | I290: ELEMENTO | J290: 4003 - SERVICO DE INFORMATICA EXECUTADO PELA PRODEMGE | K290: =VLOOKUP(CONCATENATE(A290,LEFT(J290,4)),AGRUPAMENTO!$D$2:$E$6783,2,FALSE) -> PRODEMGE | L290: 3 - Outras Despesas de Custeio | M290: =CONCATENATE("FONTE",A290) -> FONTESEJUSP | N290: 10 | O290: SUPORTE TECNOLÓGICO EM SOLUÇÃO DE TIC | P290: NÃO | Q290: MENSAL | R290: 1 | S290: VALOR DE CONTRATO | T290: 15399.6 | U290: 12 | V290: =R290*T290*U290 -> 184795.2 | W290: LIMIAR | X290: TRATA-SE DE RECURSO DESTINADO AO CUSTEIO DO SERVIÇO EMERGÊNCIA MG, QUE PERMITE O ACIONAMENTO DE EMERGÊNCIA DAS FORÇAS DE SEGURANÇA ATRAVÉS DE APLICATIVOS E VIA WEB | Y290: DESCONTINUIDADE DA PRESTAÇÃO DO SERVIÇO | Z290: PERMITE O CIDADÃO ACIONAR O SERVIÇO DE URGÊNCIA E EMERGÊNCIA VIA CANAIS DIGITAIS | AA290: 0 | AB290: 0 | AC290: 0 | AD290: 0.74255988 | AE290: 0.74255988 | AF290: =AE290*V290 -> 137221.5
A291: SEJUSP | B291: SUINT | D291: SUPERINTENDÊNCIA DE INTEGRAÇÃO E PLANEJAMENTO OPERACIONAL - SIPO | E291: =CONCATENATE(A291,"PROG") -> SEJUSPPROG | F291: 134 - GESTÃO INTEGRADA DE SEGURANÇA PÚBLICA | G291: =CONCATENATE("P",(LEFT(F291,3)),A291) -> P134SEJUSP | H291: 4378 - OPERACIONALIZAÇÃO DA POLÍTICA DE INTEGRAÇÃO DA SEGURANÇA PÚBLICA DE MINAS GERAIS | I291: ELEMENTO | J291: 1401 - DIARIAS - CIVIL | K291: =VLOOKUP(CONCATENATE(A291,LEFT(J291,4)),AGRUPAMENTO!$D$2:$E$6783,2,FALSE) -> Diárias e viagens | L291: 3 - Outras Despesas de Custeio | M291: =CONCATENATE("FONTE",A291) -> FONTESEJUSP | N291: 10 | O291: VIAGENS DE 4 DIAS PARA 3 SERVIDORES | P291: NÃO | Q291: VALOR DA MÉDIA DAS DIÁRIAS FAIXA I PARA MUNICIPIOS ESPECIAIS E DEMAIS MUNICÍPIOS | R291: 12 | S291: VALOR DA MÉDIA DAS DIÁRIAS FAIXA I PARA MUNICIPIOS ESPECIAIS E DEMAIS MUNICÍPIOS | T291: 310 | U291: 12 | V291: =R291*T291*U291 -> 44640 | W291: LIMIAR | X291: DIÁRIAS DESTINADAS A AGENTES DA SIPO/SEJUSP VISANDO SUBSIDIAR O EMPREGO DESTES EM OPERAÇÕES INTEGRADAS | Y291: NÃO PARTICIPAÇÃO DA SEJUSP EM AÇÕES E EVENTOS DE PROMOÇÃO E FORTALECIMENTO DA INTEGRAÇÃO DAS INSTITUIÇÕES DE SEGURANÇA PÚBLICA. | Z291: INTERLOCUÇÃO E ARTICULAÇÃO COM OUTRAS INSTITUIÇÕES DE SEGURANÇA PÚBLICA E CONSEQUENTE AUMENTO DO IMPACTO DAS AÇÕES DAS QUAIS A SUPERINTENDÊNCIA PARTICIPA. | AA291: 0 | AB291: 0 | AC291: 0 | AD291: 0.86749885 | AE291: 0.86749885 | AF291: =AE291*V291 -> 38725.149
A292: SEJUSP | B292: SUINT | D292: SUPERINTENDÊNCIA DE INTEGRAÇÃO E PLANEJAMENTO OPERACIONAL - SIPO | E292: =CONCATENATE(A292,"PROG") -> SEJUSPPROG | F292: 134 - GESTÃO INTEGRADA DE SEGURANÇA PÚBLICA | G292: =CONCATENATE("P",(LEFT(F292,3)),A292) -> P134SEJUSP | H292: 4378 - OPERACIONALIZAÇÃO DA POLÍTICA DE INTEGRAÇÃO DA SEGURANÇA PÚBLICA DE MINAS GERAIS | I292: ELEMENTO | J292: 3999 - OUTROS SERVICOS-PESSOA JURIDICA | K292: =VLOOKUP(CONCATENATE(A292,LEFT(J292,4)),AGRUPAMENTO!$D$2:$E$6783,2,FALSE) -> Demais despesas de custeio | L292: 3 - Outras Despesas de Custeio | M292: =CONCATENATE("FONTE",A292) -> FONTESEJUSP | N292: 10 | O292: SERVIÇO DE AFERIÇÃO DE ETILÔMETROS | P292: NÃO | Q292: AFERIÇÃO DE 50 ETILÔMETROS | R292: 50 | S292: PREÇO MÉDIA DE MERCADO | T292: 5000 | U292: 1 | V292: =R292*T292*U292 -> 250000 | W292: LIMIAR | X292: Manutenção dos etilômetros utilizados para realização das blitz lei seca da campanha Sou Pela Vida Dirijo sem Bebida | Y292: DESCONTINUIDADE DA CAMPANHA SOU PELA VIDA DIRIJO SEM BEBIDA | Z292: MANUTENÇÃO DAS BLITZ LEI SECA | AA292: 0 | AB292: 0 | AC292: 0 | AD292: 0.29138261 | AE292: 0.29138261 | AF292: =AE292*V292 -> 72845.654
A293: SEJUSP | B293: SUINT | D293: SUPERINTENDÊNCIA DE INTEGRAÇÃO E PLANEJAMENTO OPERACIONAL - SIPO | E293: =CONCATENATE(A293,"PROG") -> SEJUSPPROG | F293: 134 - GESTÃO INTEGRADA DE SEGURANÇA PÚBLICA | G293: =CONCATENATE("P",(LEFT(F293,3)),A293) -> P134SEJUSP | H293: 4378 - OPERACIONALIZAÇÃO DA POLÍTICA DE INTEGRAÇÃO DA SEGURANÇA PÚBLICA DE MINAS GERAIS | I293: ELEMENTO | J293: 3099 - OUTROS MATERIAIS | K293: =VLOOKUP(CONCATENATE(A293,LEFT(J293,4)),AGRUPAMENTO!$D$2:$E$6783,2,FALSE) -> Material de consumo | L293: 3 - Outras Despesas de Custeio | M293: =CONCATENATE("FONTE",A293) -> FONTESEJUSP | N293: 10 | O293: PRÊMIOS, DIPLOMAS, CONDECORAÇÕES E MEDALHAS | P293: SIM | Q293: NÚMERO DE MEDALHAS E PREMIOS DISTRIBUIDOS NO PRÊMIO MÉRITO NA INTEGRAÇÃO | R293: 200 | S293: CONFORME RP 5/2024 | T293: 250 | U293: 1 | V293: =R293*T293*U293 -> 50000 | W293: LIMIAR | X293: CONFORME RESOLUÇÃO SEJUSP 1773/2023 TRATA-SE DE HONRARIA PARA PROFISSIONAIS QUE CONTRIBUIRAM COM AÇÕES INTEGRADAS DE SEGURANÇA PÚBLICA | Y293: NÃO CUMPRIMENTO DA RESOLUÇÃO | Z293: FOMENTA A INTEGRAÇÃO DAS FORÇAS DE SEGURANÇA | AA293: 0 | AB293: 0 | AC293: 0 | AD293: 0 | AE293: 0 | AF293: =AE293*V293 -> 0
A294: SEJUSP | B294: SUINT | D294: SUPERINTENDÊNCIA DE INTEGRAÇÃO E PLANEJAMENTO OPERACIONAL - SIPO | E294: =CONCATENATE(A294,"PROG") -> SEJUSPPROG | F294: 134 - GESTÃO INTEGRADA DE SEGURANÇA PÚBLICA | G294: =CONCATENATE("P",(LEFT(F294,3)),A294) -> P134SEJUSP | H294: 4378 - OPERACIONALIZAÇÃO DA POLÍTICA DE INTEGRAÇÃO DA SEGURANÇA PÚBLICA DE MINAS GERAIS | I294: ELEMENTO | J294: 3612 - DESPESAS MIUDAS DE PRONTO PAGAMENTO | K294: =VLOOKUP(CONCATENATE(A294,LEFT(J294,4)),AGRUPAMENTO!$D$2:$E$6783,2,FALSE) -> Pronto Pagamento | L294: 3 - Outras Despesas de Custeio | M294: =CONCATENATE("FONTE",A294) -> FONTESEJUSP | N294: 10 | O294: DESPESA MIÚDA DPI | P294: NÃO | Q294: R$ 3.000/MÊS CONFORME DEMANDA | R294: 1 | S294: VALOR DISPONIBILIZADO A PARTIR DE DELIBERAÇÃO DA SEJUSP PARA DESPESAS URGENTES E INADIÁVEIS | T294: 3000 | U294: 12 | V294: =R294*T294*U294 -> 36000 | W294: LIMIAR | X294: ATENDIMENTO DE DEMANDAS URGENTES E INADIÁVEIS QUE NÃO PUDERAM SER PREVIAMENTE EMPENHADAS | Y294: NÃO REALIZAÇÃO DE PEQUENAS MANUTENÇÕES IMPREVISTAS, SUCATEAMENTO E INDISPONIBILIDADE DO SERVIÇO | Z294: COBERTURA DE IMPREVISTOS E MANUTENÇÃO DOS SERVIÇOS | AA294: 0 | AB294: 0 | AC294: 0 | AD294: 1 | AE294: 1 | AF294: =AE294*V294 -> 36000
A295: SEJUSP | B295: SUINT | D295: NÚCLEO DE INTELIGÊNCIA E CONHECIMENTO ESTRATÉGICO | E295: =CONCATENATE(A295,"PROG") -> SEJUSPPROG | F295: 129 - PREVENÇÃO À CRIMINALIDADE | G295: =CONCATENATE("P",(LEFT(F295,3)),A295) -> P129SEJUSP | H295: 4344 - PREVENÇÃO SOCIAL ÀS VIOLÊNCIAS E CRIMINALIDADES | I295: ELEMENTO | J295: 1401 - DIARIAS - CIVIL | K295: =VLOOKUP(CONCATENATE(A295,LEFT(J295,4)),AGRUPAMENTO!$D$2:$E$6783,2,FALSE) -> Diárias e viagens | L295: 3 - Outras Despesas de Custeio | M295: =CONCATENATE("FONTE",A295) -> FONTESEJUSP | N295: 60 | O295: DIÁRIA PARA ATENDER HOSPEDAGEM E DESLOCAMENTO DE SERVIDOR DESIGNADO | P295: NÃO | Q295: NÚMERO DE DIÁRIAS QUE SERÃO UTILIZADAS DURANTE O ANO (20) X NÚMERO DE SERVIDORES DESIGNADOS (2) | R295: 40 | S295: VALOR DA DIÁRIA DE ACORDO COM DECRETO 47.045/2016 (FAIXA 1 - MUNICÍPIO ESPECIAL) | T295: 362 | U295: 1 | V295: =R295*T295*U295 -> 14480 | W295: LIMIAR | X295: REALIZAÇÃO DE VIAGENS PARA COLETA DE DADOS DE INTELIGÊNCIA, PARTICIPAÇÃO NAS AÇÕES DA OPERAÇÃO MAR DE MINAS, EXECUÇÃO DO PROJETO COM VIVER E AÇÕES REFERENTES AO PROJETO ESTRATÉGICO VALE DO LÍTIO | Y295: A COLETA DE DADOS DE INTELIGÊNCIA, A PARTICIPAÇÃO NAS OPERAÇÕES INTEGRADAS E O ACOMPANHAMENTO DOS PROJETOS ESTRATÉGICOS, SÃO ESSENCIAIS PARA A PREVENÇÃO DA CRIMINALIDADE E ALCANCE DOS RESULTADOS PREVISTOS PELA SEJUSP | Z295: O DESLOCAMENTO DE SERVIDORES PARA EXECUSSÃO DAS TAREFAS DESCRITAS TORNA-SE ESSENCIAL PARA O ALCANCE DOS RESULTADOS ESTABELECIDOS PELA SEJUSP | AA295: 0 | AB295: 0 | AC295: 0 | AD295: 0.86749885 | AE295: 0.86749885 | AF295: =AE295*V295 -> 12561.383
A296: SEJUSP | B296: SUINT | D296: NÚCLEO DE INTELIGÊNCIA E CONHECIMENTO ESTRATÉGICO | E296: =CONCATENATE(A296,"PROG") -> SEJUSPPROG | F296: 129 - PREVENÇÃO À CRIMINALIDADE | G296: =CONCATENATE("P",(LEFT(F296,3)),A296) -> P129SEJUSP | H296: 4344 - PREVENÇÃO SOCIAL ÀS VIOLÊNCIAS E CRIMINALIDADES | I296: ELEMENTO | J296: 1401 - DIARIAS - CIVIL | K296: =VLOOKUP(CONCATENATE(A296,LEFT(J296,4)),AGRUPAMENTO!$D$2:$E$6783,2,FALSE) -> Diárias e viagens | L296: 3 - Outras Despesas de Custeio | M296: =CONCATENATE("FONTE",A296) -> FONTESEJUSP | N296: 60 | O296: DIÁRIA PARA ATENDER HOSPEDAGEM E DESLOCAMENTO DE SERVIDOR DESIGNADO | P296: NÃO | Q296: NÚMERO DE DIÁRIAS QUE SERÃO UTILIZADAS DURANTE O ANO (05) X NÚMERO DE SERVIDORES DESIGNADOS (2) | R296: 10 | S296: VALOR DA DIÁRIA DE ACORDO COM DECRETO 47.045/2016 (FAIXA 1 - CAPITAIS) | T296: 470 | U296: 1 | V296: =R296*T296*U296 -> 4700 | W296: LIMIAR | X296: REALIZAÇÃO DE VIAGENS PARA COLETA DE DADOS DE INTELIGÊNCIA, PARTICIPAÇÃO NAS AÇÕES DA OPERAÇÃO MAR DE MINAS, EXECUÇÃO DO PROJETO COM VIVER E AÇÕES REFERENTES AO PROJETO ESTRATÉGICO VALE DO LÍTIO | Y296: A COLETA DE DADOS DE INTELIGÊNCIA, A PARTICIPAÇÃO NAS OPERAÇÕES INTEGRADAS E O ACOMPANHAMENTO DOS PROJETOS ESTRATÉGICOS, SÃO ESSENCIAIS PARA A PREVENÇÃO DA CRIMINALIDADE E ALCANCE DOS RESULTADOS PREVISTOS PELA SEJUSP | Z296: O DESLOCAMENTO DE SERVIDORES PARA EXECUSSÃO DAS TAREFAS DESCRITAS TORNA-SE ESSENCIAL PARA O ALCANCE DOS RESULTADOS ESTABELECIDOS PELA SEJUSP | AA296: 0 | AB296: 0 | AC296: 0 | AD296: 0.86749885 | AE296: 0.86749885 | AF296: =AE296*V296 -> 4077.2446
... A353: SEJUSP | B353: DEPEN | D353: SUPERINTENDÊNCIA DE SEGURANÇA | E353: =CONCATENATE(A353,"PROG") -> SEJUSPPROG | F353: 130 - INFRAESTRUTURA DO SISTEMA PRISIONAL | G353: =CONCATENATE("P",(LEFT(F353,3)),A353) -> P130SEJUSP | H353: 4348 - CUSTÓDIA E RESSOCIALIZAÇÃO DE PRESOS | I353: ELEMENTO | J353: 3304 - PASSAGENS - PESSOA JURIDICA | K353: =VLOOKUP(CONCATENATE(A353,LEFT(J353,4)),AGRUPAMENTO!$D$2:$E$6783,2,FALSE) -> Diárias e viagens | L353: 3 - Outras Despesas de Custeio | M353: =CONCATENATE("FONTE",A353) -> FONTESEJUSP | N353: 60 | O353: PREVISÃO DE PASSAGENS AÉREAS PARA ESCOLTAS DE PRESOS, EXERCÍCIO ANO 2026 | P353: NÃO | Q353: MÉDIA DE PROCESSOS POR MÊS | R353: 4 | S353: PREÇO BASEADO NO HISTÓRICO DAS ÚLTIMAS VIAGENS | T353: 5000 | U353: 12 | V353: =R353*T353*U353 -> 240000 | W353: LIMIAR | X353: CUMPRIMENTO DE DETERMINÇÃO/REQUISIÇÃO JUDICIAL PARA TRANSFERÊNCIAS DE PRESOS E/OU APRESENTAÇÃO EM AUDIÊNCIAS E TRIBUNAL DO JURI | Y353: DESCUMPRIMENTO DE DETERMINAÇÃO JUDICIAL. | Z353: CUMPRIR A DETERMINAÇÃO JUDICIAL, EM CASO DE TRANSFERÊNCIAS NA CONDUÇÃO DE PRESOS PARA OUTROS ESTADOS, DIMINUINDO TAMBÉM OS CUSTOS DO ESTADO DE MINAS GERAIS COM O RESPECTIVO PRESO | AA353: 0 | AB353: 0 | AC353: 0 | AD353: 0.86749885 | AE353: 0.86749885 | AF353: =AE353*V353 -> 208199.72
A354: SEJUSP | B354: SUPOD | D354: Centro de Referência Estadual em Alcool e outras Drogas | E354: =CONCATENATE(A354,"PROG") -> SEJUSPPROG | F354: 141 - POLÍTICAS SOBRE DROGAS | G354: =CONCATENATE("P",(LEFT(F354,3)),A354) -> P141SEJUSP | H354: 4437 - APOIO À REDE COMPLEMENTAR DE SUPORTE SOCIAL NA ATENÇÃO AO DEPENDENTE QUÍMICO | I354: ELEMENTO | J354: 8501 - CONTRATO DE GESTAO COM ORGANIZACAO SOCIAL - OS | K354: =VLOOKUP(CONCATENATE(A354,LEFT(J354,4)),AGRUPAMENTO!$D$2:$E$6783,2,FALSE) -> Termos de parceria e contratos de gestão | L354: 3 - Outras Despesas de Custeio | M354: =CONCATENATE("FONTE",A354) -> FONTESEJUSP | N354: 10 | O354: Aditivo ao Contrato de Gestão com OS, cujo objeto é a descentralização da Política Sobre Drogas, por meio da oferta de atendimento territorializados, além do aprimoramento do monitoramento das parcerias celebradas no âmbito do Programa Rede Complementar de Suporte Social na Atenção ao Dependente Químico (CREAD - Unidade Risp 15/Vale do Lítio) | P354: SIM | Q354: 1 | R354: 1 | S354: Estimativa de custos com preços praticados no mercado | T354: 2473432.3 | U354: 1 | V354: =R354*T354*U354 -> 2473432.3 | W354: INCREMENTAL | X354: Expansão da atuação do Centro de Referência Estadual em Álcool e outras Drogas e, por conseguinte, das ações de atendimento, mobilização social, formação e capacitação, pesquisa, articulação de rede, assessoramento técnico, informação científica e realização de oficinas de prevenção, para a efetivação das metas e indicadores de segurança pública, pactuadas no Planejamento Estratégico da Sejusp, que envolvem o uso de álcool e outras drogas, visando a descentralização e expansão da Política Estadual sobre Drogas | Y354: Os impactos decorrentes do uso de álcool e outras drogas configuram uma das questões mais complexas e relevantes da contemporaneidade. Um problema de saúde pública com reflexos na educação, na justiça, na segurança pública e nos altos índices de mortalidade. Diante desse contexto, oferecer e buscar soluções para responder a essa demanda exponencial, é uma das atribuições da Supod, que deve estar cotidianamente buscando soluções para facilitar a execução e fortalecer a Política Pública. | Z354: Com a descentralização do Cread, é possível ofertar atendimento qualificado, diretamente na base terriotial identificada como de maior vulnerabilidade criminal e social para o uso/abuso de drogas. Assim como o aprimoramento das articulações entre as redes locais de proteção, promoção social e de justiça e segurança pública. Além disso, o trabalho da equipe prevista no contrato de gestão é fundamental para o monitoramento das instituições parceiras, considerando a expansão da Rede Complementar. As ações executadas por meio do contrato de gestão são congruentes com o Plano Mineiro de Desenvolvimento Integrado (PMDI) 2019-2030. | AA354: 1 | AB354: 1 | AC354: 5 | AD354: 0 | AE354: 0 | AF354: =AE354*V354 -> 0
A355: SEJUSP | B355: SUPOD | D355: Centro de Referência Estadual em Alcool e outras Drogas | E355: =CONCATENATE(A355,"PROG") -> SEJUSPPROG | F355: 141 - POLÍTICAS SOBRE DROGAS | G355: =CONCATENATE("P",(LEFT(F355,3)),A355) -> P141SEJUSP | H355: 4437 - APOIO À REDE COMPLEMENTAR DE SUPORTE SOCIAL NA ATENÇÃO AO DEPENDENTE QUÍMICO | I355: ELEMENTO | J355: 8501 - CONTRATO DE GESTAO COM ORGANIZACAO SOCIAL - OS | K355: =VLOOKUP(CONCATENATE(A355,LEFT(J355,4)),AGRUPAMENTO!$D$2:$E$6783,2,FALSE) -> Termos de parceria e contratos de gestão | L355: 3 - Outras Despesas de Custeio | M355: =CONCATENATE("FONTE",A355) -> FONTESEJUSP | N355: 10 | O355: Aditivo ao Contrato de Gestão com OS, cujo objeto é a descentralização da Política Sobre Drogas, por meio da oferta de atendimento territorializados, além do aprimoramento do monitoramento das parcerias celebradas no âmbito do Programa Rede Complementar de Suporte Social na Atenção ao Dependente Químico (CREAD - Unidade Vale do Aço) | P355: SIM | Q355: 1 | R355: 1 | S355: Estimativa de custos com preços praticados no mercado | T355: 2473432.3 | U355: 1 | V355: =R355*T355*U355 -> 2473432.3 | W355: INCREMENTAL | X355: Expansão da atuação do Centro de Referência Estadual em Álcool e outras Drogas e, por conseguinte, das ações de atendimento, mobilização social, formação e capacitação, pesquisa, articulação de rede, assessoramento técnico, informação científica e realização de oficinas de prevenção, para a efetivação das metas e indicadores de segurança pública, pactuadas no Planejamento Estratégico da Sejusp, que envolvem o uso de álcool e outras drogas, visando a descentralização e expansão da Política Estadual sobre Drogas | Y355: Os impactos decorrentes do uso de álcool e outras drogas configuram uma das questões mais complexas e relevantes da contemporaneidade. Um problema de saúde pública com reflexos na educação, na justiça, na segurança pública e nos altos índices de mortalidade. Diante desse contexto, oferecer e buscar soluções para responder a essa demanda exponencial, é uma das atribuições da Supod, que deve estar cotidianamente buscando soluções para facilitar a execução e fortalecer a Política Pública. | Z355: Com a descentralização do Cread, é possível ofertar atendimento qualificado, diretamente na base terriotial identificada como de maior vulnerabilidade criminal e social para o uso/abuso de drogas. Assim como o aprimoramento das articulações entre as redes locais de proteção, promoção social e de justiça e segurança pública. Além disso, o trabalho da equipe prevista no contrato de gestão é fundamental para o monitoramento das instituições parceiras, considerando a expansão da Rede Complementar. As ações executadas por meio do contrato de gestão são congruentes com o Plano Mineiro de Desenvolvimento Integrado (PMDI) 2019-2030. | AA355: 1 | AB355: 1 | AC355: 5 | AD355: 0 | AE355: 0 | AF355: =AE355*V355 -> 0
A356: SEJUSP | B356: DEPEN | D356: SUPERINTENDÊNCIA DE SEGURANÇA | E356: =CONCATENATE(A356,"PROG") -> SEJUSPPROG | F356: 130 - INFRAESTRUTURA DO SISTEMA PRISIONAL | G356: =CONCATENATE("P",(LEFT(F356,3)),A356) -> P130SEJUSP | H356: 1048 - MODERNIZAÇÃO E EXPANSÃO DO SISTEMA PRISIONAL | I356: ELEMENTO | J356: 5217 - VEICULOS | K356: =VLOOKUP(CONCATENATE(A356,LEFT(J356,4)),AGRUPAMENTO!$D$2:$E$6783,2,FALSE) -> Demais despesas de capital | L356: 4 - Investimento | M356: =CONCATENATE("FONTE",A356) -> FONTESEJUSP | N356: 10 | O356: PREVISAÕ DE AQUISIÇÃO DE VEÍCULOS CELA/ VAN BIPARTIDA PARA ESCOLTAS DE PRESOS, EXERCÍCIO ANO 2026 | P356: NÃO | Q356: VALOR MÉDIO UNITÁRIO | R356: 49 | S356: VALOR MÉDIO UNITÁRIO | T356: 440000 | U356: 1 | V356: =R356*T356*U356 -> 21560000 | W356: INCREMENTAL | X356: AQUISIÇÃO DE VEÍCULO | Y356: PODE COMPROMENTER DIRETAMENTE A SEGURANÇA, A LEGALIDADE E A EFICIÊNCIA NO CUMPRIMENTO DE AGENDAS JUDICIAIS, IMPACTO EM ATENDIMENTO MÉDICO , ENTRE OUTROS | Z356: ASSEGURAR O CUMPRIMENTO REGULAR DE ORDENS JUDICIAIS, GARANTE A INTEGRIDADE FÍSICA DE SERVIDORES E CUSTODIADOS, REDUZ RISCOS DE EVASÃOES E RESGATES. | AA356: 1 | AB356: 1 | AC356: 6 | AD356: 0 | AE356: 0 | AF356: =AE356*V356 -> 0
A357: SEJUSP | B357: SULOT | D357: SIEL - Superintendência de Infraestrutura e Logística | E357: =CONCATENATE(A357,"PROG") -> SEJUSPPROG | F357: 130 - INFRAESTRUTURA DO SISTEMA PRISIONAL | G357: =CONCATENATE("P",(LEFT(F357,3)),A357) -> P130SEJUSP | H357: 4348 - CUSTÓDIA E RESSOCIALIZAÇÃO DE PRESOS | I357: ELEMENTO | J357: 3025 - MATERIAL DE SEGURANÇA, APETRECHOS OPERACIONAIS E POLICIAIS | K357: =VLOOKUP(CONCATENATE(A357,LEFT(J357,4)),AGRUPAMENTO!$D$2:$E$6783,2,FALSE) -> Material de consumo | L357: 3 - Outras Despesas de Custeio | M357: =CONCATENATE("FONTE",A357) -> FONTESEJUSP | N357: 60 | O357: ALGEMA DE PUNHO DE TORNOZELO | P357: NÃO | Q357: NÚMERO DE MATERIAIS X NÚMERO DE PRESOS | R357: 4550 | S357: PESQUISA DE MERCADO | T357: 206.35 | U357: 1 | V357: =R357*T357*U357 -> 938892.5 | W357: INCREMENTAL | X357: AQUISIÇÃO DE MATERIAIS DE SEGURANÇA, ITEM EM DEFICIT NO ESTOQUE UTIMA COMPRA EM 2023 | Y357: A FALTA DOS ITENS PODE OCASIONAR RISCOS À SEGURANÇA AOS SERVIDORES | Z357: MELHORIA NA SEGURANÇA DAS UNIDADES E DOS SERVIDORES | AA357: 2 | AB357: 2 | AC357: 7 | AD357: 0 | AE357: 0 | AF357: =AE357*V357 -> 0
A358: SEJUSP | B358: DEPEN | D358: SUPERINTENDÊNCIA DE GESTÃO DE VAGAS | E358: =CONCATENATE(A358,"PROG") -> SEJUSPPROG | F358: 130 - INFRAESTRUTURA DO SISTEMA PRISIONAL | G358: =CONCATENATE("P",(LEFT(F358,3)),A358) -> P130SEJUSP | H358: 4350 - MANUTENÇÃO E AMPLIAÇÃO DO MONITORAMENTO ELETRÔNICO | I358: ELEMENTO | J358: 3971 - SERVIÇOS TECNICOS DE IMPLANTAÇÃO, GESTÃO E ADMINISTRAÇÃO DE SISTEMAS DE VIGILÂNCIA DE OBSERVAÇÃO | K358: =VLOOKUP(CONCATENATE(A358,LEFT(J358,4)),AGRUPAMENTO!$D$2:$E$6783,2,FALSE) -> Serviços de vigilância | L358: 3 - Outras Despesas de Custeio | M358: =CONCATENATE("FONTE",A358) -> FONTESEJUSP | N358: 60 | O358: Tornozeleiras | P358: NÃO | Q358: Quantitativo mensal de diárias referente a gestão e administração do programa de monitoração de condenados por meio de tornozeleira eletrônica, cuho contrato contempla atualmente 12.933 unidades. | R358: 10412 | S358: Custo médio mensal por tornozeleira (R$7,47 por dia x 30 dias do mês); A frequência do pagamento é mensal | T358: 224.1 | U358: 12 | V358: =R358*T358*U358 -> 27999950 | W358: LIMIAR | X358: Tornozeleira | Y358: Não ampliação de medidas alternativas a custódia, não cumprimento de decisões judiciais. | Z358: Permite o Estado de Minas Gerais cumprir decisões judiciais que determinam medidas alternativas para cumprimento de penas restritivas de liberdade, objetivando a aplicação normativa e ampliação do atendimento, bem como a promoção de humanização e consequente melhoria dos índices de ressocialização, ações alinhadas à redução dos custos para a administração pública | AA358: 0 | AB358: 0 | AC358: 0 | AD358: 0.91951401 | AE358: 0.91951401 | AF358: =AE358*V358 -> 25746347
A359: SEJUSP | B359: DEPEN | D359: SUPERINTENDÊNCIA DE GESTÃO DE VAGAS | E359: =CONCATENATE(A359,"PROG") -> SEJUSPPROG | F359: 130 - INFRAESTRUTURA DO SISTEMA PRISIONAL | G359: =CONCATENATE("P",(LEFT(F359,3)),A359) -> P130SEJUSP | H359: 4351 - MANUTENÇÃO E IMPLANTAÇÃO DE METODOLOGIA DE CUSTÓDIAS ALTERNATIVAS | I359: ELEMENTO | J359: 4301 - SUBVENCOES SOCIAIS | K359: =VLOOKUP(CONCATENATE(A359,LEFT(J359,4)),AGRUPAMENTO!$D$2:$E$6783,2,FALSE) -> SUBVENÇÕES SOCIAIS | L359: 3 - Outras Despesas de Custeio | M359: =CONCATENATE("FONTE",A359) -> FONTESEJUSP | N359: 60 | O359: APAC ALFENAS APAC DE ALMENARA APAC ARAXÁ APAC ARCOS APAC BELO HORIZONTE APAC BETIM APAC CAMPO BELO APAC CARATINGA APAC CONCEIÇÃO DAS ALAGOAS APAC CONS. LAFAIETE – FEM. APAC CONS. LAFAIETE – MASC. APAC DIVINOPOLIS APAC FRUTAL - FEM. APAC FRUTAL - MASC. APAC GUANHÃES APAC GOV. VALADARES - FEM. APAC INHAPIM APAC ITABIRA APAC ITABIRITO APAC ITAÚNA – FEM. APAC ITAÚNA – MASC. APAC ITUIUTABA APAC JAÍBA APAC JANAÚBA APAC JANUÁRIA APAC LAGOA DA PRATA APAC MANHUAÇU APAC MANHUMIRIM APAC NEPOMUCENO APAC NOVA LIMA APAC PARACATU APAC PASSOS APAC PATOS DE MINAS APAC PATROCÍNIO APAC PEDRA AZUL APAC PERDÕES APAC PIRAPORA APAC POUSO ALEGRE – FEM. APAC POUSO ALEGRE – MASC. APAC RIO PIRACICABA – FEM. APAC SALINAS APAC SANTA BÁRBARA APAC SANTA LUZIA APAC SANTA MARIA SUAÇUÍ APAC SÃO JOÃO DEL REI - FEM. APAC SÃO JOÃO DEL REI - MASC. APAC SETE LAGOAS APAC TEÓFILO OTONI APAC VARGINHA APAC VISCONDE DO RIO BRANCO APAC VIÇOSA FBAC | P359: NÃO | Q359: * Dar continuidade ao auxílio financeiro as unidades com termo de colaboração firmado com o Estado. **Quantitativa de vagas disponibilizada atualmente, 5.827 (cinco mil oitocentos e vinte e sete) vagas. ***Nesta estimativa de vagas, o cálculo foi realizado com base no custo médio mensal por recuperando de R$ 1.694,60 (um mil seiscentos e noventa e quatro reais e sessenta centavos). Cálculo custo médio é realizado com o valor previsto no orçamento dividido pelo número de vagas, dividido por 12 meses. ****O Orçamento aprovado para o exercício 2025 foi utilizado como base de cálculo para os valores ora apresentados. | R359: 5827 | S359: Custo médio mensal por recuperando de R$ 1.694,60 (um mil seiscentos e noventa e quatro reais e sessenta centavos)). Repasses trimestrais e quadrimestrais para as APACs | T359: 1694.6004 | U359: 12 | V359: =R359*T359*U359 -> 1.1849324e+08 | W359: LIMIAR | X359: Estabelecer bases de cooperação financeira (subvenção social) entre a SEJUSP - Secretaria de Estado de Justiça e Segurança Pública e as Associações de Proteção e Assistência aos Condenados, visando o atendimento das necessidades dos recuperandos assistidos pelas APACs, garantindo assim, um auxílio financeiro ao custeio da unidade conveniada, dentro de condições satisfatórias, bem como a valorização e dignificação do ser humano, com ênfase nos aspectos morais e espirituais que poderão afastá-los e tirá-los do mundo do crime. - 50 APACs e FBAC mantidas (atualmente); | Y359: NÃO ATENDIMENTO DA PRIORIZAÇÃO DO GOVERNADOR, AUMENTO DA REINCIDÊNCIA DOS RECUPERANDOS; Inviabilizar o cumprimento da Lei de Execução Penal (LEI Nº 7.210, DE 11 DE JULHO DE 1984.); Desarticular os mecanimos de gerenciamento e controle de vagas; Inviabilizar a atuação do poder Judiciário na atividade Criminal. | Z359: ALINHAMENTO COM AS DIRETRIZES DO GOVERNADOR, RESSOCIALIZAÇÃO DOS RECUPERANDOS, CUSTO BENEFÍCIO MAIOR COM RECUPERANDOS NAS APACS do que com a criação de novas vagas no Sistema prisional comum; Viabilizar o cumprimento da Lei de Execução Penal (LEI Nº 7.210, DE 11 DE JULHO DE 1984.); Redução da população carcerária; Viabilizar atuação do poder Judiciário na atividade Criminal. Obter maior eficiência em relação às execuções penais, maximizando a recuperação dos condenados. | AA359: 0 | AB359: 0 | AC359: 0 | AD359: 0.97618155 | AE359: 0.97618155 | AF359: =AE359*V359 -> 1.1567091e+08
A360: SEJUSP | B360: DEPEN | D360: SUPERINTENDÊNCIA DE GESTÃO DE VAGAS | E360: =CONCATENATE(A360,"PROG") -> SEJUSPPROG | F360: 130 - INFRAESTRUTURA DO SISTEMA PRISIONAL | G360: =CONCATENATE("P",(LEFT(F360,3)),A360) -> P130SEJUSP | H360: 4351 - MANUTENÇÃO E IMPLANTAÇÃO DE METODOLOGIA DE CUSTÓDIAS ALTERNATIVAS | I360: ELEMENTO | J360: 4301 - SUBVENCOES SOCIAIS | K360: =VLOOKUP(CONCATENATE(A360,LEFT(J360,4)),AGRUPAMENTO!$D$2:$E$6783,2,FALSE) -> SUBVENÇÕES SOCIAIS | L360: 3 - Outras Despesas de Custeio | M360: =CONCATENATE("FONTE",A360) -> FONTESEJUSP | N360: 60 | O360: CCT | P360: NÃO | Q360: O Valores dos termos de colaboração firmados entre Estado , APACs e FBAC, no que se refere as rubrícas de despesas com pessoal, quando são corrigidos utilizamos a CCT - Convenção Coletiva do Trabalho, conforme estabelece o decreto 47.132/2017. Seguindo orientação da SPOF, o valor base para cálculo foi considerado a média dos últimos três anos, desta forma o percentual estimado para cálculo foi 6,24%. | R360: 0.0624 | S360: Aplicado em correção ao valor global, CONSIDERANDO APENAS A DESPESA COM PESSOAL uma vez ao ano. | T360: 61616483 | U360: 1 | V360: =R360*T360*U360 -> 3844868.6 | W360: LIMIAR | X360: Ajuste categoria. | Y360: NÃO ATENDIMENTO DA PRIORIZAÇÃO DO GOVERNADOR, AUMENTO DA REINCIDÊNCIA DOS RECUPERANDOS; Inviabilizar o cumprimento da Lei de Execução Penal (LEI Nº 7.210, DE 11 DE JULHO DE 1984.); Desarticular os mecanimos de gerenciamento e controle de vagas; Inviabilizar a atuação do poder Judiciário na atividade Criminal. | Z360: ALINHAMENTO COM AS DIRETRIZES DO GOVERNADOR, RESSOCIALIZAÇÃO DOS RECUPERANDOS, CUSTO BENEFÍCIO MAIOR COM RECUPERANDOS NAS APACS do que com a criação de novas vagas no Sistema prisional comum; Viabilizar o cumprimento da Lei de Execução Penal (LEI Nº 7.210, DE 11 DE JULHO DE 1984.); Redução da população carcerária; Viabilizar atuação do poder Judiciário na atividade Criminal. Obter maior eficiência em relação às execuções penais, maximizando a recuperação dos condenados. | AA360: 0 | AB360: 0 | AC360: 0 | AD360: 0.97618155 | AE360: 0.97618155 | AF360: =AE360*V360 -> 3753289.8
A361: SEJUSP | B361: DEPEN | D361: SUPERINTENDÊNCIA DE GESTÃO DE VAGAS | E361: =CONCATENATE(A361,"PROG") -> SEJUSPPROG | F361: 130 - INFRAESTRUTURA DO SISTEMA PRISIONAL | G361: =CONCATENATE("P",(LEFT(F361,3)),A361) -> P130SEJUSP | H361: 4351 - MANUTENÇÃO E IMPLANTAÇÃO DE METODOLOGIA DE CUSTÓDIAS ALTERNATIVAS | I361: ELEMENTO | J361: 4301 - SUBVENCOES SOCIAIS | K361: =VLOOKUP(CONCATENATE(A361,LEFT(J361,4)),AGRUPAMENTO!$D$2:$E$6783,2,FALSE) -> SUBVENÇÕES SOCIAIS | L361: 3 - Outras Despesas de Custeio | M361: =CONCATENATE("FONTE",A361) -> FONTESEJUSP | N361: 60 | O361: IPCA | P361: NÃO | Q361: O Valores dos termos de colaboração firmados entre Estado, APACs e FBAC, no que se refere as rubrícas de custeio, quando são corrigidos utilizamos o indíce do IPCA - Índice Nacional de Preços ao Consumidor Amplo, conforme estabelece o decreto 47.132/2017. Seguindo orientação da SPOF, o valor base para cálculo foi considerado a média dos últimos três anos, desta forma o percentual estimado para cálculo foi 4,71%. | R361: 0.0471 | S361: Aplicado em correção ao valor global, PARA CUSTEIO DAS RUBRICAS uma vez ao ano. | T361: 56876754 | U361: 1 | V361: =R361*T361*U361 -> 2678895.1 | W361: LIMIAR | X361: Ajuste inflação. | Y361: NÃO ATENDIMENTO DA PRIORIZAÇÃO DO GOVERNADOR, AUMENTO DA REINCIDÊNCIA DOS RECUPERANDOS; Inviabilizar o cumprimento da Lei de Execução Penal (LEI Nº 7.210, DE 11 DE JULHO DE 1984.); Desarticular os mecanimos de gerenciamento e controle de vagas; Inviabilizar a atuação do poder Judiciário na atividade Criminal. | Z361: ALINHAMENTO COM AS DIRETRIZES DO GOVERNADOR, RESSOCIALIZAÇÃO DOS RECUPERANDOS, CUSTO BENEFÍCIO MAIOR COM RECUPERANDOS NAS APACS do que com a criação de novas vagas no Sistema prisional comum; Viabilizar o cumprimento da Lei de Execução Penal (LEI Nº 7.210, DE 11 DE JULHO DE 1984.); Redução da população carcerária; Viabilizar atuação do poder Judiciário na atividade Criminal. Obter maior eficiência em relação às execuções penais, maximizando a recuperação dos condenados. | AA361: 0 | AB361: 0 | AC361: 0 | AD361: 0.97618155 | AE361: 0.97618155 | AF361: =AE361*V361 -> 2615088
A362: SEJUSP | B362: SUASE | D362: SGES - Superintendência de Gestão Socioeducativa | E362: =CONCATENATE(A362,"PROG") -> SEJUSPPROG | F362: 146 - PROMOÇÃO DA POLÍTICA SOCIOEDUCATIVA PARA ATENDIMENTO AOS ADOLESCENTES EM CONFLITO COM A LEI | G362: =CONCATENATE("P",(LEFT(F362,3)),A362) -> P146SEJUSP | H362: 4441 - ADEQUAÇÃO, MANUTENÇÃO E DESENVOLVIMENTO DO ATENDIMENTO SOCIOEDUCATIVO | I362: ELEMENTO | J362: 5299 - OUTROS MATERIAIS PERMANENTES | K362: =VLOOKUP(CONCATENATE(A362,LEFT(J362,4)),AGRUPAMENTO!$D$2:$E$6783,2,FALSE) -> Demais despesas de capital | L362: 4 - Investimento | M362: =CONCATENATE("FONTE",A362) -> FONTESEJUSP | N362: 10 | O362: Instalação de paineis solares e boiler no Centro Socioeducativo de Governador Valadares | P362: SIM | Q362: Unidade | R362: 1 | S362: Valores estimados conforme pesquisa de mercado | T362: 260000 | U362: 1 | V362: =R362*T362*U362 -> 260000 | W362: INCREMENTAL | X362: A unidade não possui sistema de aquecimento de água, ocasionando prejuizos à qualidade de custódia dos adolescentes que não possuem água aquecida para o banho. | Y362: Descumprimento do SINASE e não garantia dos direitos básicos dos adolescentes. | Z362: Garantia dos direitos dos adolescentes com o fornecimento de água aquecida para o banho. | AA362: 2 | AB362: 2 | AC362: 8 | AD362: 0 | AE362: 0 | AF362: =AE362*V362 -> 0
A363: SEJUSP | B363: SUASE | D363: SGES - Superintendência de Gestão Socioeducativa | E363: =CONCATENATE(A363,"PROG") -> SEJUSPPROG | F363: 146 - PROMOÇÃO DA POLÍTICA SOCIOEDUCATIVA PARA ATENDIMENTO AOS ADOLESCENTES EM CONFLITO COM A LEI | G363: =CONCATENATE("P",(LEFT(F363,3)),A363) -> P146SEJUSP | H363: 4441 - ADEQUAÇÃO, MANUTENÇÃO E DESENVOLVIMENTO DO ATENDIMENTO SOCIOEDUCATIVO | I363: ELEMENTO | J363: 5299 - OUTROS MATERIAIS PERMANENTES | K363: =VLOOKUP(CONCATENATE(A363,LEFT(J363,4)),AGRUPAMENTO!$D$2:$E$6783,2,FALSE) -> Demais despesas de capital | L363: 4 - Investimento | M363: =CONCATENATE("FONTE",A363) -> FONTESEJUSP | N363: 10 | O363: Instalação de paineis solares e boiler no Centro Socioeducativo de Montes Claros | P363: SIM | Q363: Unidade | R363: 1 | S363: Valores estimados conforme pesquisa de mercado | T363: 260000 | U363: 1 | V363: =R363*T363*U363 -> 260000 | W363: INCREMENTAL | X363: A unidade não possui sistema de aquecimento de água, ocasionando prejuizos à qualidade de custódia dos adolescentes que não possuem água aquecida para o banho. | Y363: Descumprimento do SINASE e não garantia dos direitos básicos dos adolescentes. | Z363: Garantia dos direitos dos adolescentes com o fornecimento de água aquecida para o banho. | AA363: 2 | AB363: 2 | AC363: 8 | AD363: 0 | AE363: 0 | AF363: =AE363*V363 -> 0
A364: SEJUSP | B364: DEPEN | D364: SUPERINTENDÊNCIA DE INFORMAÇÃO E INTELIGÊNCIA | E364: =CONCATENATE(A364,"PROG") -> SEJUSPPROG | F364: 130 - INFRAESTRUTURA DO SISTEMA PRISIONAL | G364: =CONCATENATE("P",(LEFT(F364,3)),A364) -> P130SEJUSP | H364: 4348 - CUSTÓDIA E RESSOCIALIZAÇÃO DE PRESOS | I364: ELEMENTO | J364: 3612 - DESPESAS MIUDAS DE PRONTO PAGAMENTO | K364: =VLOOKUP(CONCATENATE(A364,LEFT(J364,4)),AGRUPAMENTO!$D$2:$E$6783,2,FALSE) -> Pronto Pagamento | L364: 3 - Outras Despesas de Custeio | M364: =CONCATENATE("FONTE",A364) -> FONTESEJUSP | N364: 60 | O364: Material de consumo para manutenção da Superintendência de Informação e Inteligência | P364: NÃO | Q364: NÚMERO MÉDIO DE LIBERAÇÕES MENSAIS | R364: 1 | S364: VALOR POR UNIDADE PRISIONAL AUTORIZADO PELA SEPLAG | T364: 3000 | U364: 12 | V364: =R364*T364*U364 -> 36000 | W364: LIMIAR | X364: Manutenções e reparos emergenciais na Superintendência | Y364: Diversos - escassez de insumos essenciais para manutenção estrutural e aquisições complementares necessárias ao desempenho dos trabalhos. | Z364: Manutenção da ordem pública. Cumprimento do disposto no item 5 do Decreto nº 8.793 de 29 de junho de 2016. | AA364: 0 | AB364: 0 | AC364: 0 | AD364: 1 | AE364: 1 | AF364: =AE364*V364 -> 36000
A365: SEJUSP | B365: DEPEN | D365: SUPERINTENDÊNCIA DE INFORMAÇÃO E INTELIGÊNCIA | E365: =CONCATENATE(A365,"PROG") -> SEJUSPPROG | F365: 130 - INFRAESTRUTURA DO SISTEMA PRISIONAL | G365: =CONCATENATE("P",(LEFT(F365,3)),A365) -> P130SEJUSP | H365: 1048 - MODERNIZAÇÃO E EXPANSÃO DO SISTEMA PRISIONAL | I365: ELEMENTO | J365: 4006 - AQUISIÇÃO DE SOFTWARE | K365: =VLOOKUP(CONCATENATE(A365,LEFT(J365,4)),AGRUPAMENTO!$D$2:$E$6783,2,FALSE) -> Aquisições de itens de TIC | L365: 4 - Investimento | M365: =CONCATENATE("FONTE",A365) -> FONTESEJUSP | N365: 60 | O365: Licença dE Software que realiza análise de vínculos e formula organogramas | P365: NÃO | Q365: CONTRATAÇÃO ANUAL | R365: 1 | S365: VALOR DA ÚLTIMA CONTRATAÇÃO REALIZADA | T365: 70000 | U365: 1 | V365: =R365*T365*U365 -> 70000 | W365: LIMIAR | X365: Manutenção de contrato de Licença de Software I2 | Y365: Redução da qualidade do trabalho já prestado, comprometimento da eficiência das atividades, descumpimento do Decreto nº 8.793 de 29 de junho de 2016 | Z365: Manutenção da ordem pública, cumprimento do disposto no item 5 do Decreto nº 8.793 de 29 de junho de 2016, bem como o recomendado na Doutrina Nacional de Inteligência Penitenciária, ampliação da capacidade técnica da atividade de inteligência penal e aumento dos índices de recaptura de indivíduos foragidos do Sistema Prisional Mineiro. | AA365: 0 | AB365: 0 | AC365: 0 | AD365: 0.23752316 | AE365: 0.23752316 | AF365: =AE365*V365 -> 16626.622
A366: SEJUSP | B366: SUASE | D366: SGES - Superintendência de Gestão Socioeducativa | E366: =CONCATENATE(A366,"PROG") -> SEJUSPPROG | F366: 146 - PROMOÇÃO DA POLÍTICA SOCIOEDUCATIVA PARA ATENDIMENTO AOS ADOLESCENTES EM CONFLITO COM A LEI | G366: =CONCATENATE("P",(LEFT(F366,3)),A366) -> P146SEJUSP | H366: 4441 - ADEQUAÇÃO, MANUTENÇÃO E DESENVOLVIMENTO DO ATENDIMENTO SOCIOEDUCATIVO | I366: ELEMENTO | J366: 5299 - OUTROS MATERIAIS PERMANENTES | K366: =VLOOKUP(CONCATENATE(A366,LEFT(J366,4)),AGRUPAMENTO!$D$2:$E$6783,2,FALSE) -> Demais despesas de capital | L366: 4 - Investimento | M366: =CONCATENATE("FONTE",A366) -> FONTESEJUSP | N366: 10 | O366: Instalação de paineis solares e boiler no Centro Socioeducativo de Uberlândia | P366: SIM | Q366: Unidade | R366: 1 | S366: Valores estimados conforme pesquisa de mercado | T366: 260000 | U366: 1 | V366: =R366*T366*U366 -> 260000 | W366: INCREMENTAL | X366: A unidade não possui sistema de aquecimento de água, ocasionando prejuizos à qualidade de custódia dos adolescentes que não possuem água aquecida para o banho. | Y366: Descumprimento do SINASE e não garantia dos direitos básicos dos adolescentes. | Z366: Garantia dos direitos dos adolescentes com o fornecimento de água aquecida para o banho. | AA366: 2 | AB366: 2 | AC366: 8 | AD366: 0 | AE366: 0 | AF366: =AE366*V366 -> 0
A367: SEJUSP | B367: SUASE | D367: SGES - Superintendência de Gestão Socioeducativa | E367: =CONCATENATE(A367,"PROG") -> SEJUSPPROG | F367: 146 - PROMOÇÃO DA POLÍTICA SOCIOEDUCATIVA PARA ATENDIMENTO AOS ADOLESCENTES EM CONFLITO COM A LEI | G367: =CONCATENATE("P",(LEFT(F367,3)),A367) -> P146SEJUSP | H367: 4441 - ADEQUAÇÃO, MANUTENÇÃO E DESENVOLVIMENTO DO ATENDIMENTO SOCIOEDUCATIVO | I367: ELEMENTO | J367: 5299 - OUTROS MATERIAIS PERMANENTES | K367: =VLOOKUP(CONCATENATE(A367,LEFT(J367,4)),AGRUPAMENTO!$D$2:$E$6783,2,FALSE) -> Demais despesas de capital | L367: 4 - Investimento | M367: =CONCATENATE("FONTE",A367) -> FONTESEJUSP | N367: 10 | O367: Instalação de paineis solares e boiler no Centro Socioeducativo de Teófilo Otoni | P367: SIM | Q367: Unidade | R367: 1 | S367: Valores estimados conforme pesquisa de mercado | T367: 260000 | U367: 1 | V367: =R367*T367*U367 -> 260000 | W367: INCREMENTAL | X367: A unidade não possui sistema de aquecimento de água, ocasionando prejuizos à qualidade de custódia dos adolescentes que não possuem água aquecida para o banho. | Y367: Descumprimento do SINASE e não garantia dos direitos básicos dos adolescentes. | Z367: Garantia dos direitos dos adolescentes com o fornecimento de água aquecida para o banho. | AA367: 2 | AB367: 2 | AC367: 8 | AD367: 0 | AE367: 0 | AF367: =AE367*V367 -> 0
... A499: SEJUSP | B499: DEPEN | D499: Superintendência de Humanização do Atendimento - SHUA | E499: =CONCATENATE(A499,"PROG") -> SEJUSPPROG | F499: 130 - INFRAESTRUTURA DO SISTEMA PRISIONAL | G499: =CONCATENATE("P",(LEFT(F499,3)),A499) -> P130SEJUSP | H499: 4353 - UNIDADES DE SAÚDE DO SISTEMA PRISIONAL | I499: ELEMENTO | J499: 5211 - INSTRUMENTOS DE LABORATORIO, MEDICOS E ODONTOLOGICOS | K499: =VLOOKUP(CONCATENATE(A499,LEFT(J499,4)),AGRUPAMENTO!$D$2:$E$6783,2,FALSE) -> Serviços de saúde e medicamentos | L499: 4 - Investimento | M499: =CONCATENATE("FONTE",A499) -> FONTESEJUSP | N499: 10 | O499: Sindesmótomo, uso odontológico nº 02 | P499: NÃO | Q499: Unidade | R499: 153 | S499: Pesquisa em site de busca - Internet | T499: 17 | U499: 1 | V499: =R499*T499*U499 -> 2601 | W499: LIMIAR | X499: Proporcionar condições de trabalho aos profissionais de saúde (médicos, enfermeiros, odontólogos e etc), através da utilização de instrumentais nos procedimentos invasivos ou não | Y499: Não execução dos procedimentos; Redução no número de atendimentos aos IPLs; Encaminhamento para atendimento externos; Aumento no número de escoltas | Z499: Melhores condições de trabalho aos servidores que ali laboram; Humanização do atendimento aos IPLs; Redução de encaminhamentos externos de saúde; Redução do número de internações hospitalares; Redução de agravos para outros níveis de complexidade (secundária e terciária) | AA499: 0 | AB499: 0 | AC499: 0 | AD499: 1 | AE499: 1 | AF499: =AE499*V499 -> 2601
A500: SEJUSP | B500: DEPEN | D500: Superintendência de Humanização do Atendimento - SHUA | E500: =CONCATENATE(A500,"PROG") -> SEJUSPPROG | F500: 130 - INFRAESTRUTURA DO SISTEMA PRISIONAL | G500: =CONCATENATE("P",(LEFT(F500,3)),A500) -> P130SEJUSP | H500: 4353 - UNIDADES DE SAÚDE DO SISTEMA PRISIONAL | I500: ELEMENTO | J500: 5211 - INSTRUMENTOS DE LABORATORIO, MEDICOS E ODONTOLOGICOS | K500: =VLOOKUP(CONCATENATE(A500,LEFT(J500,4)),AGRUPAMENTO!$D$2:$E$6783,2,FALSE) -> Serviços de saúde e medicamentos | L500: 4 - Investimento | N500: 10 | O500: Sonda exploradora, aço inox nº 5 cilíndrica | P500: NÃO | Q500: Unidade | R500: 173 | S500: Pesquisa em site de busca - Internet | T500: 23 | U500: 1 | V500: =R500*T500*U500 -> 3979 | W500: LIMIAR | X500: Proporcionar condições de trabalho aos profissionais de saúde (médicos, enfermeiros, odontólogos e etc), através da utilização de instrumentais nos procedimentos invasivos ou não | Y500: Não execução dos procedimentos; Redução no número de atendimentos aos IPLs; Encaminhamento para atendimento externos; Aumento no número de escoltas | Z500: Melhores condições de trabalho aos servidores que ali laboram; Humanização do atendimento aos IPLs; Redução de encaminhamentos externos de saúde; Redução do número de internações hospitalares; Redução de agravos para outros níveis de complexidade (secundária e terciária) | AA500: 0 | AB500: 0 | AC500: 0 | AD500: 1 | AE500: 1 | AF500: =AE500*V500 -> 3979
A501: SEJUSP | B501: DEPEN | D501: Superintendência de Humanização do Atendimento - SHUA | E501: =CONCATENATE(A501,"PROG") -> SEJUSPPROG | F501: 130 - INFRAESTRUTURA DO SISTEMA PRISIONAL | G501: =CONCATENATE("P",(LEFT(F501,3)),A501) -> P130SEJUSP | H501: 4353 - UNIDADES DE SAÚDE DO SISTEMA PRISIONAL | I501: ELEMENTO | J501: 5211 - INSTRUMENTOS DE LABORATORIO, MEDICOS E ODONTOLOGICOS | K501: =VLOOKUP(CONCATENATE(A501,LEFT(J501,4)),AGRUPAMENTO!$D$2:$E$6783,2,FALSE) -> Serviços de saúde e medicamentos | L501: 4 - Investimento | N501: 10 | O501: Tambor Inox 16x 14 cm | P501: NÃO | Q501: Unidade | R501: 65 | S501: Pesquisa em site de busca - Internet | T501: 219.58 | U501: 1 | V501: =R501*T501*U501 -> 14272.7 | W501: LIMIAR | X501: Proporcionar condições de trabalho aos profissionais de saúde (médicos, enfermeiros, odontólogos e etc), através da utilização de instrumentais nos procedimentos invasivos ou não | Y501: Não execução dos procedimentos; Redução no número de atendimentos aos IPLs; Encaminhamento para atendimento externos; Aumento no número de escoltas | Z501: Melhores condições de trabalho aos servidores que ali laboram; Humanização do atendimento aos IPLs; Redução de encaminhamentos externos de saúde; Redução do número de internações hospitalares; Redução de agravos para outros níveis de complexidade (secundária e terciária) | AA501: 0 | AB501: 0 | AC501: 0 | AD501: 1 | AE501: 1 | AF501: =AE501*V501 -> 14272.7
A502: SEJUSP | B502: DEPEN | D502: Superintendência de Humanização do Atendimento - SHUA | E502: =CONCATENATE(A502,"PROG") -> SEJUSPPROG | F502: 130 - INFRAESTRUTURA DO SISTEMA PRISIONAL | G502: =CONCATENATE("P",(LEFT(F502,3)),A502) -> P130SEJUSP | H502: 4353 - UNIDADES DE SAÚDE DO SISTEMA PRISIONAL | I502: ELEMENTO | J502: 5211 - INSTRUMENTOS DE LABORATORIO, MEDICOS E ODONTOLOGICOS | K502: =VLOOKUP(CONCATENATE(A502,LEFT(J502,4)),AGRUPAMENTO!$D$2:$E$6783,2,FALSE) -> Serviços de saúde e medicamentos | L502: 4 - Investimento | N502: 10 | O502: Tesoura cirúrgica curva 17 cm Romba | P502: NÃO | Q502: Unidade | R502: 71 | S502: Pesquisa em site de busca - Internet | T502: 52 | U502: 1 | V502: =R502*T502*U502 -> 3692 | W502: LIMIAR | X502: Proporcionar condições de trabalho aos profissionais de saúde (médicos, enfermeiros, odontólogos e etc), através da utilização de instrumentais nos procedimentos invasivos ou não | Y502: Não execução dos procedimentos; Redução no número de atendimentos aos IPLs; Encaminhamento para atendimento externos; Aumento no número de escoltas | Z502: Melhores condições de trabalho aos servidores que ali laboram; Humanização do atendimento aos IPLs; Redução de encaminhamentos externos de saúde; Redução do número de internações hospitalares; Redução de agravos para outros níveis de complexidade (secundária e terciária) | AA502: 0 | AB502: 0 | AC502: 0 | AD502: 1 | AE502: 1 | AF502: =AE502*V502 -> 3692
A503: SEJUSP | B503: DEPEN | D503: Superintendência de Humanização do Atendimento - SHUA | E503: =CONCATENATE(A503,"PROG") -> SEJUSPPROG | F503: 130 - INFRAESTRUTURA DO SISTEMA PRISIONAL | G503: =CONCATENATE("P",(LEFT(F503,3)),A503) -> P130SEJUSP | H503: 4353 - UNIDADES DE SAÚDE DO SISTEMA PRISIONAL | I503: ELEMENTO | J503: 5211 - INSTRUMENTOS DE LABORATORIO, MEDICOS E ODONTOLOGICOS | K503: =VLOOKUP(CONCATENATE(A503,LEFT(J503,4)),AGRUPAMENTO!$D$2:$E$6783,2,FALSE) -> Serviços de saúde e medicamentos | L503: 4 - Investimento | N503: 10 | O503: Tesoura cirúrgica reta 15 cm Romba Fina | P503: NÃO | Q503: Unidade | R503: 30 | S503: Pesquisa em site de busca - Internet | T503: 45 | U503: 1 | V503: =R503*T503*U503 -> 1350 | W503: LIMIAR | X503: Proporcionar condições de trabalho aos profissionais de saúde (médicos, enfermeiros, odontólogos e etc), através da utilização de instrumentais nos procedimentos invasivos ou não | Y503: Não execução dos procedimentos; Redução no número de atendimentos aos IPLs; Encaminhamento para atendimento externos; Aumento no número de escoltas | Z503: Melhores condições de trabalho aos servidores que ali laboram; Humanização do atendimento aos IPLs; Redução de encaminhamentos externos de saúde; Redução do número de internações hospitalares; Redução de agravos para outros níveis de complexidade (secundária e terciária) | AA503: 0 | AB503: 0 | AC503: 0 | AD503: 1 | AE503: 1 | AF503: =AE503*V503 -> 1350
A504: SEJUSP | B504: DEPEN | D504: Superintendência de Humanização do Atendimento - SHUA | E504: =CONCATENATE(A504,"PROG") -> SEJUSPPROG | F504: 130 - INFRAESTRUTURA DO SISTEMA PRISIONAL | G504: =CONCATENATE("P",(LEFT(F504,3)),A504) -> P130SEJUSP | H504: 4353 - UNIDADES DE SAÚDE DO SISTEMA PRISIONAL | I504: ELEMENTO | J504: 5211 - INSTRUMENTOS DE LABORATORIO, MEDICOS E ODONTOLOGICOS | K504: =VLOOKUP(CONCATENATE(A504,LEFT(J504,4)),AGRUPAMENTO!$D$2:$E$6783,2,FALSE) -> Serviços de saúde e medicamentos | L504: 4 - Investimento | N504: 10 | O504: Tesoura curva 14 cm aço inox Metzembaum | P504: NÃO | Q504: Unidade | R504: 71 | S504: Pesquisa em site de busca - Internet | T504: 50 | U504: 1 | V504: =R504*T504*U504 -> 3550 | W504: LIMIAR | X504: Proporcionar condições de trabalho aos profissionais de saúde (médicos, enfermeiros, odontólogos e etc), através da utilização de instrumentais nos procedimentos invasivos ou não | Y504: Não execução dos procedimentos; Redução no número de atendimentos aos IPLs; Encaminhamento para atendimento externos; Aumento no número de escoltas | Z504: Melhores condições de trabalho aos servidores que ali laboram; Humanização do atendimento aos IPLs; Redução de encaminhamentos externos de saúde; Redução do número de internações hospitalares; Redução de agravos para outros níveis de complexidade (secundária e terciária) | AA504: 0 | AB504: 0 | AC504: 0 | AD504: 1 | AE504: 1 | AF504: =AE504*V504 -> 3550
A505: SEJUSP | B505: DEPEN | D505: Superintendência de Humanização do Atendimento - SHUA | E505: =CONCATENATE(A505,"PROG") -> SEJUSPPROG | F505: 130 - INFRAESTRUTURA DO SISTEMA PRISIONAL | G505: =CONCATENATE("P",(LEFT(F505,3)),A505) -> P130SEJUSP | H505: 4353 - UNIDADES DE SAÚDE DO SISTEMA PRISIONAL | I505: ELEMENTO | J505: 5211 - INSTRUMENTOS DE LABORATORIO, MEDICOS E ODONTOLOGICOS | K505: =VLOOKUP(CONCATENATE(A505,LEFT(J505,4)),AGRUPAMENTO!$D$2:$E$6783,2,FALSE) -> Serviços de saúde e medicamentos | L505: 4 - Investimento | N505: 10 | O505: Tesoura iris reta 10,5cm aço inox | P505: NÃO | Q505: Unidade | R505: 105 | S505: Pesquisa em site de busca - Internet | T505: 29 | U505: 1 | V505: =R505*T505*U505 -> 3045 | W505: LIMIAR | X505: Proporcionar condições de trabalho aos profissionais de saúde (médicos, enfermeiros, odontólogos e etc), através da utilização de instrumentais nos procedimentos invasivos ou não | Y505: Não execução dos procedimentos; Redução no número de atendimentos aos IPLs; Encaminhamento para atendimento externos; Aumento no número de escoltas | Z505: Melhores condições de trabalho aos servidores que ali laboram; Humanização do atendimento aos IPLs; Redução de encaminhamentos externos de saúde; Redução do número de internações hospitalares; Redução de agravos para outros níveis de complexidade (secundária e terciária) | AA505: 0 | AB505: 0 | AC505: 0 | AD505: 1 | AE505: 1 | AF505: =AE505*V505 -> 3045
A506: SEJUSP | B506: DEPEN | D506: Superintendência de Humanização do Atendimento - SHUA | E506: =CONCATENATE(A506,"PROG") -> SEJUSPPROG | F506: 130 - INFRAESTRUTURA DO SISTEMA PRISIONAL | G506: =CONCATENATE("P",(LEFT(F506,3)),A506) -> P130SEJUSP | H506: 4353 - UNIDADES DE SAÚDE DO SISTEMA PRISIONAL | I506: ELEMENTO | J506: 5211 - INSTRUMENTOS DE LABORATORIO, MEDICOS E ODONTOLOGICOS | K506: =VLOOKUP(CONCATENATE(A506,LEFT(J506,4)),AGRUPAMENTO!$D$2:$E$6783,2,FALSE) -> Serviços de saúde e medicamentos | L506: 4 - Investimento | N506: 10 | O506: Tesoura MAYO reta 15 cm | P506: NÃO | Q506: Unidade | R506: 44 | S506: Pesquisa em site de busca - Internet | T506: 58 | U506: 1 | V506: =R506*T506*U506 -> 2552 | W506: LIMIAR | X506: Proporcionar condições de trabalho aos profissionais de saúde (médicos, enfermeiros, odontólogos e etc), através da utilização de instrumentais nos procedimentos invasivos ou não | Y506: Não execução dos procedimentos; Redução no número de atendimentos aos IPLs; Encaminhamento para atendimento externos; Aumento no número de escoltas | Z506: Melhores condições de trabalho aos servidores que ali laboram; Humanização do atendimento aos IPLs; Redução de encaminhamentos externos de saúde; Redução do número de internações hospitalares; Redução de agravos para outros níveis de complexidade (secundária e terciária) | AA506: 0 | AB506: 0 | AC506: 0 | AD506: 1 | AE506: 1 | AF506: =AE506*V506 -> 2552
A507: SEJUSP | B507: DEPEN | D507: Superintendência de Humanização do Atendimento - SHUA | E507: =CONCATENATE(A507,"PROG") -> SEJUSPPROG | F507: 130 - INFRAESTRUTURA DO SISTEMA PRISIONAL | G507: =CONCATENATE("P",(LEFT(F507,3)),A507) -> P130SEJUSP | H507: 4353 - UNIDADES DE SAÚDE DO SISTEMA PRISIONAL | I507: ELEMENTO | J507: 5211 - INSTRUMENTOS DE LABORATORIO, MEDICOS E ODONTOLOGICOS | K507: =VLOOKUP(CONCATENATE(A507,LEFT(J507,4)),AGRUPAMENTO!$D$2:$E$6783,2,FALSE) -> Serviços de saúde e medicamentos | L507: 4 - Investimento | N507: 10 | O507: Tesoura reta 15 cm aço inox Metzembaum | P507: NÃO | Q507: Unidade | R507: 73 | S507: Pesquisa em site de busca - Internet | T507: 42 | U507: 1 | V507: =R507*T507*U507 -> 3066 | W507: LIMIAR | X507: Proporcionar condições de trabalho aos profissionais de saúde (médicos, enfermeiros, odontólogos e etc), através da utilização de instrumentais nos procedimentos invasivos ou não | Y507: Não execução dos procedimentos; Redução no número de atendimentos aos IPLs; Encaminhamento para atendimento externos; Aumento no número de escoltas | Z507: Melhores condições de trabalho aos servidores que ali laboram; Humanização do atendimento aos IPLs; Redução de encaminhamentos externos de saúde; Redução do número de internações hospitalares; Redução de agravos para outros níveis de complexidade (secundária e terciária) | AA507: 0 | AB507: 0 | AC507: 0 | AD507: 1 | AE507: 1 | AF507: =AE507*V507 -> 3066
A508: SEJUSP | B508: DEPEN | D508: Superintendência de Humanização do Atendimento - SHUA | E508: =CONCATENATE(A508,"PROG") -> SEJUSPPROG | F508: 130 - INFRAESTRUTURA DO SISTEMA PRISIONAL | G508: =CONCATENATE("P",(LEFT(F508,3)),A508) -> P130SEJUSP | H508: 4353 - UNIDADES DE SAÚDE DO SISTEMA PRISIONAL | I508: ELEMENTO | J508: 5211 - INSTRUMENTOS DE LABORATORIO, MEDICOS E ODONTOLOGICOS | K508: =VLOOKUP(CONCATENATE(A508,LEFT(J508,4)),AGRUPAMENTO!$D$2:$E$6783,2,FALSE) -> Serviços de saúde e medicamentos | L508: 4 - Investimento | N508: 10 | O508: Tesoura reta retirada de pontos 11 cm spencer | P508: NÃO | Q508: Unidade | R508: 141 | S508: Pesquisa em site de busca - Internet | T508: 39 | U508: 1 | V508: =R508*T508*U508 -> 5499 | W508: LIMIAR | X508: Proporcionar condições de trabalho aos profissionais de saúde (médicos, enfermeiros, odontólogos e etc), através da utilização de instrumentais nos procedimentos invasivos ou não | Y508: Não execução dos procedimentos; Redução no número de atendimentos aos IPLs; Encaminhamento para atendimento externos; Aumento no número de escoltas | Z508: Melhores condições de trabalho aos servidores que ali laboram; Humanização do atendimento aos IPLs; Redução de encaminhamentos externos de saúde; Redução do número de internações hospitalares; Redução de agravos para outros níveis de complexidade (secundária e terciária) | AA508: 0 | AB508: 0 | AC508: 0 | AD508: 1 | AE508: 1 | AF508: =AE508*V508 -> 5499
A509: SEJUSP | B509: DEPEN | D509: Superintendência de Humanização do Atendimento - SHUA | E509: =CONCATENATE(A509,"PROG") -> SEJUSPPROG | F509: 130 - INFRAESTRUTURA DO SISTEMA PRISIONAL | G509: =CONCATENATE("P",(LEFT(F509,3)),A509) -> P130SEJUSP | H509: 4353 - UNIDADES DE SAÚDE DO SISTEMA PRISIONAL | I509: ELEMENTO | J509: 5211 - INSTRUMENTOS DE LABORATORIO, MEDICOS E ODONTOLOGICOS | K509: =VLOOKUP(CONCATENATE(A509,LEFT(J509,4)),AGRUPAMENTO!$D$2:$E$6783,2,FALSE) -> Serviços de saúde e medicamentos | L509: 4 - Investimento | N509: 10 | O509: Armário vitrine | P509: NÃO | Q509: Unidade | R509: 49 | S509: Portal de Compras MG | T509: 1375 | U509: 1 | V509: =R509*T509*U509 -> 67375 | W509: LIMIAR | X509: Proporcionar condições de trabalho aos profissionais de saúde (médicos, enfermeiros, odontólogos e etc), através da utilização de instrumentais nos procedimentos invasivos ou não | Y509: Não execução dos procedimentos; Redução no número de atendimentos aos IPLs; Encaminhamento para atendimento externos; Aumento no número de escoltas | Z509: Melhores condições de trabalho aos servidores que ali laboram; Humanização do atendimento aos IPLs; Redução de encaminhamentos externos de saúde; Redução do número de internações hospitalares; Redução de agravos para outros níveis de complexidade (secundária e terciária) | AA509: 0 | AB509: 0 | AC509: 0 | AD509: 1 | AE509: 1 | AF509: =AE509*V509 -> 67375
...

Sheet AÇÕES E PROGRAMAS
A1: AGE | B1: ARMBH | C1: ARMVA | D1: AGÊNCIA DE PROMOÇÃO DE INVESTIMENTOS DE MINAS GERAIS | E1: ARSAE | F1: ASSEMBLEIA LEGISLATIVA DO ESTADO DE MINAS GERAIS | G1: BANCO DE DESENVOLVIMENTO DE MINAS GERAIS S.A | H1: CEMIG DISTRIBUIÇÃO S.A | I1: CEMIG GERAÇÃO E TRANSMISSÃO S.A | J1: COMPANHIA DE DESENVOLVIMENTO DE MINAS GERAIS | K1: COMPANHIA DE DESENVOLVIMENTO ECONÔMICO DE MINAS GERAIS | L1: COMPANHIA DE GÁS DE MINAS GERAIS | M1: COMPANHIA DE HABITAÇÃO DO ESTADO DE MINAS GERAIS | N1: COMPANHIA DE SANEAMENTO DE MINAS GERAIS | O1: COMPANHIA DE TECNOLOGIA DA INFORMAÇÃO DO ESTADO DE MINAS GERAIS | P1: COMPANHIA ENERGÉTICA DE MINAS GERAIS | Q1: CGE | R1: COPASA - SERVIÇOS DE SANEAMENTO INTEGRADO DO NORTE E NORDESTE DE MINAS GERAIS S/A | S1: CBMMG | T1: DEFENSORIA PUBLICA DO ESTADO DE MINAS GERAIS | U1: DER | V1: EGE SEC.FAZENDA-ENCARGOS DIVERSOS | W1: EGE-SECRETARIA DE ESTADO DE PLANEJAMENTO E GESTÃO | X1: EMATER | Y1: EPAMIG | Z1: EMC | AA1: ENCARGOS GERAIS DO ESTADO - INSTRUMENTOS DE ENTRADA DE RECURSOS | AB1: ESPMG | AC1: HEMOMINAS | AD1: FCS | AE1: FAPEMIG | AF1: FAOP | AG1: UTRAMIG | AH1: FUCAM | AI1: FEAM | AJ1: FUNED | AK1: FHA | AL1: FHEMIG | AM1: FJP | AN1: TVMINAS | AO1: FUNDO DE APOIO HABITACIONAL AOS MILITARES DO ESTADO DE MINAS GERAIS | AP1: FUNDO DE APOIO HABITACIONAL DA ASSEMBLEIA LEGISLATIVA DE MINAS GERAIS | AQ1: FUNAPEC | AR1: FUNDO DE ASSISTÊNCIA AO TURISMO | AS1: FUNDO DE ATIVOS IMOBILIÁRIOS DE MINAS GERAIS | AT1: FDM | AU1: FUNDO DE FOMENTO E DESENVOLVIMENTO SOCIOECONÔMICO DO ESTADO DE MINAS GERAIS | AV1: FUNDO DE GARANTIAS DE PARCERIAS PÚBLICO - PRIVADAS DE MINAS GERAIS | AW1: FUNDO DE INVESTIMENTO DO ESTADO DE MINAS GERAIS | AX1: FUNDO DE INVESTIMENTOS IMOBILIÁRIOS DE MINAS GERAIS | AY1: FUNDO DE PAGAMENTO DE PARCERIAS PÚBLICO - PRIVADAS DE MINAS GERAIS | AZ1: FHIDRO | BA1: FUNDO DO TRIBUNAL DE CONTAS DO ESTADO DE MINAS GERAIS | BB1: FUNDO ESPECIAL DE CRÉDITOS INADIMPLIDOS E DÍVIDA ATIVA | BC1: FUNDO ESPECIAL DO MINISTÉRIO PÚBLICO DO ESTADO DE MINAS GERAIS | BD1: FUNDO ESPECIAL DO PODER JUDICIÁRIO DO ESTADO DE MINAS GERAIS | BE1: FEAS | BF1: FUNDO ESTADUAL DE CULTURA | BG1: FUNDO ESTADUAL DE DEFESA DE DIREITOS DIFUSOS | BH1: FUNTRANS | BI1: FUNDO ESTADUAL DE DESENVOLVIMENTO RURAL | BJ1: FUNDO ESTADUAL DE HABITAÇÃO | BK1: FUNDO ESTADUAL DE PREVENÇÃO, FISCALIZAÇÃO E REPRESSÃO DE ENTORPECENTES | BL1: FUNDO ESTADUAL DE PREVIDÊNCIA DO ESTADO DE MINAS GERAIS | BM1: FUNDO ESTADUAL DE PROTEÇÃO E DEFESA DO CONSUMIDOR | BN1: FES | BO1: FUNDO ESTADUAL DE SEGURANÇA PÚBLICA DE MINAS GERAIS | BP1: FUNDO ESTADUAL DO TRABALHO DE MINAS GERAIS | BQ1: FUNDO ESTADUAL DOS DIREITOS DO IDOSO | BR1: FUNDO FINANCEIRO DE PREVIDÊNCIA DO ESTADO DE MINAS GERAIS | BS1: FUNDO PARA A INFÂNCIA E A ADOLESCÊNCIA | BT1: FUNDO PENITENCIÁRIO ESTADUAL | BU1: GMG | BV1: GESTÃO DA DÍVIDA PÚBLICA ESTADUAL | BW1: IDENE | BX1: INSTITUTO DE METROLOGIA E QUALIDADE DO ESTADO DE MINAS GERAIS | BY1: INSTITUTO DE PREVIDÊNCIA DO LEGISLATIVO DO ESTADO DE MINAS GERAIS | BZ1: IPSEMG | CA1: IPSM | CB1: IEF | CC1: IEPHA | CD1: IMA | CE1: IGAM | CF1: JUCEMG | CG1: LEMG | CH1: MINAS GERAIS ADMINISTRAÇÃO E SERVIÇOS S.A | CI1: MINAS GERAIS PARTICIPAÇÕES S.A | CJ1: OGE | CK1: PARTICIPAÇÃO NO AUMENTO DO CAPITAL SOCIAL DE EMPRESAS | CL1: PCMG | CM1: PMMG | CN1: PROCURADORIA GERAL DE JUSTIÇA | CO1: RESERVA DE CONTINGÊNCIA | CP1: SCC | CQ1: SEAPA | CR1: SECOM | CS1: SECULT | CT1: SEDE | CU1: SEDESE | CV1: SEE | CW1: SEF | CX1: SEGOV | CY1: SEINFRA | CZ1: SEJUSP | DA1: SEMAD | DB1: SEPLAG | DC1: SEC.GERAL | DD1: TREM METROPOLITANO DE BELO HORIZONTE S.A | DE1: TRIBUNAL DE CONTAS DO ESTADO DE MINAS GERAIS | DF1: TRIBUNAL DE JUSTIÇA DO ESTADO DE MINAS GERAIS | DG1: TRIBUNAL DE JUSTIÇA MILITAR DO ESTADO DE MINAS GERAIS | DH1: UEMG | DI1: UNIMONTES | DJ1: ARTEMIG
